Workbook

Sheet BÁO CÁO
B2: BÁO CÁO BÁN HÀNG KÊNH ONLINE THÁNG | H2: 2 | I2: 2026 | S2: ROAS Shopee | T2: =L9/L5 -> 9.6096082
B3: Ngày báo cáo: | D3: 46054 | F3: =TODAY() -> 46082
B4: CHỈ TIÊU | D4: TARGET | E4: THỰC ĐẠT | F4: CHÊNH LỆCH TĐ/TARGET | G4: % TĐ/TARGET | H4: % CHÊNH LỆCH | I4: CHI PHÍ Ads | L4: SHOPEE | M4: GOOGLE ADS Youtube | N4: LAZADA | O4: TIKTOK | P4: FACEBOOK | Q4: ZALO | U4: =L5+N5+R3 -> 7590676
B5: DOANH SỐ | D5: =C16 -> 125000000 | E5: =K16 -> 85299165 | F5: =E5-D5 -> -39700835 | G5: =E5/D5 -> 0.68239332 | H5: =E5/D5-1 -> -0.31760668 | I5: CHI PHÍ QUẢNG CÁO | L5: ='ADS SHOPEE'!Y213 -> 7050676 | N5: 540000 | O5: 1160000 | R5: Tổng chi phí QC: | T5: =L5+M5+N5+O5+P5+Q5+L10+L11 -> 14971476
B6: Tổng PO | D6: =D16 -> 192.30769 | E6: =L16 -> 89 | F6: =E6-D6 -> -103.30769 | G6: =E6/D6 -> 0.4628 | H6: =E6/D6-1 -> -0.5372 | I6: ROAS | L6: =L9/I16 -> 0.84639063 | R6: %Chi phí Quảng cáo/NET SALE: | T6: =T5/E5 -> 0.17551726
B7: Số PO Trung Bình | D7: =D5/D6 -> 650000 | E7: =E5/E6 -> 958417.58 | F7: =E7-D7 -> 308417.58 | G7: =E7/D7 -> 1.4744886 | H7: =E7/D7-1 -> 0.47448859 | I7: % C.Phí QC/DOANH SỐ QC | L7: =L5/L9 -> 0.10406252
B8: Doanh số Trung Bình/ngày | D8: =D5/30 -> 4166666.7 | E8: =AVERAGEIF(B17:B44,"<"&TODAY(),K17:K44) -> 3046398.8 | I8: % CPhí QC/DOANH SỐ TĐ | L8: =L5/I16 -> 0.088077537 | R8: %Chi phí sàn + voucher + chiến dịch + Aff: | T8: 0.19
B9: Số lượng đơn Trung Bình/ngày | E9: =IFERROR(__xludf.DUMMYFUNCTION("IFERROR(SUM(FILTER(L17:L44, B17:B44<=$F$3)) / COUNT(FILTER(B17:B44, B17:B44<=$F$3)), """")"),3.1785714285714284) -> 3.1785714 | F9: % TỔNG CHI PHÍ/DOANH THU: | H9: =T6+T8 -> 0.36551726 | I9: Doanh số từ quảng cáo | L9: ='ADS SHOPEE'!W213 -> 67754234 | R9: % TỔNG CHI PHÍ/DOANH THU: | T9: =T6+T8 -> 0.36551726
I10: Gói tương tác cơ bản | L10: 1350000
I11: Gói tiếp thị standard | L11: 4870800
B13: GIÁ TRỊ TRUNG BÌNH PO | D13: 650000 | N13: =K16/C16-1 -> -0.31760668 | O13: =L16/D16-1 -> -0.5372
B14: Ngày | C14: TARGET | E14: THỰC HIỆN | N14: % THỰC ĐẠT/TARGET | P14: CHÊNH LỆCH THỰC ĐẠT/TARGET | R14: Đơn đã hủy | S14: Doanh số đơn hủy | T14: Đơn đã hoàn trả / hoàn tiền | U14: Doanh số các đơn Trả hàng/ Hoàn tiền
B15: =COUNTA(B17:B47) -> 28 | C15: Doanh số | D15: Tổng số PO | E15: Doanh số ZALO + HOTLINE | F15: Doanh số HARAVAN = WEBSITE | G15: Doanh số FANPAGE | H15: Doanh số LAZADA | I15: Doanh số SHOPPE | J15: Doanh số TIKTOK | K15: Tổng Doanh số Online | L15: Tổng số PO | M15: Giá Trị Po Trung Bình | N15: Doanh số | O15: Tổng số PO | P15: Doanh số | Q15: Tổng số PO
B16: TOTAL | C16: =SUBTOTAL(9,C17:C47) -> 125000000 | D16: =SUBTOTAL(9,D17:D50) -> 192.30769 | E16: =SUBTOTAL(9,E17:E50) -> 2107000 | F16: =SUBTOTAL(9,F17:F50) -> 909000 | G16: =SUBTOTAL(9,G17:G50) -> 0 | H16: =SUBTOTAL(9,H17:H50) -> 0 | I16: =SUBTOTAL(9,I17:I50) -> 80050785 | J16: =SUBTOTAL(9,J17:J50) -> 2232380 | K16: =SUBTOTAL(9,K17:K50) -> 85299165 | L16: =SUBTOTAL(9,L17:L50) -> 89 | M16: =K16/L16 -> 958417.58 | N16: =K16/C16 -> 0.68239332 | O16: =L16/D16 -> 0.4628 | P16: =SUBTOTAL(9,P17:P50) -> -39700835 | Q16: =SUBTOTAL(9,Q17:Q50) -> -103.30769 | R16: =SUBTOTAL(9,R17:R50) -> 12 | S16: =SUBTOTAL(9,S17:S50) -> 12539712 | T16: =SUBTOTAL(9,T17:T50) -> 2 | U16: =SUBTOTAL(9,U17:U50) -> 1570000
B17: 46054 | C17: =SUMIFS(TARGET!E:E,TARGET!D:D,B17) -> 4464285.7 | D17: =C17/$D$13 -> 6.8681319 | E17: =SUMIFS(ZALO!C:C,ZALO!A:A,B17) -> 0 | F17: =SUMIFS(WEB!C:C,WEB!A:A,B17) -> 0 | G17: =SUMIFS(FANPAGE!C:C,FANPAGE!A:A,B17) -> 0 | H17: =SUMIFS(LAZADA!B:B,LAZADA!A:A,B17) -> 0 | I17: =SUMIFS('DS Shoppe (đã xác nhận)'!B:B,'DS Shoppe (đã xác nhận)'!A:A,B17) -> 2764634 | J17: =SUMIFS(TIKTOK!B:B,TIKTOK!A:A,B25) -> 0 | K17: =SUM(E17:J17) -> 2764634 | L17: =SUMIFS('DS Shoppe (đã xác nhận)'!C:C,'DS Shoppe (đã xác nhận)'!A:A,B17)+SUMIFS(LAZADA!E:E,LAZADA!A:A,B17)+SUMIFS(WEB!B:B,WEB!A:A,B17)+SUMIFS(ZALO!B:B,ZALO!A:A,B17)+SUMIFS(FANPAGE!B:B,FANPAGE!A:A,B17)+SUMIFS(TIKTOK!J6:J35,TIKTOK!A6:A35,B17) -> 4 | M17: =K17/L17 -> 691158.5 | N17: =K17/C17 -> 0.61927802 | O17: =L17/D17 -> 0.5824 | P17: =K17-C17 -> -1699651.7 | Q17: =L17-D17 -> -2.8681319 | R17: =SUMIFS('DS Shoppe (đã xác nhận)'!H:H,'DS Shoppe (đã xác nhận)'!A:A,B17) -> 0 | S17: =SUMIFS('DS Shoppe (đã xác nhận)'!I:I,'DS Shoppe (đã xác nhận)'!A:A,B17) -> 0 | T17: =SUMIFS('DS Shoppe (đã xác nhận)'!J:J,'DS Shoppe (đã xác nhận)'!A:A,B17) -> 0 | U17: =SUMIFS('DS Shoppe (đã xác nhận)'!K:K,'DS Shoppe (đã xác nhận)'!A:A,B17) -> 0
B18: =B17+1 -> 46055 | C18: =SUMIFS(TARGET!E:E,TARGET!D:D,B18) -> 4464285.7 | D18: =C18/$D$13 -> 6.8681319 | E18: =SUMIFS(ZALO!C:C,ZALO!A:A,B18) -> 0 | F18: =SUMIFS(WEB!C:C,WEB!A:A,B18) -> 0 | G18: =SUMIFS(FANPAGE!C:C,FANPAGE!A:A,B18) -> 0 | H18: =SUMIFS(LAZADA!B:B,LAZADA!A:A,B18) -> 0 | I18: =SUMIFS('DS Shoppe (đã xác nhận)'!B:B,'DS Shoppe (đã xác nhận)'!A:A,B18) -> 12891791 | J18: =SUMIFS(TIKTOK!B:B,TIKTOK!A:A,B18) -> 0 | K18: =SUM(E18:J18) -> 12891791 | L18: =SUMIFS('DS Shoppe (đã xác nhận)'!C:C,'DS Shoppe (đã xác nhận)'!A:A,B18)+SUMIFS(LAZADA!E:E,LAZADA!A:A,B18)+SUMIFS(WEB!B:B,WEB!A:A,B18)+SUMIFS(ZALO!B:B,ZALO!A:A,B18)+SUMIFS(FANPAGE!B:B,FANPAGE!A:A,B18)+SUMIFS(TIKTOK!J7:J36,TIKTOK!A7:A36,B18) -> 15 | M18: =K18/L18 -> 859452.73 | N18: =K18/C18 -> 2.8877612 | O18: =L18/D18 -> 2.184 | P18: =K18-C18 -> 8427505.3 | Q18: =L18-D18 -> 8.1318681 | R18: =SUMIFS('DS Shoppe (đã xác nhận)'!H:H,'DS Shoppe (đã xác nhận)'!A:A,B18) -> 0 | S18: =SUMIFS('DS Shoppe (đã xác nhận)'!I:I,'DS Shoppe (đã xác nhận)'!A:A,B18) -> 0 | T18: =SUMIFS('DS Shoppe (đã xác nhận)'!J:J,'DS Shoppe (đã xác nhận)'!A:A,B18) -> 0 | U18: =SUMIFS('DS Shoppe (đã xác nhận)'!K:K,'DS Shoppe (đã xác nhận)'!A:A,B18) -> 0
B19: =B18+1 -> 46056 | C19: =SUMIFS(TARGET!E:E,TARGET!D:D,B19) -> 4464285.7 | D19: =C19/$D$13 -> 6.8681319 | E19: =SUMIFS(ZALO!C:C,ZALO!A:A,B19) -> 0 | F19: =SUMIFS(WEB!C:C,WEB!A:A,B19) -> 0 | G19: =SUMIFS(FANPAGE!C:C,FANPAGE!A:A,B19) -> 0 | H19: =SUMIFS(LAZADA!B:B,LAZADA!A:A,B19) -> 0 | I19: =SUMIFS('DS Shoppe (đã xác nhận)'!B:B,'DS Shoppe (đã xác nhận)'!A:A,B19) -> 3577124 | J19: =SUMIFS(TIKTOK!B:B,TIKTOK!A:A,B19) -> 0 | K19: =SUM(E19:J19) -> 3577124 | L19: =SUMIFS('DS Shoppe (đã xác nhận)'!C:C,'DS Shoppe (đã xác nhận)'!A:A,B19)+SUMIFS(LAZADA!E:E,LAZADA!A:A,B19)+SUMIFS(WEB!B:B,WEB!A:A,B19)+SUMIFS(ZALO!B:B,ZALO!A:A,B19)+SUMIFS(FANPAGE!B:B,FANPAGE!A:A,B19)+SUMIFS(TIKTOK!J8:J37,TIKTOK!A8:A37,B19) -> 5 | M19: =IF(L19=0,"0",K19/L19) -> 715424.8 | N19: =K19/C19 -> 0.80127578 | O19: =L19/D19 -> 0.728 | P19: =K19-C19 -> -887161.71 | Q19: =L19-D19 -> -1.8681319 | R19: =SUMIFS('DS Shoppe (đã xác nhận)'!H:H,'DS Shoppe (đã xác nhận)'!A:A,B19) -> 0 | S19: =SUMIFS('DS Shoppe (đã xác nhận)'!I:I,'DS Shoppe (đã xác nhận)'!A:A,B19) -> 0 | T19: =SUMIFS('DS Shoppe (đã xác nhận)'!J:J,'DS Shoppe (đã xác nhận)'!A:A,B19) -> 0 | U19: =SUMIFS('DS Shoppe (đã xác nhận)'!K:K,'DS Shoppe (đã xác nhận)'!A:A,B19) -> 0
B20: =B19+1 -> 46057 | C20: =SUMIFS(TARGET!E:E,TARGET!D:D,B20) -> 4464285.7 | D20: =C20/$D$13 -> 6.8681319 | E20: =SUMIFS(ZALO!C:C,ZALO!A:A,B20) -> 0 | F20: =SUMIFS(WEB!C:C,WEB!A:A,B20) -> 0 | G20: =SUMIFS(FANPAGE!C:C,FANPAGE!A:A,B20) -> 0 | H20: =SUMIFS(LAZADA!B:B,LAZADA!A:A,B20) -> 0 | I20: =SUMIFS('DS Shoppe (đã xác nhận)'!B:B,'DS Shoppe (đã xác nhận)'!A:A,B20) -> 2578636 | J20: =SUMIFS(TIKTOK!B:B,TIKTOK!A:A,B20) -> 0 | K20: =SUM(E20:J20) -> 2578636 | L20: =SUMIFS('DS Shoppe (đã xác nhận)'!C:C,'DS Shoppe (đã xác nhận)'!A:A,B20)+SUMIFS(LAZADA!E:E,LAZADA!A:A,B20)+SUMIFS(WEB!B:B,WEB!A:A,B20)+SUMIFS(ZALO!B:B,ZALO!A:A,B20)+SUMIFS(FANPAGE!B:B,FANPAGE!A:A,B20)+SUMIFS(TIKTOK!J9:J38,TIKTOK!A9:A38,B20) -> 3 | M20: =IF(L20=0,"0",K20/L20) -> 859545.33 | N20: =K20/C20 -> 0.57761446 | O20: =L20/D20 -> 0.4368 | P20: =K20-C20 -> -1885649.7 | Q20: =L20-D20 -> -3.8681319 | R20: =SUMIFS('DS Shoppe (đã xác nhận)'!H:H,'DS Shoppe (đã xác nhận)'!A:A,B20) -> 0 | S20: =SUMIFS('DS Shoppe (đã xác nhận)'!I:I,'DS Shoppe (đã xác nhận)'!A:A,B20) -> 0 | T20: =SUMIFS('DS Shoppe (đã xác nhận)'!J:J,'DS Shoppe (đã xác nhận)'!A:A,B20) -> 0 | U20: =SUMIFS('DS Shoppe (đã xác nhận)'!K:K,'DS Shoppe (đã xác nhận)'!A:A,B20) -> 0
B21: =B20+1 -> 46058 | C21: =SUMIFS(TARGET!E:E,TARGET!D:D,B21) -> 4464285.7 | D21: =C21/$D$13 -> 6.8681319 | E21: =SUMIFS(ZALO!C:C,ZALO!A:A,B21) -> 0 | F21: =SUMIFS(WEB!C:C,WEB!A:A,B21) -> 0 | G21: =SUMIFS(FANPAGE!C:C,FANPAGE!A:A,B21) -> 0 | H21: =SUMIFS(LAZADA!B:B,LAZADA!A:A,B21) -> 0 | I21: =SUMIFS('DS Shoppe (đã xác nhận)'!B:B,'DS Shoppe (đã xác nhận)'!A:A,B21) -> 4938391 | J21: =SUMIFS(TIKTOK!B:B,TIKTOK!A:A,B21) -> 0 | K21: =SUM(E21:J21) -> 4938391 | L21: =SUMIFS('DS Shoppe (đã xác nhận)'!C:C,'DS Shoppe (đã xác nhận)'!A:A,B21)+SUMIFS(LAZADA!E:E,LAZADA!A:A,B21)+SUMIFS(WEB!B:B,WEB!A:A,B21)+SUMIFS(ZALO!B:B,ZALO!A:A,B21)+SUMIFS(FANPAGE!B:B,FANPAGE!A:A,B21)+SUMIFS(TIKTOK!J10:J39,TIKTOK!A10:A39,B21) -> 3 | M21: =IF(L21=0,"0",K21/L21) -> 1646130.3 | N21: =K21/C21 -> 1.1061996 | O21: =L21/D21 -> 0.4368 | P21: =K21-C21 -> 474105.29 | Q21: =L21-D21 -> -3.8681319 | R21: =SUMIFS('DS Shoppe (đã xác nhận)'!H:H,'DS Shoppe (đã xác nhận)'!A:A,B21) -> 0 | S21: =SUMIFS('DS Shoppe (đã xác nhận)'!I:I,'DS Shoppe (đã xác nhận)'!A:A,B21) -> 0 | T21: =SUMIFS('DS Shoppe (đã xác nhận)'!J:J,'DS Shoppe (đã xác nhận)'!A:A,B21) -> 0 | U21: =SUMIFS('DS Shoppe (đã xác nhận)'!K:K,'DS Shoppe (đã xác nhận)'!A:A,B21) -> 0
B22: =B21+1 -> 46059 | C22: =SUMIFS(TARGET!E:E,TARGET!D:D,B22) -> 4464285.7 | D22: =C22/$D$13 -> 6.8681319 | E22: =SUMIFS(ZALO!C:C,ZALO!A:A,B22) -> 0 | F22: =SUMIFS(WEB!C:C,WEB!A:A,B22) -> 0 | G22: =SUMIFS(FANPAGE!C:C,FANPAGE!A:A,B22) -> 0 | H22: =SUMIFS(LAZADA!B:B,LAZADA!A:A,B22) -> 0 | I22: =SUMIFS('DS Shoppe (đã xác nhận)'!B:B,'DS Shoppe (đã xác nhận)'!A:A,B22) -> 60000 | J22: =SUMIFS(TIKTOK!B:B,TIKTOK!A:A,B22) -> 0 | K22: =SUM(E22:J22) -> 60000 | L22: =SUMIFS('DS Shoppe (đã xác nhận)'!C:C,'DS Shoppe (đã xác nhận)'!A:A,B22)+SUMIFS(LAZADA!E:E,LAZADA!A:A,B22)+SUMIFS(WEB!B:B,WEB!A:A,B22)+SUMIFS(ZALO!B:B,ZALO!A:A,B22)+SUMIFS(FANPAGE!B:B,FANPAGE!A:A,B22)+SUMIFS(TIKTOK!J11:J40,TIKTOK!A11:A40,B22) -> 1 | M22: =IF(L22=0,"0",K22/L22) -> 60000 | N22: =K22/C22 -> 0.01344 | O22: =L22/D22 -> 0.1456 | P22: =K22-C22 -> -4404285.7 | Q22: =L22-D22 -> -5.8681319 | R22: =SUMIFS('DS Shoppe (đã xác nhận)'!H:H,'DS Shoppe (đã xác nhận)'!A:A,B22) -> 0 | S22: =SUMIFS('DS Shoppe (đã xác nhận)'!I:I,'DS Shoppe (đã xác nhận)'!A:A,B22) -> 0 | T22: =SUMIFS('DS Shoppe (đã xác nhận)'!J:J,'DS Shoppe (đã xác nhận)'!A:A,B22) -> 0 | U22: =SUMIFS('DS Shoppe (đã xác nhận)'!K:K,'DS Shoppe (đã xác nhận)'!A:A,B22) -> 0
B23: =B22+1 -> 46060 | C23: =SUMIFS(TARGET!E:E,TARGET!D:D,B23) -> 4464285.7 | D23: =C23/$D$13 -> 6.8681319 | E23: =SUMIFS(ZALO!C:C,ZALO!A:A,B23) -> 0 | F23: =SUMIFS(WEB!C:C,WEB!A:A,B23) -> 0 | G23: =SUMIFS(FANPAGE!C:C,FANPAGE!A:A,B23) -> 0 | H23: =SUMIFS(LAZADA!B:B,LAZADA!A:A,B23) -> 0 | I23: =SUMIFS('DS Shoppe (đã xác nhận)'!B:B,'DS Shoppe (đã xác nhận)'!A:A,B23) -> 2158140 | J23: =SUMIFS(TIKTOK!B:B,TIKTOK!A:A,B23) -> 0 | K23: =SUM(E23:J23) -> 2158140 | L23: =SUMIFS('DS Shoppe (đã xác nhận)'!C:C,'DS Shoppe (đã xác nhận)'!A:A,B23)+SUMIFS(LAZADA!E:E,LAZADA!A:A,B23)+SUMIFS(WEB!B:B,WEB!A:A,B23)+SUMIFS(ZALO!B:B,ZALO!A:A,B23)+SUMIFS(FANPAGE!B:B,FANPAGE!A:A,B23)+SUMIFS(TIKTOK!J12:J41,TIKTOK!A12:A41,B23) -> 2 | M23: =IF(L23=0,"0",K23/L23) -> 1079070 | N23: =K23/C23 -> 0.48342336 | O23: =L23/D23 -> 0.2912 | P23: =K23-C23 -> -2306145.7 | Q23: =L23-D23 -> -4.8681319 | R23: =SUMIFS('DS Shoppe (đã xác nhận)'!H:H,'DS Shoppe (đã xác nhận)'!A:A,B23) -> 0 | S23: =SUMIFS('DS Shoppe (đã xác nhận)'!I:I,'DS Shoppe (đã xác nhận)'!A:A,B23) -> 0 | T23: =SUMIFS('DS Shoppe (đã xác nhận)'!J:J,'DS Shoppe (đã xác nhận)'!A:A,B23) -> 0 | U23: =SUMIFS('DS Shoppe (đã xác nhận)'!K:K,'DS Shoppe (đã xác nhận)'!A:A,B23) -> 0
B24: =B23+1 -> 46061 | C24: =SUMIFS(TARGET!E:E,TARGET!D:D,B24) -> 4464285.7 | D24: =C24/$D$13 -> 6.8681319 | E24: =SUMIFS(ZALO!C:C,ZALO!A:A,B24) -> 0 | F24: =SUMIFS(WEB!C:C,WEB!A:A,B24) -> 0 | G24: =SUMIFS(FANPAGE!C:C,FANPAGE!A:A,B24) -> 0 | H24: =SUMIFS(LAZADA!B:B,LAZADA!A:A,B24) -> 0 | I24: =SUMIFS('DS Shoppe (đã xác nhận)'!B:B,'DS Shoppe (đã xác nhận)'!A:A,B24) -> 4782887 | J24: =SUMIFS(TIKTOK!B:B,TIKTOK!A:A,B24) -> 0 | K24: =SUM(E24:J24) -> 4782887 | L24: =SUMIFS('DS Shoppe (đã xác nhận)'!C:C,'DS Shoppe (đã xác nhận)'!A:A,B24)+SUMIFS(LAZADA!E:E,LAZADA!A:A,B24)+SUMIFS(WEB!B:B,WEB!A:A,B24)+SUMIFS(ZALO!B:B,ZALO!A:A,B24)+SUMIFS(FANPAGE!B:B,FANPAGE!A:A,B24)+SUMIFS(TIKTOK!J13:J42,TIKTOK!A13:A42,B24) -> 6 | M24: =IF(L24=0,"0",K24/L24) -> 797147.83 | N24: =K24/C24 -> 1.0713667 | O24: =L24/D24 -> 0.8736 | P24: =K24-C24 -> 318601.29 | Q24: =L24-D24 -> -0.86813187 | R24: =SUMIFS('DS Shoppe (đã xác nhận)'!H:H,'DS Shoppe (đã xác nhận)'!A:A,B24) -> 0 | S24: =SUMIFS('DS Shoppe (đã xác nhận)'!I:I,'DS Shoppe (đã xác nhận)'!A:A,B24) -> 0 | T24: =SUMIFS('DS Shoppe (đã xác nhận)'!J:J,'DS Shoppe (đã xác nhận)'!A:A,B24) -> 1 | U24: =SUMIFS('DS Shoppe (đã xác nhận)'!K:K,'DS Shoppe (đã xác nhận)'!A:A,B24) -> 846000
B25: =B24+1 -> 46062 | C25: =SUMIFS(TARGET!E:E,TARGET!D:D,B25) -> 4464285.7 | D25: =C25/$D$13 -> 6.8681319 | E25: =SUMIFS(ZALO!C:C,ZALO!A:A,B25) -> 0 | F25: =SUMIFS(WEB!C:C,WEB!A:A,B25) -> 909000 | G25: =SUMIFS(FANPAGE!C:C,FANPAGE!A:A,B25) -> 0 | H25: =SUMIFS(LAZADA!B:B,LAZADA!A:A,B25) -> 0 | I25: =SUMIFS('DS Shoppe (đã xác nhận)'!B:B,'DS Shoppe (đã xác nhận)'!A:A,B25) -> 1835353 | J25: =SUMIFS(TIKTOK!B:B,TIKTOK!A:A,B25) -> 0 | K25: =SUM(E25:J25) -> 2744353 | L25: =SUMIFS('DS Shoppe (đã xác nhận)'!C:C,'DS Shoppe (đã xác nhận)'!A:A,B25)+SUMIFS(LAZADA!E:E,LAZADA!A:A,B25)+SUMIFS(WEB!B:B,WEB!A:A,B25)+SUMIFS(ZALO!B:B,ZALO!A:A,B25)+SUMIFS(FANPAGE!B:B,FANPAGE!A:A,B25)+SUMIFS(TIKTOK!J14:J43,TIKTOK!A14:A43,B25) -> 3 | M25: =IF(L25=0,"0",K25/L25) -> 914784.33 | N25: =K25/C25 -> 0.61473507 | O25: =L25/D25 -> 0.4368 | P25: =K25-C25 -> -1719932.7 | Q25: =L25-D25 -> -3.8681319 | R25: =SUMIFS('DS Shoppe (đã xác nhận)'!H:H,'DS Shoppe (đã xác nhận)'!A:A,B25) -> 1 | S25: =SUMIFS('DS Shoppe (đã xác nhận)'!I:I,'DS Shoppe (đã xác nhận)'!A:A,B25) -> 926091 | T25: =SUMIFS('DS Shoppe (đã xác nhận)'!J:J,'DS Shoppe (đã xác nhận)'!A:A,B25) -> 0 | U25: =SUMIFS('DS Shoppe (đã xác nhận)'!K:K,'DS Shoppe (đã xác nhận)'!A:A,B25) -> 0
B26: =B25+1 -> 46063 | C26: =SUMIFS(TARGET!E:E,TARGET!D:D,B26) -> 4464285.7 | D26: =C26/$D$13 -> 6.8681319 | E26: =SUMIFS(ZALO!C:C,ZALO!A:A,B26) -> 0 | F26: =SUMIFS(WEB!C:C,WEB!A:A,B26) -> 0 | G26: =SUMIFS(FANPAGE!C:C,FANPAGE!A:A,B26) -> 0 | H26: =SUMIFS(LAZADA!B:B,LAZADA!A:A,B26) -> 0 | I26: =SUMIFS('DS Shoppe (đã xác nhận)'!B:B,'DS Shoppe (đã xác nhận)'!A:A,B26) -> 5177368 | J26: =SUMIFS(TIKTOK!B:B,TIKTOK!A:A,B26) -> 0 | K26: =SUM(E26:J26) -> 5177368 | L26: =SUMIFS('DS Shoppe (đã xác nhận)'!C:C,'DS Shoppe (đã xác nhận)'!A:A,B26)+SUMIFS(LAZADA!E:E,LAZADA!A:A,B26)+SUMIFS(WEB!B:B,WEB!A:A,B26)+SUMIFS(ZALO!B:B,ZALO!A:A,B26)+SUMIFS(FANPAGE!B:B,FANPAGE!A:A,B26)+SUMIFS(TIKTOK!J15:J44,TIKTOK!A15:A44,B26) -> 6 | M26: =IF(L26=0,"0",K26/L26) -> 862894.67 | N26: =K26/C26 -> 1.1597304 | O26: =L26/D26 -> 0.8736 | P26: =K26-C26 -> 713082.29 | Q26: =L26-D26 -> -0.86813187 | R26: =SUMIFS('DS Shoppe (đã xác nhận)'!H:H,'DS Shoppe (đã xác nhận)'!A:A,B26) -> 0 | S26: =SUMIFS('DS Shoppe (đã xác nhận)'!I:I,'DS Shoppe (đã xác nhận)'!A:A,B26) -> 0 | T26: =SUMIFS('DS Shoppe (đã xác nhận)'!J:J,'DS Shoppe (đã xác nhận)'!A:A,B26) -> 1 | U26: =SUMIFS('DS Shoppe (đã xác nhận)'!K:K,'DS Shoppe (đã xác nhận)'!A:A,B26) -> 724000
B27: =B26+1 -> 46064 | C27: =SUMIFS(TARGET!E:E,TARGET!D:D,B27) -> 4464285.7 | D27: =C27/$D$13 -> 6.8681319 | E27: =SUMIFS(ZALO!C:C,ZALO!A:A,B27) -> 0 | F27: =SUMIFS(WEB!C:C,WEB!A:A,B27) -> 0 | G27: =SUMIFS(FANPAGE!C:C,FANPAGE!A:A,B27) -> 0 | H27: =SUMIFS(LAZADA!B:B,LAZADA!A:A,B27) -> 0 | I27: =SUMIFS('DS Shoppe (đã xác nhận)'!B:B,'DS Shoppe (đã xác nhận)'!A:A,B27) -> 1951880 | J27: =SUMIFS(TIKTOK!B:B,TIKTOK!A:A,B27) -> 0 | K27: =SUM(E27:J27) -> 1951880 | L27: =SUMIFS('DS Shoppe (đã xác nhận)'!C:C,'DS Shoppe (đã xác nhận)'!A:A,B27)+SUMIFS(LAZADA!E:E,LAZADA!A:A,B27)+SUMIFS(WEB!B:B,WEB!A:A,B27)+SUMIFS(ZALO!B:B,ZALO!A:A,B27)+SUMIFS(FANPAGE!B:B,FANPAGE!A:A,B27)+SUMIFS(TIKTOK!J16:J45,TIKTOK!A16:A45,B27) -> 2 | M27: =IF(L27=0,"0",K27/L27) -> 975940 | N27: =K27/C27 -> 0.43722112 | O27: =L27/D27 -> 0.2912 | P27: =K27-C27 -> -2512405.7 | Q27: =L27-D27 -> -4.8681319 | R27: =SUMIFS('DS Shoppe (đã xác nhận)'!H:H,'DS Shoppe (đã xác nhận)'!A:A,B27) -> 0 | S27: =SUMIFS('DS Shoppe (đã xác nhận)'!I:I,'DS Shoppe (đã xác nhận)'!A:A,B27) -> 0 | T27: =SUMIFS('DS Shoppe (đã xác nhận)'!J:J,'DS Shoppe (đã xác nhận)'!A:A,B27) -> 0 | U27: =SUMIFS('DS Shoppe (đã xác nhận)'!K:K,'DS Shoppe (đã xác nhận)'!A:A,B27) -> 0
B28: =B27+1 -> 46065 | C28: =SUMIFS(TARGET!E:E,TARGET!D:D,B28) -> 4464285.7 | D28: =C28/$D$13 -> 6.8681319 | E28: =SUMIFS(ZALO!C:C,ZALO!A:A,B28) -> 0 | F28: =SUMIFS(WEB!C:C,WEB!A:A,B28) -> 0 | G28: =SUMIFS(FANPAGE!C:C,FANPAGE!A:A,B28) -> 0 | H28: =SUMIFS(LAZADA!B:B,LAZADA!A:A,B28) -> 0 | I28: =SUMIFS('DS Shoppe (đã xác nhận)'!B:B,'DS Shoppe (đã xác nhận)'!A:A,B28) -> 3446276 | J28: =SUMIFS(TIKTOK!B:B,TIKTOK!A:A,B28) -> 0 | K28: =SUM(E28:J28) -> 3446276 | L28: =SUMIFS('DS Shoppe (đã xác nhận)'!C:C,'DS Shoppe (đã xác nhận)'!A:A,B28)+SUMIFS(LAZADA!E:E,LAZADA!A:A,B28)+SUMIFS(WEB!B:B,WEB!A:A,B28)+SUMIFS(ZALO!B:B,ZALO!A:A,B28)+SUMIFS(FANPAGE!B:B,FANPAGE!A:A,B28) -> 2 | M28: =IF(L28=0,"0",K28/L28) -> 1723138 | N28: =K28/C28 -> 0.77196582 | O28: =L28/D28 -> 0.2912 | P28: =K28-C28 -> -1018009.7 | Q28: =L28-D28 -> -4.8681319 | R28: =SUMIFS('DS Shoppe (đã xác nhận)'!H:H,'DS Shoppe (đã xác nhận)'!A:A,B28) -> 1 | S28: =SUMIFS('DS Shoppe (đã xác nhận)'!I:I,'DS Shoppe (đã xác nhận)'!A:A,B28) -> 2019600 | T28: =SUMIFS('DS Shoppe (đã xác nhận)'!J:J,'DS Shoppe (đã xác nhận)'!A:A,B28) -> 0 | U28: =SUMIFS('DS Shoppe (đã xác nhận)'!K:K,'DS Shoppe (đã xác nhận)'!A:A,B28) -> 0
B29: =B28+1 -> 46066 | C29: =SUMIFS(TARGET!E:E,TARGET!D:D,B29) -> 4464285.7 | D29: =C29/$D$13 -> 6.8681319 | E29: =SUMIFS(ZALO!C:C,ZALO!A:A,B29) -> 1278000 | F29: =SUMIFS(WEB!C:C,WEB!A:A,B29) -> 0 | G29: =SUMIFS(FANPAGE!C:C,FANPAGE!A:A,B29) -> 0 | H29: =SUMIFS(LAZADA!B:B,LAZADA!A:A,B29) -> 0 | I29: =SUMIFS('DS Shoppe (đã xác nhận)'!B:B,'DS Shoppe (đã xác nhận)'!A:A,B29) -> 0 | J29: =SUMIFS(TIKTOK!B:B,TIKTOK!A:A,B29) -> 1456380 | K29: =SUM(E29:J29) -> 2734380 | L29: =SUMIFS('DS Shoppe (đã xác nhận)'!C:C,'DS Shoppe (đã xác nhận)'!A:A,B29)+SUMIFS(LAZADA!E:E,LAZADA!A:A,B29)+SUMIFS(WEB!B:B,WEB!A:A,B29)+SUMIFS(ZALO!B:B,ZALO!A:A,B29)+SUMIFS(FANPAGE!B:B,FANPAGE!A:A,B29) -> 1 | M29: =IF(L29=0,"0",K29/L29) -> 2734380 | N29: =K29/C29 -> 0.61250112 | O29: =L29/D29 -> 0.1456 | P29: =K29-C29 -> -1729905.7 | Q29: =L29-D29 -> -5.8681319 | R29: =SUMIFS('DS Shoppe (đã xác nhận)'!H:H,'DS Shoppe (đã xác nhận)'!A:A,B29) -> 0 | S29: =SUMIFS('DS Shoppe (đã xác nhận)'!I:I,'DS Shoppe (đã xác nhận)'!A:A,B29) -> 0 | T29: =SUMIFS('DS Shoppe (đã xác nhận)'!J:J,'DS Shoppe (đã xác nhận)'!A:A,B29) -> 0 | U29: =SUMIFS('DS Shoppe (đã xác nhận)'!K:K,'DS Shoppe (đã xác nhận)'!A:A,B29) -> 0
B30: =B29+1 -> 46067 | C30: =SUMIFS(TARGET!E:E,TARGET!D:D,B30) -> 4464285.7 | D30: =C30/$D$13 -> 6.8681319 | E30: =SUMIFS(ZALO!C:C,ZALO!A:A,B30) -> 0 | F30: =SUMIFS(WEB!C:C,WEB!A:A,B30) -> 0 | G30: =SUMIFS(FANPAGE!C:C,FANPAGE!A:A,B30) -> 0 | H30: =SUMIFS(LAZADA!B:B,LAZADA!A:A,B30) -> 0 | I30: =SUMIFS('DS Shoppe (đã xác nhận)'!B:B,'DS Shoppe (đã xác nhận)'!A:A,B30) -> 2613091 | J30: =SUMIFS(TIKTOK!B:B,TIKTOK!A:A,B30) -> 0 | K30: =SUM(E30:J30) -> 2613091 | L30: =SUMIFS('DS Shoppe (đã xác nhận)'!C:C,'DS Shoppe (đã xác nhận)'!A:A,B30)+SUMIFS(LAZADA!E:E,LAZADA!A:A,B30)+SUMIFS(WEB!B:B,WEB!A:A,B30)+SUMIFS(ZALO!B:B,ZALO!A:A,B30)+SUMIFS(FANPAGE!B:B,FANPAGE!A:A,B30) -> 2 | M30: =IF(L30=0,"0",K30/L30) -> 1306545.5 | N30: =K30/C30 -> 0.58533238 | O30: =L30/D30 -> 0.2912 | P30: =K30-C30 -> -1851194.7 | Q30: =L30-D30 -> -4.8681319 | R30: =SUMIFS('DS Shoppe (đã xác nhận)'!H:H,'DS Shoppe (đã xác nhận)'!A:A,B30) -> 0 | S30: =SUMIFS('DS Shoppe (đã xác nhận)'!I:I,'DS Shoppe (đã xác nhận)'!A:A,B30) -> 0 | T30: =SUMIFS('DS Shoppe (đã xác nhận)'!J:J,'DS Shoppe (đã xác nhận)'!A:A,B30) -> 0 | U30: =SUMIFS('DS Shoppe (đã xác nhận)'!K:K,'DS Shoppe (đã xác nhận)'!A:A,B30) -> 0
B31: =B30+1 -> 46068 | C31: =SUMIFS(TARGET!E:E,TARGET!D:D,B31) -> 4464285.7 | D31: =C31/$D$13 -> 6.8681319 | E31: =SUMIFS(ZALO!C:C,ZALO!A:A,B31) -> 0 | F31: =SUMIFS(WEB!C:C,WEB!A:A,B31) -> 0 | G31: =SUMIFS(FANPAGE!C:C,FANPAGE!A:A,B31) -> 0 | H31: =SUMIFS(LAZADA!B:B,LAZADA!A:A,B31) -> 0 | I31: =SUMIFS('DS Shoppe (đã xác nhận)'!B:B,'DS Shoppe (đã xác nhận)'!A:A,B31) -> 0 | J31: =SUMIFS(TIKTOK!B:B,TIKTOK!A:A,B31) -> 0 | K31: =SUM(E31:J31) -> 0 | L31: =SUMIFS('DS Shoppe (đã xác nhận)'!C:C,'DS Shoppe (đã xác nhận)'!A:A,B31)+SUMIFS(LAZADA!E:E,LAZADA!A:A,B31)+SUMIFS(WEB!B:B,WEB!A:A,B31)+SUMIFS(ZALO!B:B,ZALO!A:A,B31)+SUMIFS(FANPAGE!B:B,FANPAGE!A:A,B31) -> 0 | M31: =IF(L31=0,"0",K31/L31) -> 0 | N31: =K31/C31 -> 0 | O31: =L31/D31 -> 0 | P31: =K31-C31 -> -4464285.7 | Q31: =L31-D31 -> -6.8681319 | R31: =SUMIFS('DS Shoppe (đã xác nhận)'!H:H,'DS Shoppe (đã xác nhận)'!A:A,B31) -> 2 | S31: =SUMIFS('DS Shoppe (đã xác nhận)'!I:I,'DS Shoppe (đã xác nhận)'!A:A,B31) -> 1243900 | T31: =SUMIFS('DS Shoppe (đã xác nhận)'!J:J,'DS Shoppe (đã xác nhận)'!A:A,B31) -> 0 | U31: =SUMIFS('DS Shoppe (đã xác nhận)'!K:K,'DS Shoppe (đã xác nhận)'!A:A,B31) -> 0
B32: =B31+1 -> 46069 | C32: =SUMIFS(TARGET!E:E,TARGET!D:D,B32) -> 4464285.7 | D32: =C32/$D$13 -> 6.8681319 | E32: =SUMIFS(ZALO!C:C,ZALO!A:A,B32) -> 0 | F32: =SUMIFS(WEB!C:C,WEB!A:A,B32) -> 0 | G32: =SUMIFS(FANPAGE!C:C,FANPAGE!A:A,B32) -> 0 | H32: =SUMIFS(LAZADA!B:B,LAZADA!A:A,B32) -> 0 | I32: =SUMIFS('DS Shoppe (đã xác nhận)'!B:B,'DS Shoppe (đã xác nhận)'!A:A,B32) -> 926091 | J32: =SUMIFS(TIKTOK!B:B,TIKTOK!A:A,B32) -> 0 | K32: =SUM(E32:J32) -> 926091 | L32: =SUMIFS('DS Shoppe (đã xác nhận)'!C:C,'DS Shoppe (đã xác nhận)'!A:A,B32)+SUMIFS(LAZADA!E:E,LAZADA!A:A,B32)+SUMIFS(WEB!B:B,WEB!A:A,B32)+SUMIFS(ZALO!B:B,ZALO!A:A,B32)+SUMIFS(FANPAGE!B:B,FANPAGE!A:A,B32) -> 1 | M32: =IF(L32=0,"0",K32/L32) -> 926091 | N32: =K32/C32 -> 0.20744438 | O32: =L32/D32 -> 0.1456 | P32: =K32-C32 -> -3538194.7 | Q32: =L32-D32 -> -5.8681319 | R32: =SUMIFS('DS Shoppe (đã xác nhận)'!H:H,'DS Shoppe (đã xác nhận)'!A:A,B32) -> 0 | S32: =SUMIFS('DS Shoppe (đã xác nhận)'!I:I,'DS Shoppe (đã xác nhận)'!A:A,B32) -> 0 | T32: =SUMIFS('DS Shoppe (đã xác nhận)'!J:J,'DS Shoppe (đã xác nhận)'!A:A,B32) -> 0 | U32: =SUMIFS('DS Shoppe (đã xác nhận)'!K:K,'DS Shoppe (đã xác nhận)'!A:A,B32) -> 0
B33: =B32+1 -> 46070 | C33: =SUMIFS(TARGET!E:E,TARGET!D:D,B33) -> 4464285.7 | D33: =C33/$D$13 -> 6.8681319 | E33: =SUMIFS(ZALO!C:C,ZALO!A:A,B33) -> 0 | F33: =SUMIFS(WEB!C:C,WEB!A:A,B33) -> 0 | G33: =SUMIFS(FANPAGE!C:C,FANPAGE!A:A,B33) -> 0 | H33: =SUMIFS(LAZADA!B:B,LAZADA!A:A,B33) -> 0 | I33: =SUMIFS('DS Shoppe (đã xác nhận)'!B:B,'DS Shoppe (đã xác nhận)'!A:A,B33) -> 0 | J33: =SUMIFS(TIKTOK!B:B,TIKTOK!A:A,B33) -> 0 | K33: =SUM(E33:J33) -> 0 | L33: =SUMIFS('DS Shoppe (đã xác nhận)'!C:C,'DS Shoppe (đã xác nhận)'!A:A,B33)+SUMIFS(LAZADA!E:E,LAZADA!A:A,B33)+SUMIFS(WEB!B:B,WEB!A:A,B33)+SUMIFS(ZALO!B:B,ZALO!A:A,B33)+SUMIFS(FANPAGE!B:B,FANPAGE!A:A,B33) -> 0 | M33: =IF(L33=0,"0",K33/L33) -> 0 | N33: =K33/C33 -> 0 | O33: =L33/D33 -> 0 | P33: =K33-C33 -> -4464285.7 | Q33: =L33-D33 -> -6.8681319 | R33: =SUMIFS('DS Shoppe (đã xác nhận)'!H:H,'DS Shoppe (đã xác nhận)'!A:A,B33) -> 0 | S33: =SUMIFS('DS Shoppe (đã xác nhận)'!I:I,'DS Shoppe (đã xác nhận)'!A:A,B33) -> 0 | T33: =SUMIFS('DS Shoppe (đã xác nhận)'!J:J,'DS Shoppe (đã xác nhận)'!A:A,B33) -> 0 | U33: =SUMIFS('DS Shoppe (đã xác nhận)'!K:K,'DS Shoppe (đã xác nhận)'!A:A,B33) -> 0
B34: =B33+1 -> 46071 | C34: =SUMIFS(TARGET!E:E,TARGET!D:D,B34) -> 4464285.7 | D34: =C34/$D$13 -> 6.8681319 | E34: =SUMIFS(ZALO!C:C,ZALO!A:A,B34) -> 0 | F34: =SUMIFS(WEB!C:C,WEB!A:A,B34) -> 0 | G34: =SUMIFS(FANPAGE!C:C,FANPAGE!A:A,B34) -> 0 | H34: =SUMIFS(LAZADA!B:B,LAZADA!A:A,B34) -> 0 | I34: =SUMIFS('DS Shoppe (đã xác nhận)'!B:B,'DS Shoppe (đã xác nhận)'!A:A,B34) -> 977061 | J34: =SUMIFS(TIKTOK!B:B,TIKTOK!A:A,B34) -> 0 | K34: =SUM(E34:J34) -> 977061 | L34: =SUMIFS('DS Shoppe (đã xác nhận)'!C:C,'DS Shoppe (đã xác nhận)'!A:A,B34)+SUMIFS(LAZADA!E:E,LAZADA!A:A,B34)+SUMIFS(WEB!B:B,WEB!A:A,B34)+SUMIFS(ZALO!B:B,ZALO!A:A,B34)+SUMIFS(FANPAGE!B:B,FANPAGE!A:A,B34) -> 2 | M34: =IF(L34=0,"0",K34/L34) -> 488530.5 | N34: =K34/C34 -> 0.21886166 | O34: =L34/D34 -> 0.2912 | P34: =K34-C34 -> -3487224.7 | Q34: =L34-D34 -> -4.8681319 | R34: =SUMIFS('DS Shoppe (đã xác nhận)'!H:H,'DS Shoppe (đã xác nhận)'!A:A,B34) -> 0 | S34: =SUMIFS('DS Shoppe (đã xác nhận)'!I:I,'DS Shoppe (đã xác nhận)'!A:A,B34) -> 0 | T34: =SUMIFS('DS Shoppe (đã xác nhận)'!J:J,'DS Shoppe (đã xác nhận)'!A:A,B34) -> 0 | U34: =SUMIFS('DS Shoppe (đã xác nhận)'!K:K,'DS Shoppe (đã xác nhận)'!A:A,B34) -> 0
B35: =B34+1 -> 46072 | C35: =SUMIFS(TARGET!E:E,TARGET!D:D,B35) -> 4464285.7 | D35: =C35/$D$13 -> 6.8681319 | E35: =SUMIFS(ZALO!C:C,ZALO!A:A,B35) -> 0 | F35: =SUMIFS(WEB!C:C,WEB!A:A,B35) -> 0 | G35: =SUMIFS(FANPAGE!C:C,FANPAGE!A:A,B35) -> 0 | H35: =SUMIFS(LAZADA!B:B,LAZADA!A:A,B35) -> 0 | I35: =SUMIFS('DS Shoppe (đã xác nhận)'!B:B,'DS Shoppe (đã xác nhận)'!A:A,B35) -> 1009800 | J35: =SUMIFS(TIKTOK!B:B,TIKTOK!A:A,B35) -> 0 | K35: =SUM(E35:J35) -> 1009800 | L35: =SUMIFS('DS Shoppe (đã xác nhận)'!C:C,'DS Shoppe (đã xác nhận)'!A:A,B35)+SUMIFS(LAZADA!E:E,LAZADA!A:A,B35)+SUMIFS(WEB!B:B,WEB!A:A,B35)+SUMIFS(ZALO!B:B,ZALO!A:A,B35)+SUMIFS(FANPAGE!B:B,FANPAGE!A:A,B35) -> 1 | M35: =IF(L35=0,"0",K35/L35) -> 1009800 | N35: =K35/C35 -> 0.2261952 | O35: =L35/D35 -> 0.1456 | P35: =K35-C35 -> -3454485.7 | Q35: =L35-D35 -> -5.8681319 | R35: =SUMIFS('DS Shoppe (đã xác nhận)'!H:H,'DS Shoppe (đã xác nhận)'!A:A,B35) -> 2 | S35: =SUMIFS('DS Shoppe (đã xác nhận)'!I:I,'DS Shoppe (đã xác nhận)'!A:A,B35) -> 1408252 | T35: =SUMIFS('DS Shoppe (đã xác nhận)'!J:J,'DS Shoppe (đã xác nhận)'!A:A,B35) -> 0 | U35: =SUMIFS('DS Shoppe (đã xác nhận)'!K:K,'DS Shoppe (đã xác nhận)'!A:A,B35) -> 0
B36: =B35+1 -> 46073 | C36: =SUMIFS(TARGET!E:E,TARGET!D:D,B36) -> 4464285.7 | D36: =C36/$D$13 -> 6.8681319 | E36: =SUMIFS(ZALO!C:C,ZALO!A:A,B36) -> 0 | F36: =SUMIFS(WEB!C:C,WEB!A:A,B36) -> 0 | G36: =SUMIFS(FANPAGE!C:C,FANPAGE!A:A,B36) -> 0 | H36: =SUMIFS(LAZADA!B:B,LAZADA!A:A,B36) -> 0 | I36: =SUMIFS('DS Shoppe (đã xác nhận)'!B:B,'DS Shoppe (đã xác nhận)'!A:A,B36) -> 1009800 | J36: =SUMIFS(TIKTOK!B:B,TIKTOK!A:A,B36) -> 0 | K36: =SUM(E36:J36) -> 1009800 | L36: =SUMIFS('DS Shoppe (đã xác nhận)'!C:C,'DS Shoppe (đã xác nhận)'!A:A,B36)+SUMIFS(LAZADA!E:E,LAZADA!A:A,B36)+SUMIFS(WEB!B:B,WEB!A:A,B36)+SUMIFS(ZALO!B:B,ZALO!A:A,B36)+SUMIFS(FANPAGE!B:B,FANPAGE!A:A,B36) -> 1 | M36: =IF(L36=0,"0",K36/L36) -> 1009800 | N36: =K36/C36 -> 0.2261952 | O36: =L36/D36 -> 0.1456 | P36: =K36-C36 -> -3454485.7 | Q36: =L36-D36 -> -5.8681319 | R36: =SUMIFS('DS Shoppe (đã xác nhận)'!H:H,'DS Shoppe (đã xác nhận)'!A:A,B36) -> 2 | S36: =SUMIFS('DS Shoppe (đã xác nhận)'!I:I,'DS Shoppe (đã xác nhận)'!A:A,B36) -> 2778273 | T36: =SUMIFS('DS Shoppe (đã xác nhận)'!J:J,'DS Shoppe (đã xác nhận)'!A:A,B36) -> 0 | U36: =SUMIFS('DS Shoppe (đã xác nhận)'!K:K,'DS Shoppe (đã xác nhận)'!A:A,B36) -> 0
B37: =B36+1 -> 46074 | C37: =SUMIFS(TARGET!E:E,TARGET!D:D,B37) -> 4464285.7 | D37: =C37/$D$13 -> 6.8681319 | E37: =SUMIFS(ZALO!C:C,ZALO!A:A,B37) -> 0 | F37: =SUMIFS(WEB!C:C,WEB!A:A,B37) -> 0 | G37: =SUMIFS(FANPAGE!C:C,FANPAGE!A:A,B37) -> 0 | H37: =SUMIFS(LAZADA!B:B,LAZADA!A:A,B37) -> 0 | I37: =SUMIFS('DS Shoppe (đã xác nhận)'!B:B,'DS Shoppe (đã xác nhận)'!A:A,B37) -> 1852182 | J37: =SUMIFS(TIKTOK!B:B,TIKTOK!A:A,B37) -> 0 | K37: =SUM(E37:J37) -> 1852182 | L37: =SUMIFS('DS Shoppe (đã xác nhận)'!C:C,'DS Shoppe (đã xác nhận)'!A:A,B37)+SUMIFS(LAZADA!E:E,LAZADA!A:A,B37)+SUMIFS(WEB!B:B,WEB!A:A,B37)+SUMIFS(ZALO!B:B,ZALO!A:A,B37)+SUMIFS(FANPAGE!B:B,FANPAGE!A:A,B37) -> 1 | M37: =IF(L37=0,"0",K37/L37) -> 1852182 | N37: =K37/C37 -> 0.41488877 | O37: =L37/D37 -> 0.1456 | P37: =K37-C37 -> -2612103.7 | Q37: =L37-D37 -> -5.8681319 | R37: =SUMIFS('DS Shoppe (đã xác nhận)'!H:H,'DS Shoppe (đã xác nhận)'!A:A,B37) -> 0 | S37: =SUMIFS('DS Shoppe (đã xác nhận)'!I:I,'DS Shoppe (đã xác nhận)'!A:A,B37) -> 0 | T37: =SUMIFS('DS Shoppe (đã xác nhận)'!J:J,'DS Shoppe (đã xác nhận)'!A:A,B37) -> 0 | U37: =SUMIFS('DS Shoppe (đã xác nhận)'!K:K,'DS Shoppe (đã xác nhận)'!A:A,B37) -> 0
B38: =B37+1 -> 46075 | C38: =SUMIFS(TARGET!E:E,TARGET!D:D,B38) -> 4464285.7 | D38: =C38/$D$13 -> 6.8681319 | E38: =SUMIFS(ZALO!C:C,ZALO!A:A,B38) -> 0 | F38: =SUMIFS(WEB!C:C,WEB!A:A,B38) -> 0 | G38: =SUMIFS(FANPAGE!C:C,FANPAGE!A:A,B38) -> 0 | H38: =SUMIFS(LAZADA!B:B,LAZADA!A:A,B38) -> 0 | I38: =SUMIFS('DS Shoppe (đã xác nhận)'!B:B,'DS Shoppe (đã xác nhận)'!A:A,B38) -> 2261140 | J38: =SUMIFS(TIKTOK!B:B,TIKTOK!A:A,B38) -> 0 | K38: =SUM(E38:J38) -> 2261140 | L38: =SUMIFS('DS Shoppe (đã xác nhận)'!C:C,'DS Shoppe (đã xác nhận)'!A:A,B38)+SUMIFS(LAZADA!E:E,LAZADA!A:A,B38)+SUMIFS(WEB!B:B,WEB!A:A,B38)+SUMIFS(ZALO!B:B,ZALO!A:A,B38)+SUMIFS(FANPAGE!B:B,FANPAGE!A:A,B38) -> 3 | M38: =IF(L38=0,"0",K38/L38) -> 753713.33 | N38: =K38/C38 -> 0.50649536 | O38: =L38/D38 -> 0.4368 | P38: =K38-C38 -> -2203145.7 | Q38: =L38-D38 -> -3.8681319 | R38: =SUMIFS('DS Shoppe (đã xác nhận)'!H:H,'DS Shoppe (đã xác nhận)'!A:A,B38) -> 0 | S38: =SUMIFS('DS Shoppe (đã xác nhận)'!I:I,'DS Shoppe (đã xác nhận)'!A:A,B38) -> 0 | T38: =SUMIFS('DS Shoppe (đã xác nhận)'!J:J,'DS Shoppe (đã xác nhận)'!A:A,B38) -> 0 | U38: =SUMIFS('DS Shoppe (đã xác nhận)'!K:K,'DS Shoppe (đã xác nhận)'!A:A,B38) -> 0
B39: =B38+1 -> 46076 | C39: =SUMIFS(TARGET!E:E,TARGET!D:D,B39) -> 4464285.7 | D39: =C39/$D$13 -> 6.8681319 | E39: =SUMIFS(ZALO!C:C,ZALO!A:A,B39) -> 829000 | F39: =SUMIFS(WEB!C:C,WEB!A:A,B39) -> 0 | G39: =SUMIFS(FANPAGE!C:C,FANPAGE!A:A,B39) -> 0 | H39: =SUMIFS(LAZADA!B:B,LAZADA!A:A,B39) -> 0 | I39: =SUMIFS('DS Shoppe (đã xác nhận)'!B:B,'DS Shoppe (đã xác nhận)'!A:A,B39) -> 4351400 | J39: =SUMIFS(TIKTOK!B:B,TIKTOK!A:A,B39) -> 0 | K39: =SUM(E39:J39) -> 5180400 | L39: =SUMIFS('DS Shoppe (đã xác nhận)'!C:C,'DS Shoppe (đã xác nhận)'!A:A,B39)+SUMIFS(LAZADA!E:E,LAZADA!A:A,B39)+SUMIFS(WEB!B:B,WEB!A:A,B39)+SUMIFS(ZALO!B:B,ZALO!A:A,B39)+SUMIFS(FANPAGE!B:B,FANPAGE!A:A,B39) -> 5 | M39: =IF(L39=0,"0",K39/L39) -> 1036080 | N39: =K39/C39 -> 1.1604096 | O39: =L39/D39 -> 0.728 | P39: =K39-C39 -> 716114.29 | Q39: =L39-D39 -> -1.8681319 | R39: =SUMIFS('DS Shoppe (đã xác nhận)'!H:H,'DS Shoppe (đã xác nhận)'!A:A,B39) -> 1 | S39: =SUMIFS('DS Shoppe (đã xác nhận)'!I:I,'DS Shoppe (đã xác nhận)'!A:A,B39) -> 2778276 | T39: =SUMIFS('DS Shoppe (đã xác nhận)'!J:J,'DS Shoppe (đã xác nhận)'!A:A,B39) -> 0 | U39: =SUMIFS('DS Shoppe (đã xác nhận)'!K:K,'DS Shoppe (đã xác nhận)'!A:A,B39) -> 0
... B44: =B43+1 -> 46081 | C44: =SUMIFS(TARGET!E:E,TARGET!D:D,B44) -> 4464285.7 | D44: =C44/$D$13 -> 6.8681319 | E44: =SUMIFS(ZALO!C:C,ZALO!A:A,B44) -> 0 | F44: =SUMIFS(WEB!C:C,WEB!A:A,B44) -> 0 | G44: =SUMIFS(FANPAGE!C:C,FANPAGE!A:A,B44) -> 0 | H44: =SUMIFS(LAZADA!B:B,LAZADA!A:A,B44) -> 0 | I44: =SUMIFS('DS Shoppe (đã xác nhận)'!B:B,'DS Shoppe (đã xác nhận)'!A:A,B44) -> 1836900 | J44: =SUMIFS(TIKTOK!B:B,TIKTOK!A:A,B44) -> 0 | K44: =SUM(E44:J44) -> 1836900 | L44: =SUMIFS('DS Shoppe (đã xác nhận)'!C:C,'DS Shoppe (đã xác nhận)'!A:A,B44)+SUMIFS(LAZADA!E:E,LAZADA!A:A,B44)+SUMIFS(WEB!B:B,WEB!A:A,B44)+SUMIFS(ZALO!B:B,ZALO!A:A,B44)+SUMIFS(FANPAGE!B:B,FANPAGE!A:A,B44) -> 1 | M44: =IF(L44=0,"0",K44/L44) -> 1836900 | N44: =K44/C44 -> 0.4114656 | O44: =L44/D44 -> 0.1456 | P44: =K44-C44 -> -2627385.7 | Q44: =L44-D44 -> -5.8681319 | R44: =SUMIFS('DS Shoppe (đã xác nhận)'!H:H,'DS Shoppe (đã xác nhận)'!A:A,B44) -> 0 | S44: =SUMIFS('DS Shoppe (đã xác nhận)'!I:I,'DS Shoppe (đã xác nhận)'!A:A,B44) -> 0 | T44: =SUMIFS('DS Shoppe (đã xác nhận)'!J:J,'DS Shoppe (đã xác nhận)'!A:A,B44) -> 0 | U44: =SUMIFS('DS Shoppe (đã xác nhận)'!K:K,'DS Shoppe (đã xác nhận)'!A:A,B44) -> 0

Sheet ADS SHOPEE
A1: Báo cáo quảng cáo trả theo CPC - Shopee Việt Nam
A2: Tên đăng nhập | B2: healthybeauty.officialstore
A3: Tên gian hàng | B3: DƯỢC PHẨM HEALTHY BEAUTY
A4: Mã Người bán | B4: 227240948
A5: Thời gian tạo báo cáo | B5: 45843.419
A6: Khoảng thời gian | B6: 01/06/2025 - 30/06/2025
W7: =SUM(W9:W26) -> 19452000 | Y7: =SUM(Y9:Y26) -> 3427031
A8: Thứ tự | B8: Tên quảng cáo | C8: Trạng thái | D8: Loại quảng cáo | E8: Mã sản phẩm | F8: Cài đặt Đối tượng | G8: Nội dung quảng cáo | H8: Phương thức đấu thầu | I8: Vị trí | J8: Ngày bắt đầu | K8: Ngày kết thúc | L8: Số lượt xem | M8: Số lượt click | N8: Tỷ Lệ Click | O8: Lượt chuyển đổi | P8: Lượt chuyển đổi trực tiếp | Q8: Tỷ lệ chuyển đổi | R8: Tỷ lệ chuyển đổi trực tiếp | S8: Chi phí cho mỗi lượt chuyển đổi | T8: Chi phí cho mỗi lượt chuyển đổi trực tiếp | U8: Sản phẩm đã bán | V8: Sản phẩm đã bán trực tiếp | W8: GMV | X8: GMV trực tiếp | Y8: Chi phí | Z8: ROAS | AA8: ROAS trực tiếp | AB8: ACOS | AC8: ACOS trực tiếp | AD8: Lượt xem Sản phẩm | AE8: Lượt clicks Sản phẩm | AF8: Tỷ lệ Click Sản phẩm | AG8: THÁNG
A9: 1 | B9: Auto shop | C9: Đang diễn ra | D9: Quảng cáo Shop | E9: - | F9: - | G9: Mặc định | H9: Giá thầu Tự động | I9: - | J9: 45784 | K9: Không giới hạn | L9: 6833 | M9: 1230 | N9: 18.00% | O9: 8 | P9: 6 | Q9: 0.65% | R9: 0.49% | S9: 91377.65 | T9: 121836.9 | U9: 8 | V9: 6 | W9: 5848000 | X9: 5246000 | Y9: 731021 | Z9: 8 | AA9: 7.18 | AB9: 12.50% | AC9: 13.93% | AD9: 20786 | AE9: 137 | AF9: 0.66% | AG9: 6
A10: 2 | B10: Viên Uống Giúp Chống Nắng Trắng Da Mờ Nám HB GLUTA WHITE + [4] | C10: Đang diễn ra | D10: Quảng cáo Sản phẩm | E10: 8782633181 | F10: - | G10: Tối ưu Sáng tạo đã được tắt | H10: Tối đa Doanh thu Tùy chỉnh ROAS | I10: Tất cả | J10: 45660 | K10: Không giới hạn | L10: 37018 | M10: 162 | N10: 0.44% | O10: 2 | P10: 2 | Q10: 1.23% | R10: 1.23% | S10: 438594.1 | T10: 438594.1 | U10: 2 | V10: 2 | W10: 2970000 | X10: 2970000 | Y10: 877188 | Z10: 3.39 | AA10: 3.39 | AB10: 29.53% | AC10: 29.53% | AD10: - | AE10: - | AF10: - | AG10: 6
A11: 3 | B11: Viên Uống Đông Trùng Hạ Thảo Bồi Bổ Khí Huyết HB CORDY EXTRACT [4] | C11: Đang diễn ra | D11: Quảng cáo Sản phẩm | E11: 5219966803 | F11: - | G11: Tối ưu Sáng tạo đã được bật | H11: Tối đa Doanh thu Tùy chỉnh ROAS | I11: Tất cả | J11: 45660 | K11: Không giới hạn | L11: 9756 | M11: 52 | N11: 0.53% | O11: 1 | P11: 1 | Q11: 1.92% | R11: 1.92% | S11: 277324.8 | T11: 277324.8 | U11: 1 | V11: 1 | W11: 731000 | X11: 731000 | Y11: 277325 | Z11: 2.64 | AA11: 2.64 | AB11: 37.94% | AC11: 37.94% | AD11: - | AE11: - | AF11: - | AG11: 6
A12: 4 | B12: Viên uống giúp tái tạo và nuôi dưỡng mô sụn - HB Glucollagen 7 in 1 [6] | C12: Đang diễn ra | D12: Quảng cáo Sản phẩm | E12: 25666719442 | F12: - | G12: Tối ưu Sáng tạo đã được tắt | H12: Tối đa Doanh thu Tùy chỉnh ROAS | I12: Tất cả | J12: 45833 | K12: Không giới hạn | L12: 4525 | M12: 43 | N12: 0.95% | O12: 4 | P12: 4 | Q12: 9.30% | R12: 9.30% | S12: 52036.55 | T12: 52036.55 | U12: 4 | V12: 4 | W12: 2430000 | X12: 2430000 | Y12: 208146 | Z12: 11.67 | AA12: 11.67 | AB12: 8.57% | AC12: 8.57% | AD12: - | AE12: - | AF12: - | AG12: 6
A13: 5 | B13: Viên uống HB Glucosamine 3 in 1 60 viên - 200 viên [5] | C13: Đang diễn ra | D13: Quảng cáo Sản phẩm | E13: 24867481840 | F13: Đối tượng Tự động | G13: Tối ưu Sáng tạo đã được tắt | H13: Giá thầu Thủ công | I13: Tìm kiếm | J13: 45785 | K13: Không giới hạn | L13: 1600 | M13: 25 | N13: 1.56% | O13: 1 | P13: 1 | Q13: 4.00% | R13: 4.00% | S13: 240000 | T13: 240000 | U13: 1 | V13: 1 | W13: 286000 | X13: 286000 | Y13: 240000 | Z13: 1.19 | AA13: 1.19 | AB13: 83.92% | AC13: 83.92% | AD13: - | AE13: - | AF13: - | AG13: 6
A14: 6 | B14: Viên uống HB GutCare (30 - 60 viên) hỗ trợ giảm triệu chứng đau khớp | C14: Đang diễn ra | D14: Quảng cáo Sản phẩm | E14: 22657955668 | F14: - | G14: Tối ưu Sáng tạo đã được tắt | H14: Tối đa Doanh thu Tùy chỉnh ROAS | I14: Tất cả | J14: 45660 | K14: Không giới hạn | L14: 1320 | M14: 9 | N14: 0.68% | O14: 0 | P14: 0 | Q14: 0.00% | R14: 0.00% | S14: 0 | T14: 0 | U14: 0 | V14: 0 | W14: 0 | X14: 0 | Y14: 1235 | Z14: 0 | AA14: 0 | AB14: 0.00% | AC14: 0.00% | AD14: - | AE14: - | AF14: - | AG14: 6
A15: 7 | B15: Viên Uống Giảm Gãy Rụng và Đen Tóc HB Black Hair Healthy Beauty [11] | C15: Đang diễn ra | D15: Quảng cáo Sản phẩm | E15: 5519393895 | F15: Đối tượng Tự động | G15: Tối ưu Sáng tạo đã được tắt | H15: Giá thầu Thủ công | I15: Tìm kiếm | J15: 45821 | K15: Không giới hạn | L15: 981 | M15: 19 | N15: 1.94% | O15: 2 | P15: 1 | Q15: 10.53% | R15: 5.26% | S15: 37328.79 | T15: 74657.57 | U15: 2 | V15: 1 | W15: 1246000 | X15: 856000 | Y15: 74658 | Z15: 16.69 | AA15: 11.47 | AB15: 5.99% | AC15: 8.72% | AD15: - | AE15: - | AF15: - | AG15: 6
A16: 8 | B16: Khẩu Trang Y Tế Kháng Khuẩn HB Medical Mask Cao Cấp Healthy Beauty 1 Hộp 50 cái [5] | C16: Đang diễn ra | D16: Quảng cáo Sản phẩm | E16: 5158911395 | F16: - | G16: Tối ưu Sáng tạo đã được bật | H16: Tối đa Doanh thu Tùy chỉnh ROAS | I16: Tất cả | J16: 45831 | K16: Không giới hạn | L16: 778 | M16: 24 | N16: 3.08% | O16: 0 | P16: 0 | Q16: 0.00% | R16: 0.00% | S16: 0 | T16: 0 | U16: 0 | V16: 0 | W16: 0 | X16: 0 | Y16: 45848 | Z16: 0 | AA16: 0 | AB16: 0.00% | AC16: 0.00% | AD16: - | AE16: - | AF16: - | AG16: 6
A17: 9 | B17: Viên Uống Giảm Gãy Rụng và Đen Tóc HB Black Hair Healthy Beauty [10] | C17: Đang diễn ra | D17: Quảng cáo Sản phẩm | E17: 5519393895 | F17: Đối tượng Tự động | G17: Tối ưu Sáng tạo đã được bật | H17: Giá thầu Thủ công | I17: Tìm kiếm | J17: 45821 | K17: Không giới hạn | L17: 506 | M17: 7 | N17: 1.38% | O17: 0 | P17: 0 | Q17: 0.00% | R17: 0.00% | S17: 0 | T17: 0 | U17: 0 | V17: 0 | W17: 0 | X17: 0 | Y17: 27852 | Z17: 0 | AA17: 0 | AB17: 0.00% | AC17: 0.00% | AD17: - | AE17: - | AF17: - | AG17: 6
A18: 10 | B18: Viên Uống Giảm Gãy Rụng và Đen Tóc HB Black Hair Healthy Beauty [9] | C18: Tạm dừng | D18: Quảng cáo Sản phẩm | E18: 5519393895 | F18: - | G18: Tối ưu Sáng tạo đã được bật | H18: Tối đa Doanh thu Tùy chỉnh ROAS | I18: Tất cả | J18: 45813 | K18: Không giới hạn | L18: 14810 | M18: 70 | N18: 0.47% | O18: 0 | P18: 0 | Q18: 0.00% | R18: 0.00% | S18: 0 | T18: 0 | U18: 0 | V18: 0 | W18: 0 | X18: 0 | Y18: 338540 | Z18: 0 | AA18: 0 | AB18: 0.00% | AC18: 0.00% | AD18: - | AE18: - | AF18: - | AG18: 6
A19: 11 | B19: Viên uống giúp tái tạo và nuôi dưỡng mô sụn - HB Glucollagen 7 in 1 [3] | C19: Tạm dừng | D19: Quảng cáo Sản phẩm | E19: 25666719442 | F19: - | G19: Tối ưu Sáng tạo đã được tắt | H19: Tối đa Doanh thu Tùy chỉnh ROAS | I19: Tất cả | J19: 45660 | K19: Không giới hạn | L19: 14075 | M19: 72 | N19: 0.51% | O19: 2 | P19: 0 | Q19: 2.78% | R19: 0.00% | S19: 204723.2 | T19: 0 | U19: 2 | V19: 0 | W19: 676000 | X19: 0 | Y19: 409446 | Z19: 1.65 | AA19: 0 | AB19: 60.57% | AC19: 0.00% | AD19: - | AE19: - | AF19: - | AG19: 6
A20: 12 | B20: Viên uống giúp tái tạo và nuôi dưỡng mô sụn - HB Glucollagen 7 in 1 [5] | C20: Tạm dừng | D20: Quảng cáo Sản phẩm | E20: 25666719442 | F20: Đối tượng Tự động | G20: Tối ưu Sáng tạo đã được tắt | H20: Giá thầu Thủ công | I20: Tìm kiếm | J20: 45821 | K20: Không giới hạn | L20: 1755 | M20: 38 | N20: 2.17% | O20: 6 | P20: 6 | Q20: 15.79% | R20: 15.79% | S20: 26858.19 | T20: 26858.19 | U20: 7 | V20: 7 | W20: 5265000 | X20: 5265000 | Y20: 161149 | Z20: 32.67 | AA20: 32.67 | AB20: 3.06% | AC20: 3.06% | AD20: - | AE20: - | AF20: - | AG20: 6
A21: 13 | B21: Viên uống giúp tái tạo và nuôi dưỡng mô sụn - HB Glucollagen 7 in 1 [4] | C21: Tạm dừng | D21: Quảng cáo Sản phẩm | E21: 25666719442 | F21: Đối tượng Tự động | G21: Tối ưu Sáng tạo đã được tắt | H21: Giá thầu Thủ công | I21: Tìm kiếm | J21: 45821 | K21: Không giới hạn | L21: 276 | M21: 3 | N21: 1.09% | O21: 0 | P21: 0 | Q21: 0.00% | R21: 0.00% | S21: 0 | T21: 0 | U21: 0 | V21: 0 | W21: 0 | X21: 0 | Y21: 15000 | Z21: 0 | AA21: 0 | AB21: 0.00% | AC21: 0.00% | AD21: - | AE21: - | AF21: - | AG21: 6
A22: 14 | B22: Viên uống HB Glucosamine 3 in 1 60 viên - 200 viên [6] | C22: Tạm dừng | D22: Quảng cáo Sản phẩm | E22: 24867481840 | F22: - | G22: Tối ưu Sáng tạo đã được bật | H22: Tối đa Doanh thu Tối ưu ROAS bởi Hệ thống | I22: Tất cả | J22: 45812 | K22: Không giới hạn | L22: 46 | M22: 0 | N22: 0.00% | O22: 0 | P22: 0 | Q22: 0.00% | R22: 0.00% | S22: 0 | T22: 0 | U22: 0 | V22: 0 | W22: 0 | X22: 0 | Y22: 0 | Z22: 0 | AA22: 0 | AB22: 0.00% | AC22: 0.00% | AD22: - | AE22: - | AF22: - | AG22: 6
A23: 15 | B23: Viên uống HB Arginmilk Plus 60 viên [4] | C23: Tạm dừng | D23: Quảng cáo Sản phẩm | E23: 24867724627 | F23: Đối tượng Tự động | G23: Tối ưu Sáng tạo đã được tắt | H23: Giá thầu Thủ công | I23: Tìm kiếm | J23: 45785 | K23: Không giới hạn | L23: 10 | M23: 1 | N23: 10.00% | O23: 0 | P23: 0 | Q23: 0.00% | R23: 0.00% | S23: 0 | T23: 0 | U23: 0 | V23: 0 | W23: 0 | X23: 0 | Y23: 19623 | Z23: 0 | AA23: 0 | AB23: 0.00% | AC23: 0.00% | AD23: - | AE23: - | AF23: - | AG23: 6
A24: 16 | B24: Khẩu Trang Y Tế Kháng Khuẩn HB Medical Mask Cao Cấp Healthy Beauty 1 Hộp 50 cái [4] | C24: Tạm dừng | D24: Quảng cáo Sản phẩm | E24: 5158911395 | F24: Đối tượng Tự động | G24: Tối ưu Sáng tạo đã được tắt | H24: Giá thầu Thủ công | I24: Tìm kiếm | J24: 45785 | K24: Không giới hạn | L24: 8 | M24: 0 | N24: 0.00% | O24: 0 | P24: 0 | Q24: 0.00% | R24: 0.00% | S24: 0 | T24: 0 | U24: 0 | V24: 0 | W24: 0 | X24: 0 | Y24: 0 | Z24: 0 | AA24: 0 | AB24: 0.00% | AC24: 0.00% | AD24: - | AE24: - | AF24: - | AG24: 6
A25: 17 | B25: Viên Uống Healthy Beauty Omega 3,6,9 Từ Dầu Hạt Lanh 100 Viên & 200 Viên [3] | C25: Tạm dừng | D25: Quảng cáo Sản phẩm | E25: 3127515400 | F25: - | G25: Tối ưu Sáng tạo đã được tắt | H25: Tối đa Doanh thu Tối ưu ROAS bởi Hệ thống | I25: Tất cả | J25: 45729 | K25: Không giới hạn | L25: 5 | M25: 0 | N25: 0.00% | O25: 0 | P25: 0 | Q25: 0.00% | R25: 0.00% | S25: 0 | T25: 0 | U25: 0 | V25: 0 | W25: 0 | X25: 0 | Y25: 0 | Z25: 0 | AA25: 0 | AB25: 0.00% | AC25: 0.00% | AD25: - | AE25: - | AF25: - | AG25: 6
A26: 18 | B26: Viên Uống Giảm Gãy Rụng và Đen Tóc HB Black Hair Healthy Beauty [8] | C26: Tạm dừng | D26: Quảng cáo Sản phẩm | E26: 5519393895 | F26: Đối tượng Tự động | G26: Tối ưu Sáng tạo đã được bật | H26: Giá thầu Thủ công | I26: Tìm kiếm | J26: 45785 | K26: Không giới hạn | L26: 1 | M26: 0 | N26: 0.00% | O26: 0 | P26: 0 | Q26: 0.00% | R26: 0.00% | S26: 0 | T26: 0 | U26: 0 | V26: 0 | W26: 0 | X26: 0 | Y26: 0 | Z26: 0 | AA26: 0 | AB26: 0.00% | AC26: 0.00% | AD26: - | AE26: - | AF26: - | AG26: 6
A32: Báo cáo quảng cáo trả theo CPC - Shopee Việt Nam
A33: Tên đăng nhập | B33: healthybeauty.officialstore
A34: Tên gian hàng | B34: DƯỢC PHẨM HEALTHY BEAUTY
A35: Mã Người bán | B35: 227240948
A36: Thời gian tạo báo cáo | B36: 45869.374
A37: Khoảng thời gian | B37: 01/07/2025 - 31/07/2025
W38: =SUM(W40:W51) -> 24481980 | Y38: =SUM(Y40:Y51) -> 5821526
A39: Thứ tự | B39: Tên quảng cáo | C39: Trạng thái | D39: Loại quảng cáo | E39: Mã sản phẩm | F39: Cài đặt Đối tượng | G39: Nội dung quảng cáo | H39: Phương thức đấu thầu | I39: Vị trí | J39: Ngày bắt đầu | K39: Ngày kết thúc | L39: Số lượt xem | M39: Số lượt click | N39: Tỷ Lệ Click | O39: Lượt chuyển đổi | P39: Lượt chuyển đổi trực tiếp | Q39: Tỷ lệ chuyển đổi | R39: Tỷ lệ chuyển đổi trực tiếp | S39: Chi phí cho mỗi lượt chuyển đổi | T39: Chi phí cho mỗi lượt chuyển đổi trực tiếp | U39: Sản phẩm đã bán | V39: Sản phẩm đã bán trực tiếp | W39: GMV | X39: GMV trực tiếp | Y39: Chi phí | Z39: ROAS | AA39: ROAS trực tiếp | AB39: ACOS | AC39: ACOS trực tiếp | AD39: Lượt xem Sản phẩm | AE39: Lượt clicks Sản phẩm | AF39: Tỷ lệ Click Sản phẩm | AG39: THÁNG
A40: 1 | B40: Auto shop | C40: Đang diễn ra | D40: Quảng cáo Shop | E40: - | F40: - | G40: Mặc định | H40: Giá thầu Tự động | I40: - | J40: 45784 | K40: Không giới hạn | L40: 7366 | M40: 1250 | N40: 16.97% | O40: 9 | P40: 9 | Q40: 0.72% | R40: 0.72% | S40: 118048.2 | T40: 118048.2 | U40: 10 | V40: 10 | W40: 5927080 | X40: 5927080 | Y40: 1062433 | Z40: 5.58 | AA40: 5.58 | AB40: 17.93% | AC40: 17.93% | AD40: 22518 | AE40: 141 | AF40: 0.63% | AG40: 7
A41: 2 | B41: Viên uống giúp tái tạo và nuôi dưỡng mô sụn - HB Glucollagen 7 in 1 [6] | C41: Đang diễn ra | D41: Quảng cáo Sản phẩm | E41: 25666719442 | F41: - | G41: Tối ưu Sáng tạo đã được tắt | H41: Tối đa Doanh thu Tùy chỉnh ROAS | I41: Tất cả | J41: 45833 | K41: Không giới hạn | L41: 27652 | M41: 273 | N41: 0.99% | O41: 8 | P41: 7 | Q41: 2.93% | R41: 2.56% | S41: 262211.7 | T41: 299670.5 | U41: 10 | V41: 9 | W41: 8911000 | X41: 8055000 | Y41: 2097693 | Z41: 4.25 | AA41: 3.84 | AB41: 23.54% | AC41: 26.04% | AD41: - | AE41: - | AF41: - | AG41: 7
A42: 3 | B42: Viên Uống Giúp Chống Nắng Trắng Da Mờ Nám HB GLUTA WHITE + [4] | C42: Đang diễn ra | D42: Quảng cáo Sản phẩm | E42: 8782633181 | F42: - | G42: Tối ưu Sáng tạo đã được tắt | H42: Tối đa Doanh thu Tùy chỉnh ROAS | I42: Tất cả | J42: 45660 | K42: Không giới hạn | L42: 9775 | M42: 51 | N42: 0.52% | O42: 1 | P42: 1 | Q42: 1.96% | R42: 1.96% | S42: 209051 | T42: 209051 | U42: 1 | V42: 1 | W42: 1485000 | X42: 1485000 | Y42: 209051 | Z42: 45664 | AA42: 45664 | AB42: 14.08% | AC42: 14.08% | AD42: - | AE42: - | AF42: - | AG42: 7
A43: 4 | B43: Viên Uống Giảm Gãy Rụng và Đen Tóc HB Black Hair Healthy Beauty [12] | C43: Đang diễn ra | D43: Quảng cáo Sản phẩm | E43: 5519393895 | F43: - | G43: Tối ưu Sáng tạo đã được tắt | H43: Tối đa Doanh thu Tùy chỉnh ROAS | I43: Tất cả | J43: 45849 | K43: Không giới hạn | L43: 9274 | M43: 131 | N43: 1.41% | O43: 3 | P43: 3 | Q43: 2.29% | R43: 2.29% | S43: 271978.8 | T43: 271978.8 | U43: 3 | V43: 3 | W43: 1693900 | X43: 1693900 | Y43: 815937 | Z43: 45871 | AA43: 45871 | AB43: 48.17% | AC43: 48.17% | AD43: - | AE43: - | AF43: - | AG43: 7
A44: 5 | B44: Viên uống HB GutCare (30 - 60 viên) hỗ trợ giảm triệu chứng đau khớp | C44: Đang diễn ra | D44: Quảng cáo Sản phẩm | E44: 22657955668 | F44: - | G44: Tối ưu Sáng tạo đã được tắt | H44: Tối đa Doanh thu Tùy chỉnh ROAS | I44: Tất cả | J44: 45660 | K44: Không giới hạn | L44: 7631 | M44: 68 | N44: 0.89% | O44: 3 | P44: 2 | Q44: 4.41% | R44: 2.94% | S44: 148959.1 | T44: 223438.7 | U44: 4 | V44: 2 | W44: 1904000 | X44: 1272000 | Y44: 446877 | Z44: 4.26 | AA44: 2.85 | AB44: 23.47% | AC44: 35.13% | AD44: - | AE44: - | AF44: - | AG44: 7
A45: 6 | B45: Khẩu Trang Y Tế Kháng Khuẩn HB Medical Mask Cao Cấp Healthy Beauty 1 Hộp 50 cái [5] | C45: Đang diễn ra | D45: Quảng cáo Sản phẩm | E45: 5158911395 | F45: - | G45: Tối ưu Sáng tạo đã được bật | H45: Tối đa Doanh thu Tùy chỉnh ROAS | I45: Tất cả | J45: 45831 | K45: Không giới hạn | L45: 4167 | M45: 92 | N45: 2.21% | O45: 8 | P45: 8 | Q45: 8.70% | R45: 8.70% | S45: 39475.6 | T45: 39475.6 | U45: 17 | V45: 17 | W45: 1020000 | X45: 1020000 | Y45: 315805 | Z45: 3.23 | AA45: 3.23 | AB45: 30.96% | AC45: 30.96% | AD45: - | AE45: - | AF45: - | AG45: 7
A46: 7 | B46: Viên uống HB Glucosamine 3 in 1 60 viên - 200 viên [7] | C46: Đang diễn ra | D46: Quảng cáo Sản phẩm | E46: 24867481840 | F46: - | G46: Tối ưu Sáng tạo đã được tắt | H46: Tối đa Doanh thu Tùy chỉnh ROAS | I46: Tất cả | J46: 45849 | K46: Không giới hạn | L46: 3354 | M46: 40 | N46: 1.19% | O46: 2 | P46: 1 | Q46: 5.00% | R46: 2.50% | S46: 69735.27 | T46: 139470.6 | U46: 2 | V46: 1 | W46: 1231000 | X46: 286000 | Y46: 139471 | Z46: 8.83 | AA46: 45779 | AB46: 11.33% | AC46: 48.77% | AD46: - | AE46: - | AF46: - | AG46: 7
A47: 8 | B47: Viên Uống Đông Trùng Hạ Thảo Bồi Bổ Khí Huyết HB CORDY EXTRACT [4] | C47: Đang diễn ra | D47: Quảng cáo Sản phẩm | E47: 5219966803 | F47: - | G47: Tối ưu Sáng tạo đã được bật | H47: Tối đa Doanh thu Tùy chỉnh ROAS | I47: Tất cả | J47: 45660 | K47: Không giới hạn | L47: 1176 | M47: 12 | N47: 1.02% | O47: 0 | P47: 0 | Q47: 0.00% | R47: 0.00% | S47: 0 | T47: 0 | U47: 0 | V47: 0 | W47: 0 | X47: 0 | Y47: 4592 | Z47: 0 | AA47: 0 | AB47: 0.00% | AC47: 0.00% | AD47: - | AE47: - | AF47: - | AG47: 7
A48: 9 | B48: Viên uống HB Glucosamine 3 in 1 60 viên - 200 viên [5] | C48: Tạm dừng | D48: Quảng cáo Sản phẩm | E48: 24867481840 | F48: Đối tượng Tự động | G48: Tối ưu Sáng tạo đã được tắt | H48: Giá thầu Thủ công | I48: Tìm kiếm | J48: 45785 | K48: Không giới hạn | L48: 3021 | M48: 50 | N48: 1.66% | O48: 5 | P48: 5 | Q48: 10.00% | R48: 10.00% | S48: 119320.5 | T48: 119320.5 | U48: 6 | V48: 6 | W48: 2310000 | X48: 2310000 | Y48: 596603 | Z48: 3.87 | AA48: 3.87 | AB48: 25.83% | AC48: 25.83% | AD48: - | AE48: - | AF48: - | AG48: 7
A49: 10 | B49: Viên Uống Giảm Gãy Rụng và Đen Tóc HB Black Hair Healthy Beauty [10] | C49: Tạm dừng | D49: Quảng cáo Sản phẩm | E49: 5519393895 | F49: Đối tượng Tự động | G49: Tối ưu Sáng tạo đã được bật | H49: Giá thầu Thủ công | I49: Tìm kiếm | J49: 45821 | K49: Không giới hạn | L49: 673 | M49: 15 | N49: 2.23% | O49: 0 | P49: 0 | Q49: 0.00% | R49: 0.00% | S49: 0 | T49: 0 | U49: 0 | V49: 0 | W49: 0 | X49: 0 | Y49: 69820 | Z49: 0 | AA49: 0 | AB49: 0.00% | AC49: 0.00% | AD49: - | AE49: - | AF49: - | AG49: 7
A50: 11 | B50: Viên Uống Giảm Gãy Rụng và Đen Tóc HB Black Hair Healthy Beauty [11] | C50: Tạm dừng | D50: Quảng cáo Sản phẩm | E50: 5519393895 | F50: Đối tượng Tự động | G50: Tối ưu Sáng tạo đã được tắt | H50: Giá thầu Thủ công | I50: Tìm kiếm | J50: 45821 | K50: Không giới hạn | L50: 467 | M50: 13 | N50: 2.78% | O50: 0 | P50: 0 | Q50: 0.00% | R50: 0.00% | S50: 0 | T50: 0 | U50: 0 | V50: 0 | W50: 0 | X50: 0 | Y50: 63244 | Z50: 0 | AA50: 0 | AB50: 0.00% | AC50: 0.00% | AD50: - | AE50: - | AF50: - | AG50: 7
A56: Báo cáo quảng cáo trả theo CPC - Shopee Việt Nam
A57: Tên đăng nhập | B57: healthybeauty.officialstore
A58: Tên gian hàng | B58: DƯỢC PHẨM HEALTHY BEAUTY
A59: Mã Người bán | B59: 227240948
A60: Thời gian tạo báo cáo | B60: 45903.358
A61: Khoảng thời gian | B61: 01/08/2025 - 31/08/2025
W62: =SUM(W64:W76) -> 24639954 | Y62: =SUM(Y64:Y76) -> 3368692
A63: Thứ tự | B63: Tên quảng cáo | C63: Trạng thái | D63: Loại quảng cáo | E63: Mã sản phẩm | F63: Cài đặt Đối tượng | G63: Nội dung quảng cáo | H63: Phương thức đấu thầu | I63: Vị trí | J63: Ngày bắt đầu | K63: Ngày kết thúc | L63: Số lượt xem | M63: Số lượt click | N63: Tỷ Lệ Click | O63: Lượt chuyển đổi | P63: Lượt chuyển đổi trực tiếp | Q63: Tỷ lệ chuyển đổi | R63: Tỷ lệ chuyển đổi trực tiếp | S63: Chi phí cho mỗi lượt chuyển đổi | T63: Chi phí cho mỗi lượt chuyển đổi trực tiếp | U63: Sản phẩm đã bán | V63: Sản phẩm đã bán trực tiếp | W63: GMV | X63: GMV trực tiếp | Y63: Chi phí | Z63: ROAS | AA63: ROAS trực tiếp | AB63: ACOS | AC63: ACOS trực tiếp | AD63: Lượt xem Sản phẩm | AE63: Lượt clicks Sản phẩm | AF63: Tỷ lệ Click Sản phẩm | AG63: THÁNG
A64: 1 | B64: Auto shop | C64: Đang diễn ra | D64: Quảng cáo Shop | E64: - | F64: - | G64: Mặc định | H64: Giá thầu Tự động | I64: - | J64: 45784 | K64: Không giới hạn | L64: 5530 | M64: 1426 | N64: 25.79% | O64: 4 | P64: 3 | Q64: 0.28% | R64: 0.21% | S64: 84929.42 | T64: 113239.2 | U64: 4 | V64: 3 | W64: 2343000 | X64: 1944000 | Y64: 339718 | Z64: 45906 | AA64: 5.72 | AB64: 14.50% | AC64: 17.48% | AD64: 15758 | AE64: 17 | AF64: 0.11% | AG64: 8
A65: 2 | B65: Viên Uống Giúp Chống Nắng Trắng Da Mờ Nám HB GLUTA WHITE + [4] | C65: Đang diễn ra | D65: Quảng cáo Sản phẩm | E65: 8782633181 | F65: - | G65: Tối ưu Sáng tạo đã được tắt | H65: Tối đa Doanh thu Tùy chỉnh ROAS | I65: Tất cả | J65: 45660 | K65: Không giới hạn | L65: 14778 | M65: 151 | N65: 1.02% | O65: 6 | P65: 6 | Q65: 3.97% | R65: 3.97% | S65: 180618.8 | T65: 180618.8 | U65: 8 | V65: 8 | W65: 11583000 | X65: 11583000 | Y65: 1083713 | Z65: 10.69 | AA65: 10.69 | AB65: 9.36% | AC65: 9.36% | AD65: - | AE65: - | AF65: - | AG65: 8
A66: 3 | B66: Viên uống giúp tái tạo và nuôi dưỡng mô sụn - HB Glucollagen 7 in 1 [7] | C66: Đang diễn ra | D66: Quảng cáo Sản phẩm | E66: 25666719442 | F66: - | G66: Tối ưu Sáng tạo đã được bật | H66: Tối đa Doanh thu Tùy chỉnh ROAS | I66: Tất cả | J66: 45891 | K66: 45931 | L66: 5708 | M66: 95 | N66: 1.66% | O66: 1 | P66: 1 | Q66: 1.05% | R66: 1.05% | S66: 387058 | T66: 387058 | U66: 1 | V66: 1 | W66: 945000 | X66: 945000 | Y66: 387058 | Z66: 2.44 | AA66: 2.44 | AB66: 40.96% | AC66: 40.96% | AD66: - | AE66: - | AF66: - | AG66: 8
A67: 4 | B67: Viên Uống HB Collagen Type 1,2&3 Healthy Beauty 120 Viên [4] | C67: Đang diễn ra | D67: Quảng cáo Sản phẩm | E67: 3934257539 | F67: - | G67: Tối ưu Sáng tạo đã được bật | H67: Tối đa Doanh thu Tùy chỉnh ROAS | I67: Tất cả | J67: 45891 | K67: 45931 | L67: 4995 | M67: 77 | N67: 1.54% | O67: 1 | P67: 1 | Q67: 1.30% | R67: 1.30% | S67: 331588.1 | T67: 331588.1 | U67: 1 | V67: 1 | W67: 790000 | X67: 790000 | Y67: 331588 | Z67: 2.38 | AA67: 2.38 | AB67: 41.97% | AC67: 41.97% | AD67: - | AE67: - | AF67: - | AG67: 8
A68: 5 | B68: Viên uống giúp Bổ Sung Canxi và Vitamin D3 HB CALCIDSOFT [4] | C68: Đang diễn ra | D68: Quảng cáo Sản phẩm | E68: 6917016018 | F68: - | G68: Tối ưu Sáng tạo đã được tắt | H68: Tối đa Doanh thu Tùy chỉnh ROAS | I68: Tất cả | J68: 45891 | K68: Không giới hạn | L68: 2540 | M68: 41 | N68: 1.61% | O68: 2 | P68: 2 | Q68: 4.88% | R68: 4.88% | S68: 46274.81 | T68: 46274.81 | U68: 2 | V68: 2 | W68: 533954 | X68: 533954 | Y68: 92550 | Z68: 5.77 | AA68: 5.77 | AB68: 17.33% | AC68: 17.33% | AD68: - | AE68: - | AF68: - | AG68: 8
A69: 6 | B69: Khẩu Trang Y Tế Kháng Khuẩn HB Medical Mask Cao Cấp Healthy Beauty 1 Hộp 50 cái [5] | C69: Đang diễn ra | D69: Quảng cáo Sản phẩm | E69: 5158911395 | F69: - | G69: Tối ưu Sáng tạo đã được bật | H69: Tối đa Doanh thu Tùy chỉnh ROAS | I69: Tất cả | J69: 45831 | K69: Không giới hạn | L69: 2270 | M69: 39 | N69: 1.72% | O69: 2 | P69: 2 | Q69: 5.13% | R69: 5.13% | S69: 68544.53 | T69: 68544.53 | U69: 7 | V69: 7 | W69: 420000 | X69: 420000 | Y69: 137089 | Z69: 45811 | AA69: 45811 | AB69: 32.64% | AC69: 32.64% | AD69: - | AE69: - | AF69: - | AG69: 8
A70: 7 | B70: Viên Uống Giảm Cân An Toàn Ban Ngày HB SLIMDAY 60 Viên | C70: Đang diễn ra | D70: Quảng cáo Sản phẩm | E70: 3862340378 | F70: - | G70: Tối ưu Sáng tạo đã được tắt | H70: Tối đa Doanh thu Tối ưu ROAS bởi Hệ thống | I70: Tất cả | J70: 45729 | K70: Không giới hạn | L70: 2256 | M70: 58 | N70: 2.57% | O70: 1 | P70: 1 | Q70: 1.72% | R70: 1.72% | S70: 265540.6 | T70: 265540.6 | U70: 1 | V70: 1 | W70: 880000 | X70: 880000 | Y70: 265541 | Z70: 3.31 | AA70: 3.31 | AB70: 30.18% | AC70: 30.18% | AD70: - | AE70: - | AF70: - | AG70: 8
A71: 8 | B71: Viên Uống Đông Trùng Hạ Thảo Bồi Bổ Khí Huyết HB CORDY EXTRACT [4] | C71: Đang diễn ra | D71: Quảng cáo Sản phẩm | E71: 5219966803 | F71: - | G71: Tối ưu Sáng tạo đã được bật | H71: Tối đa Doanh thu Tùy chỉnh ROAS | I71: Tất cả | J71: 45660 | K71: Không giới hạn | L71: 1986 | M71: 33 | N71: 1.66% | O71: 1 | P71: 1 | Q71: 3.03% | R71: 3.03% | S71: 87224.57 | T71: 87224.57 | U71: 1 | V71: 1 | W71: 850000 | X71: 850000 | Y71: 87225 | Z71: 9.74 | AA71: 9.74 | AB71: 10.26% | AC71: 10.26% | AD71: - | AE71: - | AF71: - | AG71: 8
A72: 9 | B72: Viên Uống Giảm Gãy Rụng và Đen Tóc HB Black Hair Healthy Beauty [12] | C72: Tạm dừng | D72: Quảng cáo Sản phẩm | E72: 5519393895 | F72: - | G72: Tối ưu Sáng tạo đã được tắt | H72: Tối đa Doanh thu Tùy chỉnh ROAS | I72: Tất cả | J72: 45849 | K72: Không giới hạn | L72: 4701 | M72: 58 | N72: 1.23% | O72: 5 | P72: 5 | Q72: 8.62% | R72: 8.62% | S72: 63213.26 | T72: 63213.26 | U72: 5 | V72: 5 | W72: 3865000 | X72: 3865000 | Y72: 316066 | Z72: 12.23 | AA72: 12.23 | AB72: 8.18% | AC72: 8.18% | AD72: - | AE72: - | AF72: - | AG72: 8
A73: 10 | B73: Viên uống giúp tái tạo và nuôi dưỡng mô sụn - HB Glucollagen 7 in 1 [6] | C73: Tạm dừng | D73: Quảng cáo Sản phẩm | E73: 25666719442 | F73: - | G73: Tối ưu Sáng tạo đã được tắt | H73: Tối đa Doanh thu Tùy chỉnh ROAS | I73: Tất cả | J73: 45833 | K73: Không giới hạn | L73: 3176 | M73: 44 | N73: 1.39% | O73: 4 | P73: 4 | Q73: 9.09% | R73: 9.09% | S73: 65590.08 | T73: 65590.08 | U73: 4 | V73: 4 | W73: 2430000 | X73: 2430000 | Y73: 262360 | Z73: 9.26 | AA73: 9.26 | AB73: 10.80% | AC73: 10.80% | AD73: - | AE73: - | AF73: - | AG73: 8
A74: 11 | B74: Viên uống HB Glucosamine 3 in 1 60 viên - 200 viên [7] | C74: Tạm dừng | D74: Quảng cáo Sản phẩm | E74: 24867481840 | F74: - | G74: Tối ưu Sáng tạo đã được tắt | H74: Tối đa Doanh thu Tùy chỉnh ROAS | I74: Tất cả | J74: 45849 | K74: Không giới hạn | L74: 251 | M74: 2 | N74: 0.80% | O74: 0 | P74: 0 | Q74: 0.00% | R74: 0.00% | S74: 0 | T74: 0 | U74: 0 | V74: 0 | W74: 0 | X74: 0 | Y74: 315 | Z74: 0 | AA74: 0 | AB74: 0.00% | AC74: 0.00% | AD74: - | AE74: - | AF74: - | AG74: 8
A75: 12 | B75: Viên uống HB GutCare (30 - 60 viên) hỗ trợ giảm triệu chứng đau khớp | C75: Đã dừng | D75: Quảng cáo Sản phẩm | E75: 22657955668 | F75: - | G75: Tối ưu Sáng tạo đã được tắt | H75: Tối đa Doanh thu Tùy chỉnh ROAS | I75: Tất cả | J75: 45660 | K75: 45901 | L75: 2162 | M75: 14 | N75: 0.65% | O75: 0 | P75: 0 | Q75: 0.00% | R75: 0.00% | S75: 0 | T75: 0 | U75: 0 | V75: 0 | W75: 0 | X75: 0 | Y75: 65469 | Z75: 0 | AA75: 0 | AB75: 0.00% | AC75: 0.00% | AD75: - | AE75: - | AF75: - | AG75: 8
A78: Báo cáo Dịch vụ Hiển thị trả theo CPC - Shopee Việt Nam
A79: Tên đăng nhập | B79: healthybeauty.officialstore
A80: Tên gian hàng | B80: DƯỢC PHẨM HEALTHY BEAUTY
A81: Mã Người bán | B81: 227240948
A82: Thời gian tạo báo cáo | B82: 45931.621
A83: Khoảng thời gian | B83: 01/09/2025 - 30/09/2025
W84: =SUM(W86:W98) -> 61383194 | Y84: =SUM(Y86:Y98) -> 10589865
A85: Thứ tự | B85: Tên Dịch vụ Hiển thị | C85: Trạng thái | D85: Loại Dịch vụ Hiển thị | E85: Mã sản phẩm | F85: Cài đặt Đối tượng | G85: Nội dung Dịch vụ Hiển thị | H85: Phương thức đấu thầu | I85: Vị trí | J85: Ngày bắt đầu | K85: Ngày kết thúc | L85: Số lượt xem | M85: Số lượt click | N85: Tỷ Lệ Click | O85: Lượt chuyển đổi | P85: Lượt chuyển đổi trực tiếp | Q85: Tỷ lệ chuyển đổi | R85: Tỷ lệ chuyển đổi trực tiếp | S85: Chi phí cho mỗi lượt chuyển đổi | T85: Chi phí cho mỗi lượt chuyển đổi trực tiếp | U85: Sản phẩm đã bán | V85: Sản phẩm đã bán trực tiếp | W85: GMV | X85: GMV trực tiếp | Y85: Chi phí | Z85: ROAS | AA85: ROAS trực tiếp | AB85: ACOS | AC85: ACOS trực tiếp | AD85: Lượt xem Sản phẩm | AE85: Lượt clicks Sản phẩm | AF85: Tỷ lệ Click Sản phẩm
A86: 1 | B86: Auto shop | C86: Đang diễn ra | D86: Dịch vụ Hiển thị Shop | E86: - | F86: - | G86: Mặc định | H86: Giá thầu Tự động | I86: - | J86: ######## | K86: Không giới hạn | L86: 8698 | M86: 1219 | N86: 14.01% | O86: 5 | P86: 5 | Q86: 0.41% | R86: 0.41% | S86: 232223.5 | T86: 232223.5 | U86: 5 | V86: 5 | W86: 2457000 | X86: 2457000 | Y86: 1161117 | Z86: 45993 | AA86: 45993 | AB86: 47.26% | AC86: 47.26% | AD86: 25919 | AE86: 36 | AF86: 0.14% | AG86: 9
A87: 2 | B87: Viên Uống Giúp Chống Nắng Trắng Da Mờ Nám HB GLUTA WHITE + [4] | C87: Đang diễn ra | D87: Dịch vụ Hiển thị Sản phẩm | E87: 8.78E+09 | F87: - | G87: Tối ưu Sáng tạo đã được tắt | H87: Tối đa Doanh thu Tùy chỉnh ROAS | I87: Tất cả | J87: ######## | K87: Không giới hạn | L87: 43640 | M87: 389 | N87: 0.89% | O87: 21 | P87: 17 | Q87: 5.40% | R87: 4.37% | S87: 128029.2 | T87: 158153.8 | U87: 26 | V87: 22 | W87: 26980200 | X87: 24057000 | Y87: 2688614 | Z87: 45726 | AA87: 8.95 | AB87: 9.97% | AC87: 11.18% | AD87: - | AE87: - | AF87: - | AG87: 9
A88: 3 | B88: Viên Uống Giảm Cân An Toàn Ban Ngày HB SLIMDAY 60 Viên | C88: Đang diễn ra | D88: Dịch vụ Hiển thị Sản phẩm | E88: 3.86E+09 | F88: - | G88: Tối ưu Sáng tạo đã được bật | H88: Tối đa Doanh thu Tối ưu ROAS bởi Hệ thống | I88: Tất cả | J88: ######## | K88: Không giới hạn | L88: 27840 | M88: 478 | N88: 1.72% | O88: 8 | P88: 8 | Q88: 1.67% | R88: 1.67% | S88: 232112 | T88: 232112 | U88: 8 | V88: 8 | W88: 6159999 | X88: 6159999 | Y88: 1856896 | Z88: 3.32 | AA88: 3.32 | AB88: 30.14% | AC88: 30.14% | AD88: - | AE88: - | AF88: - | AG88: 9
A89: 4 | B89: Viên uống giúp Bổ Sung Canxi và Vitamin D3 HB CALCIDSOFT [4] | C89: Đang diễn ra | D89: Dịch vụ Hiển thị Sản phẩm | E89: 6.92E+09 | F89: - | G89: Tối ưu Sáng tạo đã được tắt | H89: Tối đa Doanh thu Tùy chỉnh ROAS | I89: Tất cả | J89: ######## | K89: Không giới hạn | L89: 12458 | M89: 247 | N89: 1.98% | O89: 14 | P89: 13 | Q89: 5.67% | R89: 5.26% | S89: 58558.31 | T89: 63062.8 | U89: 15 | V89: 14 | W89: 5729050 | X89: 4784050 | Y89: 819816 | Z89: 6.99 | AA89: 5.84 | AB89: 14.31% | AC89: 17.14% | AD89: - | AE89: - | AF89: - | AG89: 9
A90: 5 | B90: Khẩu Trang Y Tế Kháng Khuẩn HB Medical Mask Cao Cấp Healthy Beauty 1 Hộp 50 cái [6] | C90: Đang diễn ra | D90: Dịch vụ Hiển thị Sản phẩm | E90: 5.16E+09 | F90: - | G90: Tối ưu Sáng tạo đã được bật | H90: Tối đa Doanh thu Tùy chỉnh ROAS | I90: Tất cả | J90: ######## | K90: Không giới hạn | L90: 366 | M90: 15 | N90: 4.10% | O90: 0 | P90: 0 | Q90: 0.00% | R90: 0.00% | S90: 0 | T90: 0 | U90: 0 | V90: 0 | W90: 0 | X90: 0 | Y90: 58783 | Z90: 0 | AA90: 0 | AB90: 0.00% | AC90: 0.00% | AD90: - | AE90: - | AF90: - | AG90: 9
A91: 6 | B91: Viên Uống Đông Trùng Hạ Thảo Bồi Bổ Khí Huyết HB CORDY EXTRACT [4] | C91: Tạm dừng | D91: Dịch vụ Hiển thị Sản phẩm | E91: 5.22E+09 | F91: - | G91: Tối ưu Sáng tạo đã được bật | H91: Tối đa Doanh thu Tùy chỉnh ROAS | I91: Tất cả | J91: ######## | K91: Không giới hạn | L91: 5612 | M91: 91 | N91: 1.62% | O91: 1 | P91: 1 | Q91: 1.10% | R91: 1.10% | S91: 439017.4 | T91: 439017.4 | U91: 1 | V91: 1 | W91: 996000 | X91: 996000 | Y91: 439017 | Z91: 2.27 | AA91: 2.27 | AB91: 44.08% | AC91: 44.08% | AD91: - | AE91: - | AF91: - | AG91: 9
A92: 7 | B92: Khẩu Trang Y Tế Kháng Khuẩn HB Medical Mask Cao Cấp Healthy Beauty 1 Hộp 50 cái [5] | C92: Tạm dừng | D92: Dịch vụ Hiển thị Sản phẩm | E92: 5.16E+09 | F92: - | G92: Tối ưu Sáng tạo đã được bật | H92: Tối đa Doanh thu Tùy chỉnh ROAS | I92: Tất cả | J92: ######## | K92: Không giới hạn | L92: 2194 | M92: 53 | N92: 2.42% | O92: 3 | P92: 3 | Q92: 5.66% | R92: 5.66% | S92: 50408.04 | T92: 50408.04 | U92: 8 | V92: 8 | W92: 475000 | X92: 475000 | Y92: 151224 | Z92: 3.14 | AA92: 3.14 | AB92: 31.84% | AC92: 31.84% | AD92: - | AE92: - | AF92: - | AG92: 9
A93: 8 | B93: Viên uống giúp tái tạo và nuôi dưỡng mô sụn - HB Glucollagen 7 in 1 [10] | C93: Tạm dừng | D93: Dịch vụ Hiển thị Sản phẩm | E93: 2.57E+10 | F93: - | G93: Tối ưu Sáng tạo đã được tắt | H93: Tối đa Doanh thu Tối ưu ROAS bởi Hệ thống | I93: Tất cả | J93: ######## | K93: Không giới hạn | L93: 1020 | M93: 22 | N93: 2.16% | O93: 1 | P93: 1 | Q93: 4.55% | R93: 4.55% | S93: 47439.45 | T93: 47439.45 | U93: 1 | V93: 1 | W93: 579000 | X93: 579000 | Y93: 47439 | Z93: 12.21 | AA93: 12.21 | AB93: 8.19% | AC93: 8.19% | AD93: - | AE93: - | AF93: - | AG93: 9
A94: 9 | B94: Viên uống giúp tái tạo và nuôi dưỡng mô sụn - HB Glucollagen 7 in 1 [7] | C94: Đã dừng | D94: Dịch vụ Hiển thị Sản phẩm | E94: 2.57E+10 | F94: - | G94: Tối ưu Sáng tạo đã được bật | H94: Tối đa Doanh thu Tùy chỉnh ROAS | I94: Tất cả | J94: ######## | K94: ######## | L94: 20677 | M94: 300 | N94: 1.45% | O94: 12 | P94: 12 | Q94: 4.00% | R94: 4.00% | S94: 178537.8 | T94: 178537.8 | U94: 13 | V94: 13 | W94: 11457179 | X94: 11457179 | Y94: 2142453 | Z94: 5.35 | AA94: 5.35 | AB94: 18.70% | AC94: 18.70% | AD94: - | AE94: - | AF94: - | AG94: 9
A95: 10 | B95: Viên Uống HB Collagen Type 1,2&3 Healthy Beauty 120 Viên [4] | C95: Đã dừng | D95: Dịch vụ Hiển thị Sản phẩm | E95: 3.93E+09 | F95: - | G95: Tối ưu Sáng tạo đã được bật | H95: Tối đa Doanh thu Tùy chỉnh ROAS | I95: Tất cả | J95: ######## | K95: ######## | L95: 15355 | M95: 187 | N95: 1.22% | O95: 6 | P95: 3 | Q95: 3.21% | R95: 1.60% | S95: 145198.2 | T95: 290396.3 | U95: 6 | V95: 3 | W95: 3910766 | X95: 2425766 | Y95: 871189 | Z95: 4.49 | AA95: 2.78 | AB95: 22.28% | AC95: 35.91% | AD95: - | AE95: - | AF95: - | AG95: 9
A96: 11 | B96: Viên uống giúp tái tạo và nuôi dưỡng mô sụn - HB Glucollagen 7 in 1 [8] | C96: Đã dừng | D96: Dịch vụ Hiển thị Sản phẩm | E96: 2.57E+10 | F96: Tùy chỉnh Đối tượng | G96: Tối ưu Sáng tạo đã được bật | H96: Giá thầu Thủ công | I96: Tất cả | J96: ######## | K96: ######## | L96: 5517 | M96: 45 | N96: 0.82% | O96: 0 | P96: 0 | Q96: 0.00% | R96: 0.00% | S96: 0 | T96: 0 | U96: 0 | V96: 0 | W96: 0 | X96: 0 | Y96: 65481 | Z96: 0 | AA96: 0 | AB96: 0.00% | AC96: 0.00% | AD96: - | AE96: - | AF96: - | AG96: 9
A97: 12 | B97: Combo Trẻ Hóa Làn Da Gluta White+ & HB Collagen Type 1,2,3 Healthy Beauty [3] | C97: Đã dừng | D97: Dịch vụ Hiển thị Sản phẩm | E97: 1.14E+10 | F97: - | G97: Tối ưu Sáng tạo đã được bật | H97: Tối đa Doanh thu Tùy chỉnh ROAS | I97: Tất cả | J97: ######## | K97: ######## | L97: 675 | M97: 10 | N97: 1.48% | O97: 0 | P97: 0 | Q97: 0.00% | R97: 0.00% | S97: 0 | T97: 0 | U97: 0 | V97: 0 | W97: 0 | X97: 0 | Y97: 19238 | Z97: 0 | AA97: 0 | AB97: 0.00% | AC97: 0.00% | AD97: - | AE97: - | AF97: - | AG97: 9
A98: 13 | B98: Chiến dịch Hiển thị Shop 06-09-2025 | C98: Đang diễn ra | D98: Dịch vụ Hiển thị Shop | E98: - | F98: - | G98: Tùy chỉnh | H98: Giá thầu Thủ công | I98: - | J98: ######## | K98: ######## | L98: 1257 | M98: 122 | N98: 9.71% | O98: 3 | P98: 3 | Q98: 2.46% | R98: 2.46% | S98: 89532.73 | T98: 89532.73 | U98: 3 | V98: 3 | W98: 2639000 | X98: 2639000 | Y98: 268598 | Z98: 9.83 | AA98: 9.83 | AB98: 10.18% | AC98: 10.18% | AD98: 7453 | AE98: 6 | AF98: 0.08% | AG98: 9
A101: Báo cáo Dịch vụ Hiển thị trả theo CPC - Shopee Việt Nam
A102: Tên đăng nhập | B102: healthybeauty.officialstore
A103: Tên gian hàng | B103: DƯỢC PHẨM HEALTHY BEAUTY
A104: Mã Người bán | B104: 227240948
A105: Thời gian tạo báo cáo | B105: 45960.724
A106: Khoảng thời gian | B106: 01/10/2025 - 30/10/2025
W107: =SUM(W109:W125) -> 39569564 | Y107: =SUM(Y109:Y125) -> 4947883
A108: Thứ tự | B108: Tên Dịch vụ Hiển thị | C108: Trạng thái | D108: Loại Dịch vụ Hiển thị | E108: Mã sản phẩm | F108: Cài đặt Đối tượng | G108: Nội dung Dịch vụ Hiển thị | H108: Phương thức đấu thầu | I108: Vị trí | J108: Ngày bắt đầu | K108: Ngày kết thúc | L108: Số lượt xem | M108: Số lượt click | N108: Tỷ Lệ Click | O108: Lượt chuyển đổi | P108: Lượt chuyển đổi trực tiếp | Q108: Tỷ lệ chuyển đổi | R108: Tỷ lệ chuyển đổi trực tiếp | S108: Chi phí cho mỗi lượt chuyển đổi | T108: Chi phí cho mỗi lượt chuyển đổi trực tiếp | U108: Sản phẩm đã bán | V108: Sản phẩm đã bán trực tiếp | W108: GMV | X108: GMV trực tiếp | Y108: Chi phí | Z108: ROAS | AA108: ROAS trực tiếp | AB108: ACOS | AC108: ACOS trực tiếp | AD108: Lượt xem Sản phẩm | AE108: Lượt clicks Sản phẩm | AF108: Tỷ lệ Click Sản phẩm
A109: 1 | B109: Auto shop | C109: Đang diễn ra | D109: Dịch vụ Hiển thị Shop | E109: - | F109: - | G109: Mặc định | H109: Giá thầu Tự động | I109: - | J109: 45784 | K109: Không giới hạn | L109: 15256 | M109: 3013 | N109: 19.75% | O109: 20 | P109: 20 | Q109: 0.66% | R109: 0.66% | S109: 55284.94 | T109: 55284.94 | U109: 24 | V109: 24 | W109: 3498282 | X109: 3498282 | Y109: 1105699 | Z109: 3.16 | AA109: 3.16 | AB109: 31.61% | AC109: 31.61% | AD109: 47938 | AE109: 12 | AF109: 0.03% | AG109: 10
A110: 2 | B110: Viên Uống Giúp Chống Nắng Trắng Da Mờ Nám HB GLUTA WHITE + [4] | C110: Đang diễn ra | D110: Dịch vụ Hiển thị Sản phẩm | E110: 8782633181 | F110: - | G110: - | H110: Tối đa Doanh thu Tùy chỉnh ROAS | I110: Tất cả | J110: 45660 | K110: Không giới hạn | L110: 37033 | M110: 364 | N110: 0.98% | O110: 18 | P110: 11 | Q110: 4.95% | R110: 3.02% | S110: 100709.8 | T110: 164797.9 | U110: 19 | V110: 11 | W110: 13200396 | X110: 12474000 | Y110: 1812777 | Z110: 7.28 | AA110: 6.88 | AB110: 13.73% | AC110: 14.53% | AD110: - | AE110: - | AF110: - | AG110: 10
A111: 3 | B111: Viên uống giúp tái tạo và nuôi dưỡng mô sụn - HB Glucollagen 7 in 1 [10] | C111: Đang diễn ra | D111: Dịch vụ Hiển thị Sản phẩm | E111: 25666719442 | F111: - | G111: - | H111: Tối đa Doanh thu Tối ưu ROAS bởi Hệ thống | I111: Tất cả | J111: 45923 | K111: Không giới hạn | L111: 13626 | M111: 243 | N111: 1.78% | O111: 13 | P111: 11 | Q111: 5.35% | R111: 4.53% | S111: 42498.76 | T111: 50225.8 | U111: 14 | V111: 12 | W111: 10775699 | X111: 9550699 | Y111: 552484 | Z111: 45796 | AA111: 17.29 | AB111: 5.13% | AC111: 5.78% | AD111: - | AE111: - | AF111: - | AG111: 10
A112: 4 | B112: Viên Uống HB Collagen Type 1,2&3 Healthy Beauty 120 Viên [4] | C112: Đang diễn ra | D112: Dịch vụ Hiển thị Sản phẩm | E112: 3934257539 | F112: - | G112: - | H112: Tối đa Doanh thu Tùy chỉnh ROAS | I112: Tất cả | J112: 45954 | K112: 46023 | L112: 9675 | M112: 95 | N112: 0.98% | O112: 4 | P112: 2 | Q112: 4.21% | R112: 2.11% | S112: 117218.2 | T112: 234436.3 | U112: 4 | V112: 2 | W112: 3215000 | X112: 1818000 | Y112: 468873 | Z112: 6.86 | AA112: 3.88 | AB112: 14.58% | AC112: 25.79% | AD112: - | AE112: - | AF112: - | AG112: 10
A113: 5 | B113: Viên uống giúp Bổ Sung Canxi và Vitamin D3 HB CALCIDSOFT [4] | C113: Đang diễn ra | D113: Dịch vụ Hiển thị Sản phẩm | E113: 6917016018 | F113: - | G113: - | H113: Tối đa Doanh thu Tùy chỉnh ROAS | I113: Tất cả | J113: 45891 | K113: Không giới hạn | L113: 7554 | M113: 142 | N113: 1.88% | O113: 4 | P113: 4 | Q113: 2.82% | R113: 2.82% | S113: 114229.4 | T113: 114229.4 | U113: 6 | V113: 6 | W113: 2195009 | X113: 2195009 | Y113: 456917 | Z113: 45873 | AA113: 45873 | AB113: 20.82% | AC113: 20.82% | AD113: - | AE113: - | AF113: - | AG113: 10
A114: 6 | B114: Viên Uống Healthy Beauty Omega 3,6,9 Từ Dầu Hạt Lanh 100 Viên & 200 Viên [3] | C114: Đang diễn ra | D114: Dịch vụ Hiển thị Sản phẩm | E114: 3127515400 | F114: - | G114: - | H114: Tối đa Doanh thu Tối ưu ROAS bởi Hệ thống | I114: Tất cả | J114: 45729 | K114: Không giới hạn | L114: 2455 | M114: 43 | N114: 1.75% | O114: 4 | P114: 3 | Q114: 9.30% | R114: 6.98% | S114: 20885.12 | T114: 27846.83 | U114: 4 | V114: 3 | W114: 3156000 | X114: 2211000 | Y114: 83540 | Z114: 37.78 | AA114: 26.47 | AB114: 2.65% | AC114: 3.78% | AD114: - | AE114: - | AF114: - | AG114: 10
...

Sheet DS Shoppe (đã xác nhận)
A1: Ngày | B1: Tổng doanh số (VND) | C1: Tổng số đơn hàng | D1: Doanh số trên mỗi đơn hàng | E1: Tổng số lượt xem sản phẩm | F1: Số lượt truy cập | G1: Tỷ lệ chuyển đổi (theo số đơn được đặt) | H1: Đơn đã hủy | I1: Doanh số đơn hủy | J1: Đơn đã hoàn trả / hoàn tiền | K1: Doanh số các đơn Trả hàng/Hoàn tiền | L1: số người mua | M1: số người mua mới | N1: số người mua hiện tại | O1: số người mua tiềm năng | P1: Tỉ lệ quay lại của người mua | Q1: THÁNG
A2: 01-08-2025-31-08-2025 | B2: 47713575 | C2: 67 | D2: 712142.91 | E2: 1821 | F2: 2951 | G2: 0.0368 | H2: 8 | I2: 6452176 | J2: 0 | K2: 0 | L2: 58 | M2: 38 | N2: 20 | O2: 150 | P2: 0.1552
A4: Ngày | B4: Tổng doanh số (VND) | C4: Tổng số đơn hàng | D4: Doanh số trên mỗi đơn hàng | E4: Tổng số lượt xem sản phẩm | F4: Số lượt truy cập | G4: Tỷ lệ chuyển đổi (theo Đơn đã xác nhận) | H4: Đơn đã hủy | I4: Doanh số đơn hủy | J4: Đơn đã hoàn trả / hoàn tiền | K4: Doanh số các đơn Trả hàng/Hoàn tiền | L4: số người mua | M4: số người mua mới | N4: số người mua hiện tại | O4: số người mua tiềm năng | P4: Tỉ lệ quay lại của người mua | Q4: THÁNG
A5: 45870 | B5: 93299 | C5: 1 | D5: 93299 | E5: 49 | F5: 63 | G5: 0.0204 | H5: 0 | I5: 0 | J5: 0 | K5: 0 | L5: 1 | M5: 1 | N5: 0 | O5: 6 | P5: 0 | Q5: =MONTH(A5) -> 8
A6: 45871 | B6: 1651000 | C6: 2 | D6: 825500 | E6: 39 | F6: 87 | G6: 0.0513 | H6: 0 | I6: 0 | J6: 0 | K6: 0 | L6: 2 | M6: 1 | N6: 1 | O6: 4 | P6: 0 | Q6: =MONTH(A6) -> 8
A7: 45872 | B7: 0 | C7: 0 | D7: 0 | E7: 42 | F7: 95 | G7: 0 | H7: 0 | I7: 0 | J7: 0 | K7: 0 | L7: 0 | M7: 0 | N7: 0 | O7: 11 | P7: 0 | Q7: =MONTH(A7) -> 8
A8: 45873 | B8: 1852550 | C8: 2 | D8: 926275 | E8: 53 | F8: 82 | G8: 0.0377 | H8: 1 | I8: 1045800 | J8: 0 | K8: 0 | L8: 2 | M8: 0 | N8: 2 | O8: 4 | P8: 0 | Q8: =MONTH(A8) -> 8
A9: 45874 | B9: 0 | C9: 0 | D9: 0 | E9: 39 | F9: 82 | G9: 0 | H9: 0 | I9: 0 | J9: 0 | K9: 0 | L9: 0 | M9: 0 | N9: 0 | O9: 4 | P9: 0 | Q9: =MONTH(A9) -> 8
A10: 45875 | B10: 1136080 | C10: 2 | D10: 568040 | E10: 33 | F10: 65 | G10: 0.0606 | H10: 0 | I10: 0 | J10: 0 | K10: 0 | L10: 2 | M10: 1 | N10: 1 | O10: 5 | P10: 0 | Q10: =MONTH(A10) -> 8
A11: 45876 | B11: 0 | C11: 0 | D11: 0 | E11: 53 | F11: 94 | G11: 0 | H11: 0 | I11: 0 | J11: 0 | K11: 0 | L11: 0 | M11: 0 | N11: 0 | O11: 9 | P11: 0 | Q11: =MONTH(A11) -> 8
A12: 45877 | B12: 10797560 | C12: 13 | D12: 830581.54 | E12: 80 | F12: 112 | G12: 0.1625 | H12: 1 | I12: 727600 | J12: 0 | K12: 0 | L12: 12 | M12: 5 | N12: 7 | O12: 4 | P12: 0.0833 | Q12: =MONTH(A12) -> 8
A13: 45878 | B13: 914800 | C13: 2 | D13: 457400 | E13: 53 | F13: 146 | G13: 0.0377 | H13: 0 | I13: 0 | J13: 0 | K13: 0 | L13: 2 | M13: 1 | N13: 1 | O13: 4 | P13: 0 | Q13: =MONTH(A13) -> 8
A14: 45879 | B14: 461980 | C14: 3 | D14: 153993.33 | E14: 46 | F14: 40 | G14: 0.0652 | H14: 0 | I14: 0 | J14: 0 | K14: 0 | L14: 2 | M14: 2 | N14: 0 | O14: 7 | P14: 0.5 | Q14: =MONTH(A14) -> 8
A15: 45880 | B15: 2380250 | C15: 3 | D15: 793416.67 | E15: 47 | F15: 44 | G15: 0.0638 | H15: 1 | I15: 695200 | J15: 0 | K15: 0 | L15: 3 | M15: 3 | N15: 0 | O15: 11 | P15: 0 | Q15: =MONTH(A15) -> 8
A16: 45881 | B16: 704000 | C16: 1 | D16: 704000 | E16: 37 | F16: 42 | G16: 0.027 | H16: 0 | I16: 0 | J16: 0 | K16: 0 | L16: 1 | M16: 1 | N16: 0 | O16: 12 | P16: 0 | Q16: =MONTH(A16) -> 8
... A35: 45900 | B35: 0 | C35: 0 | D35: 0 | E35: 60 | F35: 111 | G35: 0 | H35: 0 | I35: 0 | J35: 0 | K35: 0 | L35: 0 | M35: 0 | N35: 0 | O35: 4 | P35: 0 | Q35: =MONTH(A35) -> 8
A38: Ngày | B38: Tổng doanh số (VND) | C38: Tổng số đơn hàng | D38: Doanh số trên mỗi đơn hàng | E38: Tổng số lượt xem sản phẩm | F38: Số lượt truy cập | G38: Tỷ lệ chuyển đổi (theo số đơn được đặt) | H38: Đơn đã hủy | I38: Doanh số đơn hủy | J38: Đơn đã hoàn trả / hoàn tiền | K38: Doanh số các đơn Trả hàng/Hoàn tiền | L38: số người mua | M38: số người mua mới | N38: số người mua hiện tại | O38: số người mua tiềm năng | P38: Tỉ lệ quay lại của người mua
A39: 01-09-2025-25-09-2025 | B39: =SUM(B42:B75) -> 127157603 | C39: =SUM(C42:C75) -> 191 | D39: =SUM(D42:D75) -> 42415707 | E39: =SUM(E42:E75) -> 6393 | F39: =SUM(F42:F75) -> 36834 | G39: =SUM(G42:G75) -> 2.2677 | H39: =SUM(H42:H75) -> 53 | I39: =SUM(I42:I75) -> 42182229 | ... P39: =SUM(P42:P75) -> 5.5304
A41: Ngày | B41: Tổng doanh số (VND) | C41: Tổng số đơn hàng | D41: Doanh số trên mỗi đơn hàng | E41: Lượt nhấp vào sản phẩm | F41: Số lượt truy cập | G41: Tỷ lệ chuyển đổi đơn hàng | H41: Đơn đã hủy | I41: Doanh số đơn hủy | J41: Đơn đã hoàn trả / hoàn tiền | K41: Doanh số các đơn Trả hàng/Hoàn tiền | L41: số người mua | M41: số người mua mới | N41: số người mua hiện tại | O41: số người mua tiềm năng | P41: Tỉ lệ quay lại của người mua | Q41: THÁNG
A42: 45901 | B42: =R42-I42 -> 4281650 | C42: 5 | D42: 900230 | E42: 107 | F42: 140 | G42: 0.0467 | H42: 1 | I42: 219500 | J42: 0 | K42: 0 | L42: 5 | M42: 3 | N42: 2 | O42: 14 | P42: 0 | Q42: =MONTH(A42) -> 9 | R42: 4501150 | S42: 5
A43: 45902 | B43: =R43-I43 -> 1780500 | C43: 3 | D43: 593500 | E43: 79 | F43: 122 | G43: 0.038 | H43: 0 | I43: 0 | J43: 0 | K43: 0 | L43: 3 | M43: 2 | N43: 1 | O43: 10 | P43: 0 | Q43: =MONTH(A43) -> 9 | R43: 1780500 | S43: 3
A44: 45903 | B44: =R44-I44 -> 0 | C44: 1 | D44: 827200 | E44: 100 | F44: 131 | G44: 0.01 | H44: 1 | I44: 827200 | J44: 0 | K44: 0 | L44: 1 | M44: 1 | N44: 0 | O44: 9 | P44: 0 | Q44: =MONTH(A44) -> 9 | R44: 827200 | S44: 1
A45: 45904 | B45: =R45-I45 -> 1194720 | C45: 3 | D45: 398240 | E45: 128 | F45: 183 | G45: 0.0234 | H45: 0 | I45: 0 | J45: 0 | K45: 0 | L45: 3 | M45: 2 | N45: 1 | O45: 18 | P45: 0 | Q45: =MONTH(A45) -> 9 | R45: 1194720 | S45: 3
A46: 45905 | B46: =R46-I46 -> 1583200 | C46: 3 | D46: 620924 | E46: 152 | F46: 156 | G46: 0.0197 | H46: 1 | I46: 279572 | J46: 0 | K46: 0 | L46: 3 | M46: 2 | N46: 1 | O46: 9 | P46: 0 | Q46: =MONTH(A46) -> 9 | R46: 1862772 | S46: 3
A47: 45906 | B47: =R47-I47 -> 277743 | C47: 1 | D47: 277743 | E47: 120 | F47: 166 | G47: 0.0083 | H47: 0 | I47: 0 | J47: 0 | K47: 0 | L47: 1 | M47: 0 | N47: 1 | O47: 13 | P47: 0 | Q47: =MONTH(A47) -> 9 | R47: 277743 | S47: 1
A48: 45907 | B48: =R48-I48 -> 245064 | C48: 2 | D48: 381531.5 | E48: 132 | F48: 154 | G48: 0.0152 | H48: 1 | I48: 517999 | J48: 0 | K48: 0 | L48: 2 | M48: 1 | N48: 1 | O48: 13 | P48: 0 | Q48: =MONTH(A48) -> 9 | R48: 763063 | S48: 2
A49: 45908 | B49: =R49-I49 -> 0 | C49: 1 | D49: 883575 | E49: 145 | F49: 245 | G49: 0.0069 | H49: 1 | I49: 883575 | J49: 0 | K49: 0 | L49: 1 | M49: 0 | N49: 1 | O49: 12 | P49: 0 | Q49: =MONTH(A49) -> 9 | R49: 883575 | S49: 1
A50: 45909 | B50: =R50-I50 -> 11305684 | C50: 17 | D50: 729506.71 | E50: 183 | F50: 645 | G50: 0.0929 | H50: 1 | I50: 1095930 | J50: 1 | K50: 0 | L50: 16 | M50: 8 | N50: 8 | O50: 15 | P50: 0.0625 | Q50: =MONTH(A50) -> 9 | R50: 12401614 | S50: 17
A51: 45910 | B51: =R51-I51 -> 4824140 | C51: 7 | D51: 689162.86 | E51: 107 | F51: 110 | G51: 0.0654 | H51: 0 | I51: 0 | J51: 0 | K51: 0 | L51: 6 | M51: 6 | N51: 0 | O51: 9 | P51: 0.1667 | Q51: =MONTH(A51) -> 9 | R51: 4824140 | S51: 7
A52: 45911 | B52: =R52-I52 -> 2116600 | C52: 2 | D52: 1058300 | E52: 114 | F52: 227 | G52: 0.0175 | H52: 0 | I52: 0 | J52: 0 | K52: 0 | L52: 2 | M52: 1 | N52: 1 | O52: 12 | P52: 0 | Q52: =MONTH(A52) -> 9 | R52: 2116600 | S52: 2
A53: 45912 | B53: =R53-I53 -> 2514900 | C53: 2 | D53: 1257450 | E53: 72 | F53: 154 | G53: 0.0278 | H53: 0 | I53: 0 | J53: 1 | K53: 0 | L53: 2 | M53: 1 | N53: 1 | O53: 9 | P53: 0 | Q53: =MONTH(A53) -> 9 | R53: 2514900 | S53: 2
... A71: 45930 | B71: =R71-I71 -> 1333911 | C71: 2 | D71: 666955.5 | E71: 149 | F71: 232 | G71: 0.0134 | H71: 0 | I71: 0 | J71: 0 | K71: 0 | L71: 2 | M71: 1 | N71: 1 | O71: 18 | P71: 0 | Q71: =MONTH(A71) -> 9 | R71: 1333911 | S71: 2
Q72: =MONTH(A72) -> 12
A73: Ngày | B73: Tổng doanh số (VND) | C73: Tổng số đơn hàng | D73: Doanh số trên mỗi đơn hàng | E73: Tổng số lượt xem sản phẩm | F73: Số lượt truy cập | G73: Tỷ lệ chuyển đổi (theo số đơn được đặt) | H73: Đơn đã hủy | I73: Doanh số đơn hủy | J73: Đơn đã hoàn trả / hoàn tiền | K73: Doanh số các đơn Trả hàng/Hoàn tiền | L73: số người mua | M73: số người mua mới | N73: số người mua hiện tại | O73: số người mua tiềm năng | P73: Tỉ lệ quay lại của người mua
B74: =SUM(B77:B110) -> 58260779 | C74: =SUM(C77:C110) -> 83 | D74: =SUM(D77:D110) -> 21985057 | E74: =SUM(E77:E110) -> 2896 | F74: =SUM(F77:F110) -> 20505 | G74: =SUM(G77:G110) -> 1.3479 | H74: =SUM(H77:H110) -> 37 | I74: =SUM(I77:I110) -> 28442973 | ... P74: =SUM(P77:P110) -> 3.8012
A76: Ngày | B76: Tổng doanh số (VND) | C76: Tổng số đơn hàng | D76: Doanh số trên mỗi đơn hàng | E76: Lượt nhấp vào sản phẩm | F76: Số lượt truy cập | G76: Tỷ lệ chuyển đổi đơn hàng | H76: Đơn đã hủy | I76: Doanh số đơn hủy | J76: Đơn đã hoàn trả / hoàn tiền | K76: Doanh số các đơn Trả hàng/Hoàn tiền | L76: số người mua | M76: số người mua mới | N76: số người mua hiện tại | O76: số người mua tiềm năng | P76: Tỉ lệ quay lại của người mua | Q76: THÁNG
A77: 45931 | B77: =R77-I77 -> 852390 | C77: =S77-H77 -> 1 | D77: 823095 | E77: 83 | F77: 154 | G77: 0.0241 | H77: 1 | I77: 793800 | J77: 0 | K77: 0 | L77: 2 | M77: 1 | N77: 1 | O77: 13 | P77: 0 | Q77: =MONTH(A77) -> 10 | R77: 1646190 | S77: 2
A78: 45932 | B78: =R78-I78 -> 3072476 | C78: =S78-H78 -> 2 | D78: 1547012.8 | E78: 33 | F78: 131 | G78: 0.1212 | H78: 2 | I78: 3115575 | J78: 0 | K78: 0 | L78: 3 | M78: 3 | N78: 0 | O78: 4 | P78: 0.3333 | Q78: =MONTH(A78) -> 10 | R78: 6188051 | S78: 4
A79: 45933 | B79: =R79-I79 -> 702240 | C79: =S79-H79 -> 1 | D79: 702240 | E79: 34 | F79: 164 | G79: 0.0294 | H79: 0 | I79: 0 | J79: 0 | K79: 0 | L79: 1 | M79: 1 | N79: 0 | O79: 4 | P79: 0 | Q79: =MONTH(A79) -> 10 | R79: 702240 | S79: 1
A80: 45934 | B80: =R80-I80 -> 1430817 | C80: =S80-H80 -> 2 | D80: 715408.5 | E80: 48 | F80: 84 | G80: 0.0417 | H80: 0 | I80: 0 | J80: 0 | K80: 0 | L80: 2 | M80: 1 | N80: 1 | O80: 5 | P80: 0 | Q80: =MONTH(A80) -> 10 | R80: 1430817 | S80: 2
A81: 45935 | B81: =R81-I81 -> 2363950 | C81: =S81-H81 -> 3 | D81: 787983.33 | E81: 52 | F81: 55 | G81: 0.0577 | H81: 0 | I81: 0 | J81: 0 | K81: 0 | L81: 3 | M81: 1 | N81: 2 | O81: 7 | P81: 0 | Q81: =MONTH(A81) -> 10 | R81: 2363950 | S81: 3
A82: 45936 | B82: =R82-I82 -> 1877941 | C82: =S82-H82 -> 3 | D82: 625980.33 | E82: 34 | F82: 71 | G82: 0.0882 | H82: 0 | I82: 0 | J82: 0 | K82: 0 | L82: 3 | M82: 2 | N82: 1 | O82: 1 | P82: 0 | Q82: =MONTH(A82) -> 10 | R82: 1877941 | S82: 3
A83: 45937 | B83: =R83-I83 -> 569492 | C83: =S83-H83 -> 1 | D83: 569492 | E83: 36 | F83: 66 | G83: 0.0278 | H83: 0 | I83: 0 | J83: 0 | K83: 0 | L83: 1 | M83: 0 | N83: 1 | O83: 7 | P83: 0 | Q83: =MONTH(A83) -> 10 | R83: 569492 | S83: 1
A84: 45938 | B84: =R84-I84 -> 2891630 | C84: =S84-H84 -> 5 | D84: 578326 | E84: 73 | F84: 90 | G84: 0.0685 | H84: 0 | I84: 0 | J84: 0 | K84: 0 | L84: 4 | M84: 3 | N84: 1 | O84: 11 | P84: 0.25 | Q84: =MONTH(A84) -> 10 | R84: 2891630 | S84: 5
A85: 45939 | B85: =R85-I85 -> 762420 | C85: =S85-H85 -> 1 | D85: 750128 | E85: 85 | F85: 145 | G85: 0.0471 | H85: 3 | I85: 2238092 | J85: 0 | K85: 0 | L85: 1 | M85: 0 | N85: 1 | O85: 7 | P85: 1 | Q85: =MONTH(A85) -> 10 | R85: 3000512 | S85: 4
A86: 45940 | B86: =R86-I86 -> 5974178 | C86: =S86-H86 -> 6 | D86: 854514.22 | E86: 147 | F86: 273 | G86: 0.0612 | H86: 3 | I86: 1716450 | J86: 1 | K86: 416549 | L86: 8 | M86: 2 | N86: 6 | O86: 11 | P86: 0.125 | Q86: =MONTH(A86) -> 10 | R86: 7690628 | S86: 9
A87: 45941 | B87: =R87-I87 -> 1035795 | C87: =S87-H87 -> 2 | D87: 629395 | E87: 104 | F87: 1317 | G87: 0.0288 | H87: 1 | I87: 852390 | J87: 0 | K87: 0 | L87: 3 | M87: 0 | N87: 3 | O87: 14 | P87: 0 | Q87: =MONTH(A87) -> 10 | R87: 1888185 | S87: 3
A88: 45942 | B88: =R88-I88 -> 1440000 | C88: =S88-H88 -> 2 | D88: 771060 | E88: 139 | F88: 266 | G88: 0.0216 | H88: 1 | I88: 873180 | J88: 0 | K88: 0 | L88: 3 | M88: 2 | N88: 1 | O88: 18 | P88: 0 | Q88: =MONTH(A88) -> 10 | R88: 2313180 | S88: 3
... A107: 45961 | B107: =R107-I107 -> 1493852 | C107: =S107-H107 -> 2 | D107: 799884 | E107: 101 | F107: 138 | G107: 0.0297 | H107: 1 | I107: 905800 | J107: 0 | K107: 0 | L107: 2 | M107: 0 | N107: 2 | O107: 9 | P107: 0.5 | Q107: =MONTH(A107) -> 10 | R107: 2399652 | S107: 3
A110: Ngày | B110: Tổng doanh số (VND) | C110: Tổng số đơn hàng | D110: Doanh số trên mỗi đơn hàng | E110: Tổng số lượt xem sản phẩm | F110: Số lượt truy cập | G110: Tỷ lệ chuyển đổi (theo số đơn được đặt) | H110: Đơn đã hủy | I110: Doanh số đơn hủy | J110: Đơn đã hoàn trả / hoàn tiền | K110: Doanh số các đơn Trả hàng/Hoàn tiền | L110: số người mua | M110: số người mua mới | N110: số người mua hiện tại | O110: số người mua tiềm năng | P110: Tỉ lệ quay lại của người mua
B111: =SUM(B114:B147) -> 121786335 | C111: =SUM(C114:C147) -> 181 | D111: =SUM(D114:D147) -> 36397756 | E111: =SUM(E114:E147) -> 8397 | F111: =SUM(F114:F147) -> 63484 | G111: =SUM(G114:G147) -> 1.5492 | H111: =SUM(H114:H147) -> 31 | I111: =SUM(I114:I147) -> 26727913 | ... P111: =SUM(P114:P147) -> 3.3145
A113: Ngày | B113: Tổng doanh số (VND) | C113: Tổng số đơn hàng | D113: Doanh số trên mỗi đơn hàng | E113: Lượt nhấp vào sản phẩm | F113: Số lượt truy cập | G113: Tỷ lệ chuyển đổi đơn hàng | H113: Đơn đã hủy | I113: Doanh số đơn hủy | J113: Đơn đã hoàn trả / hoàn tiền | K113: Doanh số các đơn Trả hàng/Hoàn tiền | L113: số người mua | M113: số người mua mới | N113: số người mua hiện tại | O113: số người mua tiềm năng | P113: Tỉ lệ quay lại của người mua | Q113: THÁNG
A114: 45962 | B114: =R114-I114 -> 883680 | C114: =S114-H114 -> 2 | D114: 1058637.5 | E114: 118 | F114: 73 | G114: 0.0339 | H114: 2 | I114: 3350870 | J114: 0 | K114: 0 | L114: 4 | M114: 3 | N114: 1 | O114: 13 | P114: 0 | Q114: =MONTH(A114) -> 11 | R114: 4234550 | S114: 4
A115: 45963 | B115: =R115-I115 -> 727620 | C115: =S115-H115 -> 3 | D115: 242540 | E115: 77 | F115: 59 | G115: 0.039 | H115: 0 | I115: 0 | J115: 0 | K115: 0 | L115: 3 | M115: 2 | N115: 1 | O115: 7 | P115: 0 | Q115: =MONTH(A115) -> 11 | R115: 727620 | S115: 3
A116: 45964 | B116: =R116-I116 -> 659119 | C116: =S116-H116 -> 1 | D116: 659119 | E116: 54 | F116: 56 | G116: 0.0185 | H116: 0 | I116: 0 | J116: 0 | K116: 0 | L116: 1 | M116: 1 | N116: 0 | O116: 2 | P116: 0 | Q116: =MONTH(A116) -> 11 | R116: 659119 | S116: 1
A117: 45965 | B117: =R117-I117 -> 610660 | C117: =S117-H117 -> 2 | D117: 305330 | E117: 126 | F117: 304 | G117: 0.0159 | H117: 0 | I117: 0 | J117: 0 | K117: 0 | L117: 2 | M117: 0 | N117: 2 | O117: 9 | P117: 0 | Q117: =MONTH(A117) -> 11 | R117: 610660 | S117: 2
A118: 45966 | B118: =R118-I118 -> 1290780 | C118: =S118-H118 -> 1 | D118: 1290780 | E118: 132 | F118: 339 | G118: 0.0076 | H118: 0 | I118: 0 | J118: 0 | K118: 0 | L118: 1 | M118: 1 | N118: 0 | O118: 10 | P118: 0 | Q118: =MONTH(A118) -> 11 | R118: 1290780 | S118: 1
A119: 45967 | B119: =R119-I119 -> 643679 | C119: =S119-H119 -> 3 | D119: 214559.67 | E119: 146 | F119: 148 | G119: 0.0205 | H119: 0 | I119: 0 | J119: 0 | K119: 0 | L119: 3 | M119: 2 | N119: 1 | O119: 6 | P119: 0 | Q119: =MONTH(A119) -> 11 | R119: 643679 | S119: 3
A120: 45968 | B120: =R120-I120 -> 3917120 | C120: =S120-H120 -> 2 | D120: 1958560 | E120: 116 | F120: 129 | G120: 0.0172 | H120: 0 | I120: 0 | J120: 0 | K120: 0 | L120: 2 | M120: 1 | N120: 1 | O120: 7 | P120: 0 | Q120: =MONTH(A120) -> 11 | R120: 3917120 | S120: 2
A121: 45969 | B121: =R121-I121 -> 1925065 | C121: =S121-H121 -> 3 | D121: 641688.33 | E121: 118 | F121: 209 | G121: 0.0254 | H121: 0 | I121: 0 | J121: 0 | K121: 0 | L121: 3 | M121: 2 | N121: 1 | O121: 10 | P121: 0 | Q121: =MONTH(A121) -> 11 | R121: 1925065 | S121: 3
A122: 45970 | B122: =R122-I122 -> 75000 | C122: =S122-H122 -> 1 | D122: 485250 | E122: 102 | F122: 217 | G122: 0.0196 | H122: 1 | I122: 895500 | J122: 0 | K122: 0 | L122: 2 | M122: 0 | N122: 2 | O122: 12 | P122: 0 | Q122: =MONTH(A122) -> 11 | R122: 970500 | S122: 2
A123: 45971 | B123: =R123-I123 -> 1535262 | C123: =S123-H123 -> 3 | D123: 511754 | E123: 153 | F123: 231 | G123: 0.0196 | H123: 0 | I123: 0 | J123: 0 | K123: 0 | L123: 3 | M123: 2 | N123: 1 | O123: 15 | P123: 0 | Q123: =MONTH(A123) -> 11 | R123: 1535262 | S123: 3
A124: 45972 | B124: =R124-I124 -> 9535714 | C124: =S124-H124 -> 12 | D124: 794642.83 | E124: 266 | F124: 558 | G124: 0.0451 | H124: 0 | I124: 0 | J124: 0 | K124: 0 | L124: 12 | M124: 5 | N124: 7 | O124: 22 | P124: 0 | Q124: =MONTH(A124) -> 11 | R124: 9535714 | S124: 12
A125: 45973 | B125: =R125-I125 -> 1498928 | C125: =S125-H125 -> 4 | D125: 374732 | E125: 177 | F125: 390 | G125: 0.0226 | H125: 0 | I125: 0 | J125: 0 | K125: 0 | L125: 3 | M125: 2 | N125: 1 | O125: 4 | P125: 0.3333 | Q125: =MONTH(A125) -> 11 | R125: 1498928 | S125: 4
... A143: 45991 | B143: =R143-I143 -> 3093514 | C143: =S143-H143 -> 4 | D143: 880391.86 | E143: 162 | F143: 224 | G143: 0.0432 | H143: 3 | I143: 3069229 | J143: 0 | K143: 0 | L143: 6 | M143: 5 | N143: 1 | O143: 9 | P143: 0.1667 | Q143: =MONTH(A143) -> 11 | R143: 6162743 | S143: 7
A146: Ngày | B146: Tổng doanh số (VND) | C146: Tổng số đơn hàng | D146: Doanh số trên mỗi đơn hàng | E146: Tổng số lượt xem sản phẩm | F146: Số lượt truy cập | G146: Tỷ lệ chuyển đổi (theo số đơn được đặt) | H146: Đơn đã hủy | I146: Doanh số đơn hủy | J146: Đơn đã hoàn trả / hoàn tiền | K146: Doanh số các đơn Trả hàng/Hoàn tiền | L146: số người mua | M146: số người mua mới | N146: số người mua hiện tại | O146: số người mua tiềm năng | P146: Tỉ lệ quay lại của người mua
B147: =SUM(B150:B183) -> 65586509 | C147: =SUM(C150:C183) -> 98 | D147: =SUM(D150:D183) -> 16800044 | E147: =SUM(E150:E183) -> 3867 | F147: =SUM(F150:F183) -> 4255 | G147: =SUM(G150:G183) -> 0.9084 | H147: =SUM(H150:H183) -> 16 | I147: =SUM(I150:I183) -> 9982909 | ... P147: =SUM(P150:P183) -> 1.6479
A149: Ngày | B149: Tổng doanh số (VND) | C149: Tổng số đơn hàng | D149: Doanh số trên mỗi đơn hàng | E149: Lượt nhấp vào sản phẩm | F149: Số lượt truy cập | G149: Tỷ lệ chuyển đổi đơn hàng | H149: Đơn đã hủy | I149: Doanh số đơn hủy | J149: Đơn đã hoàn trả / hoàn tiền | K149: Doanh số các đơn Trả hàng/Hoàn tiền | L149: số người mua | M149: số người mua mới | N149: số người mua hiện tại | O149: số người mua tiềm năng | P149: Tỉ lệ quay lại của người mua | Q149: THÁNG
A150: 45992 | B150: =R150-I150 -> 652719 | C150: =S150-H150 -> 1 | D150: 652719 | E150: 134 | F150: 194 | G150: 0.0075 | H150: 0 | I150: 0 | J150: 0 | K150: 0 | L150: 1 | M150: 0 | N150: 1 | O150: 11 | P150: 0 | Q150: =MONTH(A150) -> 12 | R150: 652719 | S150: 1
A151: 45993 | B151: =R151-I151 -> 278346 | C151: =S151-H151 -> 2 | D151: 139173 | E151: 132 | F151: 215 | G151: 0.0152 | H151: 0 | I151: 0 | J151: 0 | K151: 0 | L151: 2 | M151: 1 | N151: 1 | O151: 10 | P151: 0 | Q151: =MONTH(A151) -> 12 | R151: 278346 | S151: 2
A152: 45994 | B152: =R152-I152 -> 3279333 | C152: =S152-H152 -> 5 | D152: 697976 | E152: 206 | F152: 169 | G152: 0.034 | H152: 2 | I152: 1606499 | J152: 0 | K152: 0 | L152: 6 | M152: 2 | N152: 4 | O152: 9 | P152: 0.1667 | Q152: =MONTH(A152) -> 12 | R152: 4885832 | S152: 7
A153: 45995 | B153: =R153-I153 -> 0 | C153: =S153-H153 -> 0 | D153: 0 | E153: 179 | F153: 188 | G153: 0 | H153: 0 | I153: 0 | J153: 0 | K153: 0 | L153: 0 | M153: 0 | N153: 0 | O153: 14 | P153: 0 | Q153: =MONTH(A153) -> 12 | R153: 0 | S153: 0
A154: 45996 | B154: =R154-I154 -> 0 | C154: =S154-H154 -> 0 | D154: 0 | E154: 200 | F154: 156 | G154: 0 | H154: 0 | I154: 0 | J154: 0 | K154: 0 | L154: 0 | M154: 0 | N154: 0 | O154: 11 | P154: 0 | Q154: =MONTH(A154) -> 12 | R154: 0 | S154: 0
A155: 45997 | B155: =R155-I155 -> 922142 | C155: =S155-H155 -> 2 | D155: 461071 | E155: 153 | F155: 144 | G155: 0.0131 | H155: 0 | I155: 0 | J155: 0 | K155: 0 | L155: 2 | M155: 2 | N155: 0 | O155: 7 | P155: 0 | Q155: =MONTH(A155) -> 12 | R155: 922142 | S155: 2
A156: 45998 | B156: =R156-I156 -> 527639 | C156: =S156-H156 -> 2 | D156: 263819.5 | E156: 119 | F156: 123 | G156: 0.0168 | H156: 0 | I156: 0 | J156: 0 | K156: 0 | L156: 2 | M156: 1 | N156: 1 | O156: 6 | P156: 0 | Q156: =MONTH(A156) -> 12 | R156: 527639 | S156: 2
A157: 45999 | B157: =R157-I157 -> 2681166 | C157: =S157-H157 -> 4 | D157: 646511.33 | E157: 111 | F157: 102 | G157: 0.0541 | H157: 2 | I157: 1197902 | J157: 0 | K157: 0 | L157: 4 | M157: 3 | N157: 1 | O157: 7 | P157: 0.25 | Q157: =MONTH(A157) -> 12 | R157: 3879068 | S157: 6
A158: 46000 | B158: =R158-I158 -> 1310644 | C158: =S158-H158 -> 3 | D158: 436881.33 | E158: 100 | F158: 114 | G158: 0.03 | H158: 0 | I158: 0 | J158: 0 | K158: 0 | L158: 3 | M158: 2 | N158: 1 | O158: 8 | P158: 0 | Q158: =MONTH(A158) -> 12 | R158: 1310644 | S158: 3
A159: 46001 | B159: =R159-I159 -> 4025969 | C159: =S159-H159 -> 6 | D159: 717066.43 | E159: 134 | F159: 122 | G159: 0.0522 | H159: 1 | I159: 993496 | J159: 0 | K159: 0 | L159: 7 | M159: 5 | N159: 2 | O159: 11 | P159: 0 | Q159: =MONTH(A159) -> 12 | R159: 5019465 | S159: 7
A160: 46002 | B160: =R160-I160 -> 2447749 | C160: =S160-H160 -> 4 | D160: 633357.8 | E160: 156 | F160: 266 | G160: 0.0321 | H160: 1 | I160: 719040 | J160: 0 | K160: 0 | L160: 5 | M160: 2 | N160: 3 | O160: 12 | P160: 0 | Q160: =MONTH(A160) -> 12 | R160: 3166789 | S160: 5
A161: 46003 | B161: =R161-I161 -> 10021030 | C161: =S161-H161 -> 13 | D161: 736183.27 | E161: 238 | F161: 229 | G161: 0.063 | H161: 2 | I161: 1021719 | J161: 0 | K161: 0 | L161: 13 | M161: 5 | N161: 8 | O161: 18 | P161: 0.1538 | Q161: =MONTH(A161) -> 12 | R161: 11042749 | S161: 15
... A179: 46021 | B179: =R179-I179 -> 1287804 | C179: =S179-H179 -> 1 | D179: 1287804 | E179: 101 | F179: 94 | G179: 0.0099 | H179: 0 | I179: 0 | J179: 0 | K179: 0 | L179: 1 | M179: 1 | N179: 0 | O179: 10 | P179: 0 | Q179: =MONTH(A179) -> 12 | R179: 1287804 | S179: 1
A180: 46022 | B180: =R180-I180 -> 3835932 | C180: =S180-H180 -> 6 | D180: 639322 | E180: 93 | F180: 132 | G180: 0.0645 | H180: 0 | I180: 0 | J180: 0 | K180: 0 | L180: 6 | M180: 1 | N180: 5 | O180: 3 | P180: 0 | R180: 3835932 | S180: 6
A183: Ngày | B183: Tổng doanh số (VND) | C183: Tổng số đơn hàng | D183: Doanh số trên mỗi đơn hàng | E183: Tổng số lượt xem sản phẩm | F183: Số lượt truy cập | G183: Tỷ lệ chuyển đổi (theo số đơn được đặt) | H183: Đơn đã hủy | I183: Doanh số đơn hủy | J183: Đơn đã hoàn trả / hoàn tiền | K183: Doanh số các đơn Trả hàng/Hoàn tiền | L183: số người mua | M183: số người mua mới | N183: số người mua hiện tại | O183: số người mua tiềm năng | P183: Tỉ lệ quay lại của người mua
B184: =SUM(B187:B220) -> 81766141 | C184: =SUM(C187:C220) -> 102 | D184: =SUM(D187:D220) -> 24448079 | E184: =SUM(E187:E220) -> 3363 | F184: =SUM(F187:F220) -> 16122 | G184: =SUM(G187:G220) -> 1.1128 | H184: =SUM(H187:H220) -> 21 | I184: =SUM(I187:I220) -> 26305436 | ... P184: =SUM(P187:P220) -> 1.7437
A186: Ngày | B186: Tổng doanh số (VND) | C186: Tổng số đơn hàng | D186: Doanh số trên mỗi đơn hàng | E186: Lượt nhấp vào sản phẩm | F186: Số lượt truy cập | G186: Tỷ lệ chuyển đổi đơn hàng | H186: Đơn đã hủy | I186: Doanh số đơn hủy | J186: Đơn đã hoàn trả / hoàn tiền | K186: Doanh số các đơn Trả hàng/Hoàn tiền | L186: số người mua | M186: số người mua mới | N186: số người mua hiện tại | O186: số người mua tiềm năng | P186: Tỉ lệ quay lại của người mua | Q186: THÁNG
A187: 46023 | B187: =R187-I187 -> 4663219 | C187: =S187-H187 -> 5 | D187: 892259.86 | E187: 96 | F187: 96 | G187: 0.0729 | H187: 2 | I187: 1582600 | J187: 0 | K187: 0 | L187: 6 | M187: 5 | N187: 1 | O187: 8 | P187: 0.1667 | Q187: =MONTH(A187) -> 1 | R187: 6245819 | S187: 7
A188: 46024 | B188: =R188-I188 -> 1511190 | C188: =S188-H188 -> 1 | D188: 1039168.5 | E188: 79 | F188: 86 | G188: 0.0253 | H188: 1 | I188: 567147 | J188: 0 | K188: 0 | L188: 2 | M188: 1 | N188: 1 | O188: 8 | P188: 0 | Q188: =MONTH(A188) -> 1 | R188: 2078337 | S188: 2
A189: 46025 | B189: =R189-I189 -> 1418617 | C189: =S189-H189 -> 2 | D189: 709308.5 | E189: 92 | F189: 103 | G189: 0.0217 | H189: 0 | I189: 0 | J189: 0 | K189: 0 | L189: 2 | M189: 2 | N189: 0 | O189: 10 | P189: 0 | Q189: =MONTH(A189) -> 1 | R189: 1418617 | S189: 2
A190: 46026 | B190: =R190-I190 -> 1615763 | C190: =S190-H190 -> 2 | D190: 807881.5 | E190: 102 | F190: 112 | G190: 0.0196 | H190: 0 | I190: 0 | J190: 0 | K190: 0 | L190: 2 | M190: 1 | N190: 1 | O190: 5 | P190: 0 | Q190: =MONTH(A190) -> 1 | R190: 1615763 | S190: 2
A191: 46027 | B191: =R191-I191 -> 4748851 | C191: =S191-H191 -> 6 | D191: 791475.17 | E191: 91 | F191: 109 | G191: 0.0659 | H191: 0 | I191: 0 | J191: 0 | K191: 0 | L191: 6 | M191: 4 | N191: 2 | O191: 9 | P191: 0 | Q191: =MONTH(A191) -> 1 | R191: 4748851 | S191: 6
A192: 46028 | B192: =R192-I192 -> 1160090 | C192: =S192-H192 -> 2 | D192: 580045 | E192: 115 | F192: 144 | G192: 0.0174 | H192: 0 | I192: 0 | J192: 0 | K192: 0 | L192: 2 | M192: 1 | N192: 1 | O192: 13 | P192: 0 | Q192: =MONTH(A192) -> 1 | R192: 1160090 | S192: 2
A193: 46029 | B193: =R193-I193 -> 0 | C193: =S193-H193 -> 0 | D193: 0 | E193: 90 | F193: 97 | G193: 0 | H193: 0 | I193: 0 | J193: 0 | K193: 0 | L193: 0 | M193: 0 | N193: 0 | O193: 9 | P193: 0 | Q193: =MONTH(A193) -> 1 | R193: 0 | S193: 0
A194: 46030 | B194: =R194-I194 -> 0 | C194: =S194-H194 -> 0 | D194: 3020100 | E194: 84 | F194: 123 | G194: 0.0119 | H194: 1 | I194: 3020100 | J194: 0 | K194: 0 | L194: 1 | M194: 1 | N194: 0 | O194: 6 | P194: 0 | Q194: =MONTH(A194) -> 1 | R194: 3020100 | S194: 1
A195: 46031 | B195: =R195-I195 -> 0 | C195: =S195-H195 -> 0 | D195: 0 | E195: 108 | F195: 154 | G195: 0 | H195: 0 | I195: 0 | J195: 0 | K195: 0 | L195: 0 | M195: 0 | N195: 0 | O195: 16 | P195: 0 | Q195: =MONTH(A195) -> 1 | R195: 0 | S195: 0
A196: 46032 | B196: =R196-I196 -> 4799434 | C196: =S196-H196 -> 6 | D196: 719690.25 | E196: 133 | F196: 103 | G196: 0.0602 | H196: 2 | I196: 958088 | J196: 0 | K196: 0 | L196: 8 | M196: 7 | N196: 1 | O196: 13 | P196: 0 | Q196: =MONTH(A196) -> 1 | R196: 5757522 | S196: 8
A197: 46033 | B197: =R197-I197 -> 2804371 | C197: =S197-H197 -> 4 | D197: 701092.75 | E197: 127 | F197: 110 | G197: 0.0315 | H197: 0 | I197: 0 | J197: 0 | K197: 0 | L197: 4 | M197: 4 | N197: 0 | O197: 8 | P197: 0 | Q197: =MONTH(A197) -> 1 | R197: 2804371 | S197: 4
A198: 46034 | B198: =R198-I198 -> 2473536 | C198: =S198-H198 -> 3 | D198: 703201.25 | E198: 94 | F198: 169 | G198: 0.0426 | H198: 1 | I198: 339269 | J198: 0 | K198: 0 | L198: 4 | M198: 3 | N198: 1 | O198: 8 | P198: 0 | Q198: =MONTH(A198) -> 1 | R198: 2812805 | S198: 4
... A217: 46053 | B217: =R217-I217 -> 3093689 | C217: =S217-H217 -> 4 | D217: 1212737.8 | E217: 82 | F217: 81 | G217: 0.061 | H217: 1 | I217: 2970000 | J217: 0 | K217: 0 | L217: 5 | M217: 1 | N217: 4 | O217: 3 | P217: 0 | Q217: =MONTH(A217) -> 1 | R217: 6063689 | S217: 5
A220: Ngày | B220: Tổng doanh số (VND) | C220: Tổng số đơn hàng | D220: Doanh số trên mỗi đơn hàng | E220: Tổng số lượt xem sản phẩm | F220: Số lượt truy cập | G220: Tỷ lệ chuyển đổi (theo số đơn được đặt) | H220: Đơn đã hủy | I220: Doanh số đơn hủy | J220: Đơn đã hoàn trả / hoàn tiền | K220: Doanh số các đơn Trả hàng/Hoàn tiền | L220: số người mua | M220: số người mua mới | N220: số người mua hiện tại | O220: số người mua tiềm năng | P220: Tỉ lệ quay lại của người mua
B221: =SUM(B224:B257) -> 80050785 | C221: =SUM(C224:C257) -> 86 | D221: =SUM(D224:D257) -> 25646663 | E221: =SUM(E224:E257) -> 3120 | F221: =SUM(F224:F257) -> 3227 | G221: =SUM(G224:G257) -> 0.7906 | H221: =SUM(H224:H257) -> 12 | I221: =SUM(I224:I257) -> 12539712 | ... P221: =SUM(P224:P257) -> 1.2714
...

Sheet BC TỔNG HỢP THÁNG
B2: BÁO CÁO DOANH SỐ KÊNH ONLINE
B3: Ngày báo cáo: | C3: 45901 | E3: =NOW() -> 46082.138
B5: THÁNG | C5: TARGET | D5: DOANH SỐ | E5: CHI PHÍ ADS | F5: CHÊNH LỆCH | G5: % DS/TARGET | H5: % CHI PHÍ/TARGET
B6: 1 | D6: =SUMIF('DS Shoppe (đã xác nhận)'!Q:Q,B6,'DS Shoppe (đã xác nhận)'!B:B)+SUMIF(LAZADA!S:S,B6,LAZADA!B:B)+SUMIF(WEB!N:N,B6,WEB!C:C)+SUMIF(ZALO!M:M,B6,ZALO!C:C)+SUMIF(FANPAGE!M:M,B6,FANPAGE!C:C) -> 100518008
B7: 2 | D7: =SUMIF('DS Shoppe (đã xác nhận)'!Q:Q,B7,'DS Shoppe (đã xác nhận)'!B:B)+SUMIF(LAZADA!S:S,B7,LAZADA!B:B)+SUMIF(WEB!N:N,B7,WEB!C:C)+SUMIF(ZALO!M:M,B7,ZALO!C:C)+SUMIF(FANPAGE!M:M,B7,FANPAGE!C:C) -> 83066785
B8: 3 | D8: =SUMIF('DS Shoppe (đã xác nhận)'!Q:Q,B8,'DS Shoppe (đã xác nhận)'!B:B)+SUMIF(LAZADA!S:S,B8,LAZADA!B:B)+SUMIF(WEB!N:N,B8,WEB!C:C)+SUMIF(ZALO!M:M,B8,ZALO!C:C)+SUMIF(FANPAGE!M:M,B8,FANPAGE!C:C) -> 0
B9: 4 | D9: =SUMIF('DS Shoppe (đã xác nhận)'!Q:Q,B9,'DS Shoppe (đã xác nhận)'!B:B)+SUMIF(LAZADA!S:S,B9,LAZADA!B:B)+SUMIF(WEB!N:N,B9,WEB!C:C)+SUMIF(ZALO!M:M,B9,ZALO!C:C)+SUMIF(FANPAGE!M:M,B9,FANPAGE!C:C) -> 0
B10: 5 | D10: =SUMIF('DS Shoppe (đã xác nhận)'!Q:Q,B10,'DS Shoppe (đã xác nhận)'!B:B)+SUMIF(LAZADA!S:S,B10,LAZADA!B:B)+SUMIF(WEB!N:N,B10,WEB!C:C)+SUMIF(ZALO!M:M,B10,ZALO!C:C)+SUMIF(FANPAGE!M:M,B10,FANPAGE!C:C) -> 0
B11: 6 | D11: =SUMIF('DS Shoppe (đã xác nhận)'!Q:Q,B11,'DS Shoppe (đã xác nhận)'!B:B)+SUMIF(LAZADA!S:S,B11,LAZADA!B:B)+SUMIF(WEB!N:N,B11,WEB!C:C)+SUMIF(ZALO!M:M,B11,ZALO!C:C)+SUMIF(FANPAGE!M:M,B11,FANPAGE!C:C) -> 0
B12: 7 | D12: =SUMIF('DS Shoppe (đã xác nhận)'!Q:Q,B12,'DS Shoppe (đã xác nhận)'!B:B)+SUMIF(LAZADA!S:S,B12,LAZADA!B:B)+SUMIF(WEB!N:N,B12,WEB!C:C)+SUMIF(ZALO!M:M,B12,ZALO!C:C)+SUMIF(FANPAGE!M:M,B12,FANPAGE!C:C) -> 0
B13: 8 | C13: 100000000 | D13: =SUMIF('DS Shoppe (đã xác nhận)'!Q:Q,B13,'DS Shoppe (đã xác nhận)'!B:B)+SUMIF(LAZADA!S:S,B13,LAZADA!B:B)+SUMIF(WEB!N:N,B13,WEB!C:C)+SUMIF(ZALO!M:M,B13,ZALO!C:C)+SUMIF(FANPAGE!M:M,B13,FANPAGE!C:C) -> 61588731 | E13: =SUMIFS('ADS SHOPEE'!Y:Y,'ADS SHOPEE'!AG:AG,B13) -> 3368692 | F13: =D13-C13 -> -38411269 | G13: =D13/C13-1 -> -0.38411269 | H13: =E13/D13 -> 0.054696565
B14: 9 | C14: 143182134 | D14: =SUMIF('DS Shoppe (đã xác nhận)'!Q:Q,B14,'DS Shoppe (đã xác nhận)'!B:B)+SUMIF(LAZADA!S:S,B14,LAZADA!B:B)+SUMIF(WEB!N:N,B14,WEB!C:C)+SUMIF(ZALO!M:M,B14,ZALO!C:C)+SUMIF(FANPAGE!M:M,B14,FANPAGE!C:C) -> 91815640 | E14: =SUMIFS('ADS SHOPEE'!Y:Y,'ADS SHOPEE'!AG:AG,B14) -> 10589865 | F14: =D14-C14 -> -51366494 | G14: =D14/C14-1 -> -0.35874933 | H14: =E14/D14 -> 0.11533836
B15: 10 | D15: =SUMIF('DS Shoppe (đã xác nhận)'!Q:Q,B15,'DS Shoppe (đã xác nhận)'!B:B)+SUMIF(LAZADA!S:S,B15,LAZADA!B:B)+SUMIF(WEB!N:N,B15,WEB!C:C)+SUMIF(ZALO!M:M,B15,ZALO!C:C)+SUMIF(FANPAGE!M:M,B15,FANPAGE!C:C) -> 95224742 | E15: =SUMIFS('ADS SHOPEE'!Y:Y,'ADS SHOPEE'!AG:AG,B15) -> 4947883 | F15: =D15-C15 -> 95224742 | G15: =D15/C15-1 -> #DIV/0! | H15: =E15/D15 -> 0.051960057
B16: 11 | D16: =SUMIF('DS Shoppe (đã xác nhận)'!Q:Q,B16,'DS Shoppe (đã xác nhận)'!B:B)+SUMIF(LAZADA!S:S,B16,LAZADA!B:B)+SUMIF(WEB!N:N,B16,WEB!C:C)+SUMIF(ZALO!M:M,B16,ZALO!C:C)+SUMIF(FANPAGE!M:M,B16,FANPAGE!C:C) -> 81368273 | E16: =SUMIFS('ADS SHOPEE'!Y:Y,'ADS SHOPEE'!AG:AG,B16) -> 10659302 | F16: =D16-C16 -> 81368273 | G16: =D16/C16-1 -> #DIV/0! | H16: =E16/D16 -> 0.13100072
B17: 12 | D17: =SUMIF('DS Shoppe (đã xác nhận)'!Q:Q,B17,'DS Shoppe (đã xác nhận)'!B:B)+SUMIF(LAZADA!S:S,B17,LAZADA!B:B)+SUMIF(WEB!N:N,B17,WEB!C:C)+SUMIF(ZALO!M:M,B17,ZALO!C:C)+SUMIF(FANPAGE!M:M,B17,FANPAGE!C:C) -> 89895107 | E17: =SUMIFS('ADS SHOPEE'!Y:Y,'ADS SHOPEE'!AG:AG,B17) -> 8399114 | F17: =D17-C17 -> 89895107 | G17: =D17/C17-1 -> #DIV/0! | H17: =E17/D17 -> 0.093432382
B18: Total | C18: =SUM(C6:C17) -> 243182134 | D18: =SUM(D6:D17) -> 603477286 | E18: =SUM(E6:E17) -> 37964856 | F18: =SUM(F6:F17) -> 176710359 | G18: =SUM(G6:G17) -> #DIV/0! | H18: =SUM(H6:H17) -> 0.44642808

Sheet TARGET
D2: GIÁ TRỊ TRUNG BÌNH PO | F2: 650000
E3: TARGET
D4: NGÀY | E4: Doanh số | F4: Tổng Số Po
A5: 8 | B5: THÁNG 08 | C5: 100000000 | D5: 45870 | E5: =$C$5/$C$6 -> 3225806.5 | F5: =E5/$F$2 -> 4.9627792
B6: Số ngày | C6: =COUNTA(D5:D35) -> 31 | D6: =D5+1 -> 45871 | E6: =$C$5/$C$6 -> 3225806.5 | F6: =E6/$F$2 -> 4.9627792
D7: =D6+1 -> 45872 | E7: =$C$5/$C$6 -> 3225806.5 | F7: =E7/$F$2 -> 4.9627792
D8: =D7+1 -> 45873 | E8: =$C$5/$C$6 -> 3225806.5 | F8: =E8/$F$2 -> 4.9627792
D9: =D8+1 -> 45874 | E9: =$C$5/$C$6 -> 3225806.5 | F9: =E9/$F$2 -> 4.9627792
D10: =D9+1 -> 45875 | E10: =$C$5/$C$6 -> 3225806.5 | F10: =E10/$F$2 -> 4.9627792
D11: =D10+1 -> 45876 | E11: =$C$5/$C$6 -> 3225806.5 | F11: =E11/$F$2 -> 4.9627792
D12: =D11+1 -> 45877 | E12: =$C$5/$C$6 -> 3225806.5 | F12: =E12/$F$2 -> 4.9627792
D13: =D12+1 -> 45878 | E13: =$C$5/$C$6 -> 3225806.5 | F13: =E13/$F$2 -> 4.9627792
D14: =D13+1 -> 45879 | E14: =$C$5/$C$6 -> 3225806.5 | F14: =E14/$F$2 -> 4.9627792
D15: =D14+1 -> 45880 | E15: =$C$5/$C$6 -> 3225806.5 | F15: =E15/$F$2 -> 4.9627792
D16: =D15+1 -> 45881 | E16: =$C$5/$C$6 -> 3225806.5 | F16: =E16/$F$2 -> 4.9627792
D17: =D16+1 -> 45882 | E17: =$C$5/$C$6 -> 3225806.5 | F17: =E17/$F$2 -> 4.9627792
D18: =D17+1 -> 45883 | E18: =$C$5/$C$6 -> 3225806.5 | F18: =E18/$F$2 -> 4.9627792
... D35: =D34+1 -> 45900 | E35: =$C$5/$C$6 -> 3225806.5 | F35: =E35/$F$2 -> 4.9627792
A36: 9 | B36: THÁNG 09 | C36: 1.4318213e+08 | D36: =D35+1 -> 45901 | E36: =$C$36/$C$37 -> 4772737.8 | F36: =E36/$F$2 -> 7.3426735
B37: Số ngày | C37: =COUNTA(D36:D65) -> 30 | D37: =D36+1 -> 45902 | E37: =$C$36/$C$37 -> 4772737.8 | F37: =E37/$F$2 -> 7.3426735
D38: =D37+1 -> 45903 | E38: =$C$36/$C$37 -> 4772737.8 | F38: =E38/$F$2 -> 7.3426735
D39: =D38+1 -> 45904 | E39: =$C$36/$C$37 -> 4772737.8 | F39: =E39/$F$2 -> 7.3426735
D40: =D39+1 -> 45905 | E40: =$C$36/$C$37 -> 4772737.8 | F40: =E40/$F$2 -> 7.3426735
D41: =D40+1 -> 45906 | E41: =$C$36/$C$37 -> 4772737.8 | F41: =E41/$F$2 -> 7.3426735
D42: =D41+1 -> 45907 | E42: =$C$36/$C$37 -> 4772737.8 | F42: =E42/$F$2 -> 7.3426735
D43: =D42+1 -> 45908 | E43: =$C$36/$C$37 -> 4772737.8 | F43: =E43/$F$2 -> 7.3426735
D44: =D43+1 -> 45909 | E44: =$C$36/$C$37 -> 4772737.8 | F44: =E44/$F$2 -> 7.3426735
D45: =D44+1 -> 45910 | E45: =$C$36/$C$37 -> 4772737.8 | F45: =E45/$F$2 -> 7.3426735
D46: =D45+1 -> 45911 | E46: =$C$36/$C$37 -> 4772737.8 | F46: =E46/$F$2 -> 7.3426735
D47: =D46+1 -> 45912 | E47: =$C$36/$C$37 -> 4772737.8 | F47: =E47/$F$2 -> 7.3426735
D48: =D47+1 -> 45913 | E48: =$C$36/$C$37 -> 4772737.8 | F48: =E48/$F$2 -> 7.3426735
D49: =D48+1 -> 45914 | E49: =$C$36/$C$37 -> 4772737.8 | F49: =E49/$F$2 -> 7.3426735
... D65: =D64+1 -> 45930 | E65: =$C$36/$C$37 -> 4772737.8 | F65: =E65/$F$2 -> 7.3426735
B66: THÁNG 10 | C66: 153986325 | D66: =D65+1 -> 45931 | E66: =$C$66/$C$67 -> 4967300.8 | F66: =E66/$F$2 -> 7.6420012
B67: Số ngày | C67: =COUNTA(D66:D96) -> 31 | D67: =D66+1 -> 45932 | E67: =$C$66/$C$67 -> 4967300.8 | F67: =E67/$F$2 -> 7.6420012
D68: =D67+1 -> 45933 | E68: =$C$66/$C$67 -> 4967300.8 | F68: =E68/$F$2 -> 7.6420012
D69: =D68+1 -> 45934 | E69: =$C$66/$C$67 -> 4967300.8 | F69: =E69/$F$2 -> 7.6420012
D70: =D69+1 -> 45935 | E70: =$C$66/$C$67 -> 4967300.8 | F70: =E70/$F$2 -> 7.6420012
D71: =D70+1 -> 45936 | E71: =$C$66/$C$67 -> 4967300.8 | F71: =E71/$F$2 -> 7.6420012
D72: =D71+1 -> 45937 | E72: =$C$66/$C$67 -> 4967300.8 | F72: =E72/$F$2 -> 7.6420012
D73: =D72+1 -> 45938 | E73: =$C$66/$C$67 -> 4967300.8 | F73: =E73/$F$2 -> 7.6420012
D74: =D73+1 -> 45939 | E74: =$C$66/$C$67 -> 4967300.8 | F74: =E74/$F$2 -> 7.6420012
D75: =D74+1 -> 45940 | E75: =$C$66/$C$67 -> 4967300.8 | F75: =E75/$F$2 -> 7.6420012
D76: =D75+1 -> 45941 | E76: =$C$66/$C$67 -> 4967300.8 | F76: =E76/$F$2 -> 7.6420012
D77: =D76+1 -> 45942 | E77: =$C$66/$C$67 -> 4967300.8 | F77: =E77/$F$2 -> 7.6420012
D78: =D77+1 -> 45943 | E78: =$C$66/$C$67 -> 4967300.8 | F78: =E78/$F$2 -> 7.6420012
D79: =D78+1 -> 45944 | E79: =$C$66/$C$67 -> 4967300.8 | F79: =E79/$F$2 -> 7.6420012
... D96: =D95+1 -> 45961 | E96: =$C$66/$C$67 -> 4967300.8 | F96: =E96/$F$2 -> 7.6420012
B97: THÁNG 11 | C97: 157925000 | D97: =D96+1 -> 45962 | E97: =$C$97/$C$98 -> 5264166.7 | F97: =E97/$F$2 -> 8.0987179
B98: Số ngày | C98: 30 | D98: =D97+1 -> 45963 | E98: =$C$97/$C$98 -> 5264166.7 | F98: =E98/$F$2 -> 8.0987179
D99: =D98+1 -> 45964 | E99: =$C$97/$C$98 -> 5264166.7 | F99: =E99/$F$2 -> 8.0987179
D100: =D99+1 -> 45965 | E100: =$C$97/$C$98 -> 5264166.7 | F100: =E100/$F$2 -> 8.0987179
D101: =D100+1 -> 45966 | E101: =$C$97/$C$98 -> 5264166.7 | F101: =E101/$F$2 -> 8.0987179
D102: =D101+1 -> 45967 | E102: =$C$97/$C$98 -> 5264166.7 | F102: =E102/$F$2 -> 8.0987179
D103: =D102+1 -> 45968 | E103: =$C$97/$C$98 -> 5264166.7 | F103: =E103/$F$2 -> 8.0987179
D104: =D103+1 -> 45969 | E104: =$C$97/$C$98 -> 5264166.7 | F104: =E104/$F$2 -> 8.0987179
D105: =D104+1 -> 45970 | E105: =$C$97/$C$98 -> 5264166.7 | F105: =E105/$F$2 -> 8.0987179
D106: =D105+1 -> 45971 | E106: =$C$97/$C$98 -> 5264166.7 | F106: =E106/$F$2 -> 8.0987179
D107: =D106+1 -> 45972 | E107: =$C$97/$C$98 -> 5264166.7 | F107: =E107/$F$2 -> 8.0987179
D108: =D107+1 -> 45973 | E108: =$C$97/$C$98 -> 5264166.7 | F108: =E108/$F$2 -> 8.0987179
D109: =D108+1 -> 45974 | E109: =$C$97/$C$98 -> 5264166.7 | F109: =E109/$F$2 -> 8.0987179
D110: =D109+1 -> 45975 | E110: =$C$97/$C$98 -> 5264166.7 | F110: =E110/$F$2 -> 8.0987179
... D126: =D125+1 -> 45991 | E126: =$C$97/$C$98 -> 5264166.7 | F126: =E126/$F$2 -> 8.0987179
B127: THÁNG 12 | C127: 150510000 | D127: =D126+1 -> 45992 | E127: =$C$127/$C$128 -> 4855161.3 | F127: =E127/$F$2 -> 7.4694789
B128: Số ngày | C128: 31 | D128: =D127+1 -> 45993 | E128: =$C$127/$C$128 -> 4855161.3 | F128: =E128/$F$2 -> 7.4694789
D129: =D128+1 -> 45994 | E129: =$C$127/$C$128 -> 4855161.3 | F129: =E129/$F$2 -> 7.4694789
D130: =D129+1 -> 45995 | E130: =$C$127/$C$128 -> 4855161.3 | F130: =E130/$F$2 -> 7.4694789
D131: =D130+1 -> 45996 | E131: =$C$127/$C$128 -> 4855161.3 | F131: =E131/$F$2 -> 7.4694789
D132: =D131+1 -> 45997 | E132: =$C$127/$C$128 -> 4855161.3 | F132: =E132/$F$2 -> 7.4694789
D133: =D132+1 -> 45998 | E133: =$C$127/$C$128 -> 4855161.3 | F133: =E133/$F$2 -> 7.4694789
D134: =D133+1 -> 45999 | E134: =$C$127/$C$128 -> 4855161.3 | F134: =E134/$F$2 -> 7.4694789
D135: =D134+1 -> 46000 | E135: =$C$127/$C$128 -> 4855161.3 | F135: =E135/$F$2 -> 7.4694789
D136: =D135+1 -> 46001 | E136: =$C$127/$C$128 -> 4855161.3 | F136: =E136/$F$2 -> 7.4694789
D137: =D136+1 -> 46002 | E137: =$C$127/$C$128 -> 4855161.3 | F137: =E137/$F$2 -> 7.4694789
D138: =D137+1 -> 46003 | E138: =$C$127/$C$128 -> 4855161.3 | F138: =E138/$F$2 -> 7.4694789
D139: =D138+1 -> 46004 | E139: =$C$127/$C$128 -> 4855161.3 | F139: =E139/$F$2 -> 7.4694789
D140: =D139+1 -> 46005 | E140: =$C$127/$C$128 -> 4855161.3 | F140: =E140/$F$2 -> 7.4694789
... D157: =D156+1 -> 46022 | E157: =$C$127/$C$128 -> 4855161.3 | F157: =E157/$F$2 -> 7.4694789
B159: THÁNG 01 | C159: 149955000 | D159: =D157+1 -> 46023 | E159: =$C$159/$C$160 -> 4837258.1 | F159: =E159/$F$2 -> 7.4419355
B160: Số ngày | C160: 31 | D160: =D159+1 -> 46024 | E160: =$C$159/$C$160 -> 4837258.1 | F160: =E160/$F$2 -> 7.4419355
D161: =D160+1 -> 46025 | E161: =$C$159/$C$160 -> 4837258.1 | F161: =E161/$F$2 -> 7.4419355
D162: =D161+1 -> 46026 | E162: =$C$159/$C$160 -> 4837258.1 | F162: =E162/$F$2 -> 7.4419355
D163: =D162+1 -> 46027 | E163: =$C$159/$C$160 -> 4837258.1 | F163: =E163/$F$2 -> 7.4419355
D164: =D163+1 -> 46028 | E164: =$C$159/$C$160 -> 4837258.1 | F164: =E164/$F$2 -> 7.4419355
D165: =D164+1 -> 46029 | E165: =$C$159/$C$160 -> 4837258.1 | F165: =E165/$F$2 -> 7.4419355
D166: =D165+1 -> 46030 | E166: =$C$159/$C$160 -> 4837258.1 | F166: =E166/$F$2 -> 7.4419355
D167: =D166+1 -> 46031 | E167: =$C$159/$C$160 -> 4837258.1 | F167: =E167/$F$2 -> 7.4419355
D168: =D167+1 -> 46032 | E168: =$C$159/$C$160 -> 4837258.1 | F168: =E168/$F$2 -> 7.4419355
D169: =D168+1 -> 46033 | E169: =$C$159/$C$160 -> 4837258.1 | F169: =E169/$F$2 -> 7.4419355
D170: =D169+1 -> 46034 | E170: =$C$159/$C$160 -> 4837258.1 | F170: =E170/$F$2 -> 7.4419355
D171: =D170+1 -> 46035 | E171: =$C$159/$C$160 -> 4837258.1 | F171: =E171/$F$2 -> 7.4419355
D172: =D171+1 -> 46036 | E172: =$C$159/$C$160 -> 4837258.1 | F172: =E172/$F$2 -> 7.4419355
... D189: =D188+1 -> 46053 | E189: =$C$159/$C$160 -> 4837258.1 | F189: =E189/$F$2 -> 7.4419355
B190: THÁNG 02 | C190: 125000000 | D190: =D189+1 -> 46054 | E190: =$C$190/$C$191 -> 4464285.7 | F190: =E190/$F$2 -> 6.8681319
B191: Số ngày | C191: 28 | D191: =D190+1 -> 46055 | E191: =$C$190/$C$191 -> 4464285.7 | F191: =E191/$F$2 -> 6.8681319
D192: =D191+1 -> 46056 | E192: =$C$190/$C$191 -> 4464285.7 | F192: =E192/$F$2 -> 6.8681319
D193: =D192+1 -> 46057 | E193: =$C$190/$C$191 -> 4464285.7 | F193: =E193/$F$2 -> 6.8681319
D194: =D193+1 -> 46058 | E194: =$C$190/$C$191 -> 4464285.7 | F194: =E194/$F$2 -> 6.8681319
D195: =D194+1 -> 46059 | E195: =$C$190/$C$191 -> 4464285.7 | F195: =E195/$F$2 -> 6.8681319
D196: =D195+1 -> 46060 | E196: =$C$190/$C$191 -> 4464285.7 | F196: =E196/$F$2 -> 6.8681319
...

Sheet Bản sao của BÁO CÁO
B1: BÁO CÁO BÁN HÀNG SHOPEE THÁNG 08.2025 | J1: 45870 | L1: - | M1: =TODAY() -> 46082
B2: Ngày báo cáo: | D2: =NOW() -> 46082.138
B3: CHỈ TIÊU | D3: TARGET | E3: THỰC ĐẠT | F3: CHÊNH LỆCH TĐ/TARGET | G3: % TĐ/TARGET | AA3: CHI PHÍ & DOANH SỐ TỪ QUẢNG CÁO SHOPEE THÁNG 08.2025
B4: DOANH SỐ | D4: =C15 -> 100000000 | E4: =E15 -> 68896824 | F4: =E4-D4 -> -31103176 | G4: =E4/D4 -> 0.68896824 | AA4: Tính đến thời điểm: | AC4: ='ADS SHOPEE'!B60 -> 45903.358
B5: Tổng PO | D5: =D15 -> 153.84615 | E5: =F15 -> 108 | F5: =E5-D5 -> -45.846154 | G5: =E5/D5 -> 0.702
B6: Doanh số từ quảng cáo | E6: ='ADS SHOPEE'!W62 -> 24639954
B7: Chi phí từ quảng cáo | E7: ='ADS SHOPEE'!Y62 -> 3368692
B8: % Doanh số từ quảng cáo/DS TĐ | G8: =E6/E4 -> 0.35763556
B9: % Chi phí quảng cáo/DS từ Quảng cáo | G9: =E7/E6 -> 0.13671665
B12: GIÁ TRỊ BÌNH QUÂN PO | D12: 650000 | H12: =E15/C15-1 -> -0.31103176 | I12: =F15/D15-1 -> -0.298
B13: Ngày | C13: TARGET | E13: THỰC HIỆN | H13: % THỰC ĐẠT/TARGET | J13: CHÊNH LỆCH THỰC ĐẠT/TARGET | L13: Đơn đã hủy | M13: Doanh số đơn hủy | N13: Đơn đã hoàn trả / hoàn tiền | O13: Doanh số các đơn Trả hàng/ Hoàn tiền | W13: =SUM(W15:W55) -> 67022819
C14: Doanh số | D14: Tổng số PO | E14: Doanh số thực đạt | F14: Tổng số PO | G14: Giá Trị Po Bình Quân | H14: Doanh số | I14: Tổng số PO | J14: Doanh số | K14: Tổng số PO | S14: STT | T14: Sản phẩm | U14: Tên Phân Loại | V14: SUM của Sản phẩm (Đơn đã xác nhận) | W14: SUM của Doanh số (Đơn đã xác nhận) (VND) | X14: NOTE | AA14: CHI PHÍ & DOANH SỐ TỪ QUẢNG CÁO SHOPEE THÁNG 07.2025
B15: TOTAL | C15: =SUBTOTAL(9,C16:C49) -> 100000000 | D15: =SUBTOTAL(9,D16:D49) -> 153.84615 | E15: =SUBTOTAL(9,E16:E49) -> 68896824 | F15: =SUBTOTAL(9,F16:F49) -> 108 | G15: =E15/F15 -> 637933.56 | H15: =E15/C15 -> 0.68896824 | I15: =F15/D15 -> 0.702 | J15: =SUBTOTAL(9,J16:J49) -> -31103176 | K15: =SUBTOTAL(9,K16:K49) -> -45.846154 | L15: =SUBTOTAL(9,L16:L49) -> 16 | M15: =SUBTOTAL(9,M16:M49) -> 13739256 | N15: =SUBTOTAL(9,N16:N49) -> 3 | O15: =SUBTOTAL(9,O16:O49) -> 0 | S15: 1 | T15: ='Bảng tổng hợp 1'!A3 -> Viên uống HB GutCare (30 - 60 viên) hỗ trợ giảm triệu chứng đau khớp | U15: ='Bảng tổng hợp 1'!B3 -> - | V15: ='Bảng tổng hợp 1'!C3 -> 2 | W15: ='Bảng tổng hợp 1'!D3 -> 1166880
B16: 45870 | C16: =100000000/31 -> 3225806.5 | D16: =C16/$D$12 -> 4.9627792 | E16: ='DS Shoppe (đã xác nhận)'!B42 -> 4281650 | F16: ='DS Shoppe (đã xác nhận)'!C42 -> 5 | G16: =E16/F16 -> 856330 | H16: =E16/C16 -> 1.3273115 | I16: =F16/D16 -> 1.0075 | J16: =E16-C16 -> 1055843.5 | K16: =F16-D16 -> 0.037220844 | L16: ='DS Shoppe (đã xác nhận)'!H42 -> 1 | M16: ='DS Shoppe (đã xác nhận)'!I42 -> 219500 | N16: ='DS Shoppe (đã xác nhận)'!J42 -> 0 | O16: ='DS Shoppe (đã xác nhận)'!K42 -> 0 | S16: =S15+1 -> 2 | T16: ='Bảng tổng hợp 1'!A4 | U16: ='Bảng tổng hợp 1'!B4 -> 60 viên | V16: ='Bảng tổng hợp 1'!C4 -> 2 | W16: ='Bảng tổng hợp 1'!D4 -> 1166880
B17: =B16+1 -> 45871 | C17: =100000000/31 -> 3225806.5 | D17: =C17/$D$12 -> 4.9627792 | E17: ='DS Shoppe (đã xác nhận)'!B43 -> 1780500 | F17: ='DS Shoppe (đã xác nhận)'!C43 -> 3 | G17: =E17/F17 -> 593500 | H17: =E17/C17 -> 0.551955 | I17: =F17/D17 -> 0.6045 | J17: =E17-C17 -> -1445306.5 | K17: =F17-D17 -> -1.9627792 | L17: ='DS Shoppe (đã xác nhận)'!H43 -> 0 | M17: ='DS Shoppe (đã xác nhận)'!I43 -> 0 | N17: ='DS Shoppe (đã xác nhận)'!J43 -> 0 | O17: ='DS Shoppe (đã xác nhận)'!K43 -> 0 | S17: =S16+1 -> 3 | T17: ='Bảng tổng hợp 1'!A6 | U17: ='Bảng tổng hợp 1'!B6 -> 30 viên | V17: ='Bảng tổng hợp 1'!C6 -> 5 | W17: ='Bảng tổng hợp 1'!D6 -> 5278000
B18: =B17+1 -> 45872 | C18: =100000000/31 -> 3225806.5 | D18: =C18/$D$12 -> 4.9627792 | E18: ='DS Shoppe (đã xác nhận)'!B44 -> 0 | F18: ='DS Shoppe (đã xác nhận)'!C44 -> 1 | H18: =E18/C18 -> 0 | I18: =F18/D18 -> 0.2015 | J18: =E18-C18 -> -3225806.5 | K18: =F18-D18 -> -3.9627792 | L18: ='DS Shoppe (đã xác nhận)'!H44 -> 1 | M18: ='DS Shoppe (đã xác nhận)'!I44 -> 827200 | N18: ='DS Shoppe (đã xác nhận)'!J44 -> 0 | O18: ='DS Shoppe (đã xác nhận)'!K44 -> 0 | S18: =S17+1 -> 4 | T18: Viên uống HB Visionfort Support 30 viên - 60 viên | U18: 60 viên | X18: HẾT HÀNG
B19: =B18+1 -> 45873 | C19: =100000000/31 -> 3225806.5 | D19: =C19/$D$12 -> 4.9627792 | E19: ='DS Shoppe (đã xác nhận)'!B45 -> 1194720 | F19: ='DS Shoppe (đã xác nhận)'!C45 -> 3 | H19: =E19/C19 -> 0.3703632 | I19: =F19/D19 -> 0.6045 | J19: =E19-C19 -> -2031086.5 | K19: =F19-D19 -> -1.9627792 | L19: ='DS Shoppe (đã xác nhận)'!H45 -> 0 | M19: ='DS Shoppe (đã xác nhận)'!I45 -> 0 | N19: ='DS Shoppe (đã xác nhận)'!J45 -> 0 | O19: ='DS Shoppe (đã xác nhận)'!K45 -> 0 | S19: =S18+1 -> 5 | T19: ='Bảng tổng hợp 1'!A8 | U19: ='Bảng tổng hợp 1'!B8 -> 60 viên | V19: ='Bảng tổng hợp 1'!C8 -> 5 | W19: ='Bảng tổng hợp 1'!D8 -> 1733140
B20: =B19+1 -> 45874 | C20: =100000000/31 -> 3225806.5 | D20: =C20/$D$12 -> 4.9627792 | E20: ='DS Shoppe (đã xác nhận)'!B46 -> 1583200 | F20: ='DS Shoppe (đã xác nhận)'!C46 -> 3 | H20: =E20/C20 -> 0.490792 | I20: =F20/D20 -> 0.6045 | J20: =E20-C20 -> -1642606.5 | K20: =F20-D20 -> -1.9627792 | L20: ='DS Shoppe (đã xác nhận)'!H46 -> 1 | M20: ='DS Shoppe (đã xác nhận)'!I46 -> 279572 | N20: ='DS Shoppe (đã xác nhận)'!J46 -> 0 | O20: ='DS Shoppe (đã xác nhận)'!K46 -> 0 | S20: =S19+1 -> 6 | T20: ='Bảng tổng hợp 1'!A10 -> Viên uống HB Arginmilk Plus 60 viên | U20: ='Bảng tổng hợp 1'!B10 -> - | V20: ='Bảng tổng hợp 1'!C10 -> 4 | W20: ='Bảng tổng hợp 1'!D10 -> 2364865
B21: =B20+1 -> 45875 | C21: =100000000/31 -> 3225806.5 | D21: =C21/$D$12 -> 4.9627792 | E21: ='DS Shoppe (đã xác nhận)'!B47 -> 277743 | F21: ='DS Shoppe (đã xác nhận)'!C47 -> 1 | G21: =E21/F21 -> 277743 | H21: =E21/C21 -> 0.08610033 | I21: =F21/D21 -> 0.2015 | J21: =E21-C21 -> -2948063.5 | K21: =F21-D21 -> -3.9627792 | L21: ='DS Shoppe (đã xác nhận)'!H47 -> 0 | M21: ='DS Shoppe (đã xác nhận)'!I47 -> 0 | N21: ='DS Shoppe (đã xác nhận)'!J47 -> 0 | O21: ='DS Shoppe (đã xác nhận)'!K47 -> 0 | S21: =S20+1 -> 7 | T21: ='Bảng tổng hợp 1'!A28 -> Viên Uống Bổ Sung 30 Loại Vitamin Và Khoáng Chất Cho Nam HB ONCE DAILY MEN'S MULTI | U21: ='Bảng tổng hợp 1'!B28 -> - | V21: ='Bảng tổng hợp 1'!C28 -> 0 | W21: ='Bảng tổng hợp 1'!D28 -> 0
B22: =B21+1 -> 45876 | C22: =100000000/31 -> 3225806.5 | D22: =C22/$D$12 -> 4.9627792 | E22: ='DS Shoppe (đã xác nhận)'!B48 -> 245064 | F22: ='DS Shoppe (đã xác nhận)'!C48 -> 2 | H22: =E22/C22 -> 0.07596984 | I22: =F22/D22 -> 0.403 | J22: =E22-C22 -> -2980742.5 | K22: =F22-D22 -> -2.9627792 | L22: ='DS Shoppe (đã xác nhận)'!H48 -> 1 | M22: ='DS Shoppe (đã xác nhận)'!I48 -> 517999 | N22: ='DS Shoppe (đã xác nhận)'!J48 -> 0 | O22: ='DS Shoppe (đã xác nhận)'!K48 -> 0 | S22: =S21+1 -> 8 | T22: ='Bảng tổng hợp 1'!A13 | U22: ='Bảng tổng hợp 1'!B13 -> 30 viên | V22: ='Bảng tổng hợp 1'!C13 -> 4 | W22: ='Bảng tổng hợp 1'!D13 -> 1818607
B23: =B22+1 -> 45877 | C23: =100000000/31 -> 3225806.5 | D23: =C23/$D$12 -> 4.9627792 | E23: ='DS Shoppe (đã xác nhận)'!B49 -> 0 | F23: ='DS Shoppe (đã xác nhận)'!C49 -> 1 | G23: =E23/F23 -> 0 | H23: =E23/C23 -> 0 | I23: =F23/D23 -> 0.2015 | J23: =E23-C23 -> -3225806.5 | K23: =F23-D23 -> -3.9627792 | L23: ='DS Shoppe (đã xác nhận)'!H49 -> 1 | M23: ='DS Shoppe (đã xác nhận)'!I49 -> 883575 | N23: ='DS Shoppe (đã xác nhận)'!J49 -> 0 | O23: ='DS Shoppe (đã xác nhận)'!K49 -> 0 | S23: =S22+1 -> 9 | T23: ='Bảng tổng hợp 1'!A15 -> Viên Uống Giúp Chống Nắng Trắng Da Mờ Nám HB GLUTA WHITE + | U23: ='Bảng tổng hợp 1'!B15 -> - | V23: ='Bảng tổng hợp 1'!C15 -> 25 | W23: ='Bảng tổng hợp 1'!D15 -> 23349080
B24: =B23+1 -> 45878 | C24: =100000000/31 -> 3225806.5 | D24: =C24/$D$12 -> 4.9627792 | E24: ='DS Shoppe (đã xác nhận)'!B50 -> 11305684 | F24: ='DS Shoppe (đã xác nhận)'!C50 -> 17 | G24: =E24/F24 -> 665040.24 | H24: =E24/C24 -> 3.504762 | I24: =F24/D24 -> 3.4255 | J24: =E24-C24 -> 8079877.5 | K24: =F24-D24 -> 12.037221 | L24: ='DS Shoppe (đã xác nhận)'!H50 -> 1 | M24: ='DS Shoppe (đã xác nhận)'!I50 -> 1095930 | N24: ='DS Shoppe (đã xác nhận)'!J50 -> 1 | O24: ='DS Shoppe (đã xác nhận)'!K50 -> 0 | S24: =S23+1 -> 10 | T24: ='Bảng tổng hợp 1'!A16 -> Viên uống giúp Bổ Sung Canxi và Vitamin D3 HB CALCIDSOFT | U24: ='Bảng tổng hợp 1'!B16 -> - | V24: ='Bảng tổng hợp 1'!C16 -> 13 | W24: ='Bảng tổng hợp 1'!D16 -> 3674311
B25: =B24+1 -> 45879 | C25: =100000000/31 -> 3225806.5 | D25: =C25/$D$12 -> 4.9627792 | E25: ='DS Shoppe (đã xác nhận)'!B51 -> 4824140 | F25: ='DS Shoppe (đã xác nhận)'!C51 -> 7 | G25: =E25/F25 -> 689162.86 | H25: =E25/C25 -> 1.4954834 | I25: =F25/D25 -> 1.4105 | J25: =E25-C25 -> 1598333.5 | K25: =F25-D25 -> 2.0372208 | L25: ='DS Shoppe (đã xác nhận)'!H51 -> 0 | M25: ='DS Shoppe (đã xác nhận)'!I51 -> 0 | N25: ='DS Shoppe (đã xác nhận)'!J51 -> 0 | O25: ='DS Shoppe (đã xác nhận)'!K51 -> 0 | S25: =S24+1 -> 11 | T25: ='Bảng tổng hợp 1'!A18 | U25: ='Bảng tổng hợp 1'!B18 -> Hộp 60 Viên | V25: ='Bảng tổng hợp 1'!C18 -> 11 | W25: ='Bảng tổng hợp 1'!D18 -> 3284431
B26: =B25+1 -> 45880 | C26: =100000000/31 -> 3225806.5 | D26: =C26/$D$12 -> 4.9627792 | E26: ='DS Shoppe (đã xác nhận)'!B52 -> 2116600 | F26: ='DS Shoppe (đã xác nhận)'!C52 -> 2 | G26: =E26/F26 -> 1058300 | H26: =E26/C26 -> 0.656146 | I26: =F26/D26 -> 0.403 | J26: =E26-C26 -> -1109206.5 | K26: =F26-D26 -> -2.9627792 | L26: ='DS Shoppe (đã xác nhận)'!H52 -> 0 | M26: ='DS Shoppe (đã xác nhận)'!I52 -> 0 | N26: ='DS Shoppe (đã xác nhận)'!J52 -> 0 | O26: ='DS Shoppe (đã xác nhận)'!K52 -> 0 | S26: =S25+1 -> 12 | T26: ='Bảng tổng hợp 1'!A19 -> Viên Uống Giảm Gãy Rụng và Đen Tóc HB Black Hair Healthy Beauty (date 15/02/2026) | U26: ='Bảng tổng hợp 1'!B19 -> - | V26: ='Bảng tổng hợp 1'!C19 -> 9 | W26: ='Bảng tổng hợp 1'!D19 -> 5496780
B27: =B26+1 -> 45881 | C27: =100000000/31 -> 3225806.5 | D27: =C27/$D$12 -> 4.9627792 | E27: ='DS Shoppe (đã xác nhận)'!B53 -> 2514900 | F27: ='DS Shoppe (đã xác nhận)'!C53 -> 2 | G27: =E27/F27 -> 1257450 | H27: =E27/C27 -> 0.779619 | I27: =F27/D27 -> 0.403 | J27: =E27-C27 -> -710906.45 | K27: =F27-D27 -> -2.9627792 | L27: ='DS Shoppe (đã xác nhận)'!H53 -> 0 | M27: ='DS Shoppe (đã xác nhận)'!I53 -> 0 | N27: ='DS Shoppe (đã xác nhận)'!J53 -> 1 | O27: ='DS Shoppe (đã xác nhận)'!K53 -> 0 | S27: =S26+1 -> 13 | T27: ='Bảng tổng hợp 1'!A23 -> Viên Uống Đông Trùng Hạ Thảo Bồi Bổ Khí Huyết HB CORDY EXTRACT | U27: ='Bảng tổng hợp 1'!B23 -> - | V27: ='Bảng tổng hợp 1'!C23 -> 0 | W27: ='Bảng tổng hợp 1'!D23 -> 0
B28: =B27+1 -> 45882 | C28: =100000000/31 -> 3225806.5 | D28: =C28/$D$12 -> 4.9627792 | E28: ='DS Shoppe (đã xác nhận)'!B54 -> 0 | F28: ='DS Shoppe (đã xác nhận)'!C54 -> 1 | G28: =E28/F28 -> 0 | H28: =E28/C28 -> 0 | I28: =F28/D28 -> 0.2015 | J28: =E28-C28 -> -3225806.5 | K28: =F28-D28 -> -3.9627792 | L28: ='DS Shoppe (đã xác nhận)'!H54 -> 1 | M28: ='DS Shoppe (đã xác nhận)'!I54 -> 704000 | N28: ='DS Shoppe (đã xác nhận)'!J54 -> 0 | O28: ='DS Shoppe (đã xác nhận)'!K54 -> 0 | S28: =S27+1 -> 14 | T28: ='Bảng tổng hợp 1'!A26 | U28: ='Bảng tổng hợp 1'!B26 -> 60 Viên | V28: ='Bảng tổng hợp 1'!C26 -> 1 | W28: ='Bảng tổng hợp 1'!D26 -> 677320
B29: =B28+1 -> 45883 | C29: =100000000/31 -> 3225806.5 | D29: =C29/$D$12 -> 4.9627792 | E29: ='DS Shoppe (đã xác nhận)'!B55 -> 2882020 | F29: ='DS Shoppe (đã xác nhận)'!C55 -> 6 | G29: =E29/F29 -> 480336.67 | H29: =E29/C29 -> 0.8934262 | I29: =F29/D29 -> 1.209 | J29: =E29-C29 -> -343786.45 | K29: =F29-D29 -> 1.0372208 | L29: ='DS Shoppe (đã xác nhận)'!H55 -> 1 | M29: ='DS Shoppe (đã xác nhận)'!I55 -> 792000 | N29: ='DS Shoppe (đã xác nhận)'!J55 -> 1 | O29: ='DS Shoppe (đã xác nhận)'!K55 -> 0 | S29: =S28+1 -> 15 | T29: ='Bảng tổng hợp 1'!A27 | U29: ='Bảng tổng hợp 1'!B27 -> Hộp/Vỉ 10 viên x 3 | V29: ='Bảng tổng hợp 1'!C27 -> 1 | W29: ='Bảng tổng hợp 1'!D27 -> 374640 | AA29: CHI PHÍ & DOANH SỐ TỪ QUẢNG CÁO SHOPEE THÁNG 06.2025
B30: =B29+1 -> 45884 | C30: =100000000/31 -> 3225806.5 | D30: =C30/$D$12 -> 4.9627792 | E30: ='DS Shoppe (đã xác nhận)'!B56 -> 5539445 | F30: ='DS Shoppe (đã xác nhận)'!C56 -> 10 | G30: =E30/F30 -> 553944.5 | H30: =E30/C30 -> 1.717228 | I30: =F30/D30 -> 2.015 | J30: =E30-C30 -> 2313638.5 | K30: =F30-D30 -> 5.0372208 | L30: ='DS Shoppe (đã xác nhận)'!H56 -> 3 | M30: ='DS Shoppe (đã xác nhận)'!I56 -> 3948210 | N30: ='DS Shoppe (đã xác nhận)'!J56 -> 0 | O30: ='DS Shoppe (đã xác nhận)'!K56 -> 0 | S30: =S29+1 -> 16 | T30: ='Bảng tổng hợp 1'!A30 -> Khẩu Trang Y Tế Kháng Khuẩn HB Medical Mask Cao Cấp Healthy Beauty 1 Hộp 50 cái | U30: ='Bảng tổng hợp 1'!B30 -> - | V30: ='Bảng tổng hợp 1'!C30 -> 17 | W30: ='Bảng tổng hợp 1'!D30 -> 952500 | AA30: Tính đến thời điểm: | AC30: =#REF! -> #REF!
B31: =B30+1 -> 45885 | C31: =100000000/31 -> 3225806.5 | D31: =C31/$D$12 -> 4.9627792 | E31: ='DS Shoppe (đã xác nhận)'!B57 -> 679400 | F31: ='DS Shoppe (đã xác nhận)'!C57 -> 1 | G31: =E31/F31 -> 679400 | H31: =E31/C31 -> 0.210614 | I31: =F31/D31 -> 0.2015 | J31: =E31-C31 -> -2546406.5 | K31: =F31-D31 -> -3.9627792 | L31: ='DS Shoppe (đã xác nhận)'!H57 -> 0 | M31: ='DS Shoppe (đã xác nhận)'!I57 -> 0 | N31: ='DS Shoppe (đã xác nhận)'!J57 -> 0 | O31: ='DS Shoppe (đã xác nhận)'!K57 -> 0 | S31: =S30+1 -> 17 | T31: ='Bảng tổng hợp 1'!A31 | U31: ='Bảng tổng hợp 1'!B31 -> Màu Trắng | V31: ='Bảng tổng hợp 1'!C31 -> 11 | W31: ='Bảng tổng hợp 1'!D31 -> 609500
B32: =B31+1 -> 45886 | C32: =100000000/31 -> 3225806.5 | D32: =C32/$D$12 -> 4.9627792 | E32: ='DS Shoppe (đã xác nhận)'!B58 -> 3231860 | F32: ='DS Shoppe (đã xác nhận)'!C58 -> 5 | G32: =E32/F32 -> 646372 | H32: =E32/C32 -> 1.0018766 | I32: =F32/D32 -> 1.0075 | J32: =E32-C32 -> 6053.5484 | K32: =F32-D32 -> 0.037220844 | L32: ='DS Shoppe (đã xác nhận)'!H58 -> 1 | M32: ='DS Shoppe (đã xác nhận)'!I58 -> 804100 | N32: ='DS Shoppe (đã xác nhận)'!J58 -> 0 | O32: ='DS Shoppe (đã xác nhận)'!K58 -> 0 | S32: =S31+1 -> 18 | T32: ='Bảng tổng hợp 1'!A33 | U32: ='Bảng tổng hợp 1'!B33 -> Than Hoạt Tính | V32: ='Bảng tổng hợp 1'!C33 -> 5 | W32: ='Bảng tổng hợp 1'!D33 -> 295000
B33: =B32+1 -> 45887 | C33: =100000000/31 -> 3225806.5 | D33: =C33/$D$12 -> 4.9627792 | E33: ='DS Shoppe (đã xác nhận)'!B59 -> 1736260 | F33: ='DS Shoppe (đã xác nhận)'!C59 -> 2 | H33: =E33/C33 -> 0.5382406 | I33: =F33/D33 -> 0.403 | J33: =E33-C33 -> -1489546.5 | K33: =F33-D33 -> -2.9627792 | L33: ='DS Shoppe (đã xác nhận)'!H59 -> 0 | M33: ='DS Shoppe (đã xác nhận)'!I59 -> 0 | N33: ='DS Shoppe (đã xác nhận)'!J59 -> 0 | O33: ='DS Shoppe (đã xác nhận)'!K59 -> 0 | S33: =S32+1 -> 19 | T33: ='Bảng tổng hợp 1'!A34 -> HB MEDICAL MASK - Túi zip - Khẩu trang y tế 4 lớp kháng khuẩn chuẩn nhóm A | U33: ='Bảng tổng hợp 1'!B34 -> - | V33: ='Bảng tổng hợp 1'!C34 -> 0 | W33: ='Bảng tổng hợp 1'!D34 -> 0
B34: =B33+1 -> 45888 | C34: =100000000/31 -> 3225806.5 | D34: =C34/$D$12 -> 4.9627792 | E34: ='DS Shoppe (đã xác nhận)'!B60 -> 2411200 | F34: ='DS Shoppe (đã xác nhận)'!C60 -> 3 | G34: =E34/F34 -> 803733.33 | H34: =E34/C34 -> 0.747472 | I34: =F34/D34 -> 0.6045 | J34: =E34-C34 -> -814606.45 | K34: =F34-D34 -> -1.9627792 | L34: ='DS Shoppe (đã xác nhận)'!H60 -> 1 | M34: ='DS Shoppe (đã xác nhận)'!I60 -> 831600 | N34: ='DS Shoppe (đã xác nhận)'!J60 -> 0 | O34: ='DS Shoppe (đã xác nhận)'!K60 -> 0 | S34: =S33+1 -> 20 | T34: ='Bảng tổng hợp 1'!A35 | U34: ='Bảng tổng hợp 1'!B35 -> Màu trắng | V34: ='Bảng tổng hợp 1'!C35 -> 0 | W34: ='Bảng tổng hợp 1'!D35 -> 0
B35: =B34+1 -> 45889 | C35: =100000000/31 -> 3225806.5 | D35: =C35/$D$12 -> 4.9627792 | E35: ='DS Shoppe (đã xác nhận)'!B61 -> 343140 | F35: ='DS Shoppe (đã xác nhận)'!C61 -> 1 | G35: =E35/F35 -> 343140 | H35: =E35/C35 -> 0.1063734 | I35: =F35/D35 -> 0.2015 | J35: =E35-C35 -> -2882666.5 | K35: =F35-D35 -> -3.9627792 | L35: ='DS Shoppe (đã xác nhận)'!H61 -> 0 | M35: ='DS Shoppe (đã xác nhận)'!I61 -> 0 | N35: ='DS Shoppe (đã xác nhận)'!J61 -> 0 | O35: ='DS Shoppe (đã xác nhận)'!K61 -> 0 | S35: =S34+1 -> 21 | T35: ='Bảng tổng hợp 1'!A36 | U35: ='Bảng tổng hợp 1'!B36 -> Màu xanh | V35: ='Bảng tổng hợp 1'!C36 -> 0 | W35: ='Bảng tổng hợp 1'!D36 -> 0
B36: =B35+1 -> 45890 | C36: =100000000/31 -> 3225806.5 | D36: =C36/$D$12 -> 4.9627792 | E36: ='DS Shoppe (đã xác nhận)'!B62 -> 196080 | F36: ='DS Shoppe (đã xác nhận)'!C62 -> 1 | H36: =E36/C36 -> 0.0607848 | I36: =F36/D36 -> 0.2015 | J36: =E36-C36 -> -3029726.5 | K36: =F36-D36 -> -3.9627792 | L36: ='DS Shoppe (đã xác nhận)'!H62 -> 0 | M36: ='DS Shoppe (đã xác nhận)'!I62 -> 0 | N36: ='DS Shoppe (đã xác nhận)'!J62 -> 0 | O36: ='DS Shoppe (đã xác nhận)'!K62 -> 0 | S36: =S35+1 -> 22 | T36: ='Bảng tổng hợp 1'!A37 -> Combo X 2 - Viên uống giúp tái tạo và nuôi dưỡng mô sụn - HB Glucollagen 7 in 1 | U36: ='Bảng tổng hợp 1'!B37 -> - | V36: ='Bảng tổng hợp 1'!C37 -> 2 | W36: ='Bảng tổng hợp 1'!D37 -> 3095820
B37: =B36+1 -> 45891 | C37: =100000000/31 -> 3225806.5 | D37: =C37/$D$12 -> 4.9627792 | E37: ='DS Shoppe (đã xác nhận)'!B63 -> 2520300 | F37: ='DS Shoppe (đã xác nhận)'!C63 -> 3 | H37: =E37/C37 -> 0.781293 | I37: =F37/D37 -> 0.6045 | J37: =E37-C37 -> -705506.45 | K37: =F37-D37 -> -1.9627792 | L37: ='DS Shoppe (đã xác nhận)'!H63 -> 0 | M37: ='DS Shoppe (đã xác nhận)'!I63 -> 0 | N37: ='DS Shoppe (đã xác nhận)'!J63 -> 0 | O37: ='DS Shoppe (đã xác nhận)'!K63 -> 0 | S37: =S36+1 -> 23 | T37: ='Bảng tổng hợp 1'!A38 | U37: ='Bảng tổng hợp 1'!B38 -> 30 viên | V37: ='Bảng tổng hợp 1'!C38 -> 0 | W37: ='Bảng tổng hợp 1'!D38 -> 0
B38: =B37+1 -> 45892 | C38: =100000000/31 -> 3225806.5 | D38: =C38/$D$12 -> 4.9627792 | E38: ='DS Shoppe (đã xác nhận)'!B64 -> 1142080 | F38: ='DS Shoppe (đã xác nhận)'!C64 -> 2 | H38: =E38/C38 -> 0.3540448 | I38: =F38/D38 -> 0.403 | J38: =E38-C38 -> -2083726.5 | K38: =F38-D38 -> -2.9627792 | L38: ='DS Shoppe (đã xác nhận)'!H64 -> 0 | M38: ='DS Shoppe (đã xác nhận)'!I64 -> 0 | N38: ='DS Shoppe (đã xác nhận)'!J64 -> 0 | O38: ='DS Shoppe (đã xác nhận)'!K64 -> 0 | S38: =S37+1 -> 24 | T38: ='Bảng tổng hợp 1'!A39 | U38: ='Bảng tổng hợp 1'!B39 -> 60 viên | V38: ='Bảng tổng hợp 1'!C39 -> 2 | W38: ='Bảng tổng hợp 1'!D39 -> 3095820
B39: =B38+1 -> 45893 | C39: =100000000/31 -> 3225806.5 | D39: =C39/$D$12 -> 4.9627792 | E39: ='DS Shoppe (đã xác nhận)'!B65 -> 2073458 | F39: ='DS Shoppe (đã xác nhận)'!C65 -> 4 | H39: =E39/C39 -> 0.64277198 | I39: =F39/D39 -> 0.806 | J39: =E39-C39 -> -1152348.5 | K39: =F39-D39 -> -0.96277916 | L39: ='DS Shoppe (đã xác nhận)'!H65 -> 1 | M39: ='DS Shoppe (đã xác nhận)'!I65 -> 1110000 | N39: ='DS Shoppe (đã xác nhận)'!J65 -> 0 | O39: ='DS Shoppe (đã xác nhận)'!K65 -> 0 | S39: =S38+1 -> 25 | T39: ='Bảng tổng hợp 1'!A40 -> ComBo Vui Khỏe Vận Động HB Calcidsoft & Shark Cartilage 750Mg Healthy Beauty Giúp Xương Chắc Khỏe Khớp Dẻo Dai | U39: ='Bảng tổng hợp 1'!B40 -> - | V39: ='Bảng tổng hợp 1'!C40 -> 0 | W39: ='Bảng tổng hợp 1'!D40 -> 0
B40: =B39+1 -> 45894 | C40: =100000000/31 -> 3225806.5 | D40: =C40/$D$12 -> 4.9627792 | E40: ='DS Shoppe (đã xác nhận)'!B66 -> 10658283 | F40: ='DS Shoppe (đã xác nhận)'!C66 -> 12 | H40: =E40/C40 -> 3.3040677 | I40: =F40/D40 -> 2.418 | J40: =E40-C40 -> 7432476.5 | K40: =F40-D40 -> 7.0372208 | L40: ='DS Shoppe (đã xác nhận)'!H66 -> 2 | M40: ='DS Shoppe (đã xác nhận)'!I66 -> 1725570 | N40: ='DS Shoppe (đã xác nhận)'!J66 -> 0 | O40: ='DS Shoppe (đã xác nhận)'!K66 -> 0 | S40: =S39+1 -> 26 | T40: ='Bảng tổng hợp 1'!A41 -> Combo Trẻ Hóa Làn Da Gluta White+ & HB Collagen Type 1,2,3 Healthy Beauty | U40: ='Bảng tổng hợp 1'!B41 -> - | V40: ='Bảng tổng hợp 1'!C41 -> 0 | W40: ='Bảng tổng hợp 1'!D41 -> 0
B41: =B40+1 -> 45895 | C41: =100000000/31 -> 3225806.5 | D41: =C41/$D$12 -> 4.9627792 | E41: ='DS Shoppe (đã xác nhận)'!B67 -> 294649 | F41: ='DS Shoppe (đã xác nhận)'!C67 -> 1 | H41: =E41/C41 -> 0.09134119 | I41: =F41/D41 -> 0.2015 | J41: =E41-C41 -> -2931157.5 | K41: =F41-D41 -> -3.9627792 | L41: ='DS Shoppe (đã xác nhận)'!H67 -> 0 | M41: ='DS Shoppe (đã xác nhận)'!I67 -> 0 | N41: ='DS Shoppe (đã xác nhận)'!J67 -> 0 | O41: ='DS Shoppe (đã xác nhận)'!K67 -> 0 | S41: =S40+1 -> 27 | T41: ='Bảng tổng hợp 1'!A21 | U41: ='Bảng tổng hợp 1'!B21 -> 60 Viên | V41: ='Bảng tổng hợp 1'!C21 -> 6 | W41: ='Bảng tổng hợp 1'!D21 -> 4253021
B42: =B41+1 -> 45896 | C42: =100000000/31 -> 3225806.5 | D42: =C42/$D$12 -> 4.9627792 | E42: ='DS Shoppe (đã xác nhận)'!B68 -> 2260897 | F42: ='DS Shoppe (đã xác nhận)'!C68 -> 3 | H42: =E42/C42 -> 0.70087807 | I42: =F42/D42 -> 0.6045 | J42: =E42-C42 -> -964909.45 | K42: =F42-D42 -> -1.9627792 | L42: ='DS Shoppe (đã xác nhận)'!H68 -> 0 | M42: ='DS Shoppe (đã xác nhận)'!I68 -> 0 | N42: ='DS Shoppe (đã xác nhận)'!J68 -> 0 | O42: ='DS Shoppe (đã xác nhận)'!K68 -> 0 | S42: =S41+1 -> 28 | T42: ='Bảng tổng hợp 1'!A20 | U42: ='Bảng tổng hợp 1'!B20 -> 30 Viên | V42: ='Bảng tổng hợp 1'!C20 -> 3 | W42: ='Bảng tổng hợp 1'!D20 -> 1243759
B43: =B42+1 -> 45897 | C43: =100000000/31 -> 3225806.5 | D43: =C43/$D$12 -> 4.9627792 | E43: ='DS Shoppe (đã xác nhận)'!B69 -> 193800 | F43: ='DS Shoppe (đã xác nhận)'!C69 -> 1 | H43: =E43/C43 -> 0.060078 | I43: =F43/D43 -> 0.2015 | J43: =E43-C43 -> -3032006.5 | K43: =F43-D43 -> -3.9627792 | L43: ='DS Shoppe (đã xác nhận)'!H69 -> 0 | M43: ='DS Shoppe (đã xác nhận)'!I69 -> 0 | N43: ='DS Shoppe (đã xác nhận)'!J69 -> 0 | O43: ='DS Shoppe (đã xác nhận)'!K69 -> 0 | S43: =S42+1 -> 29 | T43: ='Bảng tổng hợp 1'!A11 | U43: ='Bảng tổng hợp 1'!B11 -> 60 viên | V43: ='Bảng tổng hợp 1'!C11 -> 4 | W43: ='Bảng tổng hợp 1'!D11 -> 2364865
B44: =B43+1 -> 45898 | C44: =100000000/31 -> 3225806.5 | D44: =C44/$D$12 -> 4.9627792 | E44: ='DS Shoppe (đã xác nhận)'!B70 -> 1275840 | F44: ='DS Shoppe (đã xác nhận)'!C70 -> 3 | H44: =E44/C44 -> 0.3955104 | I44: =F44/D44 -> 0.6045 | J44: =E44-C44 -> -1949966.5 | K44: =F44-D44 -> -1.9627792 | L44: ='DS Shoppe (đã xác nhận)'!H70 -> 0 | M44: ='DS Shoppe (đã xác nhận)'!I70 -> 0 | N44: ='DS Shoppe (đã xác nhận)'!J70 -> 0 | O44: ='DS Shoppe (đã xác nhận)'!K70 -> 0 | S44: =S43+1 -> 30 | T44: ='Bảng tổng hợp 1'!A45 -> Combo Ngủ Ngon Sâu Giấc HB Cordy Extract & HB Ginkgo Biloba 120Mg Healthy Beauty | U44: ='Bảng tổng hợp 1'!B45 -> - | V44: ='Bảng tổng hợp 1'!C45 -> 0 | W44: ='Bảng tổng hợp 1'!D45 -> 0
B45: =B44+1 -> 45899 | C45: =100000000/31 -> 3225806.5 | D45: =C45/$D$12 -> 4.9627792 | E45: ='DS Shoppe (đã xác nhận)'!B71 -> 1333911 | F45: ='DS Shoppe (đã xác nhận)'!C71 -> 2 | H45: =E45/C45 -> 0.41351241 | I45: =F45/D45 -> 0.403 | J45: =E45-C45 -> -1891895.5 | K45: =F45-D45 -> -2.9627792 | L45: ='DS Shoppe (đã xác nhận)'!H71 -> 0 | M45: ='DS Shoppe (đã xác nhận)'!I71 -> 0 | N45: ='DS Shoppe (đã xác nhận)'!J71 -> 0 | O45: ='DS Shoppe (đã xác nhận)'!K71 -> 0 | S45: =S44+1 -> 31 | T45: ='Bảng tổng hợp 1'!A46 -> Combo Mượt khớp, chắc xương (HB CALCIDSOFT - 30V + HB SHARK CARTILARGE - 100V) | U45: ='Bảng tổng hợp 1'!B46 -> - | V45: ='Bảng tổng hợp 1'!C46 -> 1 | W45: ='Bảng tổng hợp 1'!D46 -> 727600
B46: =B45+1 -> 45900 | C46: =100000000/31 -> 3225806.5 | D46: =C46/$D$12 -> 4.9627792 | E46: ='DS Shoppe (đã xác nhận)'!B72 | F46: ='DS Shoppe (đã xác nhận)'!C72 | H46: =E46/C46 -> 0 | I46: =F46/D46 -> 0 | J46: =E46-C46 -> -3225806.5 | K46: =F46-D46 -> -4.9627792 | L46: ='DS Shoppe (đã xác nhận)'!H72 | M46: ='DS Shoppe (đã xác nhận)'!I72 | N46: ='DS Shoppe (đã xác nhận)'!J72 | O46: ='DS Shoppe (đã xác nhận)'!K72 | S46: =S45+1 -> 32 | T46: ='Bảng tổng hợp 1'!A48 -> Combo Cải Thiện Thị Lực Tăng Cường Trí Nhớ HB Ginkgo Biloba 120Mg & HB Visionfort Support 30V | U46: ='Bảng tổng hợp 1'!B48 -> - | V46: ='Bảng tổng hợp 1'!C48 -> 0 | W46: ='Bảng tổng hợp 1'!D48 -> 0
S47: =S46+1 -> 33 | T47: ='Bảng tổng hợp 1'!A44 | U47: ='Bảng tổng hợp 1'!B44 -> 60 viên | V47: ='Bảng tổng hợp 1'!C44 -> 0 | W47: ='Bảng tổng hợp 1'!D44 -> 0
S48: =S47+1 -> 34 | T48: ='Bảng tổng hợp 1'!A49 | U48: ='Bảng tổng hợp 1'!B49 -> 30 Viên | V48: ='Bảng tổng hợp 1'!C49 -> 0 | W48: ='Bảng tổng hợp 1'!D49 -> 0
S49: =S48+1 -> 35 | T49: ='Bảng tổng hợp 1'!A50 -> Bộ Đôi Giảm Cân An Toàn Hiệu Quả HB SLIMDAY & HB SLIMNIGHT | U49: ='Bảng tổng hợp 1'!B50 -> - | V49: ='Bảng tổng hợp 1'!C50 -> 0 | W49: ='Bảng tổng hợp 1'!D50 -> 0
S50: =S49+1 -> 36 | T50: ='Bảng tổng hợp 1'!A51 -> [HB Gift]_Túi vải đay linen Healthy Beauty 40x35cm, thiết kế thanh lịch, chắc chắn, dung tích rộng | U50: ='Bảng tổng hợp 1'!B51 -> - | V50: ='Bảng tổng hợp 1'!C51 -> 3 | W50: ='Bảng tổng hợp 1'!D51 -> 0
S51: =S50+1 -> 37 | T51: ='Bảng tổng hợp 1'!A52 -> [HB Gift] _01 cây Bút Bi Healthy Beauty | U51: ='Bảng tổng hợp 1'!B52 -> - | V51: ='Bảng tổng hợp 1'!C52 -> 0 | W51: ='Bảng tổng hợp 1'!D52 -> 0

Sheet Sản phẩm
A1: =IF(C1<>"", "Có giá trị", "") -> Có giá trị | B1: Sản phẩm | C1: Tình trạng sản phẩm hiện tại | D1: Mã phân loại hàng | E1: Tên Phân Loại | F1: Trạng thái phân loại sản phẩm hiện tại | G1: SKU phân loại | H1: SKU sản phẩm | I1: Lượt truy cập sản phẩm | J1: Lượt xem trang sản phẩm | K1: Số lượng khách thoát trang sản phẩm | L1: Tỷ lệ thoát Trang sản phẩm | M1: Lượt click từ Trang tìm kiếm | N1: Lượt thích | O1: Lượt truy cập sản phẩm (Thêm vào giỏ hàng) | P1: Sản phẩm (Thêm vào giỏ hàng) | Q1: Tỷ lệ chuyển đổi (theo lượt thêm vào giỏ hàng) | R1: Người mua đã đặt hàng | S1: Sản phẩm (Đơn đã đặt) | T1: Doanh số (Đơn đã đặt) (VND) | U1: Tỷ lệ chuyển đổi (Đơn đã đặt) | V1: Người mua có đơn đã xác nhận | W1: Sản phẩm (Đơn đã xác nhận) | X1: Doanh số (Đơn đã xác nhận) (VND) | Y1: Tỷ lệ chuyển đổi (Đơn đã xác nhận) | Z1: Tỷ lệ chuyển đổi (Từ Đơn đã đặt thanh Đơn đã xác nhận) | AA1: Tỷ lệ đặt hàng lặp lại (Đơn hàng đã được xác nhận) | AB1: Số ngày trung bình để lặp lại đơn hàng (Đơn hàng đã được xác nhận)
A2: 5158911395 | B2: Khẩu Trang Y Tế Kháng Khuẩn HB Medical Mask Cao Cấp Healthy Beauty 1 Hộp 50 cái | C2: Đang hoạt động | D2: - | E2: - | F2: - | G2: - | H2: - | I2: 67 | J2: 100 | K2: 26 | L2: 0.3881 | M2: 28 | N2: 4 | O2: 11 | P2: 42 | Q2: 0.1642 | R2: 7 | S2: 21 | T2: 1258799 | U2: 0.1045 | V2: 6 | W2: 16 | X2: 871299 | Y2: 0.0896 | Z2: 0.8571 | AA2: 0 | AB2: 0
A3: 5158911395 | B3: Khẩu Trang Y Tế Kháng Khuẩn HB Medical Mask Cao Cấp Healthy Beauty 1 Hộp 50 cái | C3: Đang hoạt động | D3: 93855942766 | E3: Than Hoạt Tính | F3: Đang hoạt động | G3: - | I3: - | J3: - | K3: - | L3: - | M3: - | N3: - | O3: 1 | P3: 1 | Q3: - | R3: 1 | S3: 1 | T3: 73600 | U3: - | V3: 1 | W3: 1 | X3: 73600 | Y3: - | Z3: 1 | AA3: 0 | AB3: 0
A4: 5158911395 | B4: Khẩu Trang Y Tế Kháng Khuẩn HB Medical Mask Cao Cấp Healthy Beauty 1 Hộp 50 cái | C4: Đang hoạt động | D4: 93855942767 | E4: Màu Trắng | F4: Đang hoạt động | G4: - | I4: - | J4: - | K4: - | L4: - | M4: - | N4: - | O4: 8 | P4: 37 | Q4: - | R4: 4 | S4: 12 | T4: 747199 | U4: - | V4: 3 | W4: 7 | X4: 359699 | Y4: - | Z4: 0.75 | AA4: 0 | AB4: 0
A5: 5158911395 | B5: Khẩu Trang Y Tế Kháng Khuẩn HB Medical Mask Cao Cấp Healthy Beauty 1 Hộp 50 cái | C5: Đang hoạt động | D5: 93855942768 | E5: Màu Xanh | F5: Đang hoạt động | G5: - | I5: - | J5: - | K5: - | L5: - | M5: - | N5: - | O5: 2 | P5: 4 | Q5: - | R5: 2 | S5: 8 | T5: 438000 | U5: - | V5: 2 | W5: 8 | X5: 438000 | Y5: - | Z5: 1 | AA5: 0 | AB5: 0
A6: 5519393895 | B6: Viên Uống Giảm Gãy Rụng và Đen Tóc HB Black Hair Healthy Beauty | C6: Đang hoạt động | D6: - | E6: - | F6: - | G6: - | H6: - | I6: 135 | J6: 382 | K6: 23 | L6: 0.1704 | M6: 53 | N6: 20 | O6: 35 | P6: 78 | Q6: 0.2593 | R6: 14 | S6: 18 | T6: 10068387 | U6: 0.1037 | V6: 13 | W6: 16 | X6: 8563267 | Y6: 0.0963 | Z6: 0.9286 | AA6: 0.1333 | AB6: 45785
A7: 5519393895 | B7: Viên Uống Giảm Gãy Rụng và Đen Tóc HB Black Hair Healthy Beauty | C7: Đang hoạt động | D7: 76595553673 | E7: 30 Viên | F7: Đang hoạt động | G7: HB028 | I7: - | J7: - | K7: - | L7: - | M7: - | N7: - | O7: 20 | P7: 42 | Q7: - | R7: 9 | S7: 11 | T7: 4900987 | U7: - | V7: 9 | W7: 11 | X7: 4900987 | Y7: - | Z7: 1 | AA7: 0.1 | AB7: 17
A8: 5519393895 | B8: Viên Uống Giảm Gãy Rụng và Đen Tóc HB Black Hair Healthy Beauty | C8: Đang hoạt động | D8: 76595553674 | E8: 60 Viên | F8: Đang hoạt động | G8: HB026 | I8: - | J8: - | K8: - | L8: - | M8: - | N8: - | O8: 20 | P8: 36 | Q8: - | R8: 5 | S8: 7 | T8: 5167400 | U8: - | V8: 4 | W8: 5 | X8: 3662280 | Y8: - | Z8: 0.8 | AA8: 0.2 | AB8: 0
A9: 25666719442 | B9: Viên uống giúp tái tạo và nuôi dưỡng mô sụn - HB Glucollagen 7 in 1 | C9: Đang hoạt động | D9: - | E9: - | F9: - | G9: - | H9: - | I9: 176 | J9: 436 | K9: 35 | L9: 0.1989 | M9: 38 | N9: 4 | O9: 44 | P9: 88 | Q9: 0.25 | R9: 13 | S9: 18 | T9: 12377576 | U9: 0.0739 | V9: 12 | W9: 17 | X9: 11798576 | Y9: 0.0682 | Z9: 0.9231 | AA9: 0.1429 | AB9: 0.5
A10: 25666719442 | B10: Viên uống giúp tái tạo và nuôi dưỡng mô sụn - HB Glucollagen 7 in 1 | C10: Đang hoạt động | D10: 255410547718 | E10: 30 viên | F10: Đang hoạt động | G10: HB002 | I10: - | J10: - | K10: - | L10: - | M10: - | N10: - | O10: 24 | P10: 34 | Q10: - | R10: 6 | S10: 7 | T10: 3109526 | U10: - | V10: 5 | W10: 6 | X10: 2530526 | Y10: - | Z10: 0.83 | AA10: 0.1667 | AB10: 1
A11: 25666719442 | B11: Viên uống giúp tái tạo và nuôi dưỡng mô sụn - HB Glucollagen 7 in 1 | C11: Đang hoạt động | D11: 255410547719 | E11: 60 viên | F11: Đang hoạt động | G11: HB003 | I11: - | J11: - | K11: - | L11: - | M11: - | N11: - | O11: 28 | P11: 54 | Q11: - | R11: 8 | S11: 11 | T11: 9268050 | U11: - | V11: 8 | W11: 11 | X11: 9268050 | Y11: - | Z11: 1 | AA11: 0 | AB11: 0
A12: 8782633181 | B12: Viên Uống Giúp Chống Nắng Trắng Da Mờ Nám HB GLUTA WHITE + | C12: Đang hoạt động | D12: - | E12: - | F12: - | G12: - | H12: HB006 | I12: 152 | J12: 320 | K12: 36 | L12: 0.2368 | M12: 48 | N12: 5 | O12: 18 | P12: 48 | Q12: 0.1184 | R12: 7 | S12: 13 | T12: 16232310 | U12: 0.0461 | V12: 6 | W12: 11 | X12: 13485260 | Y12: 0.0395 | Z12: 0.8571 | AA12: 0.3333 | AB12: 45722
A13: 24867481840 | B13: Viên uống HB Glucosamine 3 in 1 60 viên - 200 viên | C13: Đang hoạt động | D13: - | E13: - | F13: - | G13: - | H13: - | I13: 76 | J13: 207 | K13: 14 | L13: 0.1842 | M13: 24 | N13: 9 | O13: 21 | P13: 29 | Q13: 0.2763 | R13: 8 | S13: 10 | T13: 3067450 | U13: 0.1053 | V13: 7 | W13: 8 | X13: 2422490 | Y13: 0.0921 | Z13: 0.875 | AA13: 0 | AB13: 0
A14: 24867481840 | B14: Viên uống HB Glucosamine 3 in 1 60 viên - 200 viên | C14: Đang hoạt động | D14: 69751100999 | E14: 60 viên | F14: Đang hoạt động | G14: HB005 | I14: - | J14: - | K14: - | L14: - | M14: - | N14: - | O14: 20 | P14: 29 | Q14: - | R14: 8 | S14: 10 | T14: 3067450 | U14: - | V14: 7 | W14: 8 | X14: 2422490 | Y14: - | Z14: 0.88 | AA14: 0 | AB14: 0
A15: 6917016018 | B15: Viên uống giúp Bổ Sung Canxi và Vitamin D3 HB CALCIDSOFT | C15: Đang hoạt động | D15: - | E15: - | F15: - | G15: - | H15: - | I15: 73 | J15: 165 | K15: 17 | L15: 0.2329 | M15: 28 | N15: 2 | O15: 13 | P15: 32 | Q15: 0.1781 | R15: 5 | S15: 7 | T15: 1535774 | U15: 0.0685 | V15: 3 | W15: 5 | X15: 1001820 | Y15: 0.0411 | Z15: 0.6 | AA15: 0.25 | AB15: 12
A16: 6917016018 | B16: Viên uống giúp Bổ Sung Canxi và Vitamin D3 HB CALCIDSOFT | C16: Đang hoạt động | D16: 121223345683 | E16: Hộp 30 Viên | F16: Đang hoạt động | G16: HB024 | I16: - | J16: - | K16: - | L16: - | M16: - | N16: - | O16: 11 | P16: 22 | Q16: - | R16: 4 | S16: 4 | T16: 605820 | U16: - | V16: 3 | W16: 3 | X16: 437820 | Y16: - | Z16: 0.75 | AA16: 0 | AB16: 0
A17: 6917016018 | B17: Viên uống giúp Bổ Sung Canxi và Vitamin D3 HB CALCIDSOFT | C17: Đang hoạt động | D17: 121223345684 | E17: Hộp 60 Viên | F17: Đang hoạt động | G17: HB025 | I17: - | J17: - | K17: - | L17: - | M17: - | N17: - | O17: 5 | P17: 10 | Q17: - | R17: 2 | S17: 3 | T17: 929954 | U17: - | V17: 1 | W17: 2 | X17: 564000 | Y17: - | Z17: 0.5 | AA17: 0 | AB17: 0
A18: 3862340378 | B18: Viên Uống Giảm Cân An Toàn Ban Ngày HB SLIMDAY 60 Viên | C18: Đang hoạt động | D18: - | E18: - | F18: - | G18: - | H18: HB007 | I18: 97 | J18: 172 | K18: 29 | L18: 0.299 | M18: 50 | N18: 7 | O18: 13 | P18: 14 | Q18: 0.134 | R18: 4 | S18: 5 | T18: 3925300 | U18: 0.0412 | V18: 4 | W18: 4 | X18: 3045300 | Y18: 0.0412 | Z18: 1 | AA18: 0 | AB18: 0
A19: 3934257539 | B19: Viên Uống HB Collagen Type 1,2&3 Healthy Beauty 120 Viên | C19: Đang hoạt động | D19: - | E19: - | F19: - | G19: - | H19: HB001 | I19: 99 | J19: 185 | K19: 29 | L19: 0.2929 | M19: 56 | N19: 1 | O19: 13 | P19: 23 | Q19: 0.1313 | R19: 3 | S19: 3 | T19: 2186400 | U19: 0.0303 | V19: 3 | W19: 3 | X19: 2186400 | Y19: 0.0303 | Z19: 1 | AA19: 0 | AB19: 0
A20: 5219966803 | B20: Viên Uống Đông Trùng Hạ Thảo Bồi Bổ Khí Huyết HB CORDY EXTRACT | C20: Đang hoạt động | D20: - | E20: - | F20: - | G20: - | H20: HB015 | I20: 56 | J20: 114 | K20: 21 | L20: 0.375 | M20: 12 | N20: 0 | O20: 10 | P20: 14 | Q20: 0.1786 | R20: 2 | S20: 2 | T20: 1508083 | U20: 0.0357 | V20: 2 | W20: 2 | X20: 1508083 | Y20: 0.0357 | Z20: 1 | AA20: 0 | AB20: 0
A21: 24667488336 | B21: Viên uống HB Glutathione - C Plus 30 viên | C21: Đang hoạt động | D21: - | E21: - | F21: - | G21: - | H21: HB030 | I21: 54 | J21: 84 | K21: 17 | L21: 0.3148 | M21: 14 | N21: 0 | O21: 5 | P21: 6 | Q21: 0.0926 | R21: 2 | S21: 2 | T21: 2104200 | U21: 0.037 | V21: 2 | W21: 2 | X21: 2104200 | Y21: 0.037 | Z21: 1 | AA21: 0 | AB21: 0
A22: 24667488336 | B22: Viên uống HB Glutathione - C Plus 30 viên | C22: Đang hoạt động | D22: 222571286446 | E22: 30 viên | F22: Đang hoạt động | G22: HB030 | H22: HB030 | I22: - | J22: - | K22: - | L22: - | M22: - | N22: - | O22: 5 | P22: 6 | Q22: - | R22: 2 | S22: 2 | T22: 2104200 | U22: - | V22: 2 | W22: 2 | X22: 2104200 | Y22: - | Z22: 1 | AA22: 0 | AB22: 0
A23: 10014812415 | B23: Viên Uống Bổ Sung Vitamin & Khoáng Chất Cho Bà Bầu HB PRENATAL SUPPORT | C23: Đang hoạt động | D23: - | E23: - | F23: - | G23: - | H23: - | I23: 40 | J23: 65 | K23: 12 | L23: 0.3 | M23: 8 | N23: 1 | O23: 2 | P23: 3 | Q23: 0.05 | R23: 1 | S23: 1 | T23: 726880 | U23: 0.025 | V23: 1 | W23: 1 | X23: 726880 | Y23: 0.025 | Z23: 1 | AA23: 0 | AB23: 0
A24: 10014812415 | B24: Viên Uống Bổ Sung Vitamin & Khoáng Chất Cho Bà Bầu HB PRENATAL SUPPORT | C24: Đang hoạt động | D24: 56678491254 | E24: 60 Viên | F24: Đang hoạt động | G24: HB034 | I24: - | J24: - | K24: - | L24: - | M24: - | N24: - | O24: 2 | P24: 3 | Q24: - | R24: 1 | S24: 1 | T24: 726880 | U24: - | V24: 1 | W24: 1 | X24: 726880 | Y24: - | Z24: 1 | AA24: 0 | AB24: 0
A25: 3127515400 | B25: Viên Uống Healthy Beauty Omega 3,6,9 Từ Dầu Hạt Lanh 100 Viên & 200 Viên | C25: Đang hoạt động | D25: - | E25: - | F25: - | G25: - | H25: - | I25: 6 | J25: 13 | K25: 1 | L25: 0.1667 | M25: 1 | N25: 0 | O25: 0 | P25: 0 | Q25: 0 | R25: 0 | S25: 0 | T25: 0 | U25: 0 | V25: 0 | W25: 0 | X25: 0 | Y25: 0 | Z25: 0 | AA25: 0 | AB25: 0
A26: 6319391113 | B26: Viên Uống Bổ Sung 28 Loại Vitamin Và Khoáng Chất Cho Phụ Nữ HB ONCE DAILY WOMEN'S MULTI | C26: Đang hoạt động | D26: - | E26: - | F26: - | G26: - | H26: HB014 | I26: 2 | J26: 2 | K26: 1 | L26: 0.5 | M26: 0 | N26: 0 | O26: 0 | P26: 0 | Q26: 0 | R26: 0 | S26: 0 | T26: 0 | U26: 0 | V26: 0 | W26: 0 | X26: 0 | Y26: 0 | Z26: 0 | AA26: 0 | AB26: 0
A27: 10669789089 | B27: ComBo HB Once Daily Multi & HB Oreganol P73 Healthy Beauty Tăng Cường Hệ Miễn Dịch Bảo Vệ Hệ Tiêu Hóa | C27: Đang hoạt động | D27: - | E27: - | F27: - | G27: - | H27: - | I27: 1 | J27: 1 | K27: 0 | L27: 0 | M27: 0 | N27: 0 | O27: 0 | P27: 0 | Q27: 0 | R27: 0 | S27: 0 | T27: 0 | U27: 0 | V27: 0 | W27: 0 | X27: 0 | Y27: 0 | Z27: 0 | AA27: 0 | AB27: 0
A28: 10672362747 | B28: ComBo Hạnh Phúc Viên Mãn New Sexual Care Men & New Women Care & HB Cordy Extract Healthy Beauty | C28: Đang hoạt động | D28: - | E28: - | F28: - | G28: - | H28: - | I28: 1 | J28: 1 | K28: 0 | L28: 0 | M28: 0 | N28: 0 | O28: 0 | P28: 0 | Q28: 0 | R28: 0 | S28: 0 | T28: 0 | U28: 0 | V28: 0 | W28: 0 | X28: 0 | Y28: 0 | Z28: 0 | AA28: 0 | AB28: 0
A29: 11372319169 | B29: Combo Trẻ Hóa Làn Da Gluta White+ & HB Collagen Type 1,2,3 Healthy Beauty | C29: Đang hoạt động | D29: - | E29: - | F29: - | G29: - | H29: - | I29: 20 | J29: 34 | K29: 3 | L29: 0.15 | M29: 6 | N29: 0 | O29: 0 | P29: 0 | Q29: 0 | R29: 0 | S29: 0 | T29: 0 | U29: 0 | V29: 0 | W29: 0 | X29: 0 | Y29: 0 | Z29: 0 | AA29: 0 | AB29: 0
A30: 12146844429 | B30: Combo Cải Thiện Thị Lực Tăng Cường Trí Nhớ HB Ginkgo Biloba 120Mg & HB Visionfort Support 30V | C30: Đang hoạt động | D30: - | E30: - | F30: - | G30: - | H30: - | I30: 18 | J30: 25 | K30: 5 | L30: 0.2778 | M30: 3 | N30: 0 | O30: 1 | P30: 1 | Q30: 0.0556 | R30: 0 | S30: 0 | T30: 0 | U30: 0 | V30: 0 | W30: 0 | X30: 0 | Y30: 0 | Z30: 0 | AA30: 0 | AB30: 0
A31: 12146844429 | B31: Combo Cải Thiện Thị Lực Tăng Cường Trí Nhớ HB Ginkgo Biloba 120Mg & HB Visionfort Support 30V | C31: Đang hoạt động | D31: 27988409751 | E31: 30 Viên | F31: Đang hoạt động | G31: - | I31: - | J31: - | K31: - | L31: - | M31: - | N31: - | O31: 1 | P31: 1 | Q31: - | R31: 0 | S31: 0 | T31: 0 | U31: - | V31: 0 | W31: 0 | X31: 0 | Y31: - | Z31: 0 | AA31: 0 | AB31: 0
A32: 12244752010 | B32: [Healthy Beauty] Combo Tăng Cường Sức Khỏe & Sinh Lý Nữ | C32: Đang hoạt động | D32: - | E32: - | F32: - | G32: - | H32: - | I32: 1 | J32: 1 | K32: 0 | L32: 0 | M32: 0 | N32: 0 | O32: 0 | P32: 0 | Q32: 0 | R32: 0 | S32: 0 | T32: 0 | U32: 0 | V32: 0 | W32: 0 | X32: 0 | Y32: 0 | Z32: 0 | AA32: 0 | AB32: 0
A33: 13953468578 | B33: ComBo Vui Khỏe Vận Động HB Calcidsoft & Shark Cartilage 750Mg Healthy Beauty Giúp Xương Chắc Khỏe Khớp Dẻo Dai | C33: Đang hoạt động | D33: - | E33: - | F33: - | G33: - | H33: - | I33: 5 | J33: 10 | K33: 1 | L33: 0.2 | M33: 0 | N33: 1 | O33: 0 | P33: 0 | Q33: 0 | R33: 0 | S33: 0 | T33: 0 | U33: 0 | V33: 0 | W33: 0 | X33: 0 | Y33: 0 | Z33: 0 | AA33: 0 | AB33: 0
A34: 14500181135 | B34: Combo Ngủ Ngon Sâu Giấc HB Cordy Extract & HB Ginkgo Biloba 120Mg Healthy Beauty | C34: Đang hoạt động | D34: - | E34: - | F34: - | G34: - | H34: - | I34: 15 | J34: 18 | K34: 6 | L34: 0.4 | M34: 0 | N34: 0 | O34: 1 | P34: 1 | Q34: 0.0667 | R34: 0 | S34: 0 | T34: 0 | U34: 0 | V34: 0 | W34: 0 | X34: 0 | Y34: 0 | Z34: 0 | AA34: 0 | AB34: 0
A35: 14500181135 | B35: Combo Ngủ Ngon Sâu Giấc HB Cordy Extract & HB Ginkgo Biloba 120Mg Healthy Beauty | C35: Đang hoạt động | D35: 103942786658 | E35: Combo Ngủ Ngon Sâu Giấc HB Cordy Extract & HB Ginkgo Biloba 120Mg Healthy Beauty | F35: Đã xóa | G35: - | I35: - | J35: - | K35: - | L35: - | M35: - | N35: - | O35: 1 | P35: 1 | Q35: - | R35: 0 | S35: 0 | T35: 0 | U35: - | V35: 0 | W35: 0 | X35: 0 | Y35: - | Z35: 0 | AA35: 0 | AB35: 0
A36: 15304521256 | B36: ComBo Khỏe Đẹp Toàn Diện Tuổi Trung Niên Healthy Beauty | C36: Đang hoạt động | D36: - | E36: - | F36: - | G36: - | H36: - | I36: 1 | J36: 1 | K36: 0 | L36: 0 | M36: 0 | N36: 0 | O36: 0 | P36: 0 | Q36: 0 | R36: 0 | S36: 0 | T36: 0 | U36: 0 | V36: 0 | W36: 0 | X36: 0 | Y36: 0 | Z36: 0 | AA36: 0 | AB36: 0
A37: 15403948801 | B37: Bộ Đôi Giảm Cân An Toàn Hiệu Quả HB SLIMDAY & HB SLIMNIGHT | C37: Đang hoạt động | D37: - | E37: - | F37: - | G37: - | H37: - | I37: 1 | J37: 1 | K37: 0 | L37: 0 | M37: 0 | N37: 0 | O37: 0 | P37: 0 | Q37: 0 | R37: 0 | S37: 0 | T37: 0 | U37: 0 | V37: 0 | W37: 0 | X37: 0 | Y37: 0 | Z37: 0 | AA37: 0 | AB37: 0
A38: 21287412861 | B38: Viên uống HB Gingko Biloba 30 viên - 60 viên | C38: Đang hoạt động | D38: - | E38: - | F38: - | G38: - | H38: - | I38: 35 | J38: 42 | K38: 17 | L38: 0.4857 | M38: 2 | N38: 1 | O38: 2 | P38: 2 | Q38: 0.0571 | R38: 0 | S38: 0 | T38: 0 | U38: 0 | V38: 0 | W38: 0 | X38: 0 | Y38: 0 | Z38: 0 | AA38: 0 | AB38: 0
A39: 21287412861 | B39: Viên uống HB Gingko Biloba 30 viên - 60 viên | C39: Đang hoạt động | D39: 240436065372 | E39: 30 viên | F39: Đang hoạt động | G39: HB035 | I39: - | J39: - | K39: - | L39: - | M39: - | N39: - | O39: 2 | P39: 2 | Q39: - | R39: 0 | S39: 0 | T39: 0 | U39: - | V39: 0 | W39: 0 | X39: 0 | Y39: - | Z39: 0 | AA39: 0 | AB39: 0
A40: 22657955668 | B40: Viên uống HB GutCare (30 - 60 viên) hỗ trợ giảm triệu chứng đau khớp | C40: Đang hoạt động | D40: - | E40: - | F40: - | G40: - | H40: - | I40: 24 | J40: 36 | K40: 8 | L40: 0.3333 | M40: 3 | N40: 1 | O40: 5 | P40: 5 | Q40: 0.2083 | R40: 0 | S40: 0 | T40: 0 | U40: 0 | V40: 0 | W40: 0 | X40: 0 | Y40: 0 | Z40: 0 | AA40: 0 | AB40: 0
A41: 22657955668 | B41: Viên uống HB GutCare (30 - 60 viên) hỗ trợ giảm triệu chứng đau khớp | C41: Đang hoạt động | D41: 225738648768 | E41: 30 Viên | F41: Đang hoạt động | G41: HB037 | I41: - | J41: - | K41: - | L41: - | M41: - | N41: - | O41: 5 | P41: 5 | Q41: - | R41: 0 | S41: 0 | T41: 0 | U41: - | V41: 0 | W41: 0 | X41: 0 | Y41: - | Z41: 0 | AA41: 0 | AB41: 0
A42: 22864051694 | B42: Viên uống HB Visionfort Support 30 viên - 60 viên | C42: Đang hoạt động | D42: - | E42: - | F42: - | G42: - | H42: - | I42: 27 | J42: 28 | K42: 6 | L42: 0.2222 | M42: 0 | N42: 2 | O42: 1 | P42: 1 | Q42: 0.037 | R42: 0 | S42: 0 | T42: 0 | U42: 0 | V42: 0 | W42: 0 | X42: 0 | Y42: 0 | Z42: 0 | AA42: 0 | AB42: 0
A43: 22864051694 | B43: Viên uống HB Visionfort Support 30 viên - 60 viên | C43: Đang hoạt động | D43: 240436168671 | E43: 30 viên | F43: Đang hoạt động | G43: HB027 | I43: - | J43: - | K43: - | L43: - | M43: - | N43: - | O43: 1 | P43: 1 | Q43: - | R43: 0 | S43: 0 | T43: 0 | U43: - | V43: 0 | W43: 0 | X43: 0 | Y43: - | Z43: 0 | AA43: 0 | AB43: 0
A44: 22964444155 | B44: Viên Uống Giảm Cân An Toàn Ban Đêm HB SLIMNIGHT 30 Viên | C44: Đang hoạt động | D44: - | E44: - | F44: - | G44: - | H44: HB008 | I44: 1 | J44: 1 | K44: 0 | L44: 0 | M44: 0 | N44: 0 | O44: 0 | P44: 0 | Q44: 0 | R44: 0 | S44: 0 | T44: 0 | U44: 0 | V44: 0 | W44: 0 | X44: 0 | Y44: 0 | Z44: 0 | AA44: 0 | AB44: 0
A45: 24067721716 | B45: Viên uống HB Shark Cartilage 100 viên | C45: Đang hoạt động | D45: - | E45: - | F45: - | G45: - | H45: HB010 | I45: 16 | J45: 35 | K45: 1 | L45: 0.0625 | M45: 0 | N45: 4 | O45: 3 | P45: 3 | Q45: 0.1875 | R45: 0 | S45: 0 | T45: 0 | U45: 0 | V45: 0 | W45: 0 | X45: 0 | Y45: 0 | Z45: 0 | AA45: 0 | AB45: 0
A46: 24067721716 | B46: Viên uống HB Shark Cartilage 100 viên | C46: Đang hoạt động | D46: 88883451652 | E46: 100 viên | F46: Đang hoạt động | G46: HB010 | H46: HB010 | I46: - | J46: - | K46: - | L46: - | M46: - | N46: - | O46: 3 | P46: 3 | Q46: - | R46: 0 | S46: 0 | T46: 0 | U46: - | V46: 0 | W46: 0 | X46: 0 | Y46: - | Z46: 0 | AA46: 0 | AB46: 0
A47: 24367745053 | B47: HB MEDICAL MASK - Túi zip - Khẩu trang y tế 4 lớp kháng khuẩn chuẩn nhóm A | C47: Đang hoạt động | D47: - | E47: - | F47: - | G47: - | H47: - | I47: 5 | J47: 5 | K47: 1 | L47: 0.2 | M47: 1 | N47: 0 | O47: 0 | P47: 0 | Q47: 0 | R47: 0 | S47: 0 | T47: 0 | U47: 0 | V47: 0 | W47: 0 | X47: 0 | Y47: 0 | Z47: 0 | AA47: 0 | AB47: 0
A48: 24576774667 | B48: VIÊN UỐNG GIẢI ĐỘC GAN, CHỐNG OXY HÓA, DƯỠNG SÁNG DA HB GLUTATHION-C PLUS 30 VIÊN | C48: Đang hoạt động | D48: - | E48: - | F48: - | G48: - | H48: HB030 | I48: 19 | J48: 25 | K48: 5 | L48: 0.2632 | M48: 2 | N48: 1 | O48: 1 | P48: 1 | Q48: 0.0526 | R48: 0 | S48: 0 | T48: 0 | U48: 0 | V48: 0 | W48: 0 | X48: 0 | Y48: 0 | Z48: 0 | AA48: 0 | AB48: 0
A49: 24576774667 | B49: VIÊN UỐNG GIẢI ĐỘC GAN, CHỐNG OXY HÓA, DƯỠNG SÁNG DA HB GLUTATHION-C PLUS 30 VIÊN | C49: Đang hoạt động | D49: 255718722725 | E49: 30 viên | F49: Đang hoạt động | G49: HB030 | H49: HB030 | I49: - | J49: - | K49: - | L49: - | M49: - | N49: - | O49: 1 | P49: 1 | Q49: - | R49: 0 | S49: 0 | T49: 0 | U49: - | V49: 0 | W49: 0 | X49: 0 | Y49: - | Z49: 0 | AA49: 0 | AB49: 0
A50: 24717729485 | B50: Viên uống HB Silymarin 100 viên | C50: Đang hoạt động | D50: - | E50: - | F50: - | G50: - | H50: HB021 | I50: 4 | J50: 6 | K50: 1 | L50: 0.25 | M50: 0 | N50: 0 | O50: 0 | P50: 0 | Q50: 0 | R50: 0 | S50: 0 | T50: 0 | U50: 0 | V50: 0 | W50: 0 | X50: 0 | Y50: 0 | Z50: 0 | AA50: 0 | AB50: 0
A51: 24767728121 | B51: Viên nhai HB Omega DHA Gummies 60 viên | C51: Đang hoạt động | D51: - | E51: - | F51: - | G51: - | H51: HB029 | I51: 1 | J51: 1 | K51: 0 | L51: 0 | M51: 0 | N51: 0 | O51: 0 | P51: 0 | Q51: 0 | R51: 0 | S51: 0 | T51: 0 | U51: 0 | V51: 0 | W51: 0 | X51: 0 | Y51: 0 | Z51: 0 | AA51: 0 | AB51: 0
A52: 24867724627 | B52: Viên uống HB Arginmilk Plus 60 viên | C52: Đang hoạt động | D52: - | E52: - | F52: - | G52: - | H52: HB018 | I52: 58 | J52: 112 | K52: 20 | L52: 0.3448 | M52: 6 | N52: 4 | O52: 8 | P52: 16 | Q52: 0.1379 | R52: 0 | S52: 0 | T52: 0 | U52: 0 | V52: 0 | W52: 0 | X52: 0 | Y52: 0 | Z52: 0 | AA52: 0 | AB52: 0
A53: 24867724627 | B53: Viên uống HB Arginmilk Plus 60 viên | C53: Đang hoạt động | D53: 197356160607 | E53: 60 viên | F53: Đang hoạt động | G53: HB018 | H53: HB018 | I53: - | J53: - | K53: - | L53: - | M53: - | N53: - | O53: 8 | P53: 16 | Q53: - | R53: 0 | S53: 0 | T53: 0 | U53: - | V53: 0 | W53: 0 | X53: 0 | Y53: - | Z53: 0 | AA53: 0 | AB53: 0
A54: 25267725409 | B54: Viên uống HB Oreganol P73 30 viên | C54: Đang hoạt động | D54: - | E54: - | F54: - | G54: - | H54: HB016 | I54: 1 | J54: 2 | K54: 0 | L54: 0 | M54: 0 | N54: 0 | O54: 0 | P54: 0 | Q54: 0 | R54: 0 | S54: 0 | T54: 0 | U54: 0 | V54: 0 | W54: 0 | X54: 0 | Y54: 0 | Z54: 0 | AA54: 0 | AB54: 0
A55: 25667714981 | B55: Viên uống HB CoQ10 30 viên - 60 viên | C55: Đang hoạt động | D55: - | E55: - | F55: - | G55: - | H55: - | I55: 29 | J55: 36 | K55: 10 | L55: 0.3448 | M55: 2 | N55: 0 | O55: 1 | P55: 1 | Q55: 0.0345 | R55: 0 | S55: 0 | T55: 0 | U55: 0 | V55: 0 | W55: 0 | X55: 0 | Y55: 0 | Z55: 0 | AA55: 0 | AB55: 0
A56: 25667714981 | B56: Viên uống HB CoQ10 30 viên - 60 viên | C56: Đang hoạt động | D56: 187356061973 | E56: 30 viên | F56: Đang hoạt động | G56: HB031 | I56: - | J56: - | K56: - | L56: - | M56: - | N56: - | O56: 1 | P56: 1 | Q56: - | R56: 0 | S56: 0 | T56: 0 | U56: - | V56: 0 | W56: 0 | X56: 0 | Y56: - | Z56: 0 | AA56: 0 | AB56: 0
A57: 29178869548 | B57: Không thể lấy thông tin sản phẩm do bị xóa | C57: Đã xóa | D57: - | E57: - | F57: - | G57: - | H57: HB015 | I57: 7 | J57: 10 | K57: 3 | L57: 0.4286 | M57: 0 | N57: 0 | O57: 0 | P57: 0 | Q57: 0 | R57: 0 | S57: 0 | T57: 0 | U57: 0 | V57: 0 | W57: 0 | X57: 0 | Y57: 0 | Z57: 0 | AA57: 0 | AB57: 0
A58: 42463837349 | B58: Combo Mắt Khoẻ - Não Tinh (HB GLUCOLLAGEN 7 IN 1 - 30V + HB GINKGO BILOBA 120mg - 30V) | C58: Đã ẩn | D58: - | E58: - | F58: - | G58: - | H58: - | I58: 1 | J58: 2 | K58: 0 | L58: 0 | M58: 0 | N58: 0 | O58: 0 | P58: 0 | Q58: 0 | R58: 0 | S58: 0 | T58: 0 | U58: 0 | V58: 0 | W58: 0 | X58: 0 | Y58: 0 | Z58: 0 | AA58: 0 | AB58: 0
A59: 3817113391 | B59: Không thể lấy thông tin sản phẩm do bị xóa | C59: Đã xóa | D59: - | E59: - | F59: - | G59: - | H59: - | I59: 0 | J59: 0 | K59: 0 | L59: 0 | M59: 0 | N59: 0 | O59: 0 | P59: 0 | Q59: 0 | R59: 0 | S59: 0 | T59: 0 | U59: 0 | V59: 0 | W59: 0 | X59: 0 | Y59: 0 | Z59: 0 | AA59: 0 | AB59: 0
A60: 7117086844 | B60: Không thể lấy thông tin sản phẩm do bị xóa | C60: Đã xóa | D60: - | E60: - | F60: - | G60: - | H60: - | I60: 0 | J60: 0 | K60: 0 | L60: 0 | M60: 0 | N60: 0 | O60: 0 | P60: 0 | Q60: 0 | R60: 0 | S60: 0 | T60: 0 | U60: 0 | V60: 0 | W60: 0 | X60: 0 | Y60: 0 | Z60: 0 | AA60: 0 | AB60: 0
A61: 15506212702 | B61: ComBo Bảo Vệ Hệ Tim Mạch - Mắt - Não Healthy Beauty Cho Cả Gia Đình | C61: Đang hoạt động | D61: - | E61: - | F61: - | G61: - | H61: - | I61: 0 | J61: 0 | K61: 0 | L61: 0 | M61: 0 | N61: 0 | O61: 0 | P61: 0 | Q61: 0 | R61: 0 | S61: 0 | T61: 0 | U61: 0 | V61: 0 | W61: 0 | X61: 0 | Y61: 0 | Z61: 0 | AA61: 0 | AB61: 0
A62: 22964444155 | B62: Viên Uống Giảm Cân An Toàn Ban Đêm HB SLIMNIGHT 30 Viên | C62: Đang hoạt động | D62: - | E62: - | F62: - | G62: - | H62: HB008 | I62: 0 | J62: 0 | K62: 0 | L62: 0 | M62: 0 | N62: 0 | O62: 0 | P62: 0 | Q62: 0 | R62: 0 | S62: 0 | T62: 0 | U62: 0 | V62: 0 | W62: 0 | X62: 0 | Y62: 0 | Z62: 0 | AA62: 0 | AB62: 0
A63: 24767728121 | B63: Viên nhai HB Omega DHA Gummies 60 viên | C63: Đang hoạt động | D63: - | E63: - | F63: - | G63: - | H63: HB029 | I63: 0 | J63: 0 | K63: 0 | L63: 0 | M63: 0 | N63: 0 | O63: 0 | P63: 0 | Q63: 0 | R63: 0 | S63: 0 | T63: 0 | U63: 0 | V63: 0 | W63: 0 | X63: 0 | Y63: 0 | Z63: 0 | AA63: 0 | AB63: 0
A64: 25267725409 | B64: Viên uống HB Oreganol P73 30 viên | C64: Đang hoạt động | D64: - | E64: - | F64: - | G64: - | H64: HB016 | I64: 0 | J64: 0 | K64: 0 | L64: 0 | M64: 0 | N64: 0 | O64: 0 | P64: 0 | Q64: 0 | R64: 0 | S64: 0 | T64: 0 | U64: 0 | V64: 0 | W64: 0 | X64: 0 | Y64: 0 | Z64: 0 | AA64: 0 | AB64: 0
A65: =IF(C65<>"", "Có giá trị", "") -> Có giá trị | B65: Sản phẩm | C65: Tình trạng sản phẩm hiện tại | D65: Mã phân loại hàng | E65: Tên Phân Loại | F65: Trạng thái phân loại sản phẩm hiện tại | G65: SKU phân loại | H65: SKU sản phẩm | I65: Lượt truy cập sản phẩm | J65: Lượt xem trang sản phẩm | K65: Số lượng khách thoát trang sản phẩm | L65: Tỷ lệ thoát Trang sản phẩm | M65: Lượt click từ Trang tìm kiếm | N65: Lượt thích | O65: Lượt truy cập sản phẩm (Thêm vào giỏ hàng) | P65: Sản phẩm (Thêm vào giỏ hàng) | Q65: Tỷ lệ chuyển đổi (theo lượt thêm vào giỏ hàng) | R65: Người mua đã đặt hàng | S65: Sản phẩm (Đơn đã đặt) | T65: Doanh số (Đơn đã đặt) (VND) | U65: Tỷ lệ chuyển đổi (Đơn đã đặt) | V65: Người mua có đơn đã xác nhận | W65: Sản phẩm (Đơn đã xác nhận) | X65: Doanh số (Đơn đã xác nhận) (VND) | Y65: Tỷ lệ chuyển đổi (Đơn đã xác nhận) | Z65: Tỷ lệ chuyển đổi (Từ Đơn đã đặt thanh Đơn đã xác nhận) | AA65: Tỷ lệ đặt hàng lặp lại (Đơn hàng đã được xác nhận) | AB65: Số ngày trung bình để lặp lại đơn hàng (Đơn hàng đã được xác nhận)
A66: 25666719442 | B66: Viên uống giúp tái tạo và nuôi dưỡng mô sụn - HB Glucollagen 7 in 1 | C66: Đang hoạt động | D66: - | E66: - | F66: - | G66: - | H66: - | I66: 337 | J66: 794 | K66: 56 | L66: 0.1662 | M66: 48 | N66: 13 | O66: 72 | P66: 158 | Q66: 0.2136 | R66: 23 | S66: 33 | T66: 25286817 | U66: 0.0682 | V66: 23 | W66: 33 | X66: 25286817 | Y66: 0.0682 | Z66: 1 | AA66: 0.2069 | AB66: 45689
A67: 25666719442 | B67: Viên uống giúp tái tạo và nuôi dưỡng mô sụn - HB Glucollagen 7 in 1 | C67: Đang hoạt động | D67: 255410547718 | E67: 30 viên | F67: Đang hoạt động | G67: HB002 | I67: - | J67: - | K67: - | L67: - | M67: - | N67: - | O67: 28 | P67: 53 | Q67: - | R67: 4 | S67: 4 | T67: 1818607 | U67: - | V67: 4 | W67: 4 | X67: 1818607 | Y67: - | Z67: 1 | AA67: 0 | AB67: 0
A68: 25666719442 | B68: Viên uống giúp tái tạo và nuôi dưỡng mô sụn - HB Glucollagen 7 in 1 | C68: Đang hoạt động | D68: 255410547719 | E68: 60 viên | F68: Đang hoạt động | G68: HB003 | I68: - | J68: - | K68: - | L68: - | M68: - | N68: - | O68: 57 | P68: 105 | Q68: - | R68: 21 | S68: 29 | T68: 23468210 | U68: - | V68: 21 | W68: 29 | X68: 23468210 | Y68: - | Z68: 1 | AA68: 0.1923 | AB68: 0.4
A69: 8782633181 | B69: Viên Uống Giúp Chống Nắng Trắng Da Mờ Nám HB GLUTA WHITE + | C69: Đang hoạt động | D69: - | E69: - | F69: - | G69: - | H69: HB006 | I69: 295 | J69: 790 | K69: 67 | L69: 0.2271 | M69: 119 | N69: 24 | O69: 38 | P69: 137 | Q69: 0.1288 | R69: 10 | S69: 27 | T69: 25116230 | U69: 0.0339 | V69: 10 | W69: 25 | X69: 23349080 | Y69: 0.0339 | Z69: 1 | AA69: 0.5 | AB69: 45872
A70: 5158911395 | B70: Khẩu Trang Y Tế Kháng Khuẩn HB Medical Mask Cao Cấp Healthy Beauty 1 Hộp 50 cái | C70: Đang hoạt động | D70: - | E70: - | F70: - | G70: - | H70: - | I70: 79 | J70: 164 | K70: 18 | L70: 0.2278 | M70: 43 | N70: 11 | O70: 19 | P70: 78 | Q70: 0.2405 | R70: 6 | S70: 17 | T70: 952500 | U70: 0.0759 | V70: 6 | W70: 17 | X70: 952500 | Y70: 0.0759 | Z70: 1 | AA70: 0 | AB70: 0
A71: 5158911395 | B71: Khẩu Trang Y Tế Kháng Khuẩn HB Medical Mask Cao Cấp Healthy Beauty 1 Hộp 50 cái | C71: Đang hoạt động | D71: 93855942766 | E71: Than Hoạt Tính | F71: Đang hoạt động | G71: - | I71: - | J71: - | K71: - | L71: - | M71: - | N71: - | O71: 4 | P71: 35 | Q71: - | R71: 1 | S71: 5 | T71: 295000 | U71: - | V71: 1 | W71: 5 | X71: 295000 | Y71: - | Z71: 1 | AA71: 0 | AB71: 0
A72: 5158911395 | B72: Khẩu Trang Y Tế Kháng Khuẩn HB Medical Mask Cao Cấp Healthy Beauty 1 Hộp 50 cái | C72: Đang hoạt động | D72: 93855942767 | E72: Màu Trắng | F72: Đang hoạt động | G72: - | I72: - | J72: - | K72: - | L72: - | M72: - | N72: - | O72: 16 | P72: 40 | Q72: - | R72: 5 | S72: 11 | T72: 609500 | U72: - | V72: 5 | W72: 11 | X72: 609500 | Y72: - | Z72: 1 | AA72: 0 | AB72: 0
A73: 5158911395 | B73: Khẩu Trang Y Tế Kháng Khuẩn HB Medical Mask Cao Cấp Healthy Beauty 1 Hộp 50 cái | C73: Đang hoạt động | D73: 93855942768 | E73: Màu Xanh | F73: Đang hoạt động | G73: - | I73: - | J73: - | K73: - | L73: - | M73: - | N73: - | O73: 2 | P73: 3 | Q73: - | R73: 1 | S73: 1 | T73: 48000 | U73: - | V73: 1 | W73: 1 | X73: 48000 | Y73: - | Z73: 1 | AA73: 0 | AB73: 0
A74: 6917016018 | B74: Viên uống giúp Bổ Sung Canxi và Vitamin D3 HB CALCIDSOFT | C74: Đang hoạt động | D74: - | E74: - | F74: - | G74: - | H74: - | I74: 217 | J74: 520 | K74: 44 | L74: 0.2028 | M74: 107 | N74: 11 | O74: 33 | P74: 77 | Q74: 0.1521 | R74: 11 | S74: 14 | T74: 3955531 | U74: 0.0507 | V74: 11 | W74: 13 | X74: 3674311 | Y74: 0.0507 | Z74: 1 | AA74: 0.0833 | AB74: 18
A75: 6917016018 | B75: Viên uống giúp Bổ Sung Canxi và Vitamin D3 HB CALCIDSOFT | C75: Đang hoạt động | D75: 121223345683 | E75: Hộp 30 Viên | F75: Đang hoạt động | G75: HB024 | I75: - | J75: - | K75: - | L75: - | M75: - | N75: - | O75: 7 | P75: 10 | Q75: - | R75: 2 | S75: 2 | T75: 389880 | U75: - | V75: 2 | W75: 2 | X75: 389880 | Y75: - | Z75: 1 | AA75: 0 | AB75: 0
A76: 6917016018 | B76: Viên uống giúp Bổ Sung Canxi và Vitamin D3 HB CALCIDSOFT | C76: Đang hoạt động | D76: 121223345684 | E76: Hộp 60 Viên | F76: Đang hoạt động | G76: HB025 | I76: - | J76: - | K76: - | L76: - | M76: - | N76: - | O76: 27 | P76: 67 | Q76: - | R76: 9 | S76: 12 | T76: 3565651 | U76: - | V76: 9 | W76: 11 | X76: 3284431 | Y76: - | Z76: 1 | AA76: 0.1 | AB76: 18
A77: 5519393895 | B77: Viên Uống Giảm Gãy Rụng và Đen Tóc HB Black Hair Healthy Beauty (date 15/02/2026) | C77: Đang hoạt động | D77: - | E77: - | F77: - | G77: - | H77: - | I77: 113 | J77: 264 | K77: 32 | L77: 0.2832 | M77: 25 | N77: 13 | O77: 27 | P77: 69 | Q77: 0.2389 | R77: 8 | S77: 12 | T77: 6811660 | U77: 0.0708 | V77: 7 | W77: 9 | X77: 5496780 | Y77: 0.0619 | Z77: 0.875 | AA77: 0.125 | AB77: 0
A78: 5519393895 | B78: Viên Uống Giảm Gãy Rụng và Đen Tóc HB Black Hair Healthy Beauty (date 15/02/2026) | C78: Đang hoạt động | D78: 76595553673 | E78: 30 Viên | F78: Đang hoạt động | G78: HB028 | I78: - | J78: - | K78: - | L78: - | M78: - | N78: - | O78: 20 | P78: 32 | Q78: - | R78: 4 | S78: 6 | T78: 2558639 | U78: - | V78: 2 | W78: 3 | X78: 1243759 | Y78: - | Z78: 0.5 | AA78: 0 | AB78: 0
A79: 5519393895 | B79: Viên Uống Giảm Gãy Rụng và Đen Tóc HB Black Hair Healthy Beauty (date 15/02/2026) | C79: Đang hoạt động | D79: 76595553674 | E79: 60 Viên | F79: Đang hoạt động | G79: HB026 | I79: - | J79: - | K79: - | L79: - | M79: - | N79: - | O79: 11 | P79: 37 | Q79: - | R79: 5 | S79: 6 | T79: 4253021 | U79: - | V79: 5 | W79: 6 | X79: 4253021 | Y79: - | Z79: 1 | AA79: 0.1667 | AB79: 0
A80: 3862340378 | B80: Viên Uống Giảm Cân An Toàn Ban Ngày HB SLIMDAY 60 Viên | C80: Đang hoạt động | D80: - | E80: - | F80: - | G80: - | H80: HB007 | I80: 393 | J80: 742 | K80: 72 | L80: 0.1832 | M80: 216 | N80: 54 | O80: 34 | P80: 42 | Q80: 0.0865 | R80: 8 | S80: 8 | T80: 5310019 | U80: 0.0204 | V80: 8 | W80: 8 | X80: 5310019 | Y80: 0.0204 | Z80: 1 | AA80: 0 | AB80: 0
A81: 24667488336 | B81: Viên uống HB Glutathione - C Plus 30 viên | C81: Đang hoạt động | D81: - | E81: - | F81: - | G81: - | H81: HB030 | I81: 75 | J81: 156 | K81: 22 | L81: 0.2933 | M81: 16 | N81: 2 | O81: 10 | P81: 28 | Q81: 0.1333 | R81: 3 | S81: 5 | T81: 5278000 | U81: 0.04 | V81: 3 | W81: 5 | X81: 5278000 | Y81: 0.04 | Z81: 1 | AA81: 0.4 | AB81: 0
A82: 24667488336 | B82: Viên uống HB Glutathione - C Plus 30 viên | C82: Đang hoạt động | D82: 222571286446 | E82: 30 viên | F82: Đang hoạt động | G82: HB030 | H82: HB030 | I82: - | J82: - | K82: - | L82: - | M82: - | N82: - | O82: 9 | P82: 28 | Q82: - | R82: 3 | S82: 5 | T82: 5278000 | U82: - | V82: 3 | W82: 5 | X82: 5278000 | Y82: - | Z82: 1 | AA82: 0.4 | AB82: 0
A83: 24867481840 | B83: Viên uống HB Glucosamine 3 in 1 60 viên - 200 viên | C83: Đang hoạt động | D83: - | E83: - | F83: - | G83: - | H83: - | I83: 34 | J83: 109 | K83: 11 | L83: 0.3235 | M83: 6 | N83: 9 | O83: 8 | P83: 17 | Q83: 0.2353 | R83: 3 | S83: 5 | T83: 1733140 | U83: 0.0882 | V83: 3 | W83: 5 | X83: 1733140 | Y83: 0.0882 | Z83: 1 | AA83: 0.4 | AB83: 45780
A84: 24867481840 | B84: Viên uống HB Glucosamine 3 in 1 60 viên - 200 viên | C84: Đang hoạt động | D84: 69751100999 | E84: 60 viên | F84: Đang hoạt động | G84: HB005 | I84: - | J84: - | K84: - | L84: - | M84: - | N84: - | O84: 8 | P84: 17 | Q84: - | R84: 3 | S84: 5 | T84: 1733140 | U84: - | V84: 3 | W84: 5 | X84: 1733140 | Y84: - | Z84: 1 | AA84: 0.4 | AB84: 45780
A85: 3934257539 | B85: Viên Uống HB Collagen Type 1,2&3 Healthy Beauty 120 Viên | C85: Đang hoạt động | D85: - | E85: - | F85: - | G85: - | H85: HB001 | I85: 164 | J85: 310 | K85: 52 | L85: 0.3171 | M85: 61 | N85: 3 | O85: 16 | P85: 29 | Q85: 0.0976 | R85: 4 | S85: 4 | T85: 2753068 | U85: 0.0244 | V85: 4 | W85: 4 | X85: 2753068 | Y85: 0.0244 | Z85: 1 | AA85: 0 | AB85: 0
A86: 24867724627 | B86: Viên uống HB Arginmilk Plus 60 viên | C86: Đang hoạt động | D86: - | E86: - | F86: - | G86: - | H86: HB018 | I86: 50 | J86: 112 | K86: 7 | L86: 0.14 | M86: 3 | N86: 3 | O86: 14 | P86: 26 | Q86: 0.28 | R86: 4 | S86: 4 | T86: 2364865 | U86: 0.08 | V86: 4 | W86: 4 | X86: 2364865 | Y86: 0.08 | Z86: 1 | AA86: 0 | AB86: 0
A87: 24867724627 | B87: Viên uống HB Arginmilk Plus 60 viên | C87: Đang hoạt động | D87: 197356160607 | E87: 60 viên | F87: Đang hoạt động | G87: HB018 | H87: HB018 | I87: - | J87: - | K87: - | L87: - | M87: - | N87: - | O87: 13 | P87: 26 | Q87: - | R87: 4 | S87: 4 | T87: 2364865 | U87: - | V87: 4 | W87: 4 | X87: 2364865 | Y87: - | Z87: 1 | AA87: 0 | AB87: 0
A88: 10014812415 | B88: Viên Uống Bổ Sung Vitamin & Khoáng Chất Cho Bà Bầu HB PRENATAL SUPPORT | C88: Đang hoạt động | D88: - | E88: - | F88: - | G88: - | H88: - | I88: 23 | J88: 46 | K88: 5 | L88: 0.2174 | M88: 3 | N88: 0 | O88: 2 | P88: 2 | Q88: 0.087 | R88: 3 | S88: 3 | T88: 1447200 | U88: 0.1304 | V88: 3 | W88: 3 | X88: 1447200 | Y88: 0.1304 | Z88: 1 | AA88: 0 | AB88: 0
A89: 10014812415 | B89: Viên Uống Bổ Sung Vitamin & Khoáng Chất Cho Bà Bầu HB PRENATAL SUPPORT | C89: Đang hoạt động | D89: 56678491253 | E89: 30 Viên | F89: Đang hoạt động | G89: HB033 | I89: - | J89: - | K89: - | L89: - | M89: - | N89: - | O89: 0 | P89: 0 | Q89: - | R89: 1 | S89: 1 | T89: 395240 | U89: - | V89: 1 | W89: 1 | X89: 395240 | Y89: - | Z89: 1 | AA89: 0 | AB89: 0
A90: 10014812415 | B90: Viên Uống Bổ Sung Vitamin & Khoáng Chất Cho Bà Bầu HB PRENATAL SUPPORT | C90: Đang hoạt động | D90: 56678491254 | E90: 60 Viên | F90: Đang hoạt động | G90: HB034 | I90: - | J90: - | K90: - | L90: - | M90: - | N90: - | O90: 1 | P90: 1 | Q90: - | R90: 1 | S90: 1 | T90: 677320 | U90: - | V90: 1 | W90: 1 | X90: 677320 | Y90: - | Z90: 1 | AA90: 0 | AB90: 0
A91: 10014812415 | B91: Viên Uống Bổ Sung Vitamin & Khoáng Chất Cho Bà Bầu HB PRENATAL SUPPORT | C91: Đang hoạt động | D91: 265663431573 | E91: Hộp/Vỉ 10 viên x 3 | F91: Đang hoạt động | G91: HB039 | I91: - | J91: - | K91: - | L91: - | M91: - | N91: - | O91: 1 | P91: 1 | Q91: - | R91: 1 | S91: 1 | T91: 374640 | U91: - | V91: 1 | W91: 1 | X91: 374640 | Y91: - | Z91: 1 | AA91: 0 | AB91: 0
A92: 27540123008 | B92: [HB Gift]_Túi vải đay linen Healthy Beauty 40x35cm, thiết kế thanh lịch, chắc chắn, dung tích rộng | C92: Đang hoạt động | D92: - | E92: - | F92: - | G92: - | H92: - | I92: 10 | J92: 13 | K92: 3 | L92: 0.3 | M92: 5 | N92: 0 | O92: 0 | P92: 0 | Q92: 0 | R92: 3 | S92: 3 | T92: 0 | U92: 0.3 | V92: 3 | W92: 3 | X92: 0 | Y92: 0.3 | Z92: 1 | AA92: 0 | AB92: 0
A93: 22657955668 | B93: Viên uống HB GutCare (30 - 60 viên) hỗ trợ giảm triệu chứng đau khớp | C93: Đang hoạt động | D93: - | E93: - | F93: - | G93: - | H93: - | I93: 18 | J93: 29 | K93: 5 | L93: 0.2778 | M93: 0 | N93: 1 | O93: 2 | P93: 6 | Q93: 0.1111 | R93: 1 | S93: 2 | T93: 1166880 | U93: 0.0556 | V93: 1 | W93: 2 | X93: 1166880 | Y93: 0.0556 | Z93: 1 | AA93: 0 | AB93: 0
A94: 22657955668 | B94: Viên uống HB GutCare (30 - 60 viên) hỗ trợ giảm triệu chứng đau khớp | C94: Đang hoạt động | D94: 217104025857 | E94: 60 viên | F94: Đang hoạt động | G94: HB038 | I94: - | J94: - | K94: - | L94: - | M94: - | N94: - | O94: 2 | P94: 6 | Q94: - | R94: 1 | S94: 2 | T94: 1166880 | U94: - | V94: 1 | W94: 2 | X94: 1166880 | Y94: - | Z94: 1 | AA94: 0 | AB94: 0
A95: 26291184268 | B95: [HB Gift] _01 cây Bút Bi Healthy Beauty | C95: Đang hoạt động | D95: - | E95: - | F95: - | G95: - | H95: - | I95: 18 | J95: 26 | K95: 8 | L95: 0.4444 | M95: 1 | N95: 0 | O95: 5 | P95: 15 | Q95: 0.2778 | R95: 2 | S95: 2 | T95: 27500 | U95: 0.1111 | V95: 0 | W95: 0 | X95: 0 | Y95: 0 | Z95: 0 | AA95: 0 | AB95: 0
A96: 42318210434 | B96: Combo X 2 - Viên uống giúp tái tạo và nuôi dưỡng mô sụn - HB Glucollagen 7 in 1 | C96: Đang hoạt động | D96: - | E96: - | F96: - | G96: - | H96: - | I96: 23 | J96: 37 | K96: 3 | L96: 0.1304 | M96: 1 | N96: 1 | O96: 4 | P96: 6 | Q96: 0.1739 | R96: 1 | S96: 2 | T96: 3095820 | U96: 0.0435 | V96: 1 | W96: 2 | X96: 3095820 | Y96: 0.0435 | Z96: 1 | AA96: 0.5 | AB96: 0
A97: 42318210434 | B97: Combo X 2 - Viên uống giúp tái tạo và nuôi dưỡng mô sụn - HB Glucollagen 7 in 1 | C97: Đang hoạt động | D97: 286496443347 | E97: 30 viên | F97: Đang hoạt động | G97: HB002 | I97: - | J97: - | K97: - | L97: - | M97: - | N97: - | O97: 3 | P97: 3 | Q97: - | R97: 0 | S97: 0 | T97: 0 | U97: - | V97: 0 | W97: 0 | X97: 0 | Y97: - | Z97: 0 | AA97: 0 | AB97: 0
A98: 42318210434 | B98: Combo X 2 - Viên uống giúp tái tạo và nuôi dưỡng mô sụn - HB Glucollagen 7 in 1 | C98: Đang hoạt động | D98: 286496443348 | E98: 60 viên | F98: Đang hoạt động | G98: HB03 | I98: - | J98: - | K98: - | L98: - | M98: - | N98: - | O98: 2 | P98: 3 | Q98: - | R98: 1 | S98: 2 | T98: 3095820 | U98: - | V98: 1 | W98: 2 | X98: 3095820 | Y98: - | Z98: 1 | AA98: 0.5 | AB98: 0
A99: 5219966803 | B99: Viên Uống Đông Trùng Hạ Thảo Bồi Bổ Khí Huyết HB CORDY EXTRACT | C99: Đang hoạt động | D99: - | E99: - | F99: - | G99: - | H99: HB015 | I99: 87 | J99: 206 | K99: 19 | L99: 0.2184 | M99: 30 | N99: 2 | O99: 8 | P99: 18 | Q99: 0.092 | R99: 1 | S99: 1 | T99: 807100 | U99: 0.0115 | V99: 0 | W99: 0 | X99: 0 | Y99: 0 | Z99: 0 | AA99: 0 | AB99: 0
A100: 24367745053 | B100: HB MEDICAL MASK - Túi zip - Khẩu trang y tế 4 lớp kháng khuẩn chuẩn nhóm A | C100: Đang hoạt động | D100: - | E100: - | F100: - | G100: - | H100: - | I100: 10 | J100: 15 | K100: 2 | L100: 0.2 | M100: 1 | N100: 0 | O100: 3 | P100: 3 | Q100: 0.3 | R100: 1 | S100: 1 | T100: 18000 | U100: 0.1 | V100: 0 | W100: 0 | X100: 0 | Y100: 0 | Z100: 0 | AA100: 0 | AB100: 0
...

Sheet LAZADA
A1: Nguồn: Lazada - Công cụ phân tích - Tổng quan với Khung thời gian:01-08-2025~29-08-2025
A2: Để xem chi tiết, vui lòng truy cập công cụ phân tích - Tổng quan
A6: Ngày | B6: Lợi nhuận | C6: Khách truy cập | D6: Khách mua | E6: Đơn hàng | F6: Lượt xem | G6: Sản phẩm bán được | H6: Tỷ lệ chuyển đổi | I6: Doanh thu trên mỗi khách mua | J6: Giá trị lượt truy cập | K6: Người dùng đã thêm sản phẩm vào giỏ hàng | L6: Số lượng thêm vào giỏ hàng | M6: Danh sách yêu thích | N6: Người dùng có wishlist | O6: Giá trị đơn hàng trung bình | P6: Số sản phẩm trung bình | Q6: Số lượng hủy | R6: Khoản hoàn trả
A7: 2025-08-01~2025-08-29 | C7: 32 | D7: 1 | E7: 1 | F7: 77 | G7: 2 | H7: 3.12% | I7: 3007600 | J7: 93988 | K7: 4 | L7: 4 | M7: - | N7: - | P7: 2.00 | Q7: - | R7: - | S7: =MONTH(A7) -> #VALUE!
A8: - | C8: - | D8: - | E8: - | F8: - | G8: - | H8: - | I8: - | J8: - | K8: - | L8: - | M8: - | N8: - | P8: - | Q8: - | R8: - | S8: =MONTH(A8) -> #VALUE!
A9: 45870 | C9: 1 | D9: 0 | E9: 0 | F9: 2 | G9: 0 | H9: 0.00% | I9: - | J9: 0.00 | K9: 0 | L9: 0 | M9: - | N9: - | P9: - | Q9: 0.00 | R9: 0.00 | S9: =MONTH(A9) -> 8
A10: 45871 | C10: 1 | D10: 0 | E10: 0 | F10: 1 | G10: 0 | H10: 0.00% | I10: - | J10: 0.00 | K10: 0 | L10: 0 | M10: - | N10: - | P10: - | Q10: 0.00 | R10: 0.00 | S10: =MONTH(A10) -> 8
A11: 45872 | C11: 1 | D11: 0 | E11: 0 | F11: 1 | G11: 0 | H11: 0.00% | I11: - | J11: 0.00 | K11: 0 | L11: 0 | M11: - | N11: - | P11: - | Q11: 0.00 | R11: 0.00 | S11: =MONTH(A11) -> 8
A12: 45873 | C12: 0 | D12: 0 | E12: 0 | F12: 0 | G12: 0 | H12: - | I12: - | J12: - | K12: 0 | L12: 0 | M12: - | N12: - | P12: - | Q12: 0.00 | R12: 0.00 | S12: =MONTH(A12) -> 8
A13: 45874 | C13: 2 | D13: 0 | E13: 0 | F13: 2 | G13: 0 | H13: 0.00% | I13: - | J13: 0.00 | K13: 0 | L13: 0 | M13: - | N13: - | P13: - | Q13: 0.00 | R13: 0.00 | S13: =MONTH(A13) -> 8
A14: 45875 | C14: 1 | D14: 0 | E14: 0 | F14: 1 | G14: 0 | H14: 0.00% | I14: - | J14: 0.00 | K14: 0 | L14: 0 | M14: - | N14: - | P14: - | Q14: 0.00 | R14: 0.00 | S14: =MONTH(A14) -> 8
A15: 45876 | C15: 1 | D15: 0 | E15: 0 | F15: 3 | G15: 0 | H15: 0.00% | I15: - | J15: 0.00 | K15: 0 | L15: 0 | M15: - | N15: - | P15: - | Q15: 0.00 | R15: 0.00 | S15: =MONTH(A15) -> 8
A16: 45877 | C16: 3 | D16: 0 | E16: 0 | F16: 5 | G16: 0 | H16: 0.00% | I16: - | J16: 0.00 | K16: 0 | L16: 0 | M16: - | N16: - | P16: - | Q16: 0.00 | R16: 0.00 | S16: =MONTH(A16) -> 8
A17: 45878 | C17: 2 | D17: 0 | E17: 0 | F17: 2 | G17: 0 | H17: 0.00% | I17: - | J17: 0.00 | K17: 0 | L17: 0 | M17: - | N17: - | P17: - | Q17: 0.00 | R17: 0.00 | S17: =MONTH(A17) -> 8
A18: 45879 | C18: 1 | D18: 0 | E18: 0 | F18: 3 | G18: 0 | H18: 0.00% | I18: - | J18: 0.00 | K18: 0 | L18: 0 | M18: - | N18: - | P18: - | Q18: 0.00 | R18: 0.00 | S18: =MONTH(A18) -> 8
A19: 45880 | C19: 3 | D19: 0 | E19: 0 | F19: 5 | G19: 0 | H19: 0.00% | I19: - | J19: 0.00 | K19: 1 | L19: 1 | M19: - | N19: - | P19: - | Q19: 0.00 | R19: 0.00 | S19: =MONTH(A19) -> 8
A20: 45881 | C20: 0 | D20: 0 | E20: 0 | F20: 0 | G20: 0 | H20: - | I20: - | J20: - | K20: 0 | L20: 0 | M20: - | N20: - | P20: - | Q20: 0.00 | R20: 0.00 | S20: =MONTH(A20) -> 8
... A22: 45883 | C22: 2 | D22: 0 | E22: 0 | F22: 5 | G22: 0 | H22: 0.00% | I22: - | J22: 0.00 | K22: 0 | L22: 0 | M22: - | N22: - | P22: - | Q22: 0.00 | R22: 0.00 | S22: =MONTH(A22) -> 8
A23: 45884 | B23: 3007600 | C23: 2 | D23: 1 | E23: 1 | F23: 8 | G23: 2 | H23: 50.00% | I23: 3007600 | J23: 1503800 | K23: 1 | L23: 1 | M23: - | N23: - | P23: 2.00 | Q23: 0.00 | R23: 0.00 | S23: =MONTH(A23) -> 8
A24: 45885 | C24: 0 | D24: 0 | E24: 0 | F24: 0 | G24: 0 | H24: - | I24: - | J24: - | K24: 0 | L24: 0 | M24: - | N24: - | P24: - | Q24: 0.00 | R24: 0.00 | S24: =MONTH(A24) -> 8
A25: 45886 | C25: 1 | D25: 0 | E25: 0 | F25: 6 | G25: 0 | H25: 0.00% | I25: - | J25: 0.00 | K25: 0 | L25: 0 | M25: - | N25: - | P25: - | Q25: 0.00 | R25: 0.00 | S25: =MONTH(A25) -> 8
A26: 45887 | C26: 1 | D26: 0 | E26: 0 | F26: 1 | G26: 0 | H26: 0.00% | I26: - | J26: 0.00 | K26: 0 | L26: 0 | M26: - | N26: - | P26: - | Q26: - | R26: - | S26: =MONTH(A26) -> 8
A27: 45888 | C27: 1 | D27: 0 | E27: 0 | F27: 1 | G27: 0 | H27: 0.00% | I27: - | J27: 0.00 | K27: 0 | L27: 0 | M27: - | N27: - | P27: - | Q27: - | R27: - | S27: =MONTH(A27) -> 8
A28: 45889 | C28: 0 | D28: 0 | E28: 0 | F28: 0 | G28: 0 | H28: - | I28: - | J28: - | K28: 0 | L28: 0 | M28: - | N28: - | P28: - | Q28: - | R28: - | S28: =MONTH(A28) -> 8
A29: 45890 | C29: 0 | D29: 0 | E29: 0 | F29: 0 | G29: 0 | H29: - | I29: - | J29: - | K29: 0 | L29: 0 | M29: - | N29: - | P29: - | Q29: - | R29: - | S29: =MONTH(A29) -> 8
A30: 45891 | C30: 1 | D30: 0 | E30: 0 | F30: 1 | G30: 0 | H30: 0.00% | I30: - | J30: 0.00 | K30: 1 | L30: 1 | M30: - | N30: - | P30: - | Q30: - | R30: - | S30: =MONTH(A30) -> 8
A31: 45892 | C31: 1 | D31: 0 | E31: 0 | F31: 7 | G31: 0 | H31: 0.00% | I31: - | J31: 0.00 | K31: 0 | L31: 0 | M31: - | N31: - | P31: - | Q31: - | R31: - | S31: =MONTH(A31) -> 8
A32: 45893 | C32: 2 | D32: 0 | E32: 0 | F32: 4 | G32: 0 | H32: 0.00% | I32: - | J32: 0.00 | K32: 0 | L32: 0 | M32: - | N32: - | P32: - | Q32: - | R32: - | S32: =MONTH(A32) -> 8
A33: 45894 | C33: 0 | D33: 0 | E33: 0 | F33: 0 | G33: 0 | H33: - | I33: - | J33: - | K33: 0 | L33: 0 | M33: - | N33: - | P33: - | Q33: - | R33: - | S33: =MONTH(A33) -> 8
A34: 45895 | C34: 0 | D34: 0 | E34: 0 | F34: 0 | G34: 0 | H34: - | I34: - | J34: - | K34: 0 | L34: 0 | M34: - | N34: - | P34: - | Q34: - | R34: - | S34: =MONTH(A34) -> 8
A35: 45896 | C35: 2 | D35: 0 | E35: 0 | F35: 4 | G35: 0 | H35: 0.00% | I35: - | J35: 0.00 | K35: 0 | L35: 0 | M35: - | N35: - | P35: - | Q35: - | R35: - | S35: =MONTH(A35) -> 8
... A37: 45898 | C37: 2 | D37: 0 | E37: 0 | F37: 9 | G37: 0 | H37: 0.00% | I37: - | J37: 0.00 | K37: 1 | L37: 1 | M37: - | N37: - | P37: - | Q37: - | R37: - | S37: =MONTH(A37) -> 8
A38: 45899 | S38: =MONTH(A38) -> 8
A39: 45900 | S39: =MONTH(A39) -> 8
A44: Ngày | B44: Lợi nhuận | C44: Khách truy cập | D44: Khách mua | E44: Đơn hàng | F44: Lượt xem | G44: Sản phẩm bán được | H44: Tỷ lệ chuyển đổi | I44: Doanh thu trên mỗi khách mua | J44: Giá trị lượt truy cập | K44: Người dùng đã thêm sản phẩm vào giỏ hàng | L44: Số lượng thêm vào giỏ hàng | M44: Danh sách yêu thích | N44: Người dùng có wishlist | O44: Giá trị đơn hàng trung bình | P44: Số sản phẩm trung bình | Q44: Số lượng hủy | R44: Khoản hoàn trả | S44: =MONTH(A44) -> #VALUE!
A45: 2025-09-01~2025-09-29 | B45: =SUM(B47:B76) -> 8155315 | C45: 127 | D45: 8 | E45: 10 | F45: 643 | G45: 12 | H45: 6.30% | I45: 1019414 | J45: 64215.08 | K45: 14 | L45: 24 | M45: 9 | N45: 9 | O45: 815531.50 | P45: 1.20 | Q45: - | R45: - | S45: =MONTH(A45) -> #VALUE!
A46: - | B46: - | C46: - | D46: - | E46: - | F46: - | G46: - | H46: - | I46: - | J46: - | K46: - | L46: - | M46: - | N46: - | O46: - | P46: - | Q46: - | R46: - | S46: =MONTH(A46) -> #VALUE!
A47: 45901 | B47: 4229600 | C47: 1 | D47: 1 | E47: 1 | F47: 5 | G47: 3 | H47: 100.00% | I47: 4229600 | J47: 4229600.00 | K47: 1 | L47: 1 | M47: - | N47: - | O47: 4229600.00 | P47: 3.00 | Q47: - | R47: - | S47: =MONTH(A47) -> 9 | T47: 4229600 | U47: 1
A48: 45902 | B48: 0 | C48: 1 | D48: 0 | E48: 0 | F48: 7 | G48: 0 | H48: 0.00% | I48: - | J48: 0.00 | K48: 1 | L48: 1 | M48: - | N48: - | O48: - | P48: - | Q48: - | R48: - | S48: =MONTH(A48) -> 9 | T48: 0 | U48: 0
A49: 45903 | B49: 0 | C49: 4 | D49: 0 | E49: 0 | F49: 5 | G49: 0 | H49: 0.00% | I49: - | J49: 0.00 | K49: 0 | L49: 0 | M49: - | N49: - | O49: - | P49: - | Q49: - | R49: - | S49: =MONTH(A49) -> 9 | T49: 0 | U49: 0
A50: 45904 | B50: 0 | C50: 3 | D50: 0 | E50: 0 | F50: 19 | G50: 0 | H50: 0.00% | I50: - | J50: 0.00 | K50: 0 | L50: 0 | M50: - | N50: - | O50: - | P50: - | Q50: - | R50: - | S50: =MONTH(A50) -> 9 | T50: 0 | U50: 0
A51: 45905 | B51: 0 | C51: 2 | D51: 0 | E51: 0 | F51: 12 | G51: 0 | H51: 0.00% | I51: - | J51: 0.00 | K51: 0 | L51: 0 | M51: - | N51: - | O51: - | P51: - | Q51: - | R51: - | S51: =MONTH(A51) -> 9 | T51: 0 | U51: 0
A52: 45906 | B52: 0 | C52: 2 | D52: 0 | E52: 0 | F52: 10 | G52: 0 | H52: 0.00% | I52: - | J52: 0.00 | K52: 0 | L52: 0 | M52: - | N52: - | O52: - | P52: - | Q52: - | R52: - | S52: =MONTH(A52) -> 9 | T52: 0 | U52: 0
A53: 45907 | B53: 0 | C53: 1 | D53: 0 | E53: 0 | F53: 1 | G53: 0 | H53: 0.00% | I53: - | J53: 0.00 | K53: 0 | L53: 0 | M53: - | N53: - | O53: - | P53: - | Q53: - | R53: - | S53: =MONTH(A53) -> 9 | T53: 0 | U53: 0
A54: 45908 | B54: 0 | C54: 8 | D54: 0 | E54: 0 | F54: 15 | G54: 0 | H54: 0.00% | I54: - | J54: 0.00 | K54: 0 | L54: 0 | M54: - | N54: - | O54: - | P54: - | Q54: - | R54: - | S54: =MONTH(A54) -> 9 | T54: 0 | U54: 0
A55: 45909 | B55: 644734 | C55: 10 | D55: 2 | E55: 2 | F55: 38 | G55: 2 | H55: 20.00% | I55: 322367 | J55: 64473.40 | K55: 2 | L55: 2 | M55: 2 | N55: 2 | O55: 322367.00 | P55: 1.00 | Q55: - | R55: - | S55: =MONTH(A55) -> 9 | T55: 644734 | U55: 2
A56: 45910 | B56: 0 | C56: 12 | D56: 0 | E56: 0 | F56: 19 | G56: 0 | H56: 0.00% | I56: - | J56: 0.00 | K56: 0 | L56: 0 | M56: - | N56: - | O56: - | P56: - | Q56: - | R56: - | S56: =MONTH(A56) -> 9 | T56: 0 | U56: 0
A57: 45911 | B57: 1193727 | C57: 13 | D57: 2 | E57: 2 | F57: 71 | G57: 2 | H57: 15.38% | I57: 596863 | J57: 91825.15 | K57: 3 | L57: 12 | M57: 2 | N57: 2 | O57: 596863.50 | P57: 1.00 | Q57: - | R57: - | S57: =MONTH(A57) -> 9 | T57: 1193727 | U57: 2
A58: 45912 | B58: 0 | C58: 17 | D58: 0 | E58: 0 | F58: 160 | G58: 0 | H58: 0.00% | I58: - | J58: 0.00 | K58: 2 | L58: 3 | M58: - | N58: - | O58: - | P58: - | Q58: - | R58: - | S58: =MONTH(A58) -> 9 | T58: 0 | U58: 0
A59: 45913 | B59: 0 | C59: 12 | D59: 0 | E59: 0 | F59: 32 | G59: 0 | H59: 0.00% | I59: - | J59: 0.00 | K59: 2 | L59: 2 | M59: - | N59: - | O59: - | P59: - | Q59: - | R59: - | S59: =MONTH(A59) -> 9 | T59: 0 | U59: 0
A60: 45914 | B60: 0 | C60: 12 | D60: 0 | E60: 0 | F60: 16 | G60: 0 | H60: 0.00% | I60: - | J60: 0.00 | K60: 0 | L60: 0 | M60: - | N60: - | O60: - | P60: - | Q60: - | R60: - | S60: =MONTH(A60) -> 9 | T60: 0 | U60: 0
A61: 45915 | B61: 537600 | C61: 12 | D61: 1 | E61: 1 | F61: 53 | G61: 1 | H61: 8.33% | I61: 537600 | J61: 44800.00 | K61: 0 | L61: 0 | M61: 2 | N61: 2 | O61: 537600.00 | P61: 1.00 | Q61: - | R61: - | S61: =MONTH(A61) -> 9 | T61: 537600 | U61: 1
A62: 45916 | B62: 0 | C62: 4 | D62: 0 | E62: 0 | F62: 15 | G62: 0 | H62: 0.00% | I62: - | J62: 0.00 | K62: 0 | L62: 0 | M62: - | N62: - | O62: - | P62: - | Q62: - | R62: - | S62: =MONTH(A62) -> 9 | T62: 0 | U62: 0
A63: 45917 | B63: 0 | C63: 7 | D63: 0 | E63: 0 | F63: 28 | G63: 0 | H63: 0.00% | I63: - | J63: 0.00 | K63: 0 | L63: 0 | M63: - | N63: - | O63: - | P63: - | Q63: - | R63: - | S63: =MONTH(A63) -> 9 | T63: 0 | U63: 0
A64: 45918 | B64: 0 | C64: 10 | D64: 0 | E64: 0 | F64: 29 | G64: 0 | H64: 0.00% | I64: - | J64: 0.00 | K64: 0 | L64: 0 | M64: - | N64: - | O64: - | P64: - | Q64: - | R64: - | S64: =MONTH(A64) -> 9 | T64: 0 | U64: 0
A65: 45919 | B65: 0 | C65: 6 | D65: 0 | E65: 0 | F65: 9 | G65: 0 | H65: 0.00% | I65: - | J65: 0.00 | K65: 1 | L65: 1 | M65: - | N65: - | O65: - | P65: - | Q65: - | R65: - | S65: =MONTH(A65) -> 9 | T65: 0 | U65: 0
A66: 45920 | B66: 345600 | C66: 7 | D66: 1 | E66: 1 | F66: 20 | G66: 1 | H66: 14.29% | I66: 345600 | J66: 49371.43 | K66: 0 | L66: 0 | M66: - | N66: - | O66: 345600.00 | P66: 1.00 | Q66: - | R66: - | S66: =MONTH(A66) -> 9 | T66: 345600 | U66: 1
A67: 45921 | B67: 0 | C67: 3 | D67: 0 | E67: 0 | F67: 6 | G67: 0 | H67: 0.00% | I67: - | J67: 0.00 | K67: 1 | L67: 1 | M67: - | N67: - | O67: - | P67: - | Q67: - | R67: - | S67: =MONTH(A67) -> 9 | T67: 0 | U67: 0
A68: 45922 | B68: 345600 | C68: 4 | D68: 1 | E68: 1 | F68: 10 | G68: 1 | H68: 25.00% | I68: 345600 | J68: 86400.00 | K68: 0 | L68: 0 | M68: 1 | N68: 1 | O68: 345600.00 | P68: 1.00 | Q68: - | R68: - | S68: =MONTH(A68) -> 9 | T68: 345600 | U68: 1
A69: 45923 | B69: 0 | C69: 5 | D69: 0 | E69: 0 | F69: 7 | G69: 0 | H69: 0.00% | I69: - | J69: 0.00 | K69: 0 | L69: 0 | M69: - | N69: - | O69: - | P69: - | Q69: - | R69: - | S69: =MONTH(A69) -> 9 | T69: 0 | U69: 0
A70: 45924 | B70: 401800 | C70: 3 | D70: 1 | E70: 1 | F70: 6 | G70: 1 | H70: 33.33% | I70: 401800 | J70: 133933.33 | K70: 1 | L70: 1 | M70: 1 | N70: 1 | O70: 401800.00 | P70: 1.00 | Q70: - | R70: - | S70: =MONTH(A70) -> 9 | T70: 401800 | U70: 1
A71: 45925 | B71: 0 | C71: 2 | D71: 0 | E71: 0 | F71: 3 | G71: 0 | H71: 0.00% | I71: - | J71: 0.00 | K71: 0 | L71: 0 | M71: - | N71: - | O71: - | P71: - | Q71: - | R71: - | S71: =MONTH(A71) -> 9 | T71: 0 | U71: 0
A72: 45926 | B72: 0 | C72: 4 | D72: 0 | E72: 0 | F72: 9 | G72: 0 | H72: 0.00% | I72: - | J72: 0.00 | K72: 0 | L72: 0 | M72: - | N72: - | O72: - | P72: - | Q72: - | R72: - | S72: =MONTH(A72) -> 9 | T72: 0 | U72: 0
A73: 45927 | B73: 456654 | C73: 3 | D73: 1 | E73: 1 | F73: 22 | G73: 1 | H73: 33.33% | I73: 456654 | J73: 152218.00 | K73: 0 | L73: 0 | M73: - | N73: - | O73: 456654.00 | P73: 1.00 | Q73: - | R73: - | S73: =MONTH(A73) -> 9 | T73: 456654 | U73: 1
A74: 45931 | B74: =T74-Q74 -> 0 | C74: 1 | D74: 0 | E74: 0 | F74: 3 | G74: 0 | H74: 0.00% | I74: 0 | J74: 0 | K74: 0 | L74: 0 | M74: 0 | N74: 0 | O74: 0 | P74: 0 | Q74: 0 | R74: 0 | S74: =MONTH(A74) -> 10 | T74: 0 | U74: 0
A75: 45932 | B75: =T75-Q75 -> 0 | C75: 5 | D75: 0 | E75: 0 | F75: 8 | G75: 0 | H75: 0.00% | I75: 0 | J75: 0 | K75: 0 | L75: 0 | M75: 0 | N75: 0 | O75: 0 | P75: 0 | Q75: 0 | R75: 0 | S75: =MONTH(A75) -> 10 | T75: 0 | U75: 0
A76: 45933 | B76: =T76-Q76 -> 0 | C76: 6 | D76: 0 | E76: 0 | F76: 9 | G76: 0 | H76: 0.00% | I76: 0 | J76: 0 | K76: 0 | L76: 0 | M76: 0 | N76: 0 | O76: 0 | P76: 0 | Q76: 0 | R76: 0 | S76: =MONTH(A76) -> 10 | T76: 0 | U76: 0
A77: 45934 | B77: =T77-Q77 -> 0 | C77: 1 | D77: 0 | E77: 0 | F77: 3 | G77: 0 | H77: 0.00% | I77: 0 | J77: 0 | K77: 1 | L77: 1 | M77: 0 | N77: 0 | O77: 0 | P77: 0 | Q77: 0 | R77: 0 | S77: =MONTH(A77) -> 10 | T77: 0 | U77: 0
A78: 45935 | B78: =T78-Q78 -> 0 | C78: 6 | D78: 0 | E78: 0 | F78: 6 | G78: 0 | H78: 0.00% | I78: 0 | J78: 0 | K78: 0 | L78: 0 | M78: 0 | N78: 0 | O78: 0 | P78: 0 | Q78: 0 | R78: 0 | S78: =MONTH(A78) -> 10 | T78: 0 | U78: 0
A79: 45936 | B79: =T79-Q79 -> 0 | C79: 5 | D79: 0 | E79: 0 | F79: 5 | G79: 0 | H79: 0.00% | I79: 0 | J79: 0 | K79: 0 | L79: 0 | M79: 0 | N79: 0 | O79: 0 | P79: 0 | Q79: 0 | R79: 0 | S79: =MONTH(A79) -> 10 | T79: 0 | U79: 0
A80: 45937 | B80: =T80-Q80 -> 0 | C80: 7 | D80: 0 | E80: 0 | F80: 9 | G80: 0 | H80: 0.00% | I80: 0 | J80: 0 | K80: 0 | L80: 0 | M80: 0 | N80: 0 | O80: 0 | P80: 0 | Q80: 0 | R80: 0 | S80: =MONTH(A80) -> 10 | T80: 0 | U80: 0
A81: 45938 | B81: =T81-Q81 -> 0 | C81: 7 | D81: 0 | E81: 0 | F81: 7 | G81: 0 | H81: 0.00% | I81: 0 | J81: 0 | K81: 0 | L81: 0 | M81: 0 | N81: 0 | O81: 0 | P81: 0 | Q81: 0 | R81: 0 | S81: =MONTH(A81) -> 10 | T81: 0 | U81: 0
A82: 45939 | B82: =T82-Q82 -> 459532 | C82: 14 | D82: 1 | E82: 1 | F82: 42 | G82: 1 | H82: 7.14% | I82: 459532 | J82: 32823.71 | K82: 2 | L82: 2 | M82: 1 | N82: 1 | O82: 459532 | P82: 1 | Q82: 0 | R82: 0 | S82: =MONTH(A82) -> 10 | T82: 459532 | U82: 1
A83: 45940 | B83: =T83-Q83 -> 1767630 | C83: 6 | D83: 1 | E83: 1 | F83: 23 | G83: 4 | H83: 16.67% | I83: 1767630 | J83: 294605 | K83: 1 | L83: 4 | M83: 1 | N83: 1 | O83: 1767630 | P83: 4 | Q83: 0 | R83: 0 | S83: =MONTH(A83) -> 10 | T83: 1767630 | U83: 1
A84: 45941 | B84: =T84-Q84 -> 0 | C84: 16 | D84: 1 | E84: 1 | F84: 18 | G84: 1 | H84: 6.25% | I84: 180200 | J84: 11262.5 | K84: 0 | L84: 0 | M84: 1 | N84: 1 | O84: 180200 | P84: 1 | Q84: 180200 | R84: 0 | S84: =MONTH(A84) -> 10 | T84: 180200 | U84: 1
A85: 45942 | B85: =T85-Q85 -> 470032 | C85: 55 | D85: 1 | E85: 1 | F85: 76 | G85: 1 | H85: 1.82% | I85: 470032 | J85: 2427494 | K85: 0 | L85: 0 | M85: 1 | N85: 1 | O85: 470032 | P85: 1 | Q85: 0 | R85: 0 | S85: =MONTH(A85) -> 10 | T85: 470032 | U85: 1
A86: 45943 | B86: =T86-Q86 -> 0 | C86: 52 | D86: 0 | E86: 0 | F86: 70 | G86: 0 | H86: 0.00% | I86: 0 | J86: 0 | K86: 0 | L86: 0 | M86: 0 | N86: 0 | O86: 0 | P86: 0 | Q86: 0 | R86: 0 | S86: =MONTH(A86) -> 10 | T86: 0 | U86: 0
A87: 45944 | B87: =T87-Q87 -> 0 | C87: 136 | D87: 0 | E87: 0 | F87: 199 | G87: 0 | H87: 0.00% | I87: 0 | J87: 0 | K87: 2 | L87: 2 | M87: 0 | N87: 0 | O87: 0 | P87: 0 | Q87: 0 | R87: 0 | S87: =MONTH(A87) -> 10 | T87: 0 | U87: 0
A88: 45945 | B88: =T88-Q88 -> 526760 | C88: 94 | D88: 1 | E88: 1 | F88: 138 | G88: 1 | H88: 1.06% | I88: 526760 | J88: 5603.83 | K88: 1 | L88: 1 | M88: 1 | N88: 1 | O88: 526760 | P88: 1 | Q88: 0 | R88: 0 | S88: =MONTH(A88) -> 10 | T88: 526760 | U88: 1
A89: 45946 | B89: =T89-Q89 -> 0 | C89: 51 | D89: 0 | E89: 0 | F89: 83 | G89: 0 | H89: 0.00% | I89: 0 | J89: 0 | K89: 0 | L89: 0 | M89: 0 | N89: 0 | O89: 0 | P89: 0 | Q89: 0 | R89: 0 | S89: =MONTH(A89) -> 10 | T89: 0 | U89: 0
A90: 45947 | B90: =T90-Q90 -> 0 | C90: 5 | D90: 0 | E90: 0 | F90: 21 | G90: 0 | H90: 0.00% | I90: 0 | J90: 0 | K90: 1 | L90: 1 | M90: 0 | N90: 0 | O90: 0 | P90: 0 | Q90: 0 | R90: 0 | S90: =MONTH(A90) -> 10 | T90: 0 | U90: 0
A91: 45948 | B91: =T91-Q91 -> 728050 | C91: 28 | D91: 1 | E91: 1 | F91: 33 | G91: 1 | H91: 3.57% | I91: 728050 | J91: 26001.79 | K91: 1 | L91: 1 | M91: 1 | N91: 1 | O91: 728050 | P91: 1 | Q91: 0 | R91: 0 | S91: =MONTH(A91) -> 10 | T91: 728050 | U91: 1
A92: 45949 | B92: =T92-Q92 -> 1222910 | C92: 134 | D92: 2 | E92: 3 | F92: 247 | G92: 3 | H92: 1.49% | I92: 611455 | J92: 9126.19 | K92: 1 | L92: 2 | M92: 1 | N92: 1 | O92: 407636.67 | P92: 1 | Q92: 0 | R92: 0 | S92: =MONTH(A92) -> 10 | T92: 1222910 | U92: 3
A93: 45950 | B93: =T93-Q93 -> 660600 | C93: 253 | D93: 1 | E93: 1 | F93: 377 | G93: 1 | H93: 0.40% | I93: 660600 | J93: 259870 | K93: 1 | L93: 2 | M93: 0 | N93: 0 | O93: 660600 | P93: 1 | Q93: 0 | R93: 0 | S93: =MONTH(A93) -> 10 | T93: 660600 | U93: 1
A94: 45951 | B94: =T94-Q94 -> -526760 | C94: 99 | D94: 0 | E94: 0 | F94: 151 | G94: 0 | H94: 0.00% | I94: 0 | J94: 0 | K94: 0 | L94: 0 | M94: 0 | N94: 0 | O94: 0 | P94: 0 | Q94: 526760 | R94: 0 | S94: =MONTH(A94) -> 10 | T94: 0 | U94: 0
A95: 45952 | B95: =T95-Q95 -> 1218750 | C95: 91 | D95: 2 | E95: 2 | F95: 166 | G95: 2 | H95: 2.20% | I95: 609375 | J95: 13392.86 | K95: 3 | L95: 3 | M95: 2 | N95: 2 | O95: 609375 | P95: 1 | Q95: 0 | R95: 0 | S95: =MONTH(A95) -> 10 | T95: 1218750 | U95: 2
A96: 45953 | B96: =T96-Q96 -> 0 | C96: 198 | D96: 0 | E96: 0 | F96: 262 | G96: 0 | H96: 0.00% | I96: 0 | J96: 0 | K96: 1 | L96: 1 | M96: 0 | N96: 0 | O96: 0 | P96: 0 | Q96: 0 | R96: 0 | S96: =MONTH(A96) -> 10 | T96: 0 | U96: 0
A97: 45954 | B97: =T97-Q97 -> 0 | C97: 202 | D97: 0 | E97: 0 | F97: 282 | G97: 0 | H97: 0.00% | I97: 0 | J97: 0 | K97: 1 | L97: 1 | M97: 0 | N97: 0 | O97: 0 | P97: 0 | Q97: 0 | R97: 0 | S97: =MONTH(A97) -> 10 | T97: 0 | U97: 0
A98: 45955 | B98: =T98-Q98 -> 1229413 | C98: 169 | D98: 1 | E98: 1 | F98: 254 | G98: 1 | H98: 0.59% | I98: 1229413 | J98: 7274.63 | K98: 3 | L98: 3 | M98: 1 | N98: 1 | O98: 1229413 | P98: 1 | Q98: 0 | R98: 0 | S98: =MONTH(A98) -> 10 | T98: 1229413 | U98: 1
A99: 45956 | B99: =T99-Q99 -> 0 | C99: 180 | D99: 0 | E99: 0 | F99: 262 | G99: 0 | H99: 0.00% | I99: 0 | J99: 0 | K99: 4 | L99: 4 | M99: 0 | N99: 0 | O99: 0 | P99: 0 | Q99: 0 | R99: 0 | S99: =MONTH(A99) -> 10 | T99: 0 | U99: 0
A100: 45957 | B100: =T100-Q100 -> 0 | C100: 205 | D100: 0 | E100: 0 | F100: 270 | G100: 0 | H100: 0.00% | I100: 0 | J100: 0 | K100: 0 | L100: 0 | M100: 1 | N100: 1 | O100: 0 | P100: 0 | Q100: 0 | R100: 0 | S100: =MONTH(A100) -> 10 | T100: 0 | U100: 0
A101: 45958 | B101: =T101-Q101 -> 0 | C101: 38 | D101: 0 | E101: 0 | F101: 47 | G101: 0 | H101: 0.00% | I101: 0 | J101: 0 | K101: 0 | L101: 0 | M101: 0 | N101: 0 | O101: 0 | P101: 0 | Q101: 0 | R101: 0 | S101: =MONTH(A101) -> 10 | T101: 0 | U101: 0
A102: 45959 | B102: =T102-Q102 -> -1229413 | C102: 4 | D102: 0 | E102: 0 | F102: 7 | G102: 0 | H102: 0.00% | I102: 0 | J102: 0 | K102: 0 | L102: 0 | M102: 0 | N102: 0 | O102: 0 | P102: 0 | Q102: 1229413 | R102: 0 | S102: =MONTH(A102) -> 10 | T102: 0 | U102: 0
A103: 45960 | B103: =T103-Q103 -> 0 | S103: =MONTH(A103) -> 10
A104: 45961 | B104: =T104-Q104 -> 0 | S104: =MONTH(A104) -> 10
A105: 45962 | B105: 0 | C105: 6 | D105: 0 | E105: 0 | F105: 6 | G105: 0 | H105: 0 | I105: - | J105: 0 | K105: 0 | L105: 0 | M105: - | N105: - | O105: - | P105: - | Q105: 0 | R105: 0 | S105: =MONTH(A105) -> 11
A106: 45963 | B106: 0 | C106: 5 | D106: 0 | E106: 0 | F106: 9 | G106: 0 | H106: 0 | I106: - | J106: 0 | K106: 0 | L106: 0 | M106: - | N106: - | O106: - | P106: - | Q106: 0 | R106: 0 | S106: =MONTH(A106) -> 11
A107: 45964 | B107: 0 | C107: 6 | D107: 0 | E107: 0 | F107: 13 | G107: 0 | H107: 0 | I107: - | J107: 0 | K107: 1 | L107: 2 | M107: - | N107: - | O107: - | P107: - | Q107: 0 | R107: 0 | S107: =MONTH(A107) -> 11
A108: 45965 | B108: 0 | C108: 5 | D108: 0 | E108: 0 | F108: 8 | G108: 0 | H108: 0 | I108: - | J108: 0 | K108: 1 | L108: 1 | M108: - | N108: - | O108: - | P108: - | Q108: 0 | R108: 0 | S108: =MONTH(A108) -> 11
A109: 45966 | B109: 0 | C109: 4 | D109: 0 | E109: 0 | F109: 4 | G109: 0 | H109: 0 | I109: - | J109: 0 | K109: 0 | L109: 0 | M109: - | N109: - | O109: - | P109: - | Q109: 0 | R109: 0 | S109: =MONTH(A109) -> 11
...

Sheet ADS LAZADA
B1: =SUM(B3:B44) -> 7391198.3 | I1: =SUM(I3:I44) -> 5986256
A2: Ngày | B2: Chi Phí | D2: Impressions | E2: Số Lượng Khách Hàng Đã Hiển Thị | F2: Lượt xem | G2: Khách Truy Cập | H2: Tự Nhiên | I2: Doanh Thu | J2: ROAS | K2: THÁNG | N2: Campaign Id | O2: Campaign Name | P2: Date | Q2: Impressions | R2: Clicks | S2: Spend | T2: Add to Cart | U2: Add to Cart Value | V2: Purchase | W2: Purchase Value | X2: ROI | Y2: CTR | Z2: CPM | AA2: Purchase Rate | AB2: A2C Rate
A3: 45938 | B3: 0 | D3: 0 | E3: 0 | F3: 0 | G3: 0 | H3: 0 | I3: 0 | J3: 0.00 | K3: =MONTH(A3) -> 10
A4: 45939 | B4: 0 | D4: 0 | E4: 0 | F4: 0 | G4: 0 | H4: 0 | I4: 0 | J4: 0.00 | K4: =MONTH(A4) -> 10
A5: 45940 | B5: 0 | D5: 0 | E5: 0 | F5: 0 | G5: 0 | H5: 0 | I5: 0 | J5: 0.00 | K5: =MONTH(A5) -> 10
A6: 45941 | B6: 6868.24 | D6: 470 | E6: 304 | F6: 8 | G6: 7 | H6: 1 | I6: 180200 | J6: 26.24 | K6: =MONTH(A6) -> 10 | L6: 6868.24
A7: 45942 | B7: 339763.32 | D7: 3801 | E7: 2147 | F7: 70 | G7: 52 | H7: 1 | I7: 470032 | J7: 1.38 | K7: =MONTH(A7) -> 10 | L7: 339763.32
A8: 45943 | B8: 114671.91 | D8: 2304 | E8: 1463 | F8: 59 | G8: 48 | H8: 0 | I8: 0 | J8: 0.00 | K8: =MONTH(A8) -> 10 | L8: 114671.91
A9: 45944 | B9: 208188.95 | D9: 6046 | E9: 3210 | F9: 194 | G9: 133 | H9: 0 | I9: 0 | J9: 0.00 | K9: =MONTH(A9) -> 10 | L9: 208188.95
A10: 45945 | B10: 281821.54 | D10: 4691 | E10: 2499 | F10: 127 | G10: 89 | H10: 0 | I10: 0 | J10: 0.00 | K10: =MONTH(A10) -> 10 | L10: 281821.54
A11: 45946 | B11: 257490.17 | D11: 3031 | E11: 1765 | F11: 83 | G11: 51 | H11: 0 | I11: 0 | J11: 0.00 | K11: =MONTH(A11) -> 10 | L11: 257490.17
A12: 45947 | B12: 0 | D12: 7 | E12: 7 | F12: 0 | G12: 0 | H12: 0 | I12: 0 | J12: 0.00 | K12: =MONTH(A12) -> 10 | L12: 0.00
A13: 45948 | B13: 4565.93 | D13: 612 | E13: 390 | F13: 24 | G13: 22 | H13: 0 | I13: 0 | J13: 0.00 | K13: =MONTH(A13) -> 10 | L13: 4565.93
A14: 45949 | B14: 109078.78 | D14: 3550 | E14: 2044 | F14: 205 | G14: 125 | H14: 2 | I14: 741150 | J14: 6.79 | K14: =MONTH(A14) -> 10 | L14: 109078.78
A15: 45950 | B15: 141281.25 | D15: 5405 | E15: 2864 | F15: 364 | G15: 242 | H15: 1 | I15: 660600 | J15: 4.68 | K15: =MONTH(A15) -> 10 | L15: 141281.25
A16: 45951 | B16: 148196.67 | D16: 4070 | E16: 2290 | F16: 144 | G16: 93 | H16: 0 | I16: 0 | J16: 0.00 | K16: =MONTH(A16) -> 10 | L16: 148196.67
A17: 45952 | B17: 191894.79 | D17: 3274 | E17: 1826 | F17: 153 | G17: 84 | H17: 2 | I17: 1218750 | J17: 6.35 | K17: =MONTH(A17) -> 10 | L17: 191894.79
A18: 45953 | B18: 232469.87 | D18: 6382 | E18: 3219 | F18: 247 | G18: 188 | H18: 0 | I18: 0 | J18: 0.00 | K18: =MONTH(A18) -> 10 | L18: 232469.87
A19: 45954 | B19: =L19+S19 -> 280466.25 | D19: 5455 | E19: 3077 | F19: 208 | G19: 163 | H19: 0 | I19: 0 | J19: 0.00 | K19: =MONTH(A19) -> 10 | L19: 223846.25 | N19: 120234779399680123 | O19: NEW ARRIVAL 10.2025 | P19: 45954 | Q19: 3313 | R19: 19 | S19: 56620 | T19: 0 | U19: 0 | V19: 0 | W19: 0 | X19: 0.00 | Y19: 0.57% | Z19: 17090 | AA19: 0 | AB19: 0
A20: 45955 | B20: =L20+S20 -> 485511.26 | D20: 3910 | E20: 2467 | F20: 188 | G20: 153 | H20: 0 | I20: 0 | J20: 0.00 | K20: =MONTH(A20) -> 10 | L20: 361758.26 | N20: 120234779399680123 | O20: NEW ARRIVAL 10.2025 | P20: 45955 | Q20: 7766 | R20: 45 | S20: 123753 | T20: 0 | U20: 0 | V20: 0 | W20: 0 | X20: 0.00 | Y20: 0.58% | Z20: 15935 | AA20: 0 | AB20: 0
A21: 45956 | B21: =L21+S21 -> 342496.39 | D21: 4414 | E21: 2472 | F21: 246 | G21: 164 | H21: 0 | I21: 0 | J21: 0.00 | K21: =MONTH(A21) -> 10 | L21: 223101.39 | N21: 120234779399680123 | O21: NEW ARRIVAL 10.2025 | P21: 45956 | Q21: 5067 | R21: 40 | S21: 119395 | T21: 0 | U21: 0 | V21: 0 | W21: 0 | X21: 0.00 | Y21: 0.79% | Z21: 23563 | AA21: 0 | AB21: 0
A22: 45957 | B22: =L22+S22 -> 317099.84 | D22: 7101 | E22: 3803 | F22: 260 | G22: 199 | H22: 0 | I22: 0.00 | J22: 0.00 | K22: =MONTH(A22) -> 10 | L22: 317099.84 | N22: 120234779399680123 | O22: NEW ARRIVAL 10.2025 | P22: 45957 | Q22: 0 | R22: 0 | S22: 0 | T22: 0 | U22: 0 | V22: 0 | W22: 0 | X22: 0.00 | Y22: N/A | Z22: N/A | AA22: N/A | AB22: N/A
A23: 45958 | B23: =L23+S23 -> 41693.12 | D23: 915 | E23: 492 | F23: 39 | G23: 34 | H23: 0 | I23: 0.00 | J23: 0.00 | K23: =MONTH(A23) -> 10 | L23: 41693.12
A24: 45959 | B24: =L24+S24 -> 0 | D24: 6 | E24: 6 | F24: 0 | G24: 0 | H24: 0 | I24: 0.00 | J24: 0.00 | K24: =MONTH(A24) -> 10
A25: 45960 | B25: =L25+S25 -> 0 | D25: 4 | E25: 4 | F25: 0 | G25: 0 | H25: 0 | I25: 0.00 | J25: 0.00 | K25: =MONTH(A25) -> 10
A26: 45961 | B26: =L26+S26 -> 0
B29: =SUM(B31:B62) -> 1943820 | I29: =SUM(I31:I62) -> 1357762
A30: Ngày | B30: Chi Phí | C30: Chi Phí | D30: Impressions | E30: Số Lượng Khách Hàng Đã Hiển Thị | F30: Lượt xem | G30: Khách Truy Cập | H30: Tự Nhiên | I30: Doanh Thu | J30: ROAS | K30: THÁNG | N30: Chi Phí | O30: Số lượt hiển thị | P30: Lượt Click | Q30: Tỷ lệ click (CTR) | R30: Số Sản Phẩm Bán Được | S30: Số Sản Phẩm Đã Bán Trực Tiếp | T30: Doanh Thu | U30: Direct Revenue
A31: 45983 | B31: 262857 | C31: 0 | D31: 0 | E31: 0 | F31: N/A | G31: 0 | H31: 0 | I31: 0 | J31: 0 | K31: =MONTH(A31) -> 11 | N31: 0 | O31: 1 | P31: 0 | Q31: 0.00% | R31: 0 | S31: 0 | T31: 0.00 | U31: 0.00
A32: 45982 | B32: 152732 | C32: 0 | D32: 0 | E32: 0 | F32: N/A | G32: 0 | H32: 0 | I32: 0 | J32: 0 | K32: =MONTH(A32) -> 11 | N32: 0 | O32: 2 | P32: 0 | Q32: 0.00% | R32: 0 | S32: 0 | T32: 0.00 | U32: 0.00
A33: 45981 | B33: 239690 | C33: 0 | D33: 0 | E33: 0 | F33: N/A | G33: 0 | H33: 0 | I33: 0 | J33: 0 | K33: =MONTH(A33) -> 11 | N33: 0 | O33: 1 | P33: 0 | Q33: 0.00% | R33: 0 | S33: 0 | T33: 0.00 | U33: 0.00
A34: 45980 | B34: 281572 | C34: 0 | D34: 0 | E34: 0 | F34: N/A | G34: 0 | H34: 0 | I34: 0 | J34: 0 | K34: =MONTH(A34) -> 11 | N34: 0 | O34: 1 | P34: 0 | Q34: 0.00% | R34: 0 | S34: 0 | T34: 0.00 | U34: 0.00
A35: 45979 | B35: 52403 | C35: 0 | D35: 0 | E35: 0 | F35: N/A | G35: 0 | H35: 0 | I35: 0 | J35: 0 | K35: =MONTH(A35) -> 11 | N35: 0 | O35: 0 | P35: 0 | Q35: N/A | R35: 0 | S35: 0 | T35: 0.00 | U35: 0.00
A36: 45975 | B36: 412928 | C36: 0 | D36: 0 | E36: 0 | F36: N/A | G36: 0 | H36: 0 | I36: 0 | J36: 0 | K36: =MONTH(A36) -> 11 | N36: 0 | O36: 1 | P36: 0 | Q36: 0.00% | R36: 0 | S36: 0 | T36: 0.00 | U36: 0.00
A37: 45974 | B37: 46148 | C37: 28645.85 | D37: 244 | E37: 35 | F37: 0.1434 | G37: 0 | H37: 0 | I37: 0 | J37: 0 | K37: =MONTH(A37) -> 11 | N37: 15865.76 | O37: 576 | P37: 23 | Q37: 3.99% | R37: 0 | S37: 0 | T37: 0.00 | U37: 0.00
A38: 45973 | B38: 51443 | C38: 101747.89 | D38: 1304 | E38: 17 | F38: 0.013 | G38: 1 | H38: 1 | I38: 430815 | J38: 430815 | K38: =MONTH(A38) -> 11 | N38: 204450.51 | O38: 3186 | P38: 386 | Q38: 12.12% | R38: 0 | S38: 0 | T38: 0.00 | U38: 0.00
A39: 45971 | B39: 142925 | C39: 130143.6 | D39: 1930 | E39: 24 | F39: 0.0124 | G39: 0 | H39: 0 | I39: 0 | J39: 0 | K39: =MONTH(A39) -> 11
A40: 45971 | B40: 130143 | C40: 0 | D40: 4 | E40: 0 | F40: 0 | G40: 0 | H40: 0 | I40: 0 | J40: 0 | K40: =MONTH(A40) -> 11
A41: 45970 | B41: 5619 | C41: 51443.15 | D41: 280 | E41: 26 | F41: 0.0929 | G41: 1 | H41: 1 | I41: 479832 | J41: 479832 | K41: =MONTH(A41) -> 11
A42: 45970 | B42: 120850 | C42: 46148.34 | D42: 353 | E42: 21 | F42: 0.0595 | G42: 0 | H42: 0 | I42: 0 | J42: 0 | K42: =MONTH(A42) -> 11
A43: 45969 | B43: 28645 | C43: 412928.55 | D43: 4311 | E43: 133 | F43: 0.0309 | G43: 1 | H43: 1 | I43: 447115 | J43: 447115 | K43: =MONTH(A43) -> 11
A44: 45969 | B44: 15865 | C44: 0 | D44: 1 | E44: 0 | F44: 0 | G44: 0 | H44: 0 | I44: 0 | J44: 0 | K44: =MONTH(A44) -> 11
A45: 45992 | B45: 0.00 | C45: 0.00 | I45: 0.00 | J45: 0.00 | K45: =MONTH(A45) -> 12 | N45: 0.00 | O45: 0
A46: 45993 | B46: 0.00 | C46: 0.00 | I46: 0.00 | J46: 0.00 | K46: =MONTH(A46) -> 12 | N46: 0.00 | O46: 0
A47: 45994 | B47: 0.00 | C47: 0.00 | I47: 0.00 | J47: 0.00 | K47: =MONTH(A47) -> 12 | N47: 0.00 | O47: 2
A48: 45995 | B48: 0.00 | C48: 0.00 | I48: 0.00 | J48: 0.00 | K48: =MONTH(A48) -> 12 | N48: 0.00 | O48: 1
A49: 45996 | B49: 0.00 | C49: 0.00 | I49: 0.00 | J49: 0.00 | K49: =MONTH(A49) -> 12 | N49: 0.00 | O49: 1
A50: 45997 | B50: 0.00 | C50: 0.00 | I50: 0.00 | J50: 0.00 | K50: =MONTH(A50) -> 12 | N50: 0.00 | O50: 1
A51: 45998 | B51: 0.00 | C51: 0.00 | I51: 0.00 | J51: 0.00 | K51: =MONTH(A51) -> 12 | N51: 0.00 | O51: 0
