Workbook

Sheet Action Plan
F2: MARKETING MONTHLY SALES REVENUE | L2: Person in charge
B4: Start Date | D4: Due Date | F4: Person Responsible | L4: Quantity | M4: =SUM(M6:M14) -> 20 | N4: =SUM(N6:N14) -> 8 | O4: =N4/M4 -> 0.4 | P4: Ratio
B5: 45748 | C5: 25 | D5: 45777 | L5: Position | M5: Estimated | N5: Actual | O5: Remaining | P5: Person #1 | Q5: Person #2 | R5: Person #3 | S5: Person #4
C6: =NETWORKDAYS.INTL(B5,D5,11) -> 26 | L6: Senior Manager | M6: 1 | N6: 1 | O6: =N6-M6 -> 0 | P6: 1
F7: Sales Revenue (VND) | L7: Junior Executive | M7: 0 | N7: 0 | O7: =N7-M7 -> 0
F8: 500000000 | L8: Digital Marketer | M8: 1 | N8: 1 | O8: =N8-M8 -> 0 | P8: 1
L9: E-Com Operations | M9: 1 | N9: 1 | O9: =N9-M9 -> 0 | P9: 1
F10: Expense Budget (VND) | L10: Media Editor | M10: 1 | N10: 0 | O10: =N10-M10 -> -1
D11: 0.4 | F11: =$D$11*F8 -> 200000000 | L11: Graphic Designer | M11: 1 | N11: 1 | O11: =N11-M11 -> 0 | P11: 1
L12: Fresher AI Officer | M12: 1 | N12: 0 | O12: =N12-M12 -> -1
L13: Sale | M13: 4 | N13: 4 | O13: =N13-M13 -> 0 | P13: 0.35 | Q13: 0.3 | R13: 0.25 | S13: 0.2
A14: I | B14: Expense Budget | L14: Trainee | M14: 10 | N14: 0 | O14: =N14-M14 -> -10
B15: Direct Marketing Platform | C15: Ratio | D15: Expense Budget
B16: TOTAL | C16: =SUM(C17:C24) -> 0.85 | D16: =SUM(D17:D24) -> 170000000
B17: FACEBOOK | C17: 0.05 | D17: =$F$11*C17 -> 10000000
B18: LANDING PAGE | C18: 0.3 | D18: =$F$11*C18 -> 60000000
B19: WEBSITE | C19: 0.05 | D19: =$F$11*C19 -> 10000000
B20: TIKTOK SHOP | C20: 0.1 | D20: =$F$11*C20 -> 20000000
B21: SHOPEE | C21: 0.05 | D21: =$F$11*C21 -> 10000000
B22: ZALO | C22: 0.2 | D22: =$F$11*C22 -> 40000000
B23: BOOKING | C23: 0.05 | D23: =$F$11*C23 -> 10000000
B24: BRANDING | C24: 0.05 | D24: =$F$11*C24 -> 10000000
A26: II | B26: Sales Revenue | E26: DIGITAL | H26: SALE
A27: 45293 | B27: Direct Marketing Platform | C27: Ratio | D27: Sales Revenue | E27: Key Platform | F27: New Customers Data Lead | G27: Actual Customers Data | H27: Key Platform | I27: Sales Estimated | J27: Daily Sales Actual | K27: Estimated Conversiton Rate
B28: TOTAL | C28: =SUM(C29:C34) -> 1 | D28: =SUM(D29:D34) -> 500000000 | E28: =COUNTIF(E29:E34,"TRUE") -> 6 | F28: =SUM(F29:F34) -> 1680 | G28: =SUM(G29:G34) -> 67.2 | H28: =COUNTIF(H29:H34,"TRUE") -> 6 | I28: =SUM(I29:I34) -> 500000000 | J28: =SUM(J29:J34) -> 20000000 | K28: =SUM(K29:K34)/6 -> 0.45833333
B29: FACEBOOK | C29: 0.1 | D29: =$F$8*$C29 -> 50000000 | E29: TRUE | F29: =ROUNDUP((I29/$C$37)/K29,0) -> 313 | G29: =F29/$C$5 -> 12.52 | H29: TRUE | I29: =$F$8*$C29 -> 50000000 | J29: =I29/$C$5 -> 2000000 | K29: 0.2
B30: LANDING PAGE | C30: 0.5 | D30: =$F$8*$C30 -> 250000000 | E30: TRUE | F30: =ROUNDUP((I30/$C$37)/K30,0) -> 348 | G30: =F30/$C$5 -> 13.92 | H30: TRUE | I30: =$F$8*$C30 -> 250000000 | J30: =I30/$C$5 -> 10000000 | K30: 0.9
B31: WEBSITE | C31: 0.1 | D31: =$F$8*$C31 -> 50000000 | E31: TRUE | F31: =ROUNDUP((I31/$C$37)/K31,0) -> 125 | G31: =F31/$C$5 -> 5 | H31: TRUE | I31: =$F$8*$C31 -> 50000000 | J31: =I31/$C$5 -> 2000000 | K31: 0.5
B32: TIKTOK SHOP | C32: 0.1 | D32: =$F$8*$C32 -> 50000000 | E32: TRUE | F32: =ROUNDUP((I32/$C$37)/K32,0) -> 90 | G32: =F32/$C$5 -> 3.6 | H32: TRUE | I32: =$F$8*$C32 -> 50000000 | J32: =I32/$C$5 -> 2000000 | K32: 0.7
B33: SHOPEE | C33: 0.1 | D33: =$F$8*$C33 -> 50000000 | E33: TRUE | F33: =ROUNDUP((I33/$C$37)/K33,0) -> 179 | G33: =F33/$C$5 -> 7.16 | H33: TRUE | I33: =$F$8*$C33 -> 50000000 | J33: =I33/$C$5 -> 2000000 | K33: 0.35
B34: ZALO | C34: 0.1 | D34: =$F$8*$C34 -> 50000000 | E34: TRUE | F34: =ROUNDUP((I34/$C$37)/K34,0) -> 625 | G34: =F34/$C$5 -> 25 | H34: TRUE | I34: =$F$8*$C34 -> 50000000 | J34: =I34/$C$5 -> 2000000 | K34: 0.1
H35: Existing Customers | I35: =J35*$C$5 -> 624.60962 | J35: =(((I34/$C$37)/$C$5)/K34) -> 24.984385 | K35: =J35*K34 -> 2.4984385
C36: ARPU
C37: =$E$39 -> 800500 | D37: đ/ Order/ Customer | E37: PRODUCT | H37: BUNDLE COMBO
A38: 45324 | B38: Products | C38: Ratio | D38: Sales Revenue | E38: Retail Price | F38: Sales Volume | G38: Daily Unit Sales | H38: Combo Price | I38: Sales Volume | J38: Daily Unit Sales | K38: Daily Sales Estimated
B39: TOTAL | C39: =SUM(C40:C47) -> 1 | D39: =SUM(D40:D47) -> 500000000 | E39: =(SUM(E40:E47))/8 -> 800500 | F39: =SUM(F40:F47) -> 571 | G39: =SUM(G40:G47) -> 26 | I39: =SUM(I40:I47) -> 505 | J39: =SUM(J40:J47) -> 23 | K39: =SUM(K40:K47) -> 20000000
B40: BONE & JOINT HEALTH | C40: 0.35 | D40: =$I$28*$C40 -> 175000000 | E40: 945000 | F40: =ROUNDUP(D40/E40,0) -> 186 | G40: =ROUNDUP(F40/$C$5,0) -> 8 | H40: 1000000 | I40: =ROUNDUP(D40/H40,0) -> 175 | J40: =ROUNDUP(I40/$C$5,0) -> 7 | K40: =D40/$C$5 -> 7000000
B41: LIVER, DIGESTION, ALLERGIES | C41: 0.3 | D41: =$I$28*$C41 -> 150000000 | E41: 1260000 | F41: =ROUNDUP(D41/E41,0) -> 120 | G41: =ROUNDUP(F41/$C$5,0) -> 5 | H41: 990000 | I41: =ROUNDUP(D41/H41,0) -> 152 | J41: =ROUNDUP(I41/$C$5,0) -> 7 | K41: =D41/$C$5 -> 6000000
B42: BRAIN & EYE HEALTH | C42: 0.1 | D42: =$I$28*$C42 -> 50000000 | E42: 586000 | F42: =ROUNDUP(D42/E42,0) -> 86 | G42: =ROUNDUP(F42/$C$5,0) -> 4 | H42: 1000000 | I42: =ROUNDUP(D42/H42,0) -> 50 | J42: =ROUNDUP(I42/$C$5,0) -> 2 | K42: =D42/$C$5 -> 2000000
B43: CARDIOVASCULAR HEALTH | C43: 0.08 | D43: =$I$28*$C43 -> 40000000 | E43: 630000 | F43: =ROUNDUP(D43/E43,0) -> 64 | G43: =ROUNDUP(F43/$C$5,0) -> 3 | H43: 990000 | I43: =ROUNDUP(D43/H43,0) -> 41 | J43: =ROUNDUP(I43/$C$5,0) -> 2 | K43: =D43/$C$5 -> 1600000
B44: SKIN, HAIR, AND WEIGHT MANAGEMENT | C44: 0.08 | D44: =$I$28*$C44 -> 40000000 | E44: 856000 | F44: =ROUNDUP(D44/E44,0) -> 47 | G44: =ROUNDUP(F44/$C$5,0) -> 2 | H44: 1000000 | I44: =ROUNDUP(D44/H44,0) -> 40 | J44: =ROUNDUP(I44/$C$5,0) -> 2 | K44: =D44/$C$5 -> 1600000
B45: HORMONAL HEALTH | C45: 0.03 | D45: =$I$28*$C45 -> 15000000 | E45: 529000 | F45: =IF(ROUNDUP(D45/E45,0)<>0,ROUNDUP(D45/E45,0),0) -> 29 | G45: =ROUNDUP(F45/$C$5,0) -> 2 | H45: 990000 | I45: =ROUNDUP(D45/H45,0) -> 16 | J45: =ROUNDUP(I45/$C$5,0) -> 1 | K45: =D45/$C$5 -> 600000
B46: IMMUNE SUPPORT | C46: 0.03 | D46: =$I$28*$C46 -> 15000000 | E46: 850000 | F46: =ROUNDUP(D46/E46,0) -> 18 | G46: =ROUNDUP(F46/$C$5,0) -> 1 | H46: 1000000 | I46: =ROUNDUP(D46/H46,0) -> 15 | J46: =ROUNDUP(I46/$C$5,0) -> 1 | K46: =D46/$C$5 -> 600000
B47: MATERNITY & CHILDREN’S HEALTH | C47: 0.03 | D47: =$I$28*$C47 -> 15000000 | E47: 748000 | F47: =IF(ROUNDUP(D47/E47,0)<>0,ROUNDUP(D47/E47,0),0) -> 21 | G47: =ROUNDUP(F47/$C$5,0) -> 1 | H47: 990000 | I47: =ROUNDUP(D47/H47,0) -> 16 | J47: =ROUNDUP(I47/$C$5,0) -> 1 | K47: =D47/$C$5 -> 600000
A49: III | B49: 3P Compensation
A50: P1 | B50: 0.6 | C50: P1: Postion | D50: Actual | E50: <50% | F50: 50 - 70% | G50: >= 80% | H50: >= 90% | I50: 1
A51: P2 | B51: 0.2 | C51: P2: Person | D51: % P2+P3 | E51: 0.05 | F51: 0.05 | G51: 0.05 | H51: 0.05 | I51: 0.05
A52: P3 | B52: 0.2 | C52: P3: Performance
C53: Team | G53: Person #1 | K53: Person #2
C54: In charge | D54: Ratio | E54: KPIs | F54: Metric | G54: In charge | H54: Ratio/ Team | I54: KPIs | J54: Metric | K54: In charge | L54: Ratio/ Team | M54: KPIs | N54: Metric
B55: TOTAL | C55: Digital Team | D55: =D54 -> Ratio | E55: =E54 -> KPIs | G55: Digital Marketer | H55: =H54 -> Ratio/ Team | I55: =I54 -> KPIs | K55: E-Com Operation | L55: =L54 -> Ratio/ Team | M55: =M54 -> KPIs
B56: Digital Marketer | C56: P2 | D56: =$B$51 -> 0.2 | E56: =D$57*SUM(D$58:D$63)+D$64*SUM(D$65:D$70) -> 0.96785714 | G56: P2 | H56: =$B$51 -> 0.2 | I56: =AVERAGE(H57,H64) -> 0.51190476 | K56: P2 | L56: =$B$51 -> 0.2 | M56: =AVERAGE(L57,L64) -> 0.45595238
C57: DATA | D57: 0.5 | E57: =$F$28 -> 1680 | F57: DATA | G57: DATA | H57: =SUM($H$58:$H$63) -> 0.5952381 | I57: =SUM($I$58:$I$63) -> 1000 | J57: DATA | K57: DATA | L57: =SUM($L$58:$L$63) -> 0.34047619 | M57: =SUM($M$58:$M$63) -> 572 | N57: DATA
C58: FACEBOOK | D58: =E58/$E$57 -> 0.18630952 | E58: =$F$29 -> 313 | G58: FACEBOOK | H58: =I58/$E$57 -> 0.23809524 | I58: 400 | K58: FACEBOOK | L58: =M58/$E$57 -> -0.051785714 | M58: =E58-I58 -> -87
C59: LANDING PAGE | D59: =E59/$E$57 -> 0.20714286 | E59: =$F$30 -> 348 | G59: LANDING PAGE | H59: =I59/$E$57 -> 0.17857143 | I59: 300 | K59: LANDING PAGE | L59: =M59/$E$57 -> 0.028571429 | M59: =E59-I59 -> 48
C60: WEBSITE | D60: =E60/$E$57 -> 0.074404762 | E60: =$F$31 -> 125 | G60: WEBSITE | H60: =I60/$E$57 -> 0.05952381 | I60: 100 | K60: WEBSITE | L60: =M60/$E$57 -> 0.014880952 | M60: =E60-I60 -> 25
C61: TIKTOKSHOP | D61: =E61/$E$57 -> 0.18630952 | E61: =$F$29 -> 313 | G61: TIKTOKSHOP | H61: =I61/$E$57 -> 0.029761905 | I61: 50 | K61: TIKTOKSHOP | L61: =M61/$E$57 -> 0.15654762 | M61: =E61-I61 -> 263
C62: SHOPPEE | D62: =E62/$E$57 -> 0.20714286 | E62: =$F$30 -> 348 | G62: SHOPPEE | H62: =I62/$E$57 -> 0.029761905 | I62: 50 | K62: SHOPPEE | L62: =M62/$E$57 -> 0.17738095 | M62: =E62-I62 -> 298
C63: ZALO | D63: =E63/$E$57 -> 0.074404762 | E63: =$F$31 -> 125 | G63: ZALO | H63: =I63/$E$57 -> 0.05952381 | I63: 100 | K63: ZALO | L63: =M63/$E$57 -> 0.014880952 | M63: =E63-I63 -> 25
C64: ADS | D64: 0.5 | E64: =SUM($E$65:$E$70) -> 70 | F64: CAMPAIGN | G64: ADS | H64: =SUM($H$65:$H$70) -> 0.42857143 | I64: =SUM($I$65:$I$70) -> 30 | J64: CAMPAIGN | K64: ADS | L64: =SUM($L$65:$L$70) -> 0.57142857 | M64: =SUM($M$65:$M$70) -> 40 | N64: CAMPAIGN
C65: FACEBOOK | D65: =E65/E$64 -> 0.14285714 | E65: 10 | G65: FACEBOOK | H65: =I65/E$64 -> 0.14285714 | I65: 10 | K65: FACEBOOK | L65: =M65/E$64 -> 0 | M65: =E65-I65 -> 0
C66: LANDING PAGE | D66: =E66/E$64 -> 0.14285714 | E66: 10 | G66: LANDING PAGE | H66: =I66/E$64 -> 0.14285714 | I66: 10 | K66: LANDING PAGE | L66: =M66/E$64 -> 0 | M66: =E66-I66 -> 0
C67: WEBSITE | D67: =E67/E$64 -> 0.071428571 | E67: 5 | G67: WEBSITE | H67: =I67/E$64 -> 0.071428571 | I67: 5 | K67: WEBSITE | L67: =M67/E$64 -> 0 | M67: =E67-I67 -> 0
C68: TIKTOKSHOP | D68: =E68/E$64 -> 0.28571429 | E68: 20 | G68: TIKTOKSHOP | H68: =I68/E$64 -> 0 | I68: 0 | K68: TIKTOKSHOP | L68: =M68/E$64 -> 0.28571429 | M68: =E68-I68 -> 20
C69: SHOPPEE | D69: =E69/E$64 -> 0.28571429 | E69: 20 | G69: SHOPPEE | H69: =I69/E$64 -> 0 | I69: 0 | K69: SHOPPEE | L69: =M69/E$64 -> 0.28571429 | M69: =E69-I69 -> 20
C70: ZALO | D70: =E70/E$64 -> 0.071428571 | E70: 5 | G70: ZALO | H70: =I70/E$64 -> 0.071428571 | I70: 5 | K70: ZALO | L70: =M70/E$64 -> 0 | M70: =E70-I70 -> 0
C71: P3 | D71: =$B$52 -> 0.2 | E71: =D$72*SUM(D$73:D$78)+D$79*SUM(D$80:D$85)+D$86*SUM(D$87:D$92) -> 1 | G71: P3 | H71: =$B$52 -> 0.2 | I71: =AVERAGE(H72,H79,H86) -> 0.52121212 | K71: P3 | L71: =$B$52 -> 0.2 | M71: =AVERAGE(L72,L79,L86) -> 0.47878788
C72: SALES REVENUE | D72: 0.25 | E72: =SUM($E$73:$E$78) -> 500000000 | F72: VND | G72: SALES REVENUE | H72: =SUM($H$73:$H$78) -> 0.5 | I72: =SUM($I$73:$I$78) -> 250000000 | J72: VND | K72: SALES REVENUE | L72: =SUM($L$73:$L$78) -> 0.5 | M72: =SUM($M$73:$M$78) -> 250000000 | N72: VND
C73: FACEBOOK | D73: =$C29 -> 0.1 | E73: =$D$29 -> 50000000 | G73: FACEBOOK | H73: =(I73/E$72) -> 0.05 | I73: =E73/2 -> 25000000 | K73: FACEBOOK | L73: =M73/E$72 -> 0.05 | M73: =E73-I73 -> 25000000
C74: LANDING PAGE | D74: =$C30 -> 0.5 | E74: =$D$30 -> 250000000 | G74: LANDING PAGE | H74: =I74/E$72 -> 0.25 | I74: =E74/2 -> 125000000 | K74: LANDING PAGE | L74: =M74/E$72 -> 0.25 | M74: =E74-I74 -> 125000000
C75: WEBSITE | D75: =$C31 -> 0.1 | E75: =$D$31 -> 50000000 | G75: WEBSITE | H75: =I75/E$72 -> 0.05 | I75: =E75/2 -> 25000000 | K75: WEBSITE | L75: =M75/E$72 -> 0.05 | M75: =E75-I75 -> 25000000
C76: TIKTOKSHOP | D76: =$C32 -> 0.1 | E76: =$D$32 -> 50000000 | G76: TIKTOKSHOP | H76: =I76/E$72 -> 0.05 | I76: =E76/2 -> 25000000 | K76: TIKTOKSHOP | L76: =M76/E$72 -> 0.05 | M76: =E76-I76 -> 25000000
C77: SHOPPEE | D77: =$C33 -> 0.1 | E77: =$D$33 -> 50000000 | G77: SHOPPEE | H77: =I77/E$72 -> 0.05 | I77: =E77/2 -> 25000000 | K77: SHOPPEE | L77: =M77/E$72 -> 0.05 | M77: =E77-I77 -> 25000000
C78: ZALO | D78: =$C34 -> 0.1 | E78: =$D$34 -> 50000000 | G78: ZALO | H78: =I78/E$72 -> 0.05 | I78: =E78/2 -> 25000000 | K78: ZALO | L78: =M78/E$72 -> 0.05 | M78: =E78-I78 -> 25000000
C79: A/S RATIO | D79: 0.5 | E79: =AVERAGE($E$80:$E$85) -> 0.37333333 | F79: CAMPAIGN | G79: A/S RATIO | H79: =AVERAGE($H$80:$H$85) -> 0.5 | I79: =AVERAGE($I$80:$I$85) -> 0.18666667 | J79: CAMPAIGN | K79: A/S RATIO | L79: =AVERAGE($L$80:$L$85) -> 0.5 | M79: =AVERAGE($M$80:$M$85) -> 0.18666667 | N79: CAMPAIGN
C80: FACEBOOK | D80: 0.2 | E80: =$D$17/$D$29 -> 0.2 | G80: FACEBOOK | H80: =I80/E$79 -> 0.26785714 | I80: =E80/2 -> 0.1 | K80: FACEBOOK | L80: =M80/E$79 -> 0.26785714 | M80: =E80-I80 -> 0.1
C81: LANDING PAGE | D81: 0.4 | E81: =$D$18/$D$30 -> 0.24 | G81: LANDING PAGE | H81: =I81/E$79 -> 0.32142857 | I81: =E81/2 -> 0.12 | K81: LANDING PAGE | L81: =M81/E$79 -> 0.32142857 | M81: =E81-I81 -> 0.12
C82: WEBSITE | D82: 0.1 | E82: =$D$19/$D$31 -> 0.2 | G82: WEBSITE | H82: =I82/E$79 -> 0.26785714 | I82: =E82/2 -> 0.1 | K82: WEBSITE | L82: =M82/E$79 -> 0.26785714 | M82: =E82-I82 -> 0.1
C83: TIKTOKSHOP | D83: 0.1 | E83: =($D$20+$D$23)/$D$32 -> 0.6 | G83: TIKTOKSHOP | H83: =I83/E$79 -> 0.80357143 | I83: =E83/2 -> 0.3 | K83: TIKTOKSHOP | L83: =M83/E$79 -> 0.80357143 | M83: =E83-I83 -> 0.3
C84: SHOPPEE | D84: 0.1 | E84: =$D$21/$D$33 -> 0.2 | G84: SHOPPEE | H84: =I84/E$79 -> 0.26785714 | I84: =E84/2 -> 0.1 | K84: SHOPPEE | L84: =M84/E$79 -> 0.26785714 | M84: =E84-I84 -> 0.1
C85: ZALO | D85: 0.1 | E85: =$D$22/$D$34 -> 0.8 | G85: ZALO | H85: =I85/E$79 -> 1.0714286 | I85: =E85/2 -> 0.4 | K85: ZALO | L85: =M85/E$79 -> 1.0714286 | M85: =E85-I85 -> 0.4
C86: CONVERSION RATE | D86: 0.25 | E86: =AVERAGE($E$87:$E$92) -> 0.45833333 | F86: CAMPAIGN | G86: CONVERSION RATE | H86: =AVERAGE($H$87:$H$92) -> 0.56363636 | I86: =AVERAGE($I$87:$I$92) -> 0.25833333 | J86: CAMPAIGN | K86: CONVERSION RATE | L86: =AVERAGE($L$87:$L$92) -> 0.43636364 | M86: =AVERAGE($M$87:$M$92) -> 0.2 | N86: CAMPAIGN
C87: FACEBOOK | D87: 0.2 | E87: =$K$29 -> 0.2 | G87: FACEBOOK | H87: =I87/E$86 -> 0.32727273 | I87: 0.15 | K87: FACEBOOK | L87: =M87/E$86 -> 0.10909091 | M87: =E87-I87 -> 0.05
C88: LANDING PAGE | D88: 0.4 | E88: =$K$30 -> 0.9 | G88: LANDING PAGE | H88: =I88/E$86 -> 1.7454545 | I88: 0.8 | K88: LANDING PAGE | L88: =M88/E$86 -> 0.21818182 | M88: =E88-I88 -> 0.1
C89: WEBSITE | D89: 0.1 | E89: =$K$31 -> 0.5 | G89: WEBSITE | H89: =I89/E$86 -> 0.98181818 | I89: 0.45 | K89: WEBSITE | L89: =M89/E$86 -> 0.10909091 | M89: =E89-I89 -> 0.05
C90: TIKTOKSHOP | D90: 0.1 | E90: =$K$32 -> 0.7 | G90: TIKTOKSHOP | H90: =I90/E$86 -> 0.10909091 | I90: 0.05 | K90: TIKTOKSHOP | L90: =M90/E$86 -> 1.4181818 | M90: =E90-I90 -> 0.65
C91: SHOPPEE | D91: 0.1 | E91: =$K$33 -> 0.35 | G91: SHOPPEE | H91: =I91/E$86 -> 0.10909091 | I91: 0.05 | K91: SHOPPEE | L91: =M91/E$86 -> 0.65454545 | M91: =E91-I91 -> 0.3
C92: ZALO | D92: 0.1 | E92: =$K$34 -> 0.1 | G92: ZALO | H92: =I92/E$86 -> 0.10909091 | I92: 0.05 | K92: ZALO | L92: =M92/E$86 -> 0.10909091 | M92: =E92-I92 -> 0.05
B93: TOTAL | C93: Sale | D93: =D55 -> Ratio | E93: =E54 -> KPIs | G93: Sale #1 | H93: =H54 -> Ratio/ Team | I93: =I54 -> KPIs | K93: Sale #2 | L93: =H93 -> Ratio/ Team | M93: =I93 -> KPIs | O93: Sale #3 | P93: =L93 -> Ratio/ Team | Q93: =M93 -> KPIs | S93: Sale #4 | T93: =P93 -> Ratio/ Team | U93: =Q93 -> KPIs
B94: Sale | C94: P2 | D94: =$B$51 -> 0.2 | E94: =SUM(D$95:D$97) -> 1 | G94: P2 | H94: =$B$51 -> 0.2 | I94: =AVERAGE(H95,H96,H97) -> 0.35 | K94: P2 | L94: =$B$51 -> 0.2 | M94: =AVERAGE(L95,L96,L97) -> 0.3 | O94: P2 | P94: =$B$51 -> 0.2 | Q94: =AVERAGE(P95,P96,P97) -> 0.25 | S94: P2 | T94: =$B$51 -> 0.2 | U94: =AVERAGE(T95,T96,T97) -> 0.2
C95: CALL | D95: 0.4 | E95: =$E$59+$E$60+$E$63+$I$35 -> 1222.6096 | F95: PHONE | G95: CALL | H95: =I95/$E95 -> 0.35 | I95: =$E$95*$P$13 -> 427.91337 | J95: PHONE | K95: CALL | L95: =M95/$E95 -> 0.3 | M95: =$E$95*$Q$13 -> 366.78289 | N95: PHONE | O95: CALL | P95: =Q95/$E95 -> 0.25 | Q95: =$E$95*$R$13 -> 305.6524 | R95: PHONE | S95: CALL | T95: =U95/$E95 -> 0.2 | U95: =$E$95*$S$13 -> 244.52192 | V95: PHONE
C96: SMS | D96: 0.4 | E96: =$E$58 -> 313 | F96: MESSAGE | G96: SMS | H96: =I96/$E96 -> 0.35 | I96: =$E$96*$P$13 -> 109.55 | J96: MESSAGE | K96: SMS | L96: =M96/$E96 -> 0.3 | M96: =$E$96*$Q$13 -> 93.9 | N96: MESSAGE | O96: SMS | P96: =Q96/$E96 -> 0.25 | Q96: =$E$96*$R$13 -> 78.25 | R96: MESSAGE | S96: SMS | T96: =U96/$E96 -> 0.2 | U96: =$E$96*$S$13 -> 62.6 | V96: MESSAGE
C97: Q&A | D97: 0.2 | E97: =$N$13*$C$6 -> 104 | F97: DIALOGUE | G97: Q&A | H97: =I97/$E97 -> 0.35 | I97: =$E$97*$P$13 -> 36.4 | J97: DIALOGUE | K97: Q&A | L97: =M97/$E97 -> 0.3 | M97: =$E$97*$Q$13 -> 31.2 | N97: DIALOGUE | O97: Q&A | P97: =Q97/$E97 -> 0.25 | Q97: =$E$97*$R$13 -> 26 | R97: DIALOGUE | S97: Q&A | T97: =U97/$E97 -> 0.2 | U97: =$E$97*$S$13 -> 20.8 | V97: DIALOGUE
C98: P3 | D98: =$B$52 -> 0.2 | E98: =D$99*SUM(D$100:D$105)+D$106*SUM(D$107:D$112)+D$113*SUM(D$114:D$119)+D$120*SUM(D$121:D$126)+D$127 -> 1 | G98: P3 | H98: =$B$52 -> 0.2 | I98: =AVERAGE(H99,H106,H113,H120,H127) -> 0.35 | K98: P3 | L98: =$B$52 -> 0.2 | M98: =AVERAGE(L99,L106,L113,L120,L127) -> 0.3 | O98: P3 | P98: =$B$52 -> 0.2 | Q98: =AVERAGE(P99,P106,P113,P120,P127) -> 0.25 | S98: P3 | T98: =$B$52 -> 0.2 | U98: =AVERAGE(T99,T106,T113,T120,T127) -> 0.2
C99: SALES REVENUE | D99: 0.6 | E99: =SUM($E$100:$E$105) -> 500000000 | F99: VND | G99: SALES REVENUE | H99: =SUM($H$100:$H$105) -> 0.35 | I99: =SUM($I$100:$I$105) -> 175000000 | J99: VND | K99: SALES REVENUE | L99: =SUM($L$100:$L$105) -> 0.3 | M99: =SUM($M$100:$M$105) -> 150000000 | N99: VND | O99: SALES REVENUE | P99: =SUM($P$100:$P$105) -> 0.25 | Q99: =SUM($Q$100:$Q$105) -> 125000000 | R99: VND | S99: SALES REVENUE | T99: =SUM($T$100:$T$105) -> 0.2 | U99: =SUM($U$100:$U$105) -> 100000000 | V99: VND
C100: FACEBOOK | D100: =$C29 -> 0.1 | E100: =$D$29 -> 50000000 | G100: FACEBOOK | H100: =I100/E$99 -> 0.035 | I100: =E100*$P$13 -> 17500000 | K100: FACEBOOK | L100: =M100/E$99 -> 0.03 | M100: =E100*$Q$13 -> 15000000 | O100: FACEBOOK | P100: =Q100/E$99 -> 0.025 | Q100: =E100*$R$13 -> 12500000 | S100: FACEBOOK | T100: =U100/E$99 -> 0.02 | U100: =E100*$S$13 -> 10000000
C101: LANDING PAGE | D101: =$C30 -> 0.5 | E101: =$D$30 -> 250000000 | G101: LANDING PAGE | H101: =I101/E$99 -> 0.175 | I101: =E101*$P$13 -> 87500000 | K101: LANDING PAGE | L101: =M101/E$99 -> 0.15 | M101: =E101*$Q$13 -> 75000000 | O101: LANDING PAGE | P101: =Q101/E$99 -> 0.125 | Q101: =E101*$R$13 -> 62500000 | S101: LANDING PAGE | T101: =U101/E$99 -> 0.1 | U101: =E101*$S$13 -> 50000000
C102: WEBSITE | D102: =$C31 -> 0.1 | E102: =$D$31 -> 50000000 | G102: WEBSITE | H102: =I102/E$99 -> 0.035 | I102: =E102*$P$13 -> 17500000 | K102: WEBSITE | L102: =M102/E$99 -> 0.03 | M102: =E102*$Q$13 -> 15000000 | O102: WEBSITE | P102: =Q102/E$99 -> 0.025 | Q102: =E102*$R$13 -> 12500000 | S102: WEBSITE | T102: =U102/E$99 -> 0.02 | U102: =E102*$S$13 -> 10000000
C103: TIKTOKSHOP | D103: =$C32 -> 0.1 | E103: =$D$32 -> 50000000 | G103: TIKTOKSHOP | H103: =I103/E$99 -> 0.035 | I103: =E103*$P$13 -> 17500000 | K103: TIKTOKSHOP | L103: =M103/E$99 -> 0.03 | M103: =E103*$Q$13 -> 15000000 | O103: TIKTOKSHOP | P103: =Q103/E$99 -> 0.025 | Q103: =E103*$R$13 -> 12500000 | S103: TIKTOKSHOP | T103: =U103/E$99 -> 0.02 | U103: =E103*$S$13 -> 10000000
C104: SHOPPEE | D104: =$C33 -> 0.1 | E104: =$D$33 -> 50000000 | G104: SHOPPEE | H104: =I104/E$99 -> 0.035 | I104: =E104*$P$13 -> 17500000 | K104: SHOPPEE | L104: =M104/E$99 -> 0.03 | M104: =E104*$Q$13 -> 15000000 | O104: SHOPPEE | P104: =Q104/E$99 -> 0.025 | Q104: =E104*$R$13 -> 12500000 | S104: SHOPPEE | T104: =U104/E$99 -> 0.02 | U104: =E104*$S$13 -> 10000000
...

Sheet Dashboard
B2: MARKETING MONTHLY SALES REVENUE DASHBOARD | L2: ='Action Plan'!L2 -> Person in charge
B4: Start Date | D4: Due Date | F4: Person Responsible | L4: ='Action Plan'!L4 -> Quantity | M4: ='Action Plan'!M4 -> 20 | N4: ='Action Plan'!N4 -> 8 | O4: ='Action Plan'!O4 -> 0.4 | P4: ='Action Plan'!P4 -> Ratio
B5: 45748 | C5: ='Action Plan'!C5 -> 25 | D5: 45777 | F5: Mr/Ms: | L5: Position | M5: Estimated | N5: Actual | O5: Remaining | P5: ='Action Plan'!P5 -> Person #1 | Q5: ='Action Plan'!Q5 -> Person #2 | R5: ='Action Plan'!R5 -> Person #3 | S5: ='Action Plan'!S5 -> Person #4
C6: ='Action Plan'!C6 -> 26 | L6: ='Action Plan'!L6 -> Senior Manager | M6: ='Action Plan'!M6 -> 1 | N6: ='Action Plan'!N6 -> 1 | O6: ='Action Plan'!O6 -> 0 | P6: ='Action Plan'!P6 -> 1 | Q6: ='Action Plan'!Q6 -> 0 | R6: ='Action Plan'!R6 -> 0 | S6: ='Action Plan'!S6 -> 0
B7: Sales Revenue (VND) | F7: Actual Sales | J7: Remaining | K7: Ratio | L7: ='Action Plan'!L7 -> Junior Executive | M7: ='Action Plan'!M7 -> 0 | N7: ='Action Plan'!N7 -> 0 | O7: ='Action Plan'!O7 -> 0 | P7: ='Action Plan'!P7 -> 0 | Q7: ='Action Plan'!Q7 -> 0 | R7: ='Action Plan'!R7 -> 0 | S7: ='Action Plan'!S7 -> 0
B8: ='Action Plan'!F8 -> 500000000 | F8: 400000000 | J8: =F8-B8 -> -100000000 | K8: =F8/B8 -> 0.8 | L8: ='Action Plan'!L8 -> Digital Marketer | M8: 1 | N8: ='Action Plan'!N8 -> 1 | O8: ='Action Plan'!O8 -> 0 | P8: ='Action Plan'!P8 -> 1 | Q8: ='Action Plan'!Q8 -> 0 | R8: ='Action Plan'!R8 -> 0 | S8: ='Action Plan'!S8 -> 0
B9: ='Action Plan'!D11 -> 0.4 | F9: =F11/F8 -> 0.11425 | L9: ='Action Plan'!L9 -> E-Com Operations | M9: ='Action Plan'!M9 -> 1 | N9: ='Action Plan'!N9 -> 1 | O9: ='Action Plan'!O9 -> 0 | P9: ='Action Plan'!P9 -> 1 | Q9: ='Action Plan'!Q9 -> 0 | R9: ='Action Plan'!R9 -> 0 | S9: ='Action Plan'!S9 -> 0
B10: Expense Budget (VND) | F10: Actual Budget | J10: Remaining | K10: Ratio | L10: ='Action Plan'!L10 -> Media Editor | M10: ='Action Plan'!M10 -> 1 | N10: ='Action Plan'!N10 -> 0 | O10: ='Action Plan'!O10 -> -1 | P10: ='Action Plan'!P10 -> 0 | Q10: ='Action Plan'!Q10 -> 0 | R10: ='Action Plan'!R10 -> 0 | S10: ='Action Plan'!S10 -> 0
B11: ='Action Plan'!F11 -> 200000000 | F11: =F15 -> 45700000 | J11: =B11-F11 -> 154300000 | K11: =F11/B11 -> 0.2285 | L11: ='Action Plan'!L11 -> Graphic Designer | M11: ='Action Plan'!M11 -> 1 | N11: ='Action Plan'!N11 -> 1 | O11: ='Action Plan'!O11 -> 0 | P11: ='Action Plan'!P11 -> 1 | Q11: ='Action Plan'!Q11 -> 0 | R11: ='Action Plan'!R11 -> 0 | S11: ='Action Plan'!S11 -> 0
L12: ='Action Plan'!L12 -> Fresher AI Officer | M12: ='Action Plan'!M12 -> 1 | N12: ='Action Plan'!N12 -> 0 | O12: ='Action Plan'!O12 -> -1 | P12: ='Action Plan'!P12 -> 0 | Q12: ='Action Plan'!Q12 -> 0 | R12: ='Action Plan'!R12 -> 0 | S12: ='Action Plan'!S12 -> 0
A13: I | B13: Expense Budget | L13: ='Action Plan'!L13 -> Sale | M13: ='Action Plan'!M13 -> 4 | N13: ='Action Plan'!N13 -> 4 | O13: ='Action Plan'!O13 -> 0 | P13: ='Action Plan'!P13 -> 0.35 | Q13: ='Action Plan'!Q13 -> 0.3 | R13: ='Action Plan'!R13 -> 0.25 | S13: ='Action Plan'!S13 -> 0.2
B14: Direct Marketing Platform | C14: Expense Ratio | D14: Actual Ratio | E14: Expense Budget | F14: Actual Budget | G14: Remaining | H14: Remaining Ratio | L14: ='Action Plan'!L14 -> Trainee | M14: ='Action Plan'!M14 -> 10 | N14: ='Action Plan'!N14 -> 0 | O14: ='Action Plan'!O14 -> -10 | P14: ='Action Plan'!P14 -> 0 | Q14: ='Action Plan'!Q14 -> 0 | R14: ='Action Plan'!R14 -> 0 | S14: ='Action Plan'!S14 -> 0
B15: TOTAL | C15: =SUM(C16:C23) -> 0.85 | D15: =SUM(D16:D23) -> 1 | E15: =SUM(E16:E23) -> 170000000 | F15: =SUM(F16:F23) -> 45700000 | G15: =SUM(G16:G23) -> 124300000 | H15: =SUM(H16:H23) -> 0.15
B16: ='Action Plan'!B17 -> FACEBOOK | C16: ='Action Plan'!C17 -> 0.05 | D16: =F16/$F$15 -> 0.0065645514 | E16: =$B$11*C16 -> 10000000 | F16: ='Digital Marketer #1'!E9+'E-Com Operations'!E9 -> 300000 | G16: =E16-F16 -> 9700000 | H16: =D16-C16 -> -0.043435449
B17: ='Action Plan'!B18 -> LANDING PAGE | C17: ='Action Plan'!C18 -> 0.3 | D17: =F17/$F$15 -> 0.32822757 | E17: =$B$11*C17 -> 60000000 | F17: ='Digital Marketer #1'!E15+'E-Com Operations'!E15 -> 15000000 | G17: =E17-F17 -> 45000000 | H17: =D17-C17 -> 0.028227571
B18: ='Action Plan'!B19 -> WEBSITE | C18: ='Action Plan'!C19 -> 0.05 | D18: =F18/$F$15 -> 0.078774617 | E18: =$B$11*C18 -> 10000000 | F18: ='Digital Marketer #1'!E21+'E-Com Operations'!E21 -> 3600000 | G18: =E18-F18 -> 6400000 | H18: =D18-C18 -> 0.028774617
B19: ='Action Plan'!B20 -> TIKTOK SHOP | C19: ='Action Plan'!C20 -> 0.1 | D19: =F19/$F$15 -> 0.15973742 | E19: =$B$11*C19 -> 20000000 | F19: ='Digital Marketer #1'!E24+'E-Com Operations'!E24 -> 7300000 | G19: =E19-F19 -> 12700000 | H19: =D19-C19 -> 0.059737418
B20: ='Action Plan'!B21 -> SHOPEE | C20: ='Action Plan'!C21 -> 0.05 | D20: =F20/$F$15 -> 0.13347921 | E20: =$B$11*C20 -> 10000000 | F20: ='Digital Marketer #1'!E25+'E-Com Operations'!E25 -> 6100000 | G20: =E20-F20 -> 3900000 | H20: =D20-C20 -> 0.083479212
B21: ='Action Plan'!B22 -> ZALO | C21: ='Action Plan'!C22 -> 0.2 | D21: =F21/$F$15 -> 0.060175055 | E21: =$B$11*C21 -> 40000000 | F21: ='Digital Marketer #1'!E26+'E-Com Operations'!E26 -> 2750000 | G21: =E21-F21 -> 37250000 | H21: =D21-C21 -> -0.13982495
B22: ='Action Plan'!B23 -> BOOKING | C22: ='Action Plan'!C23 -> 0.05 | D22: =F22/$F$15 -> 0.1345733 | E22: =$B$11*C22 -> 10000000 | F22: ='Digital Marketer #1'!E27+'E-Com Operations'!E27 -> 6150000 | G22: =E22-F22 -> 3850000 | H22: =D22-C22 -> 0.084573304
B23: ='Action Plan'!B24 -> BRANDING | C23: ='Action Plan'!C24 -> 0.05 | D23: =F23/$F$15 -> 0.098468271 | E23: =$B$11*C23 -> 10000000 | F23: ='Digital Marketer #1'!E28+'E-Com Operations'!E28 -> 4500000 | G23: =E23-F23 -> 5500000 | H23: =D23-C23 -> 0.048468271
A24: II | B24: Sales Revenue | J24: SALE | O24: SALE + DIGITAL | S24: DIGITAL
A25: 2.1 | B25: Direct Marketing Platform | C25: Expense Ratio | D25: Actual Ratio | E25: Sales Revenue | F25: Actual Sales | G25: Remaining | H25: Remaining Ratio | I25: Expense Sales | J25: Key Platform | K25: Sales Estimated | L25: Actual Sales | M25: Remaining | N25: Ratio | O25: Estimated Conversiton Rate | P25: Daily Conversiton Rate | Q25: Remaining | R25: Ratio | S25: Key Platform | T25: Data Lead | U25: Daily Data | V25: Remaining | W25: Ratio
B26: TOTAL | C26: =SUM(C27:C32) -> 1 | D26: =SUM(D27:D32) -> 1 | E26: =SUM(E27:E32) -> 500000000 | F26: =SUM(F27:F32) -> 373050000 | G26: =SUM(G27:G32) -> -126950000 | H26: =SUM(H27:H32) -> 1 | I26: =SUM(I27:I32) -> -3077662500 | J26: =COUNTIF(J27:J32,"TRUE") -> 6 | K26: =SUM(K27:K32) -> 500000000 | L26: =SUM(L27:L32) -> 373050000 | M26: =SUM(M27:M32) -> -126950000 | N26: =SUM(N27:N32) -> 1 | O26: =SUM(O27:O32) -> 2.75 | P26: =SUM(P27:P32) -> 9.690121 | Q26: =SUM(Q27:Q32) -> 6.940121 | R26: =SUM(R27:R32) -> 1 | S26: =COUNTIF(S27:S32,"TRUE") -> 6 | T26: =SUM(T27:T32) -> 1680 | U26: =SUM(U27:U32) -> 1335 | V26: =SUM(V27:V32) -> -345 | W26: =SUM(W27:W32) -> 1
B27: ='Action Plan'!B29 -> FACEBOOK | C27: ='Action Plan'!C29 -> 0.1 | D27: =F27/$F$26 -> 0.13697896 | E27: =$B$8*$C27 -> 50000000 | F27: ='Digital Marketer #1'!E49+'E-Com Operations'!E49 -> 51100000 | G27: =F27-E27 -> 1100000 | H27: =G27/$G$26 -> -0.0086648287 | I27: =F27/(TODAY()-$B$5)*($D$5-TODAY()) -> -421575000 | J27: TRUE | K27: =$B$8*$C27 -> 50000000 | L27: =F27 -> 51100000 | M27: =L27-K27 -> 1100000 | N27: =M27/$M$26 -> -0.0086648287 | O27: ='Action Plan'!K29 -> 0.2 | P27: =AVERAGE(F83,F117) -> 2.1876478 | Q27: =P27-O27 -> 1.9876478 | R27: =Q27/$Q$26 -> 0.2863996 | S27: TRUE | T27: =ROUNDUP((K27/$C$34)/O27,0) -> 313 | U27: =F54 -> 372 | V27: =U27-T27 -> 59 | W27: =V27/$V$26 -> -0.17101449
B28: ='Action Plan'!B30 -> LANDING PAGE | C28: ='Action Plan'!C30 -> 0.5 | D28: =F28/$F$26 -> 0.13697896 | E28: =$B$8*$C28 -> 250000000 | F28: ='Digital Marketer #1'!E50+'E-Com Operations'!E50 -> 51100000 | G28: =F28-E28 -> -198900000 | H28: =G28/$G$26 -> 1.5667586 | I28: =F28/(TODAY()-$B$5)*($D$5-TODAY()) -> -421575000 | J28: TRUE | K28: =$B$8*$C28 -> 250000000 | L28: =F28 -> 51100000 | M28: =L28-K28 -> -198900000 | N28: =M28/$M$26 -> 1.5667586 | O28: ='Action Plan'!K30 -> 0.9 | P28: =AVERAGE(F84,F118) -> 1.7017204 | Q28: =P28-O28 -> 0.80172043 | R28: =Q28/$Q$26 -> 0.11551966 | S28: TRUE | T28: =ROUNDUP((K28/$C$34)/O28,0) -> 348 | U28: =F55 -> 341 | V28: =U28-T28 -> -7 | W28: =V28/$V$26 -> 0.020289855
B29: ='Action Plan'!B31 -> WEBSITE | C29: ='Action Plan'!C31 -> 0.1 | D29: =F29/$F$26 -> 0.12893714 | E29: =$B$8*$C29 -> 50000000 | F29: ='Digital Marketer #1'!E51+'E-Com Operations'!E51 -> 48100000 | G29: =F29-E29 -> -1900000 | H29: =G29/$G$26 -> 0.014966522 | I29: =F29/(TODAY()-$B$5)*($D$5-TODAY()) -> -396825000 | J29: TRUE | K29: =$B$8*$C29 -> 50000000 | L29: =F29 -> 48100000 | M29: =L29-K29 -> -1900000 | N29: =M29/$M$26 -> 0.014966522 | O29: ='Action Plan'!K31 -> 0.5 | P29: =AVERAGE(F85,F119) -> 1.0083333 | Q29: =P29-O29 -> 0.50833333 | R29: =Q29/$Q$26 -> 0.073245601 | S29: TRUE | T29: =ROUNDUP((K29/$C$34)/O29,0) -> 125 | U29: =F59 -> 310 | V29: =U29-T29 -> 185 | W29: =V29/$V$26 -> -0.53623188
B30: ='Action Plan'!B32 -> TIKTOK SHOP | C30: ='Action Plan'!C32 -> 0.1 | D30: =F30/$F$26 -> 0.2482241 | E30: =$B$8*$C30 -> 50000000 | F30: ='Digital Marketer #1'!E52+'E-Com Operations'!E52 -> 92600000 | G30: =F30-E30 -> 42600000 | H30: =G30/$G$26 -> -0.33556518 | I30: =F30/(TODAY()-$B$5)*($D$5-TODAY()) -> -763950000 | J30: TRUE | K30: =$B$8*$C30 -> 50000000 | L30: =F30 -> 92600000 | M30: =L30-K30 -> 42600000 | N30: =M30/$M$26 -> -0.33556518 | O30: ='Action Plan'!K32 -> 0.7 | P30: =AVERAGE(F86,F120) -> 1.4866129 | Q30: =P30-O30 -> 0.7866129 | R30: =Q30/$Q$26 -> 0.11334282 | S30: TRUE | T30: =ROUNDUP((K30/$C$34)/O30,0) -> 90 | U30: =F60 -> 188 | V30: =U30-T30 -> 98 | W30: =V30/$V$26 -> -0.28405797
B31: ='Action Plan'!B33 -> SHOPEE | C31: ='Action Plan'!C33 -> 0.1 | D31: =F31/$F$26 -> 0.25224501 | E31: =$B$8*$C31 -> 50000000 | F31: ='Digital Marketer #1'!E53+'E-Com Operations'!E53 -> 94100000 | G31: =F31-E31 -> 44100000 | H31: =G31/$G$26 -> -0.34738086 | I31: =F31/(TODAY()-$B$5)*($D$5-TODAY()) -> -776325000 | J31: TRUE | K31: =$B$8*$C31 -> 50000000 | L31: =F31 -> 94100000 | M31: =L31-K31 -> 44100000 | N31: =M31/$M$26 -> -0.34738086 | O31: ='Action Plan'!K33 -> 0.35 | P31: =AVERAGE(F87,F121) -> 1.165 | Q31: =P31-O31 -> 0.815 | R31: =Q31/$Q$26 -> 0.11743311 | S31: TRUE | T31: =ROUNDUP((K31/$C$34)/O31,0) -> 179 | U31: =F61 -> 62 | V31: =U31-T31 -> -117 | W31: =V31/$V$26 -> 0.33913043
B32: ='Action Plan'!B34 -> ZALO | C32: ='Action Plan'!C34 -> 0.1 | D32: =F32/$F$26 -> 0.09663584 | E32: =$B$8*$C32 -> 50000000 | F32: ='Digital Marketer #1'!E54+'E-Com Operations'!E54 -> 36050000 | G32: =F32-E32 -> -13950000 | H32: =G32/$G$26 -> 0.10988578 | I32: =F32/(TODAY()-$B$5)*($D$5-TODAY()) -> -297412500 | J32: TRUE | K32: =$B$8*$C32 -> 50000000 | L32: =F32 -> 36050000 | M32: =L32-K32 -> -13950000 | N32: =M32/$M$26 -> 0.10988578 | O32: ='Action Plan'!K34 -> 0.1 | P32: =AVERAGE(F88,F122) -> 2.1408065 | Q32: =P32-O32 -> 2.0408065 | R32: =Q32/$Q$26 -> 0.2940592 | S32: TRUE | T32: =ROUNDUP((K32/$C$34)/O32,0) -> 625 | U32: =F62 -> 62 | V32: =U32-T32 -> -563 | W32: =V32/$V$26 -> 1.6318841
C33: Expense | D33: Actual
B34: ARPU | C34: ='Action Plan'!C37 -> 800500 | D34: =F26/(W26*P26) -> 38497971 | I34: PRODUCT | S34: BUNDLE COMBO
A35: 45324 | B35: Products | C35: Expense Ratio | D35: Actual Ratio | E35: Total Sales | F35: Total Actual Sales | G35: Remaining | H35: Remaining Ratio | I35: Retail Price | J35: Push Sale | K35: Quantity | L35: Actual Quantity | M35: Remaining | N35: Ratio | O35: Daily Quantity | P35: Actual Daily Quantity | Q35: Remaining | R35: Ratio | S35: Combo Price | T35: Push Sale | U35: Quantity | V35: Actual Quantity | W35: Remaining | X35: Ratio | Y35: Daily Quantity | Z35: Actual Daily Quantity | AA35: Remaining | AB35: Ratio | AC35: Sales KPI | AD35: Actual Sales | AE35: Remaining | AF35: Ratio
B36: TOTAL | C36: =SUM(C37:C44) -> 1 | D36: =SUM(D37:D44) -> 2.2 | E36: =SUM(E37:E44) -> 500000000 | F36: ='Sale #1'!F50+'Sale #2'!F50+'Sale #3'!F50+'Sale #4'!F50 -> 331700000 | G36: =SUM(G37:G44) -> -168300000 | H36: =SUM(H37:H44) -> 1 | J36: =COUNTIF(J37:J44,"TRUE") -> 8 | K36: =SUM(K37:K44) -> 571 | L36: =SUM(L37:L44) -> 1705 | M36: =SUM(M37:M44) -> 1134 | N36: =SUM(N37:N44) -> 1 | O36: =SUM(O37:O44) -> 26 | P36: =SUM(P37:P44) -> 0 | Q36: =SUM(Q37:Q44) -> -26 | R36: =SUM(R37:R44) -> 1 | T36: =COUNTIF(T37:T42,"TRUE") -> 6 | U36: =SUM(U37:U44) -> 505 | V36: =SUM(V37:V44) -> 2015 | W36: =SUM(W37:W44) -> 1510 | X36: =SUM(X37:X44) -> 1 | Y36: =SUM(Y37:Y44) -> 23 | Z36: =SUM(Z37:Z44) -> 0 | AA36: =SUM(AA37:AA44) -> -23 | AB36: =SUM(AB37:AB44) -> 1 | ... AF36: =SUM(AF37:AF44) -> 0.15754234
B37: ='Action Plan'!B40 -> BONE & JOINT HEALTH | C37: ='Action Plan'!C40 -> 0.35 | D37: 0.6 | E37: =$B$8*$C37 -> 175000000 | F37: ='Sale #1'!F51+'Sale #2'!F51+'Sale #3'!F51+'Sale #4'!F51 -> 40300000 | G37: =F37-E37 -> -134700000 | H37: =G37/$G$36 -> 0.80035651 | I37: ='Action Plan'!E40 -> 945000 | J37: TRUE | K37: =IF(ROUNDUP(E37/I37,0)<>0,ROUNDUP(E37/I37,0),0) -> 186 | L37: ='Sale #1'!D51+'Sale #2'!D51+'Sale #3'!D51+'Sale #4'!D51 -> 93 | M37: =L37-K37 -> -93 | N37: =M37/$M$36 -> -0.082010582 | O37: =ROUNDUP(K37/$C$5,0) -> 8 | P37: ='Sale #1'!J51+'Sale #2'!J51+'Sale #3'!J51+'Sale #4'!J51 -> 0 | Q37: =P37-O37 -> -8 | R37: =Q37/$Q$36 -> 0.30769231 | S37: ='Action Plan'!H40 -> 1000000 | T37: TRUE | U37: =ROUNDUP(E37/S37,0) -> 175 | V37: ='Sale #1'!E51+'Sale #2'!E51+'Sale #3'!E51+'Sale #4'!E51 -> 155 | W37: =V37-U37 -> -20 | X37: =W37/$W$36 -> -0.013245033 | Y37: =ROUNDUP(U37/$C$5,0) -> 7 | Z37: ='Sale #1'!K51+'Sale #2'!K51+'Sale #3'!K51+'Sale #4'!K51 -> 0 | AA37: =Z37-Y37 -> -7 | AB37: =AA37/$AA$36 -> 0.30434783 | AC37: =E37/$C$5 -> 7000000 | AD37: ='Sale #1'!L51+'Sale #2'!L51+'Sale #3'!L51+'Sale #4'!L51 -> 0 | AE37: =AD37-AC37 -> -7000000 | AF37: =AE37/$G$26 -> 0.055139819
B38: ='Action Plan'!B41 -> LIVER, DIGESTION, ALLERGIES | C38: ='Action Plan'!C41 -> 0.3 | D38: 0.2 | E38: =$B$8*$C38 -> 150000000 | F38: ='Sale #1'!F52+'Sale #2'!F52+'Sale #3'!F52+'Sale #4'!F52 -> 40300000 | G38: =F38-E38 -> -109700000 | H38: =G38/$G$36 -> 0.65181224 | I38: ='Action Plan'!E41 -> 1260000 | J38: TRUE | K38: =IF(ROUNDUP(E38/I38,0)<>0,ROUNDUP(E38/I38,0),0) -> 120 | L38: ='Sale #1'!D52+'Sale #2'!D52+'Sale #3'!D52+'Sale #4'!D52 -> 217 | M38: =L38-K38 -> 97 | N38: =M38/$M$36 -> 0.085537919 | O38: =ROUNDUP(K38/$C$5,0) -> 5 | P38: ='Sale #1'!J52+'Sale #2'!J52+'Sale #3'!J52+'Sale #4'!J52 -> 0 | Q38: =P38-O38 -> -5 | R38: =Q38/$Q$36 -> 0.19230769 | S38: ='Action Plan'!H41 -> 990000 | T38: TRUE | U38: =ROUNDUP(E38/S38,0) -> 152 | V38: ='Sale #1'!E52+'Sale #2'!E52+'Sale #3'!E52+'Sale #4'!E52 -> 217 | W38: =V38-U38 -> 65 | X38: =W38/$W$36 -> 0.043046358 | Y38: =ROUNDUP(U38/$C$5,0) -> 7 | Z38: ='Sale #1'!K52+'Sale #2'!K52+'Sale #3'!K52+'Sale #4'!K52 -> 0 | AA38: =Z38-Y38 -> -7 | AB38: =AA38/$AA$36 -> 0.30434783 | AC38: =E38/$C$5 -> 6000000 | AD38: ='Sale #1'!L52+'Sale #2'!L52+'Sale #3'!L52+'Sale #4'!L52 -> 0 | AE38: =AD38-AC38 -> -6000000 | AF38: =AE38/$G$26 -> 0.047262702
B39: ='Action Plan'!B42 -> BRAIN & EYE HEALTH | C39: ='Action Plan'!C42 -> 0.1 | D39: 0.5 | E39: =$B$8*$C39 -> 50000000 | F39: ='Sale #1'!F53+'Sale #2'!F53+'Sale #3'!F53+'Sale #4'!F53 -> 40300000 | G39: =F39-E39 -> -9700000 | H39: =G39/$G$36 -> 0.057635175 | I39: ='Action Plan'!E42 -> 586000 | J39: TRUE | K39: =IF(ROUNDUP(E39/I39,0)<>0,ROUNDUP(E39/I39,0),0) -> 86 | L39: ='Sale #1'!D53+'Sale #2'!D53+'Sale #3'!D53+'Sale #4'!D53 -> 155 | M39: =L39-K39 -> 69 | N39: =M39/$M$36 -> 0.060846561 | O39: =ROUNDUP(K39/$C$5,0) -> 4 | P39: ='Sale #1'!J53+'Sale #2'!J53+'Sale #3'!J53+'Sale #4'!J53 -> 0 | Q39: =P39-O39 -> -4 | R39: =Q39/$Q$36 -> 0.15384615 | S39: ='Action Plan'!H42 -> 1000000 | T39: TRUE | U39: =ROUNDUP(E39/S39,0) -> 50 | V39: ='Sale #1'!E53+'Sale #2'!E53+'Sale #3'!E53+'Sale #4'!E53 -> 217 | W39: =V39-U39 -> 167 | X39: =W39/$W$36 -> 0.11059603 | Y39: =ROUNDUP(U39/$C$5,0) -> 2 | Z39: ='Sale #1'!K53+'Sale #2'!K53+'Sale #3'!K53+'Sale #4'!K53 -> 0 | AA39: =Z39-Y39 -> -2 | AB39: =AA39/$AA$36 -> 0.086956522 | AC39: =E39/$C$5 -> 2000000 | AD39: ='Sale #1'!L53+'Sale #2'!L53+'Sale #3'!L53+'Sale #4'!L53 -> 0 | AE39: =AD39-AC39 -> -2000000 | AF39: =AE39/$G$26 -> 0.015754234
B40: ='Action Plan'!B43 -> CARDIOVASCULAR HEALTH | C40: ='Action Plan'!C43 -> 0.08 | D40: 0.2 | E40: =$B$8*$C40 -> 40000000 | F40: ='Sale #1'!F54+'Sale #2'!F54+'Sale #3'!F54+'Sale #4'!F54 -> 40300000 | G40: =F40-E40 -> 300000 | H40: =G40/$G$36 -> -0.0017825312 | I40: ='Action Plan'!E43 -> 630000 | J40: TRUE | K40: =IF(ROUNDUP(E40/I40,0)<>0,ROUNDUP(E40/I40,0),0) -> 64 | L40: ='Sale #1'!D54+'Sale #2'!D54+'Sale #3'!D54+'Sale #4'!D54 -> 217 | M40: =L40-K40 -> 153 | N40: =M40/$M$36 -> 0.13492063 | O40: =ROUNDUP(K40/$C$5,0) -> 3 | P40: ='Sale #1'!J54+'Sale #2'!J54+'Sale #3'!J54+'Sale #4'!J54 -> 0 | Q40: =P40-O40 -> -3 | R40: =Q40/$Q$36 -> 0.11538462 | S40: ='Action Plan'!H43 -> 990000 | T40: TRUE | U40: =ROUNDUP(E40/S40,0) -> 41 | V40: ='Sale #1'!E54+'Sale #2'!E54+'Sale #3'!E54+'Sale #4'!E54 -> 341 | W40: =V40-U40 -> 300 | X40: =W40/$W$36 -> 0.1986755 | Y40: =ROUNDUP(U40/$C$5,0) -> 2 | Z40: ='Sale #1'!K54+'Sale #2'!K54+'Sale #3'!K54+'Sale #4'!K54 -> 0 | AA40: =Z40-Y40 -> -2 | AB40: =AA40/$AA$36 -> 0.086956522 | AC40: =E40/$C$5 -> 1600000 | AD40: ='Sale #1'!L54+'Sale #2'!L54+'Sale #3'!L54+'Sale #4'!L54 -> 0 | AE40: =AD40-AC40 -> -1600000 | AF40: =AE40/$G$26 -> 0.012603387
B41: ='Action Plan'!B44 -> SKIN, HAIR, AND WEIGHT MANAGEMENT | C41: ='Action Plan'!C44 -> 0.08 | D41: 0.1 | E41: =$B$8*$C41 -> 40000000 | F41: ='Sale #1'!F55+'Sale #2'!F55+'Sale #3'!F55+'Sale #4'!F55 -> 40300000 | G41: =F41-E41 -> 300000 | H41: =G41/$G$36 -> -0.0017825312 | I41: ='Action Plan'!E44 -> 856000 | J41: TRUE | K41: =IF(ROUNDUP(E41/I41,0)<>0,ROUNDUP(E41/I41,0),0) -> 47 | L41: ='Sale #1'!D55+'Sale #2'!D55+'Sale #3'!D55+'Sale #4'!D55 -> 155 | M41: =L41-K41 -> 108 | N41: =M41/$M$36 -> 0.095238095 | O41: =ROUNDUP(K41/$C$5,0) -> 2 | P41: ='Sale #1'!J55+'Sale #2'!J55+'Sale #3'!J55+'Sale #4'!J55 -> 0 | Q41: =P41-O41 -> -2 | R41: =Q41/$Q$36 -> 0.076923077 | S41: ='Action Plan'!H44 -> 1000000 | T41: TRUE | U41: =ROUNDUP(E41/S41,0) -> 40 | V41: ='Sale #1'!E55+'Sale #2'!E55+'Sale #3'!E55+'Sale #4'!E55 -> 279 | W41: =V41-U41 -> 239 | X41: =W41/$W$36 -> 0.15827815 | Y41: =ROUNDUP(U41/$C$5,0) -> 2 | Z41: ='Sale #1'!K55+'Sale #2'!K55+'Sale #3'!K55+'Sale #4'!K55 -> 0 | AA41: =Z41-Y41 -> -2 | AB41: =AA41/$AA$36 -> 0.086956522 | AC41: =E41/$C$5 -> 1600000 | AD41: ='Sale #1'!L55+'Sale #2'!L55+'Sale #3'!L55+'Sale #4'!L55 -> 0 | AE41: =AD41-AC41 -> -1600000 | AF41: =AE41/$G$26 -> 0.012603387
B42: ='Action Plan'!B45 -> HORMONAL HEALTH | C42: ='Action Plan'!C45 -> 0.03 | D42: 0.2 | E42: =$B$8*$C42 -> 15000000 | F42: ='Sale #1'!F56+'Sale #2'!F56+'Sale #3'!F56+'Sale #4'!F56 -> 40300000 | G42: =F42-E42 -> 25300000 | H42: =G42/$G$36 -> -0.1503268 | I42: ='Action Plan'!E45 -> 529000 | J42: TRUE | K42: =IF(ROUNDUP(E42/I42,0)<>0,ROUNDUP(E42/I42,0),0) -> 29 | L42: ='Sale #1'!D56+'Sale #2'!D56+'Sale #3'!D56+'Sale #4'!D56 -> 279 | M42: =L42-K42 -> 250 | N42: =M42/$M$36 -> 0.22045855 | O42: =ROUNDUP(K42/$C$5,0) -> 2 | P42: ='Sale #1'!J56+'Sale #2'!J56+'Sale #3'!J56+'Sale #4'!J56 -> 0 | Q42: =P42-O42 -> -2 | R42: =Q42/$Q$36 -> 0.076923077 | S42: ='Action Plan'!H45 -> 990000 | T42: TRUE | U42: =ROUNDUP(E42/S42,0) -> 16 | V42: ='Sale #1'!E56+'Sale #2'!E56+'Sale #3'!E56+'Sale #4'!E56 -> 217 | W42: =V42-U42 -> 201 | X42: =W42/$W$36 -> 0.13311258 | Y42: =ROUNDUP(U42/$C$5,0) -> 1 | Z42: ='Sale #1'!K56+'Sale #2'!K56+'Sale #3'!K56+'Sale #4'!K56 -> 0 | AA42: =Z42-Y42 -> -1 | AB42: =AA42/$AA$36 -> 0.043478261 | AC42: =E42/$C$5 -> 600000 | AD42: ='Sale #1'!L56+'Sale #2'!L56+'Sale #3'!L56+'Sale #4'!L56 -> 0 | AE42: =AD42-AC42 -> -600000 | AF42: =AE42/$G$26 -> 0.0047262702
B43: ='Action Plan'!B46 -> IMMUNE SUPPORT | C43: ='Action Plan'!C46 -> 0.03 | D43: 0.2 | E43: =$B$8*$C43 -> 15000000 | F43: ='Sale #1'!F57+'Sale #2'!F57+'Sale #3'!F57+'Sale #4'!F57 -> 40300000 | G43: =F43-E43 -> 25300000 | H43: =G43/$G$36 -> -0.1503268 | I43: ='Action Plan'!E46 -> 850000 | J43: TRUE | K43: =IF(ROUNDUP(E43/I43,0)<>0,ROUNDUP(E43/I43,0),0) -> 18 | L43: ='Sale #1'!D57+'Sale #2'!D57+'Sale #3'!D57+'Sale #4'!D57 -> 217 | M43: =L43-K43 -> 199 | N43: =M43/$M$36 -> 0.17548501 | O43: =ROUNDUP(K43/$C$5,0) -> 1 | P43: ='Sale #1'!J57+'Sale #2'!J57+'Sale #3'!J57+'Sale #4'!J57 -> 0 | Q43: =P43-O43 -> -1 | R43: =Q43/$Q$36 -> 0.038461538 | S43: ='Action Plan'!H46 -> 1000000 | T43: TRUE | U43: =ROUNDUP(E43/S43,0) -> 15 | V43: ='Sale #1'!E57+'Sale #2'!E57+'Sale #3'!E57+'Sale #4'!E57 -> 341 | W43: =V43-U43 -> 326 | X43: =W43/$W$36 -> 0.21589404 | Y43: =ROUNDUP(U43/$C$5,0) -> 1 | Z43: ='Sale #1'!K57+'Sale #2'!K57+'Sale #3'!K57+'Sale #4'!K57 -> 0 | AA43: =Z43-Y43 -> -1 | AB43: =AA43/$AA$36 -> 0.043478261 | AC43: =E43/$C$5 -> 600000 | AD43: ='Sale #1'!L57+'Sale #2'!L57+'Sale #3'!L57+'Sale #4'!L57 -> 0 | AE43: =AD43-AC43 -> -600000 | AF43: =AE43/$G$26 -> 0.0047262702
B44: ='Action Plan'!B47 -> MATERNITY & CHILDREN’S HEALTH | C44: ='Action Plan'!C47 -> 0.03 | D44: 0.2 | E44: =$B$8*$C44 -> 15000000 | F44: ='Sale #1'!F58+'Sale #2'!F58+'Sale #3'!F58+'Sale #4'!F58 -> 49600000 | G44: =F44-E44 -> 34600000 | H44: =G44/$G$36 -> -0.20558526 | I44: ='Action Plan'!E47 -> 748000 | J44: TRUE | K44: =IF(ROUNDUP(E44/I44,0)<>0,ROUNDUP(E44/I44,0),0) -> 21 | L44: ='Sale #1'!D58+'Sale #2'!D58+'Sale #3'!D58+'Sale #4'!D58 -> 372 | M44: =L44-K44 -> 351 | N44: =M44/$M$36 -> 0.30952381 | O44: =ROUNDUP(K44/$C$5,0) -> 1 | P44: ='Sale #1'!J58+'Sale #2'!J58+'Sale #3'!J58+'Sale #4'!J58 -> 0 | Q44: =P44-O44 -> -1 | R44: =Q44/$Q$36 -> 0.038461538 | S44: ='Action Plan'!H47 -> 990000 | T44: TRUE | U44: =ROUNDUP(E44/S44,0) -> 16 | V44: ='Sale #1'!E58+'Sale #2'!E58+'Sale #3'!E58+'Sale #4'!E58 -> 248 | W44: =V44-U44 -> 232 | X44: =W44/$W$36 -> 0.15364238 | Y44: =ROUNDUP(U44/$C$5,0) -> 1 | Z44: ='Sale #1'!K58+'Sale #2'!K58+'Sale #3'!K58+'Sale #4'!K58 -> 0 | AA44: =Z44-Y44 -> -1 | AB44: =AA44/$AA$36 -> 0.043478261 | AC44: =E44/$C$5 -> 600000 | AD44: ='Sale #1'!L58+'Sale #2'!L58+'Sale #3'!L58+'Sale #4'!L58 -> 0 | AE44: =AD44-AC44 -> -600000 | AF44: =AE44/$G$26 -> 0.0047262702
A45: ='Action Plan'!A49 -> III | B45: ='Action Plan'!B49 -> 3P Compensation
A46: ='Action Plan'!A50 -> P1 | B46: ='Action Plan'!B50 -> 0.6 | C46: ='Action Plan'!C50 -> P1: Postion | D46: ='Action Plan'!D50 -> Actual | E46: ='Action Plan'!E50 -> <50% | F46: ='Action Plan'!F50 -> 50 - 70% | G46: ='Action Plan'!G50 -> >= 80% | H46: ='Action Plan'!H50 -> >= 90% | I46: ='Action Plan'!I50 -> 1
A47: ='Action Plan'!A51 -> P2 | B47: ='Action Plan'!B51 -> 0.2 | C47: ='Action Plan'!C51 -> P2: Person | D47: ='Action Plan'!D51 -> % P2+P3 | E47: ='Action Plan'!E51 -> 0.05 | F47: ='Action Plan'!F51 -> 0.05 | G47: ='Action Plan'!G51 -> 0.05 | H47: ='Action Plan'!H51 -> 0.05 | I47: ='Action Plan'!I51 -> 0.05
A48: ='Action Plan'!A52 -> P3 | B48: ='Action Plan'!B52 -> 0.2 | C48: ='Action Plan'!C52 -> P3: Performance
C49: ='Action Plan'!C53 -> Team | K49: ='Action Plan'!G53 -> Person #1 | S49: ='Action Plan'!K53 -> Person #2
C50: ='Action Plan'!C54 -> In charge | D50: ='Action Plan'!$D54 -> Ratio | E50: ='Action Plan'!$E54 -> KPIs | F50: Actual | G50: Remaining | H50: Ratio | I50: Weight Rate | J50: ='Action Plan'!F54 -> Metric | K50: ='Action Plan'!G54 -> In charge | L50: ='Action Plan'!$H54 -> Ratio/ Team | M50: ='Action Plan'!$I54 -> KPIs | N50: Actual | O50: Remaining | P50: Ratio | Q50: Weight Rate | R50: ='Action Plan'!N54 -> Metric | S50: ='Action Plan'!K54 -> In charge | T50: ='Action Plan'!$L54 -> Ratio/ Team | U50: ='Action Plan'!$M54 -> KPIs | V50: Actual | W50: Remaining | X50: Ratio | Y50: Weight Rate | Z50: ='Action Plan'!N54 -> Metric
B51: ='Action Plan'!B55 -> TOTAL | C51: ='Action Plan'!C55 -> Digital Team | D51: ='Action Plan'!$D54 -> Ratio | E51: ='Action Plan'!$E54 -> KPIs | F51: Actual | G51: Remaining | H51: Ratio | I51: Weight Rate | K51: ='Action Plan'!G55 -> Digital Marketer | L51: ='Action Plan'!$H54 -> Ratio/ Team | M51: ='Action Plan'!$I54 -> KPIs | N51: Actual | O51: Remaining | P51: Ratio | Q51: Weight Rate | S51: ='Action Plan'!K55 -> E-Com Operation | T51: ='Action Plan'!$H54 -> Ratio/ Team | U51: ='Action Plan'!$I54 -> KPIs | V51: Actual | W51: Remaining | X51: Ratio | Y51: Weight Rate
B52: ='Action Plan'!B56 -> Digital Marketer | C52: ='Action Plan'!C56 -> P2 | D52: ='Action Plan'!D56 -> 0.2 | E52: ='Action Plan'!E56 -> 0.96785714 | F52: =I53+I60 -> 0.75790141 | G52: =F52-E52 -> -0.20995574 | H52: =IF(G52>=0,1,F52/E52) -> 0.78307156 | I52: =F52*D52 -> 0.15158028 | K52: ='Action Plan'!K56 -> P2 | L52: ='Action Plan'!H56 -> 0.2 | M52: ='Action Plan'!I56 -> 0.51190476 | N52: =AVERAGE(Q53,Q60) -> 0.44241071 | O52: =N52-M52 -> -0.069494048 | P52: =IF(O52>=0,1,N52/M52) -> 0.86424419 | Q52: =N52*L52 -> 0.088482143 | T52: ='Action Plan'!L56 -> 0.2 | U52: ='Action Plan'!M56 -> 0.45595238 | V52: =AVERAGE(Y53,Y60) -> 0.3557257 | W52: =V52-U52 -> -0.10022668 | X52: =IF(W52>=0,1,V52/U52) -> 0.78018169 | Y52: =V52*T52 -> 0.07114514
C53: DATA | D53: ='Action Plan'!D57 -> 0.5 | E53: ='Action Plan'!E57 -> 1680 | F53: =SUM(F54:F59) -> 1528 | G53: =F53-E53 -> -152 | H53: =AVERAGE(H54:H59) -> 0.80746948 | I53: =H53*D53 -> 0.40373474 | J53: DATA | K53: DATA | L53: ='Action Plan'!H57 -> 0.5952381 | M53: ='Action Plan'!I57 -> 1000 | N53: =SUM(N54:N59) -> 1125 | O53: =N53-M53 -> 125 | P53: =AVERAGE(P54:P59) -> 0.8625 | Q53: =P53*L53 -> 0.51339286 | R53: DATA | S53: DATA | T53: ='Action Plan'!L57 -> 0.34047619 | U53: ='Action Plan'!M57 -> 572 | V53: =SUM(V54:V59) -> 403 | W53: =V53-U53 -> -169 | X53: =AVERAGE(X54:X59) -> 0.67699012 | Y53: =X53*T53 -> 0.23049902 | Z53: DATA
C54: FACEBOOK | D54: ='Action Plan'!D61 -> 0.18630952 | E54: ='Action Plan'!E61 -> 313 | F54: =N54+V54 -> 372 | G54: =F54-E54 -> 59 | H54: =_xlfn.IFS(G54>=0,1,G54<0,F54/E54) -> 1 | I54: =H54*D54 -> 0.18630952 | K54: FACEBOOK | L54: ='Action Plan'!H58 -> 0.23809524 | M54: ='Action Plan'!I58 -> 400 | N54: ='Digital Marketer #1'!E32 -> 310 | O54: =N54-M54 -> -90 | P54: =_xlfn.IFS(O54>=0,1,O54<0,N54/M54) -> 0.775 | Q54: =P54*L54 -> 0.18452381 | S54: FACEBOOK | T54: ='Action Plan'!L58 -> -0.051785714 | U54: ='Action Plan'!M58 -> -87 | V54: ='E-Com Operations'!E32 -> 62 | W54: =V54-U54 -> 149 | X54: =_xlfn.IFS(W54>=0,1,W54<0,V54/U54) -> 1 | Y54: =X54*T54 -> -0.051785714
C55: LANDING PAGE | D55: ='Action Plan'!D62 -> 0.20714286 | E55: ='Action Plan'!E62 -> 348 | F55: =N55+V55 -> 341 | G55: =F55-E55 -> -7 | H55: =_xlfn.IFS(G55>=0,1,G55<0,F55/E55) -> 0.97988506 | I55: =H55*D55 -> 0.20297619 | K55: LANDING PAGE | L55: ='Action Plan'!H59 -> 0.17857143 | M55: ='Action Plan'!I59 -> 300 | N55: ='Digital Marketer #1'!E33 -> 310 | O55: =N55-M55 -> 10 | P55: =_xlfn.IFS(O55>=0,1,O55<0,N55/M55) -> 1 | Q55: =P55*L55 -> 0.17857143 | S55: LANDING PAGE | T55: ='Action Plan'!L59 -> 0.028571429 | U55: ='Action Plan'!M59 -> 48 | V55: ='E-Com Operations'!E33 -> 31 | W55: =V55-U55 -> -17 | X55: =_xlfn.IFS(W55>=0,1,W55<0,V55/U55) -> 0.64583333 | Y55: =X55*T55 -> 0.018452381
C56: WEBSITE | D56: ='Action Plan'!D60 -> 0.074404762 | E56: ='Action Plan'!E60 -> 125 | F56: =N56+V56 -> 71 | G56: =F56-E56 -> -54 | H56: =_xlfn.IFS(G56>=0,1,G56<0,F56/E56) -> 0.568 | I56: =H56*D56 -> 0.042261905 | K56: WEBSITE | L56: ='Action Plan'!H60 -> 0.05952381 | M56: ='Action Plan'!I60 -> 100 | N56: ='Digital Marketer #1'!E34 -> 40 | O56: =N56-M56 -> -60 | P56: =_xlfn.IFS(O56>=0,1,O56<0,N56/M56) -> 0.4 | Q56: =P56*L56 -> 0.023809524 | S56: WEBSITE | T56: ='Action Plan'!L60 -> 0.014880952 | U56: ='Action Plan'!M60 -> 25 | V56: ='E-Com Operations'!E34 -> 31 | W56: =V56-U56 -> 6 | X56: =_xlfn.IFS(W56>=0,1,W56<0,V56/U56) -> 1 | Y56: =X56*T56 -> 0.014880952
C57: TIKTOKSHOP | D57: ='Action Plan'!D61 -> 0.18630952 | E57: ='Action Plan'!E61 -> 313 | F57: =N57+V57 -> 155 | G57: =F57-E57 -> -158 | H57: =_xlfn.IFS(G57>=0,1,G57<0,F57/E57) -> 0.49520767 | I57: =H57*D57 -> 0.092261905 | K57: TIKTOKSHOP | L57: ='Action Plan'!H61 -> 0.029761905 | M57: ='Action Plan'!I61 -> 50 | N57: ='Digital Marketer #1'!E35 -> 155 | O57: =N57-M57 -> 105 | P57: =_xlfn.IFS(O57>=0,1,O57<0,N57/M57) -> 1 | Q57: =P57*L57 -> 0.029761905 | S57: TIKTOKSHOP | T57: ='Action Plan'!L61 -> 0.15654762 | U57: ='Action Plan'!M61 -> 263 | V57: ='E-Com Operations'!E35 -> 0 | W57: =V57-U57 -> -263 | X57: =_xlfn.IFS(W57>=0,1,W57<0,V57/U57) -> 0 | Y57: =X57*T57 -> 0
C58: SHOPPEE | D58: ='Action Plan'!D62 -> 0.20714286 | E58: ='Action Plan'!E62 -> 348 | F58: =N58+V58 -> 279 | G58: =F58-E58 -> -69 | H58: =_xlfn.IFS(G58>=0,1,G58<0,F58/E58) -> 0.80172414 | I58: =H58*D58 -> 0.16607143 | K58: SHOPPEE | L58: ='Action Plan'!H62 -> 0.029761905 | M58: ='Action Plan'!I62 -> 50 | N58: ='Digital Marketer #1'!E36 -> 155 | O58: =N58-M58 -> 105 | P58: =_xlfn.IFS(O58>=0,1,O58<0,N58/M58) -> 1 | Q58: =P58*L58 -> 0.029761905 | S58: SHOPPEE | T58: ='Action Plan'!L62 -> 0.17738095 | U58: ='Action Plan'!M62 -> 298 | V58: ='E-Com Operations'!E36 -> 124 | W58: =V58-U58 -> -174 | X58: =_xlfn.IFS(W58>=0,1,W58<0,V58/U58) -> 0.41610738 | Y58: =X58*T58 -> 0.073809524
C59: ZALO | D59: ='Action Plan'!D63 -> 0.074404762 | E59: ='Action Plan'!E63 -> 125 | F59: =N59+V59 -> 310 | G59: =F59-E59 -> 185 | H59: =_xlfn.IFS(G59>=0,1,G59<0,F59/E59) -> 1 | I59: =H59*D59 -> 0.074404762 | K59: ZALO | L59: ='Action Plan'!H63 -> 0.05952381 | M59: ='Action Plan'!I63 -> 100 | N59: ='Digital Marketer #1'!E37 -> 155 | O59: =N59-M59 -> 55 | P59: =_xlfn.IFS(O59>=0,1,O59<0,N59/M59) -> 1 | Q59: =P59*L59 -> 0.05952381 | S59: ZALO | T59: ='Action Plan'!L63 -> 0.014880952 | U59: ='Action Plan'!M63 -> 25 | V59: ='E-Com Operations'!E37 -> 155 | W59: =V59-U59 -> 130 | X59: =_xlfn.IFS(W59>=0,1,W59<0,V59/U59) -> 1 | Y59: =X59*T59 -> 0.014880952
C60: ADS | D60: ='Action Plan'!D64 -> 0.5 | E60: ='Action Plan'!E64 -> 70 | F60: =SUM(F61:F66) -> 188 | G60: =F60-E60 -> 118 | H60: =AVERAGE(H61:H66) -> 0.70833333 | I60: =H60*D60 -> 0.35416667 | J60: CAMPAIGN | K60: ADS | L60: ='Action Plan'!H64 -> 0.42857143 | M60: ='Action Plan'!I64 -> 30 | N60: =SUM(N61:N66) -> 156 | O60: =N60-M60 -> 126 | P60: =AVERAGE(P61:P66) -> 0.86666667 | Q60: =P60*L60 -> 0.37142857 | R60: CAMPAIGN | S60: ADS | T60: ='Action Plan'!L64 -> 0.57142857 | U60: ='Action Plan'!M64 -> 40 | V60: =SUM(V61:V66) -> 32 | W60: =V60-U60 -> -8 | X60: =AVERAGE(X61:X66) -> 0.84166667 | Y60: =X60*T60 -> 0.48095238 | Z60: CAMPAIGN
C61: FACEBOOK | D61: ='Action Plan'!D65 -> 0.14285714 | E61: ='Action Plan'!E65 -> 10 | F61: =N61+V61 -> 62 | G61: =F61-E61 -> 52 | H61: =_xlfn.IFS(G61>=0,1,G61<0,F61/E61) -> 1 | I61: =H61*D61 -> 0.14285714 | K61: FACEBOOK | L61: ='Action Plan'!H65 -> 0.14285714 | M61: ='Action Plan'!I65 -> 10 | N61: ='Digital Marketer #1'!E40 -> 62 | O61: =N61-M61 -> 52 | P61: =_xlfn.IFS(O61>=0,1,O61<0,N61/M61) -> 1 | Q61: =P61*L61 -> 0.14285714 | S61: FACEBOOK | T61: ='Action Plan'!L65 -> 0 | U61: ='Action Plan'!M65 -> 0 | V61: ='E-Com Operations'!E40 -> 0 | W61: =V61-U61 -> 0 | X61: =_xlfn.IFS(W61>=0,1,W61<0,V61/U61) -> 1 | Y61: =X61*T61 -> 0
C62: LANDING PAGE | D62: ='Action Plan'!D66 -> 0.14285714 | E62: ='Action Plan'!E66 -> 10 | F62: =N62+V62 -> 62 | G62: =F62-E62 -> 52 | H62: =_xlfn.IFS(G62>=0,1,G62<0,F62/E62) -> 1 | I62: =H62*D62 -> 0.14285714 | K62: LANDING PAGE | L62: ='Action Plan'!H66 -> 0.14285714 | M62: ='Action Plan'!I66 -> 10 | N62: ='Digital Marketer #1'!E41 -> 62 | O62: =N62-M62 -> 52 | P62: =_xlfn.IFS(O62>=0,1,O62<0,N62/M62) -> 1 | Q62: =P62*L62 -> 0.14285714 | S62: LANDING PAGE | T62: ='Action Plan'!L66 -> 0 | U62: ='Action Plan'!M66 -> 0 | V62: ='E-Com Operations'!E41 -> 0 | W62: =V62-U62 -> 0 | X62: =_xlfn.IFS(W62>=0,1,W62<0,V62/U62) -> 1 | Y62: =X62*T62 -> 0
C63: WEBSITE | D63: ='Action Plan'!D67 -> 0.071428571 | E63: ='Action Plan'!E67 -> 5 | F63: =N63+V63 -> 1 | G63: =F63-E63 -> -4 | H63: =_xlfn.IFS(G63>=0,1,G63<0,F63/E63) -> 0.2 | I63: =H63*D63 -> 0.014285714 | K63: WEBSITE | L63: ='Action Plan'!H67 -> 0.071428571 | M63: ='Action Plan'!I67 -> 5 | N63: ='Digital Marketer #1'!E42 -> 1 | O63: =N63-M63 -> -4 | P63: =_xlfn.IFS(O63>=0,1,O63<0,N63/M63) -> 0.2 | Q63: =P63*L63 -> 0.014285714 | S63: WEBSITE | T63: ='Action Plan'!L67 -> 0 | U63: ='Action Plan'!M67 -> 0 | V63: ='E-Com Operations'!E42 -> 0 | W63: =V63-U63 -> 0 | X63: =_xlfn.IFS(W63>=0,1,W63<0,V63/U63) -> 1 | Y63: =X63*T63 -> 0
C64: TIKTOKSHOP | D64: ='Action Plan'!D68 -> 0.28571429 | E64: ='Action Plan'!E68 -> 20 | F64: =N64+V64 -> 1 | G64: =F64-E64 -> -19 | H64: =_xlfn.IFS(G64>=0,1,G64<0,F64/E64) -> 0.05 | I64: =H64*D64 -> 0.014285714 | K64: TIKTOKSHOP | L64: ='Action Plan'!H68 -> 0 | M64: ='Action Plan'!I68 -> 0 | N64: ='Digital Marketer #1'!E43 -> 0 | O64: =N64-M64 -> 0 | P64: =_xlfn.IFS(O64>=0,1,O64<0,N64/M64) -> 1 | Q64: =P64*L64 -> 0 | S64: TIKTOKSHOP | T64: ='Action Plan'!L68 -> 0.28571429 | U64: ='Action Plan'!M68 -> 20 | V64: ='E-Com Operations'!E43 -> 1 | W64: =V64-U64 -> -19 | X64: =_xlfn.IFS(W64>=0,1,W64<0,V64/U64) -> 0.05 | Y64: =X64*T64 -> 0.014285714
C65: SHOPPEE | D65: ='Action Plan'!D69 -> 0.28571429 | E65: ='Action Plan'!E69 -> 20 | F65: =N65+V65 -> 31 | G65: =F65-E65 -> 11 | H65: =_xlfn.IFS(G65>=0,1,G65<0,F65/E65) -> 1 | I65: =H65*D65 -> 0.28571429 | K65: SHOPPEE | L65: ='Action Plan'!H69 -> 0 | M65: ='Action Plan'!I69 -> 0 | N65: ='Digital Marketer #1'!E44 -> 0 | O65: =N65-M65 -> 0 | P65: =_xlfn.IFS(O65>=0,1,O65<0,N65/M65) -> 1 | Q65: =P65*L65 -> 0 | S65: SHOPPEE | T65: ='Action Plan'!L69 -> 0.28571429 | U65: ='Action Plan'!M69 -> 20 | V65: ='E-Com Operations'!E44 -> 31 | W65: =V65-U65 -> 11 | X65: =_xlfn.IFS(W65>=0,1,W65<0,V65/U65) -> 1 | Y65: =X65*T65 -> 0.28571429
C66: ZALO | D66: ='Action Plan'!D70 -> 0.071428571 | E66: ='Action Plan'!E70 -> 5 | F66: =N66+V66 -> 31 | G66: =F66-E66 -> 26 | H66: =_xlfn.IFS(G66>=0,1,G66<0,F66/E66) -> 1 | I66: =H66*D66 -> 0.071428571 | K66: ZALO | L66: ='Action Plan'!H70 -> 0.071428571 | M66: ='Action Plan'!I70 -> 5 | N66: ='Digital Marketer #1'!E45 -> 31 | O66: =N66-M66 -> 26 | P66: =_xlfn.IFS(O66>=0,1,O66<0,N66/M66) -> 1 | Q66: =P66*L66 -> 0.071428571 | S66: ZALO | T66: ='Action Plan'!L70 -> 0 | U66: ='Action Plan'!M70 -> 0 | V66: ='E-Com Operations'!E45 -> 0 | W66: =V66-U66 -> 0 | X66: =_xlfn.IFS(W66>=0,1,W66<0,V66/U66) -> 1 | Y66: =X66*T66 -> 0
C67: ='Action Plan'!C71 -> P3 | D67: ='Action Plan'!D71 -> 0.2 | E67: ='Action Plan'!E71 -> 1 | F67: =I68+I75+I82 -> 0.45426144 | G67: =F67-E67 -> -0.54573856 | H67: =IF(G67>=0,1,F67/E67) -> 0.45426144 | I67: =F67*D67 -> 0.090852289 | K67: ='Action Plan'!K71 -> P3 | L67: ='Action Plan'!H71 -> 0.2 | M67: ='Action Plan'!I71 -> 0.52121212 | N67: =AVERAGE(Q68,Q75,Q82) -> 0.22047761 | O67: =N67-M67 -> -0.30073451 | P67: =IF(O67>=0,1,N67/M67) -> 0.42300937 | Q67: =N67*L67 -> 0.044095522 | T67: ='Action Plan'!L71 -> 0.2 | U67: ='Action Plan'!M71 -> 0.47878788 | V67: =AVERAGE(Y68,Y75,Y82) -> 0.34813949 | W67: =V67-U67 -> -0.13064839 | X67: =IF(W67>=0,1,V67/U67) -> 0.72712678 | Y67: =V67*T67 -> 0.069627898
C68: SALES REVENUE | D68: ='Action Plan'!D72 -> 0.25 | E68: ='Action Plan'!E72 -> 500000000 | F68: =SUM(F69:F74) -> 373050000 | G68: =F68-E68 -> -126950000 | H68: =AVERAGE(H69:H74) -> 0.81456667 | I68: =H68*D68 -> 0.20364167 | J68: VND | K68: SALES REVENUE | L68: ='Action Plan'!H72 -> 0.5 | M68: ='Action Plan'!I72 -> 250000000 | N68: =SUM(N69:N74) -> 53050000 | O68: =N68-M68 -> -196950000 | P68: =AVERAGE(P69:P74) -> 0.27313333 | Q68: =P68*L68 -> 0.13656667 | R68: VND | S68: SALES REVENUE | T68: ='Action Plan'!L72 -> 0.5 | U68: ='Action Plan'!M72 -> 250000000 | V68: =SUM(V69:V74) -> 320000000 | W68: =V68-U68 -> 70000000 | X68: =AVERAGE(X69:X74) -> 0.88133333 | Y68: =X68*T68 -> 0.44066667 | Z68: VND
C69: FACEBOOK | D69: ='Action Plan'!D73 -> 0.1 | E69: ='Action Plan'!E73 -> 50000000 | F69: =N69+V69 -> 51100000 | G69: =F69-E69 -> 1100000 | H69: =_xlfn.IFS(G69>=0,1,G69<0,F69/E69) -> 1 | I69: =H69*D69 -> 0.1 | K69: FACEBOOK | L69: ='Action Plan'!H73 -> 0.05 | M69: ='Action Plan'!I73 -> 25000000 | N69: ='Digital Marketer #1'!E49 -> 15100000 | O69: =N69-M69 -> -9900000 | P69: =_xlfn.IFS(O69>=0,1,O69<0,N69/M69) -> 0.604 | Q69: =P69*L69 -> 0.0302 | S69: FACEBOOK | T69: ='Action Plan'!L73 -> 0.05 | U69: ='Action Plan'!M73 -> 25000000 | V69: ='E-Com Operations'!E49 -> 36000000 | W69: =V69-U69 -> 11000000 | X69: =_xlfn.IFS(W69>=0,1,W69<0,V69/U69) -> 1 | Y69: =X69*T69 -> 0.05
C70: LANDING PAGE | D70: ='Action Plan'!D74 -> 0.5 | E70: ='Action Plan'!E74 -> 250000000 | F70: =N70+V70 -> 51100000 | G70: =F70-E70 -> -198900000 | H70: =_xlfn.IFS(G70>=0,1,G70<0,F70/E70) -> 0.2044 | I70: =H70*D70 -> 0.1022 | K70: LANDING PAGE | L70: ='Action Plan'!H74 -> 0.25 | M70: ='Action Plan'!I74 -> 125000000 | N70: ='Digital Marketer #1'!E50 -> 15100000 | O70: =N70-M70 -> -109900000 | P70: =_xlfn.IFS(O70>=0,1,O70<0,N70/M70) -> 0.1208 | Q70: =P70*L70 -> 0.0302 | S70: LANDING PAGE | T70: ='Action Plan'!L74 -> 0.25 | U70: ='Action Plan'!M74 -> 125000000 | V70: ='E-Com Operations'!E50 -> 36000000 | W70: =V70-U70 -> -89000000 | X70: =_xlfn.IFS(W70>=0,1,W70<0,V70/U70) -> 0.288 | Y70: =X70*T70 -> 0.072
C71: WEBSITE | D71: ='Action Plan'!D75 -> 0.1 | E71: ='Action Plan'!E75 -> 50000000 | F71: =N71+V71 -> 48100000 | G71: =F71-E71 -> -1900000 | H71: =_xlfn.IFS(G71>=0,1,G71<0,F71/E71) -> 0.962 | I71: =H71*D71 -> 0.0962 | K71: WEBSITE | L71: ='Action Plan'!H75 -> 0.05 | M71: ='Action Plan'!I75 -> 25000000 | N71: ='Digital Marketer #1'!E51 -> 15100000 | O71: =N71-M71 -> -9900000 | P71: =_xlfn.IFS(O71>=0,1,O71<0,N71/M71) -> 0.604 | Q71: =P71*L71 -> 0.0302 | S71: WEBSITE | T71: ='Action Plan'!L75 -> 0.05 | U71: ='Action Plan'!M75 -> 25000000 | V71: ='E-Com Operations'!E51 -> 33000000 | W71: =V71-U71 -> 8000000 | X71: =_xlfn.IFS(W71>=0,1,W71<0,V71/U71) -> 1 | Y71: =X71*T71 -> 0.05
C72: TIKTOKSHOP | D72: ='Action Plan'!D76 -> 0.1 | E72: ='Action Plan'!E76 -> 50000000 | F72: =N72+V72 -> 92600000 | G72: =F72-E72 -> 42600000 | H72: =_xlfn.IFS(G72>=0,1,G72<0,F72/E72) -> 1 | I72: =H72*D72 -> 0.1 | K72: TIKTOKSHOP | L72: ='Action Plan'!H76 -> 0.05 | M72: ='Action Plan'!I76 -> 25000000 | N72: ='Digital Marketer #1'!E52 -> 1600000 | O72: =N72-M72 -> -23400000 | P72: =_xlfn.IFS(O72>=0,1,O72<0,N72/M72) -> 0.064 | Q72: =P72*L72 -> 0.0032 | S72: TIKTOKSHOP | T72: ='Action Plan'!L76 -> 0.05 | U72: ='Action Plan'!M76 -> 25000000 | V72: ='E-Com Operations'!E52 -> 91000000 | W72: =V72-U72 -> 66000000 | X72: =_xlfn.IFS(W72>=0,1,W72<0,V72/U72) -> 1 | Y72: =X72*T72 -> 0.05
C73: SHOPPEE | D73: ='Action Plan'!D77 -> 0.1 | E73: ='Action Plan'!E77 -> 50000000 | F73: =N73+V73 -> 94100000 | G73: =F73-E73 -> 44100000 | H73: =_xlfn.IFS(G73>=0,1,G73<0,F73/E73) -> 1 | I73: =H73*D73 -> 0.1 | K73: SHOPPEE | L73: ='Action Plan'!H77 -> 0.05 | M73: ='Action Plan'!I77 -> 25000000 | N73: ='Digital Marketer #1'!E53 -> 3100000 | O73: =N73-M73 -> -21900000 | P73: =_xlfn.IFS(O73>=0,1,O73<0,N73/M73) -> 0.124 | Q73: =P73*L73 -> 0.0062 | S73: SHOPPEE | T73: ='Action Plan'!L77 -> 0.05 | U73: ='Action Plan'!M77 -> 25000000 | V73: ='E-Com Operations'!E53 -> 91000000 | W73: =V73-U73 -> 66000000 | X73: =_xlfn.IFS(W73>=0,1,W73<0,V73/U73) -> 1 | Y73: =X73*T73 -> 0.05
C74: ZALO | D74: ='Action Plan'!D78 -> 0.1 | E74: ='Action Plan'!E78 -> 50000000 | F74: =N74+V74 -> 36050000 | G74: =F74-E74 -> -13950000 | H74: =_xlfn.IFS(G74>=0,1,G74<0,F74/E74) -> 0.721 | I74: =H74*D74 -> 0.0721 | K74: ZALO | L74: ='Action Plan'!H78 -> 0.05 | M74: ='Action Plan'!I78 -> 25000000 | N74: ='Digital Marketer #1'!E54 -> 3050000 | O74: =N74-M74 -> -21950000 | P74: =_xlfn.IFS(O74>=0,1,O74<0,N74/M74) -> 0.122 | Q74: =P74*L74 -> 0.0061 | S74: ZALO | T74: ='Action Plan'!L78 -> 0.05 | U74: ='Action Plan'!M78 -> 25000000 | V74: ='E-Com Operations'!E54 -> 33000000 | W74: =V74-U74 -> 8000000 | X74: =_xlfn.IFS(W74>=0,1,W74<0,V74/U74) -> 1 | Y74: =X74*T74 -> 0.05
C75: A/S RATIO | D75: ='Action Plan'!D79 -> 0.5 | E75: ='Action Plan'!E79 -> 0.37333333 | F75: =IF(SUM(F76:F81)>0,AVERAGEIF(F76:F81,">0"),0) -> 19.066667 | G75: =E75-F75 -> -18.693333 | H75: =AVERAGE(H76:H81) -> 0.082853311 | I75: =H75*D75 -> 0.041426656 | J75: ='Action Plan'!F79 -> CAMPAIGN | K75: A/S RATIO | L75: ='Action Plan'!H79 -> 0.5 | M75: ='Action Plan'!I79 -> 0.18666667 | N75: =AVERAGE(N76:N81) -> 18.35 | O75: =M75-N75 -> -18.163333 | P75: =AVERAGE(P76:P81) -> 0.20036364 | Q75: =P75*L75 -> 0.10018182 | R75: ='Action Plan'!N79 -> CAMPAIGN | S75: A/S RATIO | T75: ='Action Plan'!L79 -> 0.5 | U75: ='Action Plan'!M79 -> 0.18666667 | V75: =AVERAGE(V76:V81) -> 0.71666667 | W75: =U75-V75 -> -0.53 | X75: =AVERAGE(X76:X81) -> 0.6984127 | Y75: =X75*T75 -> 0.34920635 | Z75: CAMPAIGN
C76: FACEBOOK | D76: ='Action Plan'!D80 -> 0.2 | E76: ='Action Plan'!E80 -> 0.2 | F76: =(N76+V76) -> 0.6 | G76: =E76-F76 -> -0.4 | H76: =_xlfn.IFS(G76>=0,1,G76<0,E76/F76) -> 0.33333333 | I76: =H76*D76 -> 0.066666667 | J76: HIGHER = BAD | K76: FACEBOOK | L76: ='Action Plan'!H80 -> 0.26785714 | M76: ='Action Plan'!I80 -> 0.1 | N76: ='Digital Marketer #1'!E56 -> 0.6 | O76: =M76-N76 -> -0.5 | P76: =_xlfn.IFS(O76>=0,1,O76<0,M76/N76) -> 0.16666667 | Q76: =P76*L76 -> 0.044642857 | S76: FACEBOOK | T76: ='Action Plan'!L80 -> 0.26785714 | U76: ='Action Plan'!M80 -> 0.1 | V76: ='E-Com Operations'!E56 -> 0 | W76: =U76-V76 -> 0.1 | X76: =_xlfn.IFS(W76>=0,1,W76<0,U76/V76) -> 1 | Y76: =X76*T76 -> 0.26785714
C77: LANDING PAGE | D77: ='Action Plan'!D81 -> 0.4 | E77: ='Action Plan'!E81 -> 0.24 | F77: =(N77+V77) -> 30 | G77: =E77-F77 -> -29.76 | H77: =_xlfn.IFS(G77>=0,1,G77<0,E77/F77) -> 0.008 | I77: =H77*D77 -> 0.0032 | K77: LANDING PAGE | L77: ='Action Plan'!H81 -> 0.32142857 | M77: ='Action Plan'!I81 -> 0.12 | N77: ='Digital Marketer #1'!E57 -> 30 | O77: =M77-N77 -> -29.88 | P77: =_xlfn.IFS(O77>=0,1,O77<0,M77/N77) -> 0.004 | Q77: =P77*L77 -> 0.0012857143 | S77: LANDING PAGE | T77: ='Action Plan'!L81 -> 0.32142857 | U77: ='Action Plan'!M81 -> 0.12 | V77: ='E-Com Operations'!E57 -> 0 | W77: =U77-V77 -> 0.12 | X77: =_xlfn.IFS(W77>=0,1,W77<0,U77/V77) -> 1 | Y77: =X77*T77 -> 0.32142857
C78: WEBSITE | D78: ='Action Plan'!D82 -> 0.1 | E78: ='Action Plan'!E82 -> 0.2 | F78: =(N78+V78) -> 30 | G78: =E78-F78 -> -29.8 | H78: =_xlfn.IFS(G78>=0,1,G78<0,E78/F78) -> 0.0066666667 | I78: =H78*D78 -> 0.00066666667 | K78: WEBSITE | L78: ='Action Plan'!H82 -> 0.26785714 | M78: ='Action Plan'!I82 -> 0.1 | N78: ='Digital Marketer #1'!E58 -> 30 | O78: =M78-N78 -> -29.9 | P78: =_xlfn.IFS(O78>=0,1,O78<0,M78/N78) -> 0.0033333333 | Q78: =P78*L78 -> 0.00089285714 | S78: WEBSITE | T78: ='Action Plan'!L82 -> 0.26785714 | U78: ='Action Plan'!M82 -> 0.1 | V78: ='E-Com Operations'!E58 -> 0 | W78: =U78-V78 -> 0.1 | X78: =_xlfn.IFS(W78>=0,1,W78<0,U78/V78) -> 1 | Y78: =X78*T78 -> 0.26785714
C79: TIKTOKSHOP | D79: ='Action Plan'!D83 -> 0.1 | E79: ='Action Plan'!E83 -> 0.6 | F79: =(N79+V79) -> 24.1 | G79: =E79-F79 -> -23.5 | H79: =_xlfn.IFS(G79>=0,1,G79<0,E79/F79) -> 0.024896266 | I79: =H79*D79 -> 0.0024896266 | K79: TIKTOKSHOP | L79: ='Action Plan'!H83 -> 0.80357143 | M79: ='Action Plan'!I83 -> 0.3 | N79: ='Digital Marketer #1'!E59 -> 22 | O79: =M79-N79 -> -21.7 | P79: =_xlfn.IFS(O79>=0,1,O79<0,M79/N79) -> 0.013636364 | Q79: =P79*L79 -> 0.010957792 | S79: TIKTOKSHOP | T79: ='Action Plan'!L83 -> 0.80357143 | U79: ='Action Plan'!M83 -> 0.3 | V79: ='E-Com Operations'!E59 -> 2.1 | W79: =U79-V79 -> -1.8 | X79: =_xlfn.IFS(W79>=0,1,W79<0,U79/V79) -> 0.14285714 | Y79: =X79*T79 -> 0.11479592
C80: SHOPPEE | D80: ='Action Plan'!D84 -> 0.1 | E80: ='Action Plan'!E84 -> 0.2 | F80: =(N80+V80) -> 2.1 | G80: =E80-F80 -> -1.9 | H80: =_xlfn.IFS(G80>=0,1,G80<0,E80/F80) -> 0.095238095 | I80: =H80*D80 -> 0.0095238095 | K80: SHOPPEE | L80: ='Action Plan'!H84 -> 0.26785714 | M80: ='Action Plan'!I84 -> 0.1 | N80: ='Digital Marketer #1'!E60 -> 0 | O80: =M80-N80 -> 0.1 | P80: =_xlfn.IFS(O80>=0,1,O80<0,M80/N80) -> 1 | Q80: =P80*L80 -> 0.26785714 | S80: SHOPPEE | T80: ='Action Plan'!L84 -> 0.26785714 | U80: ='Action Plan'!M84 -> 0.1 | V80: ='E-Com Operations'!E60 -> 2.1 | W80: =U80-V80 -> -2 | X80: =_xlfn.IFS(W80>=0,1,W80<0,U80/V80) -> 0.047619048 | Y80: =X80*T80 -> 0.012755102
C81: ZALO | D81: ='Action Plan'!D85 -> 0.1 | E81: ='Action Plan'!E85 -> 0.8 | F81: =(N81+V81) -> 27.6 | G81: =E81-F81 -> -26.8 | H81: =_xlfn.IFS(G81>=0,1,G81<0,E81/F81) -> 0.028985507 | I81: =H81*D81 -> 0.0028985507 | K81: ZALO | L81: ='Action Plan'!H85 -> 1.0714286 | M81: ='Action Plan'!I85 -> 0.4 | N81: ='Digital Marketer #1'!E61 -> 27.5 | O81: =M81-N81 -> -27.1 | P81: =_xlfn.IFS(O81>=0,1,O81<0,M81/N81) -> 0.014545455 | Q81: =P81*L81 -> 0.015584416 | S81: ZALO | T81: ='Action Plan'!L85 -> 1.0714286 | U81: ='Action Plan'!M85 -> 0.4 | V81: ='E-Com Operations'!E61 -> 0.1 | W81: =U81-V81 -> 0.3 | X81: =_xlfn.IFS(W81>=0,1,W81<0,U81/V81) -> 1 | Y81: =X81*T81 -> 1.0714286
C82: CONVERSION RATE | D82: ='Action Plan'!D86 -> 0.25 | E82: ='Action Plan'!E86 -> 0.45833333 | F82: =IF(SUM(F83:F88)>0,AVERAGEIF(F83:F88,">0"),0) -> 0.45 | G82: =F82-E82 -> -0.0083333333 | H82: =AVERAGE(H83:H88) -> 0.83677249 | I82: =H82*D82 -> 0.20919312 | J82: ='Action Plan'!F86 -> CAMPAIGN | K82: CONVERSION RATE | L82: ='Action Plan'!H86 -> 0.56363636 | M82: ='Action Plan'!I86 -> 0.25833333 | N82: =AVERAGE(N83:N88) -> 0.23166667 | O82: =N82-M82 -> -0.026666667 | P82: =AVERAGE(P83:P88) -> 0.75347222 | Q82: =P82*L82 -> 0.42468434 | R82: ='Action Plan'!N86 -> CAMPAIGN | S82: CONVERSION RATE | T82: ='Action Plan'!L86 -> 0.43636364 | U82: ='Action Plan'!M86 -> 0.2 | V82: =AVERAGE(V83:V88) -> 0.21833333 | W82: =V82-U82 -> 0.018333333 | X82: =AVERAGE(X83:X88) -> 0.58333333 | Y82: =X82*T82 -> 0.25454545 | Z82: CAMPAIGN
C83: FACEBOOK | D83: ='Action Plan'!D87 -> 0.2 | E83: ='Action Plan'!E87 -> 0.2 | F83: =(N83+V83) -> 0.38 | G83: =F83-E83 -> 0.18 | H83: =_xlfn.IFS(G83>=0,1,G83<0,F83/E83) -> 1 | I83: =H83*D83 -> 0.2 | J83: HIGHER = GOOD | K83: FACEBOOK | L83: ='Action Plan'!H87 -> 0.32727273 | M83: ='Action Plan'!I87 -> 0.15 | N83: ='Digital Marketer #1'!E63 -> 0.35 | O83: =N83-M83 -> 0.2 | P83: =_xlfn.IFS(O83>=0,1,O83<0,N83/M83) -> 1 | Q83: =P83*L83 -> 0.32727273 | S83: FACEBOOK | T83: ='Action Plan'!L87 -> 0.10909091 | U83: ='Action Plan'!M87 -> 0.05 | V83: ='E-Com Operations'!E63 -> 0.03 | W83: =V83-U83 -> -0.02 | X83: =_xlfn.IFS(W83>=0,1,W83<0,V83/U83) -> 0.6 | Y83: =X83*T83 -> 0.065454545
C84: LANDING PAGE | D84: ='Action Plan'!D88 -> 0.4 | E84: ='Action Plan'!E88 -> 0.9 | F84: =(N84+V84) -> 0.34 | G84: =F84-E84 -> -0.56 | H84: =_xlfn.IFS(G84>=0,1,G84<0,F84/E84) -> 0.37777778 | I84: =H84*D84 -> 0.15111111 | K84: LANDING PAGE | L84: ='Action Plan'!H88 -> 1.7454545 | M84: ='Action Plan'!I88 -> 0.8 | N84: ='Digital Marketer #1'!E64 -> 0.31 | O84: =N84-M84 -> -0.49 | P84: =_xlfn.IFS(O84>=0,1,O84<0,N84/M84) -> 0.3875 | Q84: =P84*L84 -> 0.67636364 | S84: LANDING PAGE | T84: ='Action Plan'!L88 -> 0.21818182 | U84: ='Action Plan'!M88 -> 0.1 | V84: ='E-Com Operations'!E64 -> 0.03 | W84: =V84-U84 -> -0.07 | X84: =_xlfn.IFS(W84>=0,1,W84<0,V84/U84) -> 0.3 | Y84: =X84*T84 -> 0.065454545
C85: WEBSITE | D85: ='Action Plan'!D89 -> 0.1 | E85: ='Action Plan'!E89 -> 0.5 | F85: =(N85+V85) -> 0.35 | G85: =F85-E85 -> -0.15 | H85: =_xlfn.IFS(G85>=0,1,G85<0,F85/E85) -> 0.7 | I85: =H85*D85 -> 0.07 | K85: WEBSITE | L85: ='Action Plan'!H89 -> 0.98181818 | M85: ='Action Plan'!I89 -> 0.45 | N85: ='Digital Marketer #1'!E65 -> 0.33 | O85: =N85-M85 -> -0.12 | P85: =_xlfn.IFS(O85>=0,1,O85<0,N85/M85) -> 0.73333333 | Q85: =P85*L85 -> 0.72 | S85: WEBSITE | T85: ='Action Plan'!L89 -> 0.10909091 | U85: ='Action Plan'!M89 -> 0.05 | V85: ='E-Com Operations'!E65 -> 0.02 | W85: =V85-U85 -> -0.03 | X85: =_xlfn.IFS(W85>=0,1,W85<0,V85/U85) -> 0.4 | Y85: =X85*T85 -> 0.043636364
C86: TIKTOKSHOP | D86: ='Action Plan'!D90 -> 0.1 | E86: ='Action Plan'!E90 -> 0.7 | F86: =(N86+V86) -> 0.97 | G86: =F86-E86 -> 0.27 | H86: =_xlfn.IFS(G86>=0,1,G86<0,F86/E86) -> 1 | I86: =H86*D86 -> 0.1 | K86: TIKTOKSHOP | L86: ='Action Plan'!H90 -> 0.10909091 | M86: ='Action Plan'!I90 -> 0.05 | N86: ='Digital Marketer #1'!E66 -> 0.06 | O86: =N86-M86 -> 0.01 | P86: =_xlfn.IFS(O86>=0,1,O86<0,N86/M86) -> 1 | Q86: =P86*L86 -> 0.10909091 | S86: TIKTOKSHOP | T86: ='Action Plan'!L90 -> 1.4181818 | U86: ='Action Plan'!M90 -> 0.65 | V86: ='E-Com Operations'!E66 -> 0.91 | W86: =V86-U86 -> 0.26 | X86: =_xlfn.IFS(W86>=0,1,W86<0,V86/U86) -> 1 | Y86: =X86*T86 -> 1.4181818
C87: SHOPPEE | D87: ='Action Plan'!D91 -> 0.1 | E87: ='Action Plan'!E91 -> 0.35 | F87: =(N87+V87) -> 0.33 | G87: =F87-E87 -> -0.02 | H87: =_xlfn.IFS(G87>=0,1,G87<0,F87/E87) -> 0.94285714 | I87: =H87*D87 -> 0.094285714 | K87: SHOPPEE | L87: ='Action Plan'!H91 -> 0.10909091 | M87: ='Action Plan'!I91 -> 0.05 | N87: ='Digital Marketer #1'!E67 -> 0.02 | O87: =N87-M87 -> -0.03 | P87: =_xlfn.IFS(O87>=0,1,O87<0,N87/M87) -> 0.4 | Q87: =P87*L87 -> 0.043636364 | S87: SHOPPEE | T87: ='Action Plan'!L91 -> 0.65454545 | U87: ='Action Plan'!M91 -> 0.3 | V87: ='E-Com Operations'!E67 -> 0.31 | W87: =V87-U87 -> 0.01 | X87: =_xlfn.IFS(W87>=0,1,W87<0,V87/U87) -> 1 | Y87: =X87*T87 -> 0.65454545
C88: ZALO | D88: ='Action Plan'!D92 -> 0.1 | E88: ='Action Plan'!E92 -> 0.1 | F88: =(N88+V88) -> 0.33 | G88: =F88-E88 -> 0.23 | H88: =_xlfn.IFS(G88>=0,1,G88<0,F88/E88) -> 1 | I88: =H88*D88 -> 0.1 | K88: ZALO | L88: ='Action Plan'!H92 -> 0.10909091 | M88: ='Action Plan'!I92 -> 0.05 | N88: ='Digital Marketer #1'!E68 -> 0.32 | O88: =N88-M88 -> 0.27 | P88: =_xlfn.IFS(O88>=0,1,O88<0,N88/M88) -> 1 | Q88: =P88*L88 -> 0.10909091 | S88: ZALO | T88: ='Action Plan'!L92 -> 0.10909091 | U88: ='Action Plan'!M92 -> 0.05 | V88: ='E-Com Operations'!E68 -> 0.01 | W88: =V88-U88 -> -0.04 | X88: =_xlfn.IFS(W88>=0,1,W88<0,V88/U88) -> 0.2 | Y88: =X88*T88 -> 0.021818182
B89: ='Action Plan'!B93 -> TOTAL | C89: ='Action Plan'!C93 -> Sale | D89: =D50 -> Ratio | E89: =E50 -> KPIs | F89: Actual | G89: Remaining | H89: Ratio | I89: Weight Rate | K89: ='Action Plan'!G93 -> Sale #1 | L89: =L50 -> Ratio/ Team | M89: =M50 -> KPIs | N89: Actual | O89: Remaining | P89: Ratio | Q89: Weight Rate | S89: ='Action Plan'!K93 -> Sale #2 | T89: =T50 -> Ratio/ Team | U89: =U50 -> KPIs | V89: Actual | W89: Remaining | X89: Ratio | Y89: Weight Rate | AA89: ='Action Plan'!O93 -> Sale #3 | AB89: =T50 -> Ratio/ Team | AC89: =U50 -> KPIs | AD89: Actual | AE89: Remaining | AF89: Ratio | AG89: Weight Rate | AI89: ='Action Plan'!S93 -> Sale #4 | AJ89: =T50 -> Ratio/ Team | AK89: =U50 -> KPIs | AL89: Actual | AM89: Remaining | AN89: Ratio | AO89: Weight Rate
B90: ='Action Plan'!B94 -> Sale | C90: ='Action Plan'!C94 -> P2 | D90: ='Action Plan'!D94 -> 0.2 | E90: ='Action Plan'!E94 -> 1 | F90: =I91+I92+I93 -> 1 | G90: =F90-E90 -> 0 | H90: =IF(G90>=0,1,F90/E90) -> 1 | I90: =F90*D90 -> 0.2 | K90: ='Action Plan'!G94 -> P2 | L90: ='Action Plan'!H94 -> 0.2 | M90: ='Action Plan'!I94 -> 0.35 | N90: =AVERAGE(Q91,Q92,Q93) -> 0.35 | O90: =N90-M90 -> 0 | P90: =IF(O90>=0,1,N90/M90) -> 1 | Q90: =N90*L90 -> 0.07 | S90: ='Action Plan'!K94 -> P2 | T90: ='Action Plan'!L94 -> 0.2 | U90: ='Action Plan'!M94 -> 0.3 | V90: =AVERAGE(Y91,Y92,Y93) -> 0.3 | W90: =V90-U90 -> 0 | X90: =IF(W90>=0,1,V90/U90) -> 1 | Y90: =V90*T90 -> 0.06 | AA90: ='Action Plan'!O94 -> P2 | AB90: ='Action Plan'!P94 -> 0.2 | AC90: ='Action Plan'!Q94 -> 0.25 | AD90: =AVERAGE(AG91,AG92,AG93) -> 0.25 | AE90: =AD90-AC90 -> 0 | AF90: =IF(AE90>=0,1,AD90/AC90) -> 1 | AG90: =AD90*AB90 -> 0.05 | AI90: ='Action Plan'!S94 -> P2 | AJ90: ='Action Plan'!T94 -> 0.2 | AK90: ='Action Plan'!U94 -> 0.2 | AL90: =AVERAGE(AO91,AO92,AO93) -> 0.2 | AM90: =AL90-AK90 -> 0 | AN90: =IF(AM90>=0,1,AL90/AK90) -> 1 | AO90: =AL90*AJ90 -> 0.04
C91: CALL | D91: ='Action Plan'!D95 -> 0.4 | E91: ='Action Plan'!E95 -> 1222.6096 | F91: =N91+V91+AD91+AL91 -> 2727 | G91: =F91-E91 -> 1504.3904 | H91: =IF(G91>0,1,F91/E91) -> 1 | I91: =H91*D91 -> 0.4 | J91: ='Action Plan'!F95 -> PHONE | K91: CALL | L91: ='Action Plan'!H95 -> 0.35 | M91: ='Action Plan'!I95 -> 427.91337 | N91: ='Sale #1'!$E15 -> 681 | O91: =N91-M91 -> 253.08663 | P91: =IF(O91>0,1,N91/M91) -> 1 | Q91: =P91*L91 -> 0.35 | R91: ='Action Plan'!N95 -> PHONE | S91: CALL | T91: ='Action Plan'!L95 -> 0.3 | U91: ='Action Plan'!M95 -> 366.78289 | V91: ='Sale #2'!$E15 -> 682 | W91: =V91-U91 -> 315.21711 | X91: =IF(W91>0,1,V91/U91) -> 1 | Y91: =X91*T91 -> 0.3 | Z91: ='Action Plan'!V95 -> PHONE | AA91: CALL | AB91: ='Action Plan'!P95 -> 0.25 | AC91: ='Action Plan'!Q95 -> 305.6524 | AD91: ='Sale #3'!$E15 -> 682 | AE91: =AD91-AC91 -> 376.3476 | AF91: =IF(AE91>0,1,AD91/AC91) -> 1 | AG91: =AF91*AB91 -> 0.25 | AH91: Phone | AI91: CALL | AJ91: ='Action Plan'!T95 -> 0.2 | AK91: ='Action Plan'!U95 -> 244.52192 | AL91: ='Sale #4'!$E15 -> 682 | AM91: =AL91-AK91 -> 437.47808 | AN91: =IF(AM91>0,1,AL91/AK91) -> 1 | AO91: =AN91*AJ91 -> 0.2 | AP91: Phone
C92: SMS | D92: ='Action Plan'!D96 -> 0.4 | E92: ='Action Plan'!E96 -> 313 | F92: =N92+V92+AD92+AL92 -> 2981 | G92: =F92-E92 -> 2668 | H92: =IF(G92>0,1,F92/E92) -> 1 | I92: =H92*D92 -> 0.4 | J92: ='Action Plan'!F96 -> MESSAGE | K92: SMS | L92: ='Action Plan'!H96 -> 0.35 | M92: ='Action Plan'!I96 -> 109.55 | N92: ='Sale #1'!$E16 -> 747 | O92: =N92-M92 -> 637.45 | P92: =IF(O92>0,1,N92/M92) -> 1 | Q92: =P92*L92 -> 0.35 | R92: ='Action Plan'!N96 -> MESSAGE | S92: SMS | T92: ='Action Plan'!L96 -> 0.3 | U92: ='Action Plan'!M96 -> 93.9 | V92: ='Sale #2'!$E16 -> 744 | W92: =V92-U92 -> 650.1 | X92: =IF(W92>0,1,V92/U92) -> 1 | Y92: =X92*T92 -> 0.3 | Z92: ='Action Plan'!V96 -> MESSAGE | AA92: SMS | AB92: ='Action Plan'!P96 -> 0.25 | AC92: ='Action Plan'!Q96 -> 78.25 | AD92: ='Sale #3'!$E16 -> 744 | AE92: =AD92-AC92 -> 665.75 | AF92: =IF(AE92>0,1,AD92/AC92) -> 1 | AG92: =AF92*AB92 -> 0.25 | AH92: Message | AI92: SMS | AJ92: ='Action Plan'!T96 -> 0.2 | AK92: ='Action Plan'!U96 -> 62.6 | AL92: ='Sale #4'!$E16 -> 746 | AM92: =AL92-AK92 -> 683.4 | AN92: =IF(AM92>0,1,AL92/AK92) -> 1 | AO92: =AN92*AJ92 -> 0.2 | AP92: Message
C93: Q&A | D93: ='Action Plan'!D97 -> 0.2 | E93: ='Action Plan'!E97 -> 104 | F93: =N93+V93+AD93+AL93 -> 5708 | G93: =F93-E93 -> 5604 | H93: =IF(G93>0,1,F93/E93) -> 1 | I93: =H93*D93 -> 0.2 | J93: ='Action Plan'!F97 -> DIALOGUE | K93: Q&A | L93: ='Action Plan'!H97 -> 0.35 | M93: ='Action Plan'!I97 -> 36.4 | N93: ='Sale #1'!$E17 -> 1428 | O93: =N93-M93 -> 1391.6 | P93: =IF(O93>0,1,N93/M93) -> 1 | Q93: =P93*L93 -> 0.35 | R93: ='Action Plan'!N97 -> DIALOGUE | S93: Q&A | T93: ='Action Plan'!L97 -> 0.3 | U93: ='Action Plan'!M97 -> 31.2 | V93: ='Sale #2'!$E17 -> 1426 | W93: =V93-U93 -> 1394.8 | X93: =IF(W93>0,1,V93/U93) -> 1 | Y93: =X93*T93 -> 0.3 | Z93: ='Action Plan'!V97 -> DIALOGUE | AA93: Q&A | AB93: ='Action Plan'!P97 -> 0.25 | AC93: ='Action Plan'!Q97 -> 26 | AD93: ='Sale #3'!$E17 -> 1426 | AE93: =AD93-AC93 -> 1400 | AF93: =IF(AE93>0,1,AD93/AC93) -> 1 | AG93: =AF93*AB93 -> 0.25 | AH93: Dialogue | AI93: Q&A | AJ93: ='Action Plan'!T97 -> 0.2 | AK93: ='Action Plan'!U97 -> 20.8 | AL93: ='Sale #4'!$E17 -> 1428 | AM93: =AL93-AK93 -> 1407.2 | AN93: =IF(AM93>0,1,AL93/AK93) -> 1 | AO93: =AN93*AJ93 -> 0.2 | AP93: Dialogue
C94: ='Action Plan'!C98 -> P3 | D94: ='Action Plan'!D98 -> 0.2 | E94: ='Action Plan'!E98 -> 1 | F94: =I95+I102+I109+I116+I123 -> 0.80745962 | G94: =F94-E94 -> -0.19254038 | H94: =IF(G94>=0,1,F94/E94) -> 0.80745962 | I94: =F94*D94 -> 0.16149192 | K94: ='Action Plan'!G98 -> P3 | L94: ='Action Plan'!H98 -> 0.2 | M94: ='Action Plan'!I98 -> 0.35 | N94: =AVERAGE(Q95,Q102,Q109,Q116,Q123) -> 0.30828589 | O94: =N94-M94 -> -0.041714111 | P94: =IF(O94>=0,1,N94/M94) -> 0.88081683 | Q94: =N94*L94 -> 0.061657178 | S94: ='Action Plan'!K98 -> P3 | T94: ='Action Plan'!L98 -> 0.2 | U94: ='Action Plan'!M98 -> 0.3 | V94: =AVERAGE(Y95,Y102,Y109,Y116,Y123) -> 0.24664267 | W94: =V94-U94 -> -0.053357333 | X94: =IF(W94>=0,1,V94/U94) -> 0.82214222 | Y94: =V94*T94 -> 0.049328533 | AA94: ='Action Plan'!O98 -> P3 | AB94: ='Action Plan'!P98 -> 0.2 | AC94: ='Action Plan'!Q98 -> 0.25 | AD94: =AVERAGE(AG95,AG102,AG109,AG116,AG123) -> 0.20549667 | AE94: =AD94-AC94 -> -0.044503333 | AF94: =IF(AE94>=0,1,AD94/AC94) -> 0.82198667 | AG94: =AD94*AB94 -> 0.041099333 | AI94: ='Action Plan'!S98 -> P3 | AJ94: ='Action Plan'!T98 -> 0.2 | AK94: ='Action Plan'!U98 -> 0.2 | AL94: =AVERAGE(AO95,AO102,AO109,AO116,AO123) -> 0.158384 | AM94: =AL94-AK94 -> -0.041616 | AN94: =IF(AM94>=0,1,AL94/AK94) -> 0.79192 | AO94: =AL94*AJ94 -> 0.0316768
C95: SALES REVENUE | D95: ='Action Plan'!D99 -> 0.6 | E95: ='Action Plan'!E99 -> 500000000 | F95: =SUM(F96:F101) -> 396800000 | G95: =F95-E95 -> -103200000 | H95: =AVERAGE(H96:H101) -> 0.832 | I95: =H95*D95 -> 0.4992 | J95: ='Action Plan'!F99 -> VND | K95: SALES REVENUE | L95: ='Action Plan'!H99 -> 0.35 | M95: ='Action Plan'!I99 -> 175000000 | N95: ='Sale #1'!$E19 -> 99200000 | O95: =N95-M95 -> -75800000 | P95: =AVERAGE(P96:P101) -> 0.76142857 | Q95: =P95*L95 -> 0.2665 | R95: ='Action Plan'!J99 -> VND | S95: SALES REVENUE | T95: ='Action Plan'!L99 -> 0.3 | U95: ='Action Plan'!M99 -> 150000000 | V95: ='Sale #2'!$E19 -> 99200000 | W95: =V95-U95 -> -50800000 | X95: =AVERAGE(X96:X101) -> 0.80444444 | Y95: =X95*T95 -> 0.24133333 | Z95: VND | AA95: SALES REVENUE | AB95: ='Action Plan'!P99 -> 0.25 | AC95: ='Action Plan'!Q99 -> 125000000 | AD95: ='Sale #3'!$E19 -> 99200000 | AE95: =AD95-AC95 -> -25800000 | AF95: =AVERAGE(AF96:AF101) -> 0.832 | AG95: =AF95*AB95 -> 0.208 | AH95: VND | AI95: SALES REVENUE | AJ95: ='Action Plan'!T99 -> 0.2 | AK95: ='Action Plan'!U99 -> 100000000 | AL95: ='Sale #4'!$E19 -> 99200000 | AM95: =AL95-AK95 -> -800000 | AN95: =AVERAGE(AN96:AN101) -> 0.87333333 | AO95: =AN95*AJ95 -> 0.17466667 | AP95: VND
C96: FACEBOOK | D96: ='Action Plan'!D100 -> 0.1 | E96: ='Action Plan'!E100 -> 50000000 | F96: =N96+V96+AD96+AL96 -> 93000000 | G96: =F96-E96 -> 43000000 | H96: =_xlfn.IFS(G96>=0,1,G96<0,F96/E96) -> 1 | I96: =H96*D96 -> 0.1 | K96: FACEBOOK | L96: ='Action Plan'!H100 -> 0.035 | M96: ='Action Plan'!I100 -> 17500000 | N96: ='Sale #1'!$E20 -> 23250000 | O96: =N96-M96 -> 5750000 | P96: =_xlfn.IFS(O96>0,1,O96<=0,N96/M96) -> 1 | Q96: =P96*L96 -> 0.035 | S96: FACEBOOK | T96: ='Action Plan'!L100 -> 0.03 | U96: ='Action Plan'!M100 -> 15000000 | V96: ='Sale #2'!$E20 -> 23250000 | W96: =V96-U96 -> 8250000 | X96: =_xlfn.IFS(W96>0,1,W96<=0,V96/U96) -> 1 | Y96: =X96*T96 -> 0.03 | AA96: FACEBOOK | AB96: ='Action Plan'!P100 -> 0.025 | AC96: ='Action Plan'!Q100 -> 12500000 | AD96: ='Sale #3'!$E20 -> 23250000 | AE96: =AD96-AC96 -> 10750000 | AF96: =_xlfn.IFS(AE96>0,1,AE96<=0,AD96/AC96) -> 1 | AG96: =AF96*AB96 -> 0.025 | AI96: FACEBOOK | AJ96: ='Action Plan'!T100 -> 0.02 | AK96: ='Action Plan'!U100 -> 10000000 | AL96: ='Sale #4'!$E20 -> 23250000 | AM96: =AL96-AK96 -> 13250000 | AN96: =_xlfn.IFS(AM96>0,1,AM96<=0,AL96/AK96) -> 1 | AO96: =AN96*AJ96 -> 0.02
C97: LANDING PAGE | D97: ='Action Plan'!D101 -> 0.5 | E97: ='Action Plan'!E101 -> 250000000 | F97: =N97+V97+AD97+AL97 -> 62000000 | G97: =F97-E97 -> -188000000 | H97: =_xlfn.IFS(G97>=0,1,G97<0,F97/E97) -> 0.248 | I97: =H97*D97 -> 0.124 | K97: LANDING PAGE | L97: ='Action Plan'!H101 -> 0.175 | M97: ='Action Plan'!I101 -> 87500000 | N97: ='Sale #1'!$E26 -> 15500000 | O97: =N97-M97 -> -72000000 | P97: =_xlfn.IFS(O97>0,1,O97<=0,N97/M97) -> 0.17714286 | Q97: =P97*L97 -> 0.031 | S97: LANDING PAGE | T97: ='Action Plan'!L101 -> 0.15 | U97: ='Action Plan'!M101 -> 75000000 | V97: ='Sale #2'!$E26 -> 15500000 | W97: =V97-U97 -> -59500000 | X97: =_xlfn.IFS(W97>0,1,W97<=0,V97/U97) -> 0.20666667 | Y97: =X97*T97 -> 0.031 | AA97: LANDING PAGE | AB97: ='Action Plan'!P101 -> 0.125 | AC97: ='Action Plan'!Q101 -> 62500000 | AD97: ='Sale #3'!$E26 -> 15500000 | AE97: =AD97-AC97 -> -47000000 | AF97: =_xlfn.IFS(AE97>0,1,AE97<=0,AD97/AC97) -> 0.248 | AG97: =AF97*AB97 -> 0.031 | AI97: LANDING PAGE | AJ97: ='Action Plan'!T101 -> 0.1 | AK97: ='Action Plan'!U101 -> 50000000 | AL97: ='Sale #4'!$E26 -> 15500000 | AM97: =AL97-AK97 -> -34500000 | AN97: =_xlfn.IFS(AM97>0,1,AM97<=0,AL97/AK97) -> 0.31 | AO97: =AN97*AJ97 -> 0.031
C98: WEBSITE | D98: ='Action Plan'!D102 -> 0.1 | E98: ='Action Plan'!E102 -> 50000000 | F98: =N98+V98+AD98+AL98 -> 68200000 | G98: =F98-E98 -> 18200000 | H98: =_xlfn.IFS(G98>=0,1,G98<0,F98/E98) -> 1 | I98: =H98*D98 -> 0.1 | K98: WEBSITE | L98: ='Action Plan'!H102 -> 0.035 | M98: ='Action Plan'!I102 -> 17500000 | N98: ='Sale #1'!$E32 -> 17050000 | O98: =N98-M98 -> -450000 | P98: =_xlfn.IFS(O98>0,1,O98<=0,N98/M98) -> 0.97428571 | Q98: =P98*L98 -> 0.0341 | S98: WEBSITE | T98: ='Action Plan'!L102 -> 0.03 | U98: ='Action Plan'!M102 -> 15000000 | V98: ='Sale #2'!$E32 -> 17050000 | W98: =V98-U98 -> 2050000 | X98: =_xlfn.IFS(W98>0,1,W98<=0,V98/U98) -> 1 | Y98: =X98*T98 -> 0.03 | AA98: WEBSITE | AB98: ='Action Plan'!P102 -> 0.025 | AC98: ='Action Plan'!Q102 -> 12500000 | AD98: ='Sale #3'!$E32 -> 17050000 | AE98: =AD98-AC98 -> 4550000 | AF98: =_xlfn.IFS(AE98>0,1,AE98<=0,AD98/AC98) -> 1 | AG98: =AF98*AB98 -> 0.025 | AI98: WEBSITE | AJ98: ='Action Plan'!T102 -> 0.02 | AK98: ='Action Plan'!U102 -> 10000000 | AL98: ='Sale #4'!$E32 -> 17050000 | AM98: =AL98-AK98 -> 7050000 | AN98: =_xlfn.IFS(AM98>0,1,AM98<=0,AL98/AK98) -> 1 | AO98: =AN98*AJ98 -> 0.02
C99: TIKTOKSHOP | D99: ='Action Plan'!D103 -> 0.1 | E99: ='Action Plan'!E103 -> 50000000 | F99: =N99+V99+AD99+AL99 -> 62000000 | G99: =F99-E99 -> 12000000 | H99: =_xlfn.IFS(G99>=0,1,G99<0,F99/E99) -> 1 | I99: =H99*D99 -> 0.1 | K99: TIKTOKSHOP | L99: ='Action Plan'!H103 -> 0.035 | M99: ='Action Plan'!I103 -> 17500000 | N99: ='Sale #1'!$E35 -> 15500000 | O99: =N99-M99 -> -2000000 | P99: =_xlfn.IFS(O99>0,1,O99<=0,N99/M99) -> 0.88571429 | Q99: =P99*L99 -> 0.031 | S99: TIKTOKSHOP | T99: ='Action Plan'!L103 -> 0.03 | U99: ='Action Plan'!M103 -> 15000000 | V99: ='Sale #2'!$E35 -> 15500000 | W99: =V99-U99 -> 500000 | X99: =_xlfn.IFS(W99>0,1,W99<=0,V99/U99) -> 1 | Y99: =X99*T99 -> 0.03 | AA99: TIKTOKSHOP | AB99: ='Action Plan'!P103 -> 0.025 | AC99: ='Action Plan'!Q103 -> 12500000 | AD99: ='Sale #3'!$E35 -> 15500000 | AE99: =AD99-AC99 -> 3000000 | AF99: =_xlfn.IFS(AE99>0,1,AE99<=0,AD99/AC99) -> 1 | AG99: =AF99*AB99 -> 0.025 | AI99: TIKTOKSHOP | AJ99: ='Action Plan'!T103 -> 0.02 | AK99: ='Action Plan'!U103 -> 10000000 | AL99: ='Sale #4'!$E35 -> 15500000 | AM99: =AL99-AK99 -> 5500000 | AN99: =_xlfn.IFS(AM99>0,1,AM99<=0,AL99/AK99) -> 1 | AO99: =AN99*AJ99 -> 0.02
C100: SHOPPEE | D100: ='Action Plan'!D104 -> 0.1 | E100: ='Action Plan'!E104 -> 50000000 | F100: =N100+V100+AD100+AL100 -> 74400000 | G100: =F100-E100 -> 24400000 | H100: =_xlfn.IFS(G100>=0,1,G100<0,F100/E100) -> 1 | I100: =H100*D100 -> 0.1 | K100: SHOPPEE | L100: ='Action Plan'!H104 -> 0.035 | M100: ='Action Plan'!I104 -> 17500000 | N100: ='Sale #1'!$E36 -> 18600000 | O100: =N100-M100 -> 1100000 | P100: =_xlfn.IFS(O100>0,1,O100<=0,N100/M100) -> 1 | Q100: =P100*L100 -> 0.035 | S100: SHOPPEE | T100: ='Action Plan'!L104 -> 0.03 | U100: ='Action Plan'!M104 -> 15000000 | V100: ='Sale #2'!$E36 -> 18600000 | W100: =V100-U100 -> 3600000 | X100: =_xlfn.IFS(W100>0,1,W100<=0,V100/U100) -> 1 | Y100: =X100*T100 -> 0.03 | AA100: SHOPPEE | AB100: ='Action Plan'!P104 -> 0.025 | AC100: ='Action Plan'!Q104 -> 12500000 | AD100: ='Sale #3'!$E36 -> 18600000 | AE100: =AD100-AC100 -> 6100000 | AF100: =_xlfn.IFS(AE100>0,1,AE100<=0,AD100/AC100) -> 1 | AG100: =AF100*AB100 -> 0.025 | AI100: SHOPPEE | AJ100: ='Action Plan'!T104 -> 0.02 | AK100: ='Action Plan'!U104 -> 10000000 | AL100: ='Sale #4'!$E36 -> 18600000 | AM100: =AL100-AK100 -> 8600000 | AN100: =_xlfn.IFS(AM100>0,1,AM100<=0,AL100/AK100) -> 1 | AO100: =AN100*AJ100 -> 0.02
C101: ZALO | D101: ='Action Plan'!D105 -> 0.1 | E101: ='Action Plan'!E105 -> 50000000 | F101: =N101+V101+AD101+AL101 -> 37200000 | G101: =F101-E101 -> -12800000 | H101: =_xlfn.IFS(G101>=0,1,G101<0,F101/E101) -> 0.744 | I101: =H101*D101 -> 0.0744 | K101: ZALO | L101: ='Action Plan'!H105 -> 0.035 | M101: ='Action Plan'!I105 -> 17500000 | N101: ='Sale #1'!$E39 -> 9300000 | O101: =N101-M101 -> -8200000 | P101: =_xlfn.IFS(O101>0,1,O101<=0,N101/M101) -> 0.53142857 | Q101: =P101*L101 -> 0.0186 | S101: ZALO | T101: ='Action Plan'!L105 -> 0.03 | U101: ='Action Plan'!M105 -> 15000000 | V101: ='Sale #2'!$E39 -> 9300000 | W101: =V101-U101 -> -5700000 | X101: =_xlfn.IFS(W101>0,1,W101<=0,V101/U101) -> 0.62 | Y101: =X101*T101 -> 0.0186 | AA101: ZALO | AB101: ='Action Plan'!P105 -> 0.025 | AC101: ='Action Plan'!Q105 -> 12500000 | AD101: ='Sale #3'!$E39 -> 9300000 | AE101: =AD101-AC101 -> -3200000 | AF101: =_xlfn.IFS(AE101>0,1,AE101<=0,AD101/AC101) -> 0.744 | AG101: =AF101*AB101 -> 0.0186 | AI101: ZALO | AJ101: ='Action Plan'!T105 -> 0.02 | AK101: ='Action Plan'!U105 -> 10000000 | AL101: ='Sale #4'!$E39 -> 9300000 | AM101: =AL101-AK101 -> -700000 | AN101: =_xlfn.IFS(AM101>0,1,AM101<=0,AL101/AK101) -> 0.93 | AO101: =AN101*AJ101 -> 0.0186
C102: A/S RATIO | D102: ='Action Plan'!D106 -> 0.05 | E102: ='Action Plan'!E106 -> 0.37333333 | F102: =IF(SUM(F103:F108)>0,AVERAGEIF(F103:F108,">0"),0) -> 0.12111238 | G102: =E102-F102 -> 0.25222096 | H102: =AVERAGE(H103:H108) -> 0.95721212 | I102: =H102*D102 -> 0.047860606 | K102: A/S RATIO | L102: ='Action Plan'!H106 -> 0.35 | M102: ='Action Plan'!I106 -> 0.13066667 | N102: =IF(SUM(N103:N108)>0,AVERAGEIF(N103:N108,">0"),0) -> 0.038535756 | O102: =M102-N102 -> 0.09213091 | P102: =AVERAGE(P103:P108) -> 0.9696 | Q102: =P102*L102 -> 0.33936 | S102: A/S RATIO | T102: ='Action Plan'!L106 -> 0.3 | U102: =IF(SUM(U103:U108)>0,AVERAGEIF(U103:U108,">0"),0) -> 0.112 | V102: =IF(SUM(V103:V108)>0,AVERAGEIF(V103:V108,">0"),0) -> 0.033030648 | W102: =U102-V102 -> 0.078969352 | X102: =AVERAGE(X103:X108) -> 0.9696 | Y102: =X102*T102 -> 0.29088 | AA102: A/S RATIO | AB102: ='Action Plan'!P106 -> 0.25 | AC102: ='Action Plan'!Q106 -> 0.093333333 | AD102: =IF(SUM(AD103:AD108)>0,AVERAGEIF(AD103:AD108,">0"),0) -> 0.02752554 | AE102: =AC102-AD102 -> 0.065807793 | AF102: =AVERAGE(AF103:AF108) -> 0.9696 | AG102: =AF102*AB102 -> 0.2424 | AI102: A/S RATIO | AJ102: ='Action Plan'!T106 -> 0.2 | AK102: ='Action Plan'!U106 -> 0.074666667 | AL102: =IF(SUM(AL103:AL108)>0,AVERAGEIF(AL103:AL108,">0"),0) -> 0.022020432 | AM102: =AK102-AL102 -> 0.052646234 | AN102: =AVERAGE(AN103:AN108) -> 0.9696 | AO102: =AN102*AJ102 -> 0.19392
...

Sheet Digital Marketer #1
A1: KPIs TRACKING
A2: MONTH | B2: 4 | D2: 1. REPORT IN ORDER WITH LATEST DATE ON TOP. FILL IN BC IN ALL GREEN CELLS (AS ABOVE) 2. FINAL REPORT ON THE SAME DAY BEFORE 5:30 PM 3. ALL APPROVED EXPORT FILES MUST BE SAVED IN THE COMPANY ACCOUNT IN ACCORDANCE WITH THE FOLDER AND FILE NAMING INSTRUCTIONS AS FOLLOWS: HB MARKETING -> LOCATION + NAME -> BY DEPLOYMENT CONTENT -> FILE NAME: TITLE FILE
A3: YEAR | B3: 2025
A4: VND | B4: 1000000
J5: 45748 | K5: =J5+1 -> 45749 | L5: =K5+1 -> 45750 | M5: =L5+1 -> 45751 | N5: =M5+1 -> 45752 | O5: =N5+1 -> 45753 | P5: =O5+1 -> 45754 | Q5: =P5+1 -> 45755 | R5: =Q5+1 -> 45756 | ... AN5: =AM5+1 -> 45778
D6: ESTIMATED | E6: ACTUAL | F6: REMAINING | G6: RATIO | H6: KPIs | I6: TASKS COMPLETED | J6: =IF(WEEKDAY(J5)=1,"CN","T"&WEEKDAY(J5)) -> T3 | K6: =IF(WEEKDAY(K5)=1,"CN","T"&WEEKDAY(K5)) -> T4 | L6: =IF(WEEKDAY(L5)=1,"CN","T"&WEEKDAY(L5)) -> T5 | M6: =IF(WEEKDAY(M5)=1,"CN","T"&WEEKDAY(M5)) -> T6 | N6: =IF(WEEKDAY(N5)=1,"CN","T"&WEEKDAY(N5)) -> T7 | O6: =IF(WEEKDAY(O5)=1,"CN","T"&WEEKDAY(O5)) -> CN | P6: =IF(WEEKDAY(P5)=1,"CN","T"&WEEKDAY(P5)) -> T2 | Q6: =IF(WEEKDAY(Q5)=1,"CN","T"&WEEKDAY(Q5)) -> T3 | ... AN6: =IF(WEEKDAY(AN5)=1,"CN","T"&WEEKDAY(AN5)) -> T5
C7: BUDGET | D7: =Dashboard!E15 -> 170000000 | E7: =E8+'E-Com Operations'!E7 -> 45700000 | F7: =D7-E7 -> 124300000 | G7: =_xlfn.IFS(F7>0,1,F7<=0,D7/E7) -> 1 | H7: =D7/'Action Plan'!$C$6 -> 6538461.5 | I7: =SUMIF($J$5:$AN$5,TODAY(),J7:AN7) -> 0 | J7: =J8 -> 850000 | K7: =K8 -> 900000 | L7: =L8 -> 900000 | M7: =M8 -> 900000 | N7: =N8 -> 900000 | O7: =O8 -> 900000 | P7: =P8 -> 900000 | Q7: =Q8 -> 900000 | ... AN7: =AN8 -> 1100000
C8: BUDGET | D8: =D9+D15+D21+D24+D25+D27+D28+D26 -> 200000000 | E8: =E9+E15+E21+E24+E25+E27+E28+E26 -> 28900000 | F8: =F9+F15+F21+F24+F25+F27+F28+F26 -> 171100000 | G8: =_xlfn.IFS(F8>0,1,F8<=0,D8/E8) -> 1 | H8: =H9+H15+H21+H24+H25+H27+H28+H26 -> 7692307.7 | I8: =I9+I15+I21+I24+I25+I27+I28+I26 -> 0 | J8: =J9+J15+J21+J24+J25+J27+J28+J26 -> 850000 | K8: =K9+K15+K21+K24+K25+K27+K28+K26 -> 900000 | L8: =L9+L15+L21+L24+L25+L27+L28+L26 -> 900000 | M8: =M9+M15+M21+M24+M25+M27+M28+M26 -> 900000 | N8: =N9+N15+N21+N24+N25+N27+N28+N26 -> 900000 | O8: =O9+O15+O21+O24+O25+O27+O28+O26 -> 900000 | ... AN8: =AN9+AN15+AN21+AN24+AN25+AN27+AN28+AN26 -> 1100000
C9: =Dashboard!B16 -> FACEBOOK | D9: =Dashboard!E16*Dashboard!$P$8 -> 10000000 | E9: =SUM(E10:E14) -> 300000 | F9: =D9-E9 -> 9700000 | G9: =_xlfn.IFS(F9>0,1,F9<=0,D9/E9) -> 1 | H9: =D9/'Action Plan'!$C$6 -> 384615.38 | I9: =SUM(I10:I14) -> 0 | J9: =SUM(J10:J14) -> 0 | K9: =SUM(K10:K14) -> 0 | L9: =SUM(L10:L14) -> 0 | M9: =SUM(M10:M14) -> 0 | N9: =SUM(N10:N14) -> 0 | O9: =SUM(O10:O14) -> 0 | P9: =SUM(P10:P14) -> 0 | ... AN9: =SUM(AN10:AN14) -> 0
C10: VISION | D10: =$D$9/5 -> 2000000 | E10: =SUM(J10:AN10) -> 60000 | F10: =D10-E10 -> 1940000 | I10: =SUMIF($J$5:$AN$5,TODAY(),J10:AN10) -> 0 | AL10: 30000 | AM10: 30000 | AN10: 0
C11: BLACKHAIR | D11: =$D$9/5 -> 2000000 | E11: =SUM(J11:AN11) -> 60000 | F11: =D11-E11 -> 1940000 | I11: =SUMIF($J$5:$AN$5,TODAY(),J11:AN11) -> 0 | AL11: 30000 | AM11: 30000 | AN11: 0
C12: GLUTAWHITE | D12: =$D$9/5 -> 2000000 | E12: =SUM(J12:AN12) -> 60000 | F12: =D12-E12 -> 1940000 | I12: =SUMIF($J$5:$AN$5,TODAY(),J12:AN12) -> 0 | AL12: 30000 | AM12: 30000 | AN12: 0
C13: GLUTATHION | D13: =$D$9/5 -> 2000000 | E13: =SUM(J13:AN13) -> 60000 | F13: =D13-E13 -> 1940000 | I13: =SUMIF($J$5:$AN$5,TODAY(),J13:AN13) -> 0 | AL13: 30000 | AM13: 30000 | AN13: 0
C14: CORDY | D14: =$D$9/5 -> 2000000 | E14: =SUM(J14:AN14) -> 60000 | F14: =D14-E14 -> 1940000 | I14: =SUMIF($J$5:$AN$5,TODAY(),J14:AN14) -> 0 | AL14: 30000 | AM14: 30000 | AN14: 0
C15: =Dashboard!B17 -> LANDING PAGE | D15: =Dashboard!E17*Dashboard!$P$8 -> 60000000 | E15: =SUM(E16:E20) -> 15000000 | F15: =D15-E15 -> 45000000 | G15: =_xlfn.IFS(F15>0,1,F15<=0,D15/E15) -> 1 | H15: =D15/'Action Plan'!$C$6 -> 2307692.3 | I15: =SUM(I16:I20) -> 0 | J15: =SUM(J16:J20) -> 500000 | K15: =SUM(K16:K20) -> 500000 | L15: =SUM(L16:L20) -> 500000 | M15: =SUM(M16:M20) -> 500000 | N15: =SUM(N16:N20) -> 500000 | O15: =SUM(O16:O20) -> 500000 | P15: =SUM(P16:P20) -> 500000 | ... AN15: =SUM(AN16:AN20) -> 0
C16: VISION | D16: =$D$15/5 -> 12000000 | E16: =SUM(J16:AN16) -> 3000000 | F16: =D16-E16 -> 9000000 | I16: =SUMIF($J$5:$AN$5,TODAY(),J16:AN16) -> 0 | J16: 100000 | K16: 100000 | L16: 100000 | M16: 100000 | N16: 100000 | O16: 100000 | P16: 100000 | Q16: 100000 | R16: 100000 | S16: 100000 | T16: 100000 | U16: 100000 | V16: 100000 | W16: 100000 | X16: 100000 | Y16: 100000 | Z16: 100000 | AA16: 100000 | AB16: 100000 | AC16: 100000 | AD16: 100000 | AE16: 100000 | AF16: 100000 | AG16: 100000 | AH16: 100000 | AI16: 100000 | AJ16: 100000 | AK16: 100000 | AL16: 100000 | AM16: 100000 | AN16: 0
C17: BLACKHAIR | D17: =$D$15/5 -> 12000000 | E17: =SUM(J17:AN17) -> 3000000 | F17: =D17-E17 -> 9000000 | I17: =SUMIF($J$5:$AN$5,TODAY(),J17:AN17) -> 0 | J17: 100000 | K17: 100000 | L17: 100000 | M17: 100000 | N17: 100000 | O17: 100000 | P17: 100000 | Q17: 100000 | R17: 100000 | S17: 100000 | T17: 100000 | U17: 100000 | V17: 100000 | W17: 100000 | X17: 100000 | Y17: 100000 | Z17: 100000 | AA17: 100000 | AB17: 100000 | AC17: 100000 | AD17: 100000 | AE17: 100000 | AF17: 100000 | AG17: 100000 | AH17: 100000 | AI17: 100000 | AJ17: 100000 | AK17: 100000 | AL17: 100000 | AM17: 100000 | AN17: 0
C18: GLUTAWHITE | D18: =$D$15/5 -> 12000000 | E18: =SUM(J18:AN18) -> 3000000 | F18: =D18-E18 -> 9000000 | I18: =SUMIF($J$5:$AN$5,TODAY(),J18:AN18) -> 0 | J18: 100000 | K18: 100000 | L18: 100000 | M18: 100000 | N18: 100000 | O18: 100000 | P18: 100000 | Q18: 100000 | R18: 100000 | S18: 100000 | T18: 100000 | U18: 100000 | V18: 100000 | W18: 100000 | X18: 100000 | Y18: 100000 | Z18: 100000 | AA18: 100000 | AB18: 100000 | AC18: 100000 | AD18: 100000 | AE18: 100000 | AF18: 100000 | AG18: 100000 | AH18: 100000 | AI18: 100000 | AJ18: 100000 | AK18: 100000 | AL18: 100000 | AM18: 100000 | AN18: 0
C19: GLUTATHION | D19: =$D$15/5 -> 12000000 | E19: =SUM(J19:AN19) -> 3000000 | F19: =D19-E19 -> 9000000 | I19: =SUMIF($J$5:$AN$5,TODAY(),J19:AN19) -> 0 | J19: 100000 | K19: 100000 | L19: 100000 | M19: 100000 | N19: 100000 | O19: 100000 | P19: 100000 | Q19: 100000 | R19: 100000 | S19: 100000 | T19: 100000 | U19: 100000 | V19: 100000 | W19: 100000 | X19: 100000 | Y19: 100000 | Z19: 100000 | AA19: 100000 | AB19: 100000 | AC19: 100000 | AD19: 100000 | AE19: 100000 | AF19: 100000 | AG19: 100000 | AH19: 100000 | AI19: 100000 | AJ19: 100000 | AK19: 100000 | AL19: 100000 | AM19: 100000 | AN19: 0
C20: CORDY | D20: =$D$15/5 -> 12000000 | E20: =SUM(J20:AN20) -> 3000000 | F20: =D20-E20 -> 9000000 | I20: =SUMIF($J$5:$AN$5,TODAY(),J20:AN20) -> 0 | J20: 100000 | K20: 100000 | L20: 100000 | M20: 100000 | N20: 100000 | O20: 100000 | P20: 100000 | Q20: 100000 | R20: 100000 | S20: 100000 | T20: 100000 | U20: 100000 | V20: 100000 | W20: 100000 | X20: 100000 | Y20: 100000 | Z20: 100000 | AA20: 100000 | AB20: 100000 | AC20: 100000 | AD20: 100000 | AE20: 100000 | AF20: 100000 | AG20: 100000 | AH20: 100000 | AI20: 100000 | AJ20: 100000 | AK20: 100000 | AL20: 100000 | AM20: 100000 | AN20: 0
C21: =Dashboard!B18 -> WEBSITE | D21: =Dashboard!E18*Dashboard!$P$8 -> 10000000 | E21: =SUM(E22:E23) -> 3600000 | F21: =D21-E21 -> 6400000 | G21: =_xlfn.IFS(F21>0,1,F21<=0,D21/E21) -> 1 | H21: =D21/'Action Plan'!$C$6 -> 384615.38 | I21: =SUM(I22:I23) -> 0 | J21: =SUM(J22:J23) -> 100000 | K21: =SUM(K22:K23) -> 100000 | L21: =SUM(L22:L23) -> 100000 | M21: =SUM(M22:M23) -> 100000 | N21: =SUM(N22:N23) -> 100000 | O21: =SUM(O22:O23) -> 100000 | P21: =SUM(P22:P23) -> 100000 | ... AN21: =SUM(AN22:AN23) -> 600000
C22: HBPHARMA | D22: =$D$21/2 -> 5000000 | E22: =SUM(J22:AN22) -> 1800000 | F22: =D22-E22 -> 3200000 | H22: =D22/'Action Plan'!$C$6 -> 192307.69 | I22: =SUMIF($J$5:$AN$5,TODAY(),J22:AN22) -> 0 | J22: 50000 | K22: 50000 | L22: 50000 | M22: 50000 | N22: 50000 | O22: 50000 | P22: 50000 | Q22: 50000 | R22: 50000 | S22: 50000 | T22: 50000 | U22: 50000 | V22: 50000 | W22: 50000 | X22: 50000 | Y22: 50000 | Z22: 50000 | AA22: 50000 | AB22: 50000 | AC22: 50000 | AD22: 50000 | AE22: 50000 | AF22: 50000 | AG22: 50000 | AH22: 50000 | AI22: 50000 | AJ22: 50000 | AK22: 50000 | AL22: 50000 | AM22: 50000 | AN22: 300000
C23: HOTLINE | D23: =$D$21/2 -> 5000000 | E23: =SUM(J23:AN23) -> 1800000 | F23: =D23-E23 -> 3200000 | H23: =D23/'Action Plan'!$C$6 -> 192307.69 | I23: =SUMIF($J$5:$AN$5,TODAY(),J23:AN23) -> 0 | J23: 50000 | K23: 50000 | L23: 50000 | M23: 50000 | N23: 50000 | O23: 50000 | P23: 50000 | Q23: 50000 | R23: 50000 | S23: 50000 | T23: 50000 | U23: 50000 | V23: 50000 | W23: 50000 | X23: 50000 | Y23: 50000 | Z23: 50000 | AA23: 50000 | AB23: 50000 | AC23: 50000 | AD23: 50000 | AE23: 50000 | AF23: 50000 | AG23: 50000 | AH23: 50000 | AI23: 50000 | AJ23: 50000 | AK23: 50000 | AL23: 50000 | AM23: 50000 | AN23: 300000
C24: =Dashboard!B19 -> TIKTOK SHOP | D24: =Dashboard!E19*Dashboard!$P$8 -> 20000000 | E24: =SUM(J24:AN24) -> 1200000 | F24: =D24-E24 -> 18800000 | G24: =_xlfn.IFS(F24>0,1,F24<=0,D24/E24) -> 1 | H24: =D24/'Action Plan'!$C$6 -> 769230.77 | I24: =SUMIF($J$5:$AN$5,TODAY(),J24:AN24) -> 0 | J24: 0 | K24: 0 | L24: 0 | M24: 0 | N24: 0 | O24: 0 | P24: 0 | Q24: 0 | R24: 0 | S24: 0 | T24: 0 | U24: 0 | V24: 0 | W24: 0 | X24: 0 | Y24: 0 | Z24: 0 | AA24: 0 | AB24: 0 | AC24: 0 | AD24: 0 | AE24: 0 | AF24: 0 | AG24: 0 | AH24: 0 | AI24: 200000 | AJ24: 200000 | AK24: 200000 | AL24: 200000 | AM24: 200000 | AN24: 200000
C25: =Dashboard!B20 -> SHOPEE | D25: =Dashboard!E20*Dashboard!$P$8 -> 10000000 | E25: =SUM(J25:AN25) -> 0 | F25: =D25-E25 -> 10000000 | G25: =_xlfn.IFS(F25>0,1,F25<=0,D25/E25) -> 1 | H25: =D25/'Action Plan'!$C$6 -> 384615.38 | I25: =SUMIF($J$5:$AN$5,TODAY(),J25:AN25) -> 0 | J25: 0 | K25: 0 | L25: 0 | M25: 0 | N25: 0 | O25: 0 | P25: 0 | Q25: 0 | R25: 0 | S25: 0 | T25: 0 | U25: 0 | V25: 0 | W25: 0 | X25: 0 | Y25: 0 | Z25: 0 | AA25: 0 | AB25: 0 | AC25: 0 | AD25: 0 | AE25: 0 | AF25: 0 | AG25: 0 | AH25: 0 | AI25: 0 | AJ25: 0 | AK25: 0 | AL25: 0 | AM25: 0 | AN25: 0
C26: =Dashboard!B21 -> ZALO | D26: =Dashboard!E21*Dashboard!$P$8 -> 40000000 | E26: =SUM(J26:AN26) -> 2650000 | F26: =D26-E26 -> 37350000 | G26: =_xlfn.IFS(F26>0,1,F26<=0,D26/E26) -> 1 | H26: =D26/'Action Plan'!$C$6 -> 1538461.5 | I26: =SUMIF($J$5:$AN$5,TODAY(),J26:AN26) -> 0 | J26: 100000 | K26: 100000 | L26: 100000 | M26: 100000 | N26: 100000 | O26: 100000 | P26: 100000 | Q26: 100000 | R26: 100000 | S26: 100000 | T26: 100000 | U26: 100000 | V26: 100000 | W26: 100000 | X26: 100000 | Y26: 100000 | Z26: 100000 | AA26: 100000 | AB26: 100000 | AC26: 100000 | AD26: 100000 | AE26: 100000 | AF26: 100000 | AG26: 100000 | AH26: 100000 | AI26: 10000 | AJ26: 10000 | AK26: 10000 | AL26: 10000 | AM26: 10000 | AN26: 100000
C27: =Dashboard!B22 -> BOOKING | D27: =Dashboard!E21*Dashboard!$P$8 -> 40000000 | E27: =SUM(J27:AN27) -> 3150000 | F27: =D27-E27 -> 36850000 | G27: =_xlfn.IFS(F27>0,1,F27<=0,D27/E27) -> 1 | H27: =D27/'Action Plan'!$C$6 -> 1538461.5 | I27: =SUMIF($J$5:$AN$5,TODAY(),J27:AN27) -> 0 | J27: 150000 | K27: 100000 | L27: 100000 | M27: 100000 | N27: 100000 | O27: 100000 | P27: 100000 | Q27: 100000 | R27: 100000 | S27: 100000 | T27: 100000 | U27: 100000 | V27: 100000 | W27: 100000 | X27: 100000 | Y27: 100000 | Z27: 100000 | AA27: 100000 | AB27: 100000 | AC27: 100000 | AD27: 100000 | AE27: 100000 | AF27: 100000 | AG27: 100000 | AH27: 100000 | AI27: 100000 | AJ27: 100000 | AK27: 100000 | AL27: 100000 | AM27: 100000 | AN27: 100000
C28: =Dashboard!B23 -> BRANDING | D28: =Dashboard!E22*Dashboard!$P$8 -> 10000000 | E28: =SUM(J28:AN28) -> 3000000 | F28: =D28-E28 -> 7000000 | G28: =_xlfn.IFS(F28>0,1,F28<=0,D28/E28) -> 1 | H28: =D28/'Action Plan'!$C$6 -> 384615.38 | I28: =SUMIF($J$5:$AN$5,TODAY(),J28:AN28) -> 0 | J28: 0 | K28: 100000 | L28: 100000 | M28: 100000 | N28: 100000 | O28: 100000 | P28: 100000 | Q28: 100000 | R28: 100000 | S28: 100000 | T28: 100000 | U28: 100000 | V28: 100000 | W28: 100000 | X28: 100000 | Y28: 100000 | Z28: 100000 | AA28: 100000 | AB28: 100000 | AC28: 100000 | AD28: 100000 | AE28: 100000 | AF28: 100000 | AG28: 100000 | AH28: 100000 | AI28: 100000 | AJ28: 100000 | AK28: 100000 | AL28: 100000 | AM28: 100000 | AN28: 100000
C29: =Dashboard!K52 -> P2
C30: DATA | D30: =Dashboard!E53 -> 1680 | E30: =Dashboard!F53 -> 1528 | F30: =E30-D30 -> -152 | G30: =_xlfn.IFS(F30>0,1,F30<0,E30/D30,F30=0,0) -> 0.90952381 | H30: =D30/'Action Plan'!$C$6 -> 64.615385 | I30: =SUMIF($J$5:$AN$5,TODAY(),J30:AN30) -> 0 | J30: =J31 -> 36 | K30: =K31 -> 36 | L30: =L31 -> 36 | M30: =M31 -> 36 | N30: =N31 -> 36 | O30: =O31 -> 36 | P30: =P31 -> 36 | Q30: =Q31 -> 36 | ... AN30: =AN31 -> 45
C31: =Dashboard!K53 -> DATA | D31: =Dashboard!M53 -> 1000 | E31: =SUM(E32:E37) -> 1125 | F31: =E31-D31 -> 125 | G31: =_xlfn.IFS(F31>0,1,F31<0,E31/D31,F31=0,0) -> 1 | H31: =D31/'Action Plan'!$C$6 -> 38.461538 | I31: =SUM(I32:I37) -> 0 | J31: =SUM(J32:J37) -> 36 | K31: =SUM(K32:K37) -> 36 | L31: =SUM(L32:L37) -> 36 | M31: =SUM(M32:M37) -> 36 | N31: =SUM(N32:N37) -> 36 | O31: =SUM(O32:O37) -> 36 | P31: =SUM(P32:P37) -> 36 | ... AN31: =SUM(AN32:AN37) -> 45
C32: =Dashboard!K54 -> FACEBOOK | D32: =Dashboard!M54 -> 400 | E32: =SUM(J32:AN32) -> 310 | F32: =E32-D32 -> -90 | G32: =_xlfn.IFS(F32>0,1,F32<0,E32/D32,F32=0,0) -> 0.775 | H32: =D32/'Action Plan'!$C$6 -> 15.384615 | I32: =SUMIF($J$5:$AN$5,TODAY(),J32:AN32) -> 0 | J32: 10 | K32: 10 | L32: 10 | M32: 10 | N32: 10 | O32: 10 | P32: 10 | Q32: 10 | R32: 10 | S32: 10 | T32: 10 | U32: 10 | V32: 10 | W32: 10 | X32: 10 | Y32: 10 | Z32: 10 | AA32: 10 | AB32: 10 | AC32: 10 | AD32: 10 | AE32: 10 | AF32: 10 | AG32: 10 | AH32: 10 | AI32: 10 | AJ32: 10 | AK32: 10 | AL32: 10 | AM32: 10 | AN32: 10
C33: =Dashboard!K55 -> LANDING PAGE | D33: =Dashboard!M55 -> 300 | E33: =SUM(J33:AN33) -> 310 | F33: =E33-D33 -> 10 | G33: =_xlfn.IFS(F33>0,1,F33<0,E33/D33,F33=0,0) -> 1 | H33: =D33/'Action Plan'!$C$6 -> 11.538462 | I33: =SUMIF($J$5:$AN$5,TODAY(),J33:AN33) -> 0 | J33: 10 | K33: 10 | L33: 10 | M33: 10 | N33: 10 | O33: 10 | P33: 10 | Q33: 10 | R33: 10 | S33: 10 | T33: 10 | U33: 10 | V33: 10 | W33: 10 | X33: 10 | Y33: 10 | Z33: 10 | AA33: 10 | AB33: 10 | AC33: 10 | AD33: 10 | AE33: 10 | AF33: 10 | AG33: 10 | AH33: 10 | AI33: 10 | AJ33: 10 | AK33: 10 | AL33: 10 | AM33: 10 | AN33: 10
C34: =Dashboard!K56 -> WEBSITE | D34: =Dashboard!M56 -> 100 | E34: =SUM(J34:AN34) -> 40 | F34: =E34-D34 -> -60 | G34: =_xlfn.IFS(F34>0,1,F34<0,E34/D34,F34=0,0) -> 0.4 | H34: =D34/'Action Plan'!$C$6 -> 3.8461538 | I34: =SUMIF($J$5:$AN$5,TODAY(),J34:AN34) -> 0 | J34: 1 | K34: 1 | L34: 1 | M34: 1 | N34: 1 | O34: 1 | P34: 1 | Q34: 1 | R34: 1 | S34: 1 | T34: 1 | U34: 1 | V34: 1 | W34: 1 | X34: 1 | Y34: 1 | Z34: 1 | AA34: 1 | AB34: 1 | AC34: 1 | AD34: 1 | AE34: 1 | AF34: 1 | AG34: 1 | AH34: 1 | AI34: 1 | AJ34: 1 | AK34: 1 | AL34: 1 | AM34: 1 | AN34: 10
C35: =Dashboard!K57 -> TIKTOKSHOP | D35: =Dashboard!M57 -> 50 | E35: =SUM(J35:AN35) -> 155 | F35: =E35-D35 -> 105 | G35: =_xlfn.IFS(F35>0,1,F35<0,E35/D35,F35=0,0) -> 1 | H35: =D35/'Action Plan'!$C$6 -> 1.9230769 | I35: =SUMIF($J$5:$AN$5,TODAY(),J35:AN35) -> 0 | J35: 5 | K35: 5 | L35: 5 | M35: 5 | N35: 5 | O35: 5 | P35: 5 | Q35: 5 | R35: 5 | S35: 5 | T35: 5 | U35: 5 | V35: 5 | W35: 5 | X35: 5 | Y35: 5 | Z35: 5 | AA35: 5 | AB35: 5 | AC35: 5 | AD35: 5 | AE35: 5 | AF35: 5 | AG35: 5 | AH35: 5 | AI35: 5 | AJ35: 5 | AK35: 5 | AL35: 5 | AM35: 5 | AN35: 5
C36: =Dashboard!K58 -> SHOPPEE | D36: =Dashboard!M58 -> 50 | E36: =SUM(J36:AN36) -> 155 | F36: =E36-D36 -> 105 | G36: =_xlfn.IFS(F36>0,1,F36<0,E36/D36,F36=0,0) -> 1 | H36: =D36/'Action Plan'!$C$6 -> 1.9230769 | I36: =SUMIF($J$5:$AN$5,TODAY(),J36:AN36) -> 0 | J36: 5 | K36: 5 | L36: 5 | M36: 5 | N36: 5 | O36: 5 | P36: 5 | Q36: 5 | R36: 5 | S36: 5 | T36: 5 | U36: 5 | V36: 5 | W36: 5 | X36: 5 | Y36: 5 | Z36: 5 | AA36: 5 | AB36: 5 | AC36: 5 | AD36: 5 | AE36: 5 | AF36: 5 | AG36: 5 | AH36: 5 | AI36: 5 | AJ36: 5 | AK36: 5 | AL36: 5 | AM36: 5 | AN36: 5
C37: =Dashboard!K59 -> ZALO | D37: =Dashboard!M59 -> 100 | E37: =SUM(J37:AN37) -> 155 | F37: =E37-D37 -> 55 | G37: =_xlfn.IFS(F37>0,1,F37<0,E37/D37,F37=0,0) -> 1 | H37: =D37/'Action Plan'!$C$6 -> 3.8461538 | I37: =SUMIF($J$5:$AN$5,TODAY(),J37:AN37) -> 0 | J37: 5 | K37: 5 | L37: 5 | M37: 5 | N37: 5 | O37: 5 | P37: 5 | Q37: 5 | R37: 5 | S37: 5 | T37: 5 | U37: 5 | V37: 5 | W37: 5 | X37: 5 | Y37: 5 | Z37: 5 | AA37: 5 | AB37: 5 | AC37: 5 | AD37: 5 | AE37: 5 | AF37: 5 | AG37: 5 | AH37: 5 | AI37: 5 | AJ37: 5 | AK37: 5 | AL37: 5 | AM37: 5 | AN37: 5
C38: ADS | D38: =Dashboard!E60 -> 70 | E38: =Dashboard!F60 -> 188 | F38: =E38-D38 -> 118 | G38: =_xlfn.IFS(F38>0,1,F38<=0,E38/D38) -> 1 | H38: =D38/'Action Plan'!$C$6 -> 2.6923077 | I38: =SUMIF($J$5:$AN$5,TODAY(),J38:AN38) -> 0 | J38: =J39 -> 5 | K38: =K39 -> 5 | L38: =L39 -> 5 | M38: =M39 -> 5 | N38: =N39 -> 5 | O38: =O39 -> 5 | P38: =P39 -> 5 | Q38: =Q39 -> 5 | ... AN38: =AN39 -> 6
C39: =Dashboard!K60 -> ADS | D39: =Dashboard!M60 -> 30 | E39: =SUM(E40:E45) -> 156 | F39: =E39-D39 -> 126 | G39: =_xlfn.IFS(F39>0,1,F39<=0,E39/D39) -> 1 | H39: =D39/'Action Plan'!$C$6 -> 1.1538462 | I39: =SUM(I40:I45) -> 0 | J39: =SUM(J40:J45) -> 5 | K39: =SUM(K40:K45) -> 5 | L39: =SUM(L40:L45) -> 5 | M39: =SUM(M40:M45) -> 5 | N39: =SUM(N40:N45) -> 5 | O39: =SUM(O40:O45) -> 5 | P39: =SUM(P40:P45) -> 5 | ... AN39: =SUM(AN40:AN45) -> 6
C40: =Dashboard!K61 -> FACEBOOK | D40: =Dashboard!M61 -> 10 | E40: =SUM(J40:AN40) -> 62 | F40: =E40-D40 -> 52 | G40: =_xlfn.IFS(F40>0,1,F40<0,E40/D40,F40=0,0) -> 1 | H40: =D40/'Action Plan'!$C$6 -> 0.38461538 | I40: =SUMIF($J$5:$AN$5,TODAY(),J40:AN40) -> 0 | J40: 2 | K40: 2 | L40: 2 | M40: 2 | N40: 2 | O40: 2 | P40: 2 | Q40: 2 | R40: 2 | S40: 2 | T40: 2 | U40: 2 | V40: 2 | W40: 2 | X40: 2 | Y40: 2 | Z40: 2 | AA40: 2 | AB40: 2 | AC40: 2 | AD40: 2 | AE40: 2 | AF40: 2 | AG40: 2 | AH40: 2 | AI40: 2 | AJ40: 2 | AK40: 2 | AL40: 2 | AM40: 2 | AN40: 2
C41: =Dashboard!K62 -> LANDING PAGE | D41: =Dashboard!M62 -> 10 | E41: =SUM(J41:AN41) -> 62 | F41: =E41-D41 -> 52 | G41: =_xlfn.IFS(F41>0,1,F41<0,E41/D41,F41=0,0) -> 1 | H41: =D41/'Action Plan'!$C$6 -> 0.38461538 | I41: =SUMIF($J$5:$AN$5,TODAY(),J41:AN41) -> 0 | J41: 2 | K41: 2 | L41: 2 | M41: 2 | N41: 2 | O41: 2 | P41: 2 | Q41: 2 | R41: 2 | S41: 2 | T41: 2 | U41: 2 | V41: 2 | W41: 2 | X41: 2 | Y41: 2 | Z41: 2 | AA41: 2 | AB41: 2 | AC41: 2 | AD41: 2 | AE41: 2 | AF41: 2 | AG41: 2 | AH41: 2 | AI41: 2 | AJ41: 2 | AK41: 2 | AL41: 2 | AM41: 2 | AN41: 2
C42: =Dashboard!K63 -> WEBSITE | D42: =Dashboard!M63 -> 5 | E42: =SUM(J42:AN42) -> 1 | F42: =E42-D42 -> -4 | G42: =_xlfn.IFS(F42>0,1,F42<0,E42/D42,F42=0,0) -> 0.2 | H42: =D42/'Action Plan'!$C$6 -> 0.19230769 | I42: =SUMIF($J$5:$AN$5,TODAY(),J42:AN42) -> 0 | J42: 0 | K42: 0 | L42: 0 | M42: 0 | N42: 0 | O42: 0 | P42: 0 | Q42: 0 | R42: 0 | S42: 0 | T42: 0 | U42: 0 | V42: 0 | W42: 0 | X42: 0 | Y42: 0 | Z42: 0 | AA42: 0 | AB42: 0 | AC42: 0 | AD42: 0 | AE42: 0 | AF42: 0 | AG42: 0 | AH42: 0 | AI42: 0 | AJ42: 0 | AK42: 0 | AL42: 0 | AM42: 0 | AN42: 1
C43: =Dashboard!K64 -> TIKTOKSHOP | D43: =Dashboard!M64 -> 0 | E43: =SUM(J43:AN43) -> 0 | F43: =E43-D43 -> 0 | G43: =_xlfn.IFS(F43>0,1,F43<0,E43/D43,F43=0,0) -> 0 | H43: =D43/'Action Plan'!$C$6 -> 0 | I43: =SUMIF($J$5:$AN$5,TODAY(),J43:AN43) -> 0 | J43: 0 | K43: 0 | L43: 0 | M43: 0 | N43: 0 | O43: 0 | P43: 0 | Q43: 0 | R43: 0 | S43: 0 | T43: 0 | U43: 0 | V43: 0 | W43: 0 | X43: 0 | Y43: 0 | Z43: 0 | AA43: 0 | AB43: 0 | AC43: 0 | AD43: 0 | AE43: 0 | AF43: 0 | AG43: 0 | AH43: 0 | AI43: 0 | AJ43: 0 | AK43: 0 | AL43: 0 | AM43: 0 | AN43: 0
C44: =Dashboard!K65 -> SHOPPEE | D44: =Dashboard!M65 -> 0 | E44: =SUM(J44:AN44) -> 0 | F44: =E44-D44 -> 0 | G44: =_xlfn.IFS(F44>0,1,F44<0,E44/D44,F44=0,0) -> 0 | H44: =D44/'Action Plan'!$C$6 -> 0 | I44: =SUMIF($J$5:$AN$5,TODAY(),J44:AN44) -> 0 | J44: 0 | K44: 0 | L44: 0 | M44: 0 | N44: 0 | O44: 0 | P44: 0 | Q44: 0 | R44: 0 | S44: 0 | T44: 0 | U44: 0 | V44: 0 | W44: 0 | X44: 0 | Y44: 0 | Z44: 0 | AA44: 0 | AB44: 0 | AC44: 0 | AD44: 0 | AE44: 0 | AF44: 0 | AG44: 0 | AH44: 0 | AI44: 0 | AJ44: 0 | AK44: 0 | AL44: 0 | AM44: 0 | AN44: 0
C45: =Dashboard!K66 -> ZALO | D45: =Dashboard!M66 -> 5 | E45: =SUM(J45:AN45) -> 31 | F45: =E45-D45 -> 26 | G45: =_xlfn.IFS(F45>0,1,F45<0,E45/D45,F45=0,0) -> 1 | H45: =D45/'Action Plan'!$C$6 -> 0.19230769 | I45: =SUMIF($J$5:$AN$5,TODAY(),J45:AN45) -> 0 | J45: 1 | K45: 1 | L45: 1 | M45: 1 | N45: 1 | O45: 1 | P45: 1 | Q45: 1 | R45: 1 | S45: 1 | T45: 1 | U45: 1 | V45: 1 | W45: 1 | X45: 1 | Y45: 1 | Z45: 1 | AA45: 1 | AB45: 1 | AC45: 1 | AD45: 1 | AE45: 1 | AF45: 1 | AG45: 1 | AH45: 1 | AI45: 1 | AJ45: 1 | AK45: 1 | AL45: 1 | AM45: 1 | AN45: 1
C46: =Dashboard!K67 -> P3
C47: SALES | D47: =Dashboard!E68 -> 500000000 | E47: =Dashboard!F68 -> 373050000 | F47: =E47-D47 -> -126950000 | G47: =_xlfn.IFS(F47>0,1,F47<=0,E47/D47) -> 0.7461 | H47: =D47/'Action Plan'!$C$6 -> 19230769 | I47: =SUMIF($J$5:$AN$5,TODAY(),J47:AN47) -> 0 | J47: =J48 -> 1750000 | K47: =K48 -> 1750000 | L47: =L48 -> 1750000 | M47: =M48 -> 1750000 | N47: =N48 -> 1750000 | O47: =O48 -> 1750000 | P47: =P48 -> 1750000 | Q47: =Q48 -> 1750000 | ... AN47: =AN48 -> 550000
C48: =Dashboard!K68 -> SALES REVENUE | D48: =Dashboard!M68 -> 250000000 | E48: =SUM(E49:E54) -> 53050000 | F48: =E48-D48 -> -196950000 | G48: =_xlfn.IFS(F48>0,1,F48<=0,E48/D48) -> 0.2122 | H48: =D48/'Action Plan'!$C$6 -> 9615384.6 | I48: =SUM(I49:I54) -> 0 | J48: =SUM(J49:J54) -> 1750000 | K48: =SUM(K49:K54) -> 1750000 | L48: =SUM(L49:L54) -> 1750000 | M48: =SUM(M49:M54) -> 1750000 | N48: =SUM(N49:N54) -> 1750000 | O48: =SUM(O49:O54) -> 1750000 | P48: =SUM(P49:P54) -> 1750000 | ... AN48: =SUM(AN49:AN54) -> 550000
C49: =Dashboard!K69 -> FACEBOOK | D49: =Dashboard!M69 -> 25000000 | E49: =SUM(J49:AN49) -> 15100000 | F49: =E49-D49 -> -9900000 | G49: =_xlfn.IFS(F49>0,1,F49<=0,E49/D49) -> 0.604 | H49: =D49/'Action Plan'!$C$6 -> 961538.46 | I49: =SUMIF($J$5:$AN$5,TODAY(),J49:AN49) -> 0 | J49: 500000 | K49: 500000 | L49: 500000 | M49: 500000 | N49: 500000 | O49: 500000 | P49: 500000 | Q49: 500000 | R49: 500000 | S49: 500000 | T49: 500000 | U49: 500000 | V49: 500000 | W49: 500000 | X49: 500000 | Y49: 500000 | Z49: 500000 | AA49: 500000 | AB49: 500000 | AC49: 500000 | AD49: 500000 | AE49: 500000 | AF49: 500000 | AG49: 500000 | AH49: 500000 | AI49: 500000 | AJ49: 500000 | AK49: 500000 | AL49: 500000 | AM49: 500000 | AN49: 100000
C50: =Dashboard!K70 -> LANDING PAGE | D50: =Dashboard!M70 -> 125000000 | E50: =SUM(J50:AN50) -> 15100000 | F50: =E50-D50 -> -109900000 | G50: =_xlfn.IFS(F50>0,1,F50<=0,E50/D50) -> 0.1208 | H50: =D50/'Action Plan'!$C$6 -> 4807692.3 | I50: =SUMIF($J$5:$AN$5,TODAY(),J50:AN50) -> 0 | J50: 500000 | K50: 500000 | L50: 500000 | M50: 500000 | N50: 500000 | O50: 500000 | P50: 500000 | Q50: 500000 | R50: 500000 | S50: 500000 | T50: 500000 | U50: 500000 | V50: 500000 | W50: 500000 | X50: 500000 | Y50: 500000 | Z50: 500000 | AA50: 500000 | AB50: 500000 | AC50: 500000 | AD50: 500000 | AE50: 500000 | AF50: 500000 | AG50: 500000 | AH50: 500000 | AI50: 500000 | AJ50: 500000 | AK50: 500000 | AL50: 500000 | AM50: 500000 | AN50: 100000
C51: =Dashboard!K71 -> WEBSITE | D51: =Dashboard!M71 -> 25000000 | E51: =SUM(J51:AN51) -> 15100000 | F51: =E51-D51 -> -9900000 | G51: =_xlfn.IFS(F51>0,1,F51<=0,E51/D51) -> 0.604 | H51: =D51/'Action Plan'!$C$6 -> 961538.46 | I51: =SUMIF($J$5:$AN$5,TODAY(),J51:AN51) -> 0 | J51: 500000 | K51: 500000 | L51: 500000 | M51: 500000 | N51: 500000 | O51: 500000 | P51: 500000 | Q51: 500000 | R51: 500000 | S51: 500000 | T51: 500000 | U51: 500000 | V51: 500000 | W51: 500000 | X51: 500000 | Y51: 500000 | Z51: 500000 | AA51: 500000 | AB51: 500000 | AC51: 500000 | AD51: 500000 | AE51: 500000 | AF51: 500000 | AG51: 500000 | AH51: 500000 | AI51: 500000 | AJ51: 500000 | AK51: 500000 | AL51: 500000 | AM51: 500000 | AN51: 100000
C52: =Dashboard!K72 -> TIKTOKSHOP | D52: =Dashboard!M72 -> 25000000 | E52: =SUM(J52:AN52) -> 1600000 | F52: =E52-D52 -> -23400000 | G52: =_xlfn.IFS(F52>0,1,F52<=0,E52/D52) -> 0.064 | H52: =D52/'Action Plan'!$C$6 -> 961538.46 | I52: =SUMIF($J$5:$AN$5,TODAY(),J52:AN52) -> 0 | J52: 50000 | K52: 50000 | L52: 50000 | M52: 50000 | N52: 50000 | O52: 50000 | P52: 50000 | Q52: 50000 | R52: 50000 | S52: 50000 | T52: 50000 | U52: 50000 | V52: 50000 | W52: 50000 | X52: 50000 | Y52: 50000 | Z52: 50000 | AA52: 50000 | AB52: 50000 | AC52: 50000 | AD52: 50000 | AE52: 50000 | AF52: 50000 | AG52: 50000 | AH52: 50000 | AI52: 50000 | AJ52: 50000 | AK52: 50000 | AL52: 50000 | AM52: 50000 | AN52: 100000
C53: =Dashboard!K73 -> SHOPPEE | D53: =Dashboard!M73 -> 25000000 | E53: =SUM(J53:AN53) -> 3100000 | F53: =E53-D53 -> -21900000 | G53: =_xlfn.IFS(F53>0,1,F53<=0,E53/D53) -> 0.124 | H53: =D53/'Action Plan'!$C$6 -> 961538.46 | I53: =SUMIF($J$5:$AN$5,TODAY(),J53:AN53) -> 0 | J53: 100000 | K53: 100000 | L53: 100000 | M53: 100000 | N53: 100000 | O53: 100000 | P53: 100000 | Q53: 100000 | R53: 100000 | S53: 100000 | T53: 100000 | U53: 100000 | V53: 100000 | W53: 100000 | X53: 100000 | Y53: 100000 | Z53: 100000 | AA53: 100000 | AB53: 100000 | AC53: 100000 | AD53: 100000 | AE53: 100000 | AF53: 100000 | AG53: 100000 | AH53: 100000 | AI53: 100000 | AJ53: 100000 | AK53: 100000 | AL53: 100000 | AM53: 100000 | AN53: 100000
C54: =Dashboard!K74 -> ZALO | D54: =Dashboard!M74 -> 25000000 | E54: =SUM(J54:AN54) -> 3050000 | F54: =E54-D54 -> -21950000 | G54: =_xlfn.IFS(F54>0,1,F54<=0,E54/D54) -> 0.122 | H54: =D54/'Action Plan'!$C$6 -> 961538.46 | I54: =SUMIF($J$5:$AN$5,TODAY(),J54:AN54) -> 0 | J54: 100000 | K54: 100000 | L54: 100000 | M54: 100000 | N54: 100000 | O54: 100000 | P54: 100000 | Q54: 100000 | R54: 100000 | S54: 100000 | T54: 100000 | U54: 100000 | V54: 100000 | W54: 100000 | X54: 100000 | Y54: 100000 | Z54: 100000 | AA54: 100000 | AB54: 100000 | AC54: 100000 | AD54: 100000 | AE54: 100000 | AF54: 100000 | AG54: 100000 | AH54: 100000 | AI54: 100000 | AJ54: 100000 | AK54: 100000 | AL54: 100000 | AM54: 100000 | AN54: 50000
B55: HIGHER = BAD | C55: =Dashboard!K75 -> A/S RATIO | D55: =Dashboard!M75 -> 0.18666667 | E55: =AVERAGE(E56:E61) -> 18.35 | F55: =D55-E55 -> -18.163333 | G55: =_xlfn.IFS(F55>0,1,F55<=0,D55/E55) -> 0.01017257 | H55: =D55/'Action Plan'!$C$6 -> 0.0071794872 | I55: =AVERAGE(I56:I61) -> 0 | J55: =SUM(J56:J61) -> 3 | K55: =SUM(K56:K61) -> 3 | L55: =SUM(L56:L61) -> 3 | M55: =SUM(M56:M61) -> 3 | N55: =SUM(N56:N61) -> 3 | O55: =SUM(O56:O61) -> 3 | P55: =SUM(P56:P61) -> 3 | Q55: =SUM(Q56:Q61) -> 3 | ... AN55: =SUM(AN56:AN61) -> 4
C56: =Dashboard!K76 -> FACEBOOK | D56: =Dashboard!M76 -> 0.1 | E56: =SUM(J56:AN56) -> 0.6 | F56: =D56-E56 -> -0.5 | G56: =_xlfn.IFS(F56>0,1,F56<=0,D56/E56) -> 0.16666667 | H56: =D56/'Action Plan'!$C$6 -> 0.0038461538 | I56: =SUMIF($J$5:$AN$5,TODAY(),J56:AN56) -> 0 | J56: =_xlfn.IFS(J49<=0,0,J49>0,J9/J49) -> 0 | K56: =_xlfn.IFS(K49<=0,0,K49>0,K9/K49) -> 0 | L56: =_xlfn.IFS(L49<=0,0,L49>0,L9/L49) -> 0 | M56: =_xlfn.IFS(M49<=0,0,M49>0,M9/M49) -> 0 | N56: =_xlfn.IFS(N49<=0,0,N49>0,N9/N49) -> 0 | O56: =_xlfn.IFS(O49<=0,0,O49>0,O9/O49) -> 0 | P56: =_xlfn.IFS(P49<=0,0,P49>0,P9/P49) -> 0 | Q56: =_xlfn.IFS(Q49<=0,0,Q49>0,Q9/Q49) -> 0 | ... AN56: =_xlfn.IFS(AN49<=0,0,AN49>0,AN9/AN49) -> 0
C57: =Dashboard!K77 -> LANDING PAGE | D57: =Dashboard!M77 -> 0.12 | E57: =SUM(J57:AN57) -> 30 | F57: =D57-E57 -> -29.88 | G57: =_xlfn.IFS(F57>0,1,F57<=0,D57/E57) -> 0.004 | H57: =D57/'Action Plan'!$C$6 -> 0.0046153846 | I57: =SUMIF($J$5:$AN$5,TODAY(),J57:AN57) -> 0 | J57: =_xlfn.IFS(J50<=0,0,J50>0,J15/J50) -> 1 | K57: =_xlfn.IFS(K50<=0,0,K50>0,K15/K50) -> 1 | L57: =_xlfn.IFS(L50<=0,0,L50>0,L15/L50) -> 1 | M57: =_xlfn.IFS(M50<=0,0,M50>0,M15/M50) -> 1 | N57: =_xlfn.IFS(N50<=0,0,N50>0,N15/N50) -> 1 | O57: =_xlfn.IFS(O50<=0,0,O50>0,O15/O50) -> 1 | P57: =_xlfn.IFS(P50<=0,0,P50>0,P15/P50) -> 1 | Q57: =_xlfn.IFS(Q50<=0,0,Q50>0,Q15/Q50) -> 1 | ... AN57: =_xlfn.IFS(AN50<=0,0,AN50>0,AN15/AN50) -> 0
C58: =Dashboard!K78 -> WEBSITE | D58: =Dashboard!M78 -> 0.1 | E58: =SUM(J58:AN58) -> 30 | F58: =D58-E58 -> -29.9 | G58: =_xlfn.IFS(F58>0,1,F58<=0,D58/E58) -> 0.0033333333 | H58: =D58/'Action Plan'!$C$6 -> 0.0038461538 | I58: =SUMIF($J$5:$AN$5,TODAY(),J58:AN58) -> 0 | J58: =_xlfn.IFS(J51<=0,0,J51>0,J15/J51) -> 1 | K58: =_xlfn.IFS(K51<=0,0,K51>0,K15/K51) -> 1 | L58: =_xlfn.IFS(L51<=0,0,L51>0,L15/L51) -> 1 | M58: =_xlfn.IFS(M51<=0,0,M51>0,M15/M51) -> 1 | N58: =_xlfn.IFS(N51<=0,0,N51>0,N15/N51) -> 1 | O58: =_xlfn.IFS(O51<=0,0,O51>0,O15/O51) -> 1 | P58: =_xlfn.IFS(P51<=0,0,P51>0,P15/P51) -> 1 | Q58: =_xlfn.IFS(Q51<=0,0,Q51>0,Q15/Q51) -> 1 | ... AN58: =_xlfn.IFS(AN51<=0,0,AN51>0,AN15/AN51) -> 0
C59: =Dashboard!K79 -> TIKTOKSHOP | D59: =Dashboard!M79 -> 0.3 | E59: =SUM(J59:AN59) -> 22 | F59: =D59-E59 -> -21.7 | G59: =_xlfn.IFS(F59>0,1,F59<=0,D59/E59) -> 0.013636364 | H59: =D59/'Action Plan'!$C$6 -> 0.011538462 | I59: =SUMIF($J$5:$AN$5,TODAY(),J59:AN59) -> 0 | J59: =_xlfn.IFS(J52<=0,0,J52>0,J24/J52) -> 0 | K59: =_xlfn.IFS(K52<=0,0,K52>0,K24/K52) -> 0 | L59: =_xlfn.IFS(L52<=0,0,L52>0,L24/L52) -> 0 | M59: =_xlfn.IFS(M52<=0,0,M52>0,M24/M52) -> 0 | N59: =_xlfn.IFS(N52<=0,0,N52>0,N24/N52) -> 0 | O59: =_xlfn.IFS(O52<=0,0,O52>0,O24/O52) -> 0 | P59: =_xlfn.IFS(P52<=0,0,P52>0,P24/P52) -> 0 | Q59: =_xlfn.IFS(Q52<=0,0,Q52>0,Q24/Q52) -> 0 | ... AN59: =_xlfn.IFS(AN52<=0,0,AN52>0,AN24/AN52) -> 2
C60: =Dashboard!K80 -> SHOPPEE | D60: =Dashboard!M80 -> 0.1 | E60: =SUM(J60:AN60) -> 0 | F60: =D60-E60 -> 0.1 | G60: =_xlfn.IFS(F60>0,1,F60<=0,D60/E60) -> 1 | H60: =D60/'Action Plan'!$C$6 -> 0.0038461538 | I60: =SUMIF($J$5:$AN$5,TODAY(),J60:AN60) -> 0 | J60: =_xlfn.IFS(J53<=0,0,J53>0,J25/J53) -> 0 | K60: =_xlfn.IFS(K53<=0,0,K53>0,K25/K53) -> 0 | L60: =_xlfn.IFS(L53<=0,0,L53>0,L25/L53) -> 0 | M60: =_xlfn.IFS(M53<=0,0,M53>0,M25/M53) -> 0 | N60: =_xlfn.IFS(N53<=0,0,N53>0,N25/N53) -> 0 | O60: =_xlfn.IFS(O53<=0,0,O53>0,O25/O53) -> 0 | P60: =_xlfn.IFS(P53<=0,0,P53>0,P25/P53) -> 0 | Q60: =_xlfn.IFS(Q53<=0,0,Q53>0,Q25/Q53) -> 0 | ... AN60: =_xlfn.IFS(AN53<=0,0,AN53>0,AN25/AN53) -> 0
C61: =Dashboard!K81 -> ZALO | D61: =Dashboard!M81 -> 0.4 | E61: =SUM(J61:AN61) -> 27.5 | F61: =D61-E61 -> -27.1 | G61: =_xlfn.IFS(F61>0,1,F61<=0,D61/E61) -> 0.014545455 | H61: =D61/'Action Plan'!$C$6 -> 0.015384615 | I61: =SUMIF($J$5:$AN$5,TODAY(),J61:AN61) -> 0 | J61: =_xlfn.IFS(J54<=0,0,J54>0,J26/J54) -> 1 | K61: =_xlfn.IFS(K54<=0,0,K54>0,K26/K54) -> 1 | L61: =_xlfn.IFS(L54<=0,0,L54>0,L26/L54) -> 1 | M61: =_xlfn.IFS(M54<=0,0,M54>0,M26/M54) -> 1 | N61: =_xlfn.IFS(N54<=0,0,N54>0,N26/N54) -> 1 | O61: =_xlfn.IFS(O54<=0,0,O54>0,O26/O54) -> 1 | P61: =_xlfn.IFS(P54<=0,0,P54>0,P26/P54) -> 1 | Q61: =_xlfn.IFS(Q54<=0,0,Q54>0,Q26/Q54) -> 1 | ... AN61: =_xlfn.IFS(AN54<=0,0,AN54>0,AN26/AN54) -> 2
B62: HIGHER = GOOD | C62: =Dashboard!K82 -> CONVERSION RATE | D62: =Dashboard!M82 -> 0.25833333 | E62: =AVERAGE(E63:E69) -> 0.19857143 | F62: =E62-D62 -> -0.059761905 | G62: =_xlfn.IFS(F62>0,1,F62<=0,E62/D62) -> 0.76866359 | H62: =D62/'Action Plan'!$C$6 -> 0.0099358974 | I62: =AVERAGE(I63:I68) -> 0 | J62: =SUM(J63:J69) -> 0.04 | K62: =SUM(K63:K69) -> 0.04 | L62: =SUM(L63:L69) -> 0.04 | M62: =SUM(M63:M69) -> 0.04 | N62: =SUM(N63:N69) -> 0.04 | O62: =SUM(O63:O69) -> 0.04 | P62: =SUM(P63:P69) -> 0.04 | Q62: =SUM(Q63:Q69) -> 0.04 | ... AN62: =SUM(AN63:AN69) -> 0.19
C63: =Dashboard!K83 -> FACEBOOK | D63: =Dashboard!M83 -> 0.15 | E63: =SUM(J63:AN63) -> 0.35 | F63: =E63-D63 -> 0.2 | G63: =_xlfn.IFS(F63>0,1,F63<=0,E63/D63) -> 1 | H63: =D63/'Action Plan'!$C$6 -> 0.0057692308 | I63: =SUMIF($J$5:$AN$5,TODAY(),J63:AN63) -> 0 | J63: 0.01 | K63: 0.01 | L63: 0.01 | M63: 0.01 | N63: 0.01 | O63: 0.01 | P63: 0.01 | Q63: 0.01 | R63: 0.01 | S63: 0.01 | T63: 0.01 | U63: 0.01 | V63: 0.01 | W63: 0.01 | X63: 0.01 | Y63: 0.01 | Z63: 0.01 | AA63: 0.01 | AB63: 0.01 | AC63: 0.01 | AD63: 0.01 | AE63: 0.01 | AF63: 0.01 | AG63: 0.01 | AH63: 0.01 | AI63: 0.01 | AJ63: 0.01 | AK63: 0.01 | AL63: 0.01 | AM63: 0.01 | AN63: 0.05
C64: =Dashboard!K84 -> LANDING PAGE | D64: =Dashboard!M84 -> 0.8 | E64: =SUM(J64:AN64) -> 0.31 | F64: =E64-D64 -> -0.49 | G64: =_xlfn.IFS(F64>0,1,F64<=0,E64/D64) -> 0.3875 | H64: =D64/'Action Plan'!$C$6 -> 0.030769231 | I64: =SUMIF($J$5:$AN$5,TODAY(),J64:AN64) -> 0 | J64: 0.01 | K64: 0.01 | L64: 0.01 | M64: 0.01 | N64: 0.01 | O64: 0.01 | P64: 0.01 | Q64: 0.01 | R64: 0.01 | S64: 0.01 | T64: 0.01 | U64: 0.01 | V64: 0.01 | W64: 0.01 | X64: 0.01 | Y64: 0.01 | Z64: 0.01 | AA64: 0.01 | AB64: 0.01 | AC64: 0.01 | AD64: 0.01 | AE64: 0.01 | AF64: 0.01 | AG64: 0.01 | AH64: 0.01 | AI64: 0.01 | AJ64: 0.01 | AK64: 0.01 | AL64: 0.01 | AM64: 0.01 | AN64: 0.01
C65: =Dashboard!K85 -> WEBSITE | D65: =Dashboard!M85 -> 0.45 | E65: =SUM(J65:AN65) -> 0.33 | F65: =E65-D65 -> -0.12 | G65: =_xlfn.IFS(F65>0,1,F65<=0,E65/D65) -> 0.73333333 | H65: =D65/'Action Plan'!$C$6 -> 0.017307692 | I65: =SUMIF($J$5:$AN$5,TODAY(),J65:AN65) -> 0 | J65: 0.01 | K65: 0.01 | L65: 0.01 | M65: 0.01 | N65: 0.01 | O65: 0.01 | P65: 0.01 | Q65: 0.01 | R65: 0.01 | S65: 0.01 | T65: 0.01 | U65: 0.01 | V65: 0.01 | W65: 0.01 | X65: 0.01 | Y65: 0.01 | Z65: 0.01 | AA65: 0.01 | AB65: 0.01 | AC65: 0.01 | AD65: 0.01 | AE65: 0.01 | AF65: 0.01 | AG65: 0.01 | AH65: 0.01 | AI65: 0.01 | AJ65: 0.01 | AK65: 0.01 | AL65: 0.01 | AM65: 0.01 | AN65: 0.03
C66: =Dashboard!K86 -> TIKTOKSHOP | D66: =Dashboard!M86 -> 0.05 | E66: =SUM(J66:AN66) -> 0.06 | F66: =E66-D66 -> 0.01 | G66: =_xlfn.IFS(F66>0,1,F66<=0,E66/D66) -> 1 | H66: =D66/'Action Plan'!$C$6 -> 0.0019230769 | I66: =SUMIF($J$5:$AN$5,TODAY(),J66:AN66) -> 0 | J66: 0 | K66: 0 | L66: 0 | M66: 0 | N66: 0 | O66: 0 | P66: 0 | Q66: 0 | R66: 0 | S66: 0 | T66: 0 | U66: 0 | V66: 0 | W66: 0 | X66: 0 | Y66: 0 | Z66: 0 | AA66: 0 | AB66: 0 | AC66: 0 | AD66: 0 | AE66: 0 | AF66: 0 | AG66: 0 | AH66: 0 | AI66: 0 | AJ66: 0 | AK66: 0 | AL66: 0 | AM66: 0 | AN66: 0.06
C67: =Dashboard!K87 -> SHOPPEE | D67: =Dashboard!M87 -> 0.05 | E67: =SUM(J67:AN67) -> 0.02 | F67: =E67-D67 -> -0.03 | G67: =_xlfn.IFS(F67>0,1,F67<=0,E67/D67) -> 0.4 | H67: =D67/'Action Plan'!$C$6 -> 0.0019230769 | I67: =SUMIF($J$5:$AN$5,TODAY(),J67:AN67) -> 0 | J67: 0 | K67: 0 | L67: 0 | M67: 0 | N67: 0 | O67: 0 | P67: 0 | Q67: 0 | R67: 0 | S67: 0 | T67: 0 | U67: 0 | V67: 0 | W67: 0 | X67: 0 | Y67: 0 | Z67: 0 | AA67: 0 | AB67: 0 | AC67: 0 | AD67: 0 | AE67: 0 | AF67: 0 | AG67: 0 | AH67: 0 | AI67: 0 | AJ67: 0 | AK67: 0 | AL67: 0 | AM67: 0 | AN67: 0.02
C68: =Dashboard!K88 -> ZALO | D68: =Dashboard!M88 -> 0.05 | E68: =SUM(J68:AN68) -> 0.32 | F68: =E68-D68 -> 0.27 | G68: =_xlfn.IFS(F68>0,1,F68<=0,E68/D68) -> 1 | H68: =D68/'Action Plan'!$C$6 -> 0.0019230769 | I68: =SUMIF($J$5:$AN$5,TODAY(),J68:AN68) -> 0 | J68: 0.01 | K68: 0.01 | L68: 0.01 | M68: 0.01 | N68: 0.01 | O68: 0.01 | P68: 0.01 | Q68: 0.01 | R68: 0.01 | S68: 0.01 | T68: 0.01 | U68: 0.01 | V68: 0.01 | W68: 0.01 | X68: 0.01 | Y68: 0.01 | Z68: 0.01 | AA68: 0.01 | AB68: 0.01 | AC68: 0.01 | AD68: 0.01 | AE68: 0.01 | AF68: 0.01 | AG68: 0.01 | AH68: 0.01 | AI68: 0.01 | AJ68: 0.01 | AK68: 0.01 | AL68: 0.01 | AM68: 0.01 | AN68: 0.02
C69: =Dashboard!K74 -> ZALO | D69: =Dashboard!M74 -> 25000000 | E69: =SUM(J69:AN69) -> 0 | F69: =E69-D69 -> -25000000 | G69: =_xludf.IFS(F69>0,1,F69<=0,E69/D69) -> #NAME? | H69: =D69/'Action Plan'!$C$6 -> 961538.46 | I69: =SUMIF($J$5:$AN$5,TODAY(),J69:AN69) -> 0
C70: TỔNG A/S | D70: =Dashboard!E75 -> 0.37333333 | E70: =Dashboard!F75 -> 19.066667 | F70: =E70-D70 -> 18.693333 | G70: =_xludf.IFS(F70>0,0,F70<=0,E70/D70) -> #NAME? | H70: =D70/'Action Plan'!$C$6 -> 0.014358974 | I70: =SUMIF($J$5:$AN$5,TODAY(),J70:AN70) -> 0 | J70: =(J71+#REF!)/2 -> #REF! | K70: =(K71+#REF!)/2 -> #REF! | L70: =(L71+#REF!)/2 -> #REF! | M70: =(M71+#REF!)/2 -> #REF! | N70: =(N71+#REF!)/2 -> #REF! | O70: =(O71+#REF!)/2 -> #REF! | P70: =(P71+#REF!)/2 -> #REF! | Q70: =(Q71+#REF!)/2 -> #REF! | ... AN70: =(AN71+#REF!)/2 -> #REF!
C71: =Dashboard!K75 -> A/S RATIO | D71: =Dashboard!M75 -> 0.18666667 | E71: =AVERAGE(E72:E77) -> 3.0916667e+08 | F71: =AVERAGE(F72:F77) -> 3.0916667e+08 | G71: =_xludf.IFS(F71>0,0,F71<=0,E71/D71) -> #NAME? | H71: =AVERAGE(H72:H77) -> 0.0071794872 | I71: =AVERAGE(I72:I77) -> 0 | J71: =AVERAGE(J72:J77) -> 10000000 | K71: =AVERAGE(K72:K77) -> 10000000 | L71: =AVERAGE(L72:L77) -> 10000000 | M71: =AVERAGE(M72:M77) -> 10000000 | N71: =AVERAGE(N72:N77) -> 10000000 | O71: =AVERAGE(O72:O77) -> 10000000 | ... AN71: =AVERAGE(AN72:AN77) -> 4166666.7
C72: =Dashboard!K76 -> FACEBOOK | D72: =Dashboard!M76 -> 0.1 | E72: =SUM(J72:AN72) -> 30000000 | F72: =E72-D72 -> 30000000 | G72: =_xludf.IFS(F72>0,0,F72<=0,E72/D72) -> #NAME? | H72: =D72/'Action Plan'!$C$6 -> 0.0038461538 | I72: =SUMIF($J$5:$AN$5,TODAY(),J72:AN72) -> 0 | J72: =IF(J63<>0,J$9/J63,0) -> 0 | K72: =IF(K63<>0,K$9/K63,0) -> 0 | L72: =IF(L63<>0,L$9/L63,0) -> 0 | M72: =IF(M63<>0,M$9/M63,0) -> 0 | N72: =IF(N63<>0,N$9/N63,0) -> 0 | O72: =IF(O63<>0,O$9/O63,0) -> 0 | P72: =IF(P63<>0,P$9/P63,0) -> 0 | Q72: =IF(Q63<>0,Q$9/Q63,0) -> 0 | ... AN72: =IF(AN63<>0,AN$9/AN63,0) -> 0
C73: =Dashboard!K77 -> LANDING PAGE | D73: =Dashboard!M77 -> 0.12 | E73: =SUM(J73:AN73) -> 1500000000 | F73: =E73-D73 -> 1.5e+09 | G73: =_xludf.IFS(F73>0,0,F73<=0,E73/D73) -> #NAME? | H73: =D73/'Action Plan'!$C$6 -> 0.0046153846 | I73: =SUMIF($J$5:$AN$5,TODAY(),J73:AN73) -> 0 | J73: =IF(J64<>0,J$15/J64,0) -> 50000000 | K73: =IF(K64<>0,K$15/K64,0) -> 50000000 | L73: =IF(L64<>0,L$15/L64,0) -> 50000000 | M73: =IF(M64<>0,M$15/M64,0) -> 50000000 | N73: =IF(N64<>0,N$15/N64,0) -> 50000000 | O73: =IF(O64<>0,O$15/O64,0) -> 50000000 | P73: =IF(P64<>0,P$15/P64,0) -> 50000000 | Q73: =IF(Q64<>0,Q$15/Q64,0) -> 50000000 | ... AN73: =IF(AN64<>0,AN$15/AN64,0) -> 0
C74: =Dashboard!K78 -> WEBSITE | D74: =Dashboard!M78 -> 0.1 | E74: =SUM(J74:AN74) -> 320000000 | F74: =E74-D74 -> 3.2e+08 | G74: =_xludf.IFS(F74>0,0,F74<=0,E74/D74) -> #NAME? | H74: =D74/'Action Plan'!$C$6 -> 0.0038461538 | I74: =SUMIF($J$5:$AN$5,TODAY(),J74:AN74) -> 0 | J74: =IF(J65<>0,J$21/J65,0) -> 10000000 | K74: =IF(K65<>0,K$21/K65,0) -> 10000000 | L74: =IF(L65<>0,L$21/L65,0) -> 10000000 | M74: =IF(M65<>0,M$21/M65,0) -> 10000000 | N74: =IF(N65<>0,N$21/N65,0) -> 10000000 | O74: =IF(O65<>0,O$21/O65,0) -> 10000000 | P74: =IF(P65<>0,P$21/P65,0) -> 10000000 | Q74: =IF(Q65<>0,Q$21/Q65,0) -> 10000000 | ... AN74: =IF(AN65<>0,AN$21/AN65,0) -> 20000000
C75: =Dashboard!K79 -> TIKTOKSHOP | D75: =Dashboard!M79 -> 0.3 | E75: =SUM(J75:AN75) -> 5000000 | F75: =E75-D75 -> 4999999.7 | G75: =_xludf.IFS(F75>0,0,F75<=0,E75/D75) -> #NAME? | H75: =D75/'Action Plan'!$C$6 -> 0.011538462 | I75: =SUMIF($J$5:$AN$5,TODAY(),J75:AN75) -> 0 | J75: =IF(J66<>0,(J$24+J$28)/J66,0) -> 0 | K75: =IF(K66<>0,(K$24+K$28)/K66,0) -> 0 | L75: =IF(L66<>0,(L$24+L$28)/L66,0) -> 0 | M75: =IF(M66<>0,(M$24+M$28)/M66,0) -> 0 | N75: =IF(N66<>0,(N$24+N$28)/N66,0) -> 0 | O75: =IF(O66<>0,(O$24+O$28)/O66,0) -> 0 | P75: =IF(P66<>0,(P$24+P$28)/P66,0) -> 0 | Q75: =IF(Q66<>0,(Q$24+Q$28)/Q66,0) -> 0 | ... AN75: =IF(AN66<>0,(AN$24+AN$28)/AN66,0) -> 5000000
C76: =Dashboard!K80 -> SHOPPEE | D76: =Dashboard!M80 -> 0.1 | E76: =SUM(J76:AN76) -> 0 | F76: =E76-D76 -> -0.1 | G76: =_xludf.IFS(F76>0,0,F76<=0,E76/D76) -> #NAME? | H76: =D76/'Action Plan'!$C$6 -> 0.0038461538 | I76: =SUMIF($J$5:$AN$5,TODAY(),J76:AN76) -> 0 | J76: =IF(J68<>0,J$25/J68,0) -> 0 | K76: =IF(K68<>0,K$25/K68,0) -> 0 | L76: =IF(L68<>0,L$25/L68,0) -> 0 | M76: =IF(M68<>0,M$25/M68,0) -> 0 | N76: =IF(N68<>0,N$25/N68,0) -> 0 | O76: =IF(O68<>0,O$25/O68,0) -> 0 | P76: =IF(P68<>0,P$25/P68,0) -> 0 | Q76: =IF(Q68<>0,Q$25/Q68,0) -> 0 | ... AN76: =IF(AN68<>0,AN$25/AN68,0) -> 0
C77: =Dashboard!K81 -> ZALO | D77: =Dashboard!M81 -> 0.4 | E77: =SUM(J77:AN77) -> 0 | F77: =E77-D77 -> -0.4 | G77: =_xludf.IFS(F77>0,0,F77<=0,E77/D77) -> #NAME? | H77: =D77/'Action Plan'!$C$6 -> 0.015384615 | I77: =SUMIF($J$5:$AN$5,TODAY(),J77:AN77) -> 0 | J77: =IF(J69<>0,J$28/J69,0) -> 0 | K77: =IF(K69<>0,K$28/K69,0) -> 0 | L77: =IF(L69<>0,L$28/L69,0) -> 0 | M77: =IF(M69<>0,M$28/M69,0) -> 0 | N77: =IF(N69<>0,N$28/N69,0) -> 0 | O77: =IF(O69<>0,O$28/O69,0) -> 0 | P77: =IF(P69<>0,P$28/P69,0) -> 0 | Q77: =IF(Q69<>0,Q$28/Q69,0) -> 0 | ... AN77: =IF(AN69<>0,AN$28/AN69,0) -> 0
C78: TỔNG CVR | D78: =Dashboard!E82 -> 0.45833333 | E78: =Dashboard!F82 -> 0.45 | F78: =E78-D78 -> -0.0083333333 | G78: =_xludf.IFS(F78>0,0,F78<=0,E78/D78) -> #NAME? | H78: =D78/'Action Plan'!$C$6 -> 0.017628205 | I78: =SUMIF($J$5:$AN$5,TODAY(),J78:AN78) -> 0 | J78: =(J79+#REF!)/2 -> #DIV/0! | K78: =(K79+#REF!)/2 -> #DIV/0! | L78: =(L79+#REF!)/2 -> #DIV/0! | M78: =(M79+#REF!)/2 -> #DIV/0! | N78: =(N79+#REF!)/2 -> #DIV/0! | O78: =(O79+#REF!)/2 -> #DIV/0! | P78: =(P79+#REF!)/2 -> #DIV/0! | Q78: =(Q79+#REF!)/2 -> #DIV/0! | ... AN78: =(AN79+#REF!)/2 -> #DIV/0!
C79: =Dashboard!K82 -> CONVERSION RATE | D79: =Dashboard!M82 -> 0.25833333 | E79: =AVERAGE(E80:E82) -> 0 | F79: =AVERAGE(F80:F82) -> -0.05 | G79: =_xludf.IFS(F79>0,0,F79<=0,E79/D79) -> #NAME? | H79: =AVERAGE(H80:H82) -> 0.0019230769 | I79: =AVERAGE(I80:I82) -> 0 | J79: =AVERAGE(J80:J82) -> #DIV/0! | K79: =AVERAGE(K80:K82) -> #DIV/0! | L79: =AVERAGE(L80:L82) -> #DIV/0! | M79: =AVERAGE(M80:M82) -> #DIV/0! | N79: =AVERAGE(N80:N82) -> #DIV/0! | O79: =AVERAGE(O80:O82) -> #DIV/0! | ... AN79: =AVERAGE(AN80:AN82) -> #DIV/0!
C80: =Dashboard!K86 -> TIKTOKSHOP | D80: =Dashboard!M86 -> 0.05 | E80: =SUM(J80:AN80) -> 0 | F80: =E80-D80 -> -0.05 | G80: =_xludf.IFS(F80>0,0,F80<=0,E80/D80) -> #NAME? | H80: =D80/'Action Plan'!$C$6 -> 0.0019230769 | I80: =SUMIF($J$5:$AN$5,TODAY(),J80:AN80) -> 0
C81: =Dashboard!K87 -> SHOPPEE | D81: =Dashboard!M87 -> 0.05 | E81: =SUM(J81:AN81) -> 0 | F81: =E81-D81 -> -0.05 | G81: =_xludf.IFS(F81>0,0,F81<=0,E81/D81) -> #NAME? | H81: =D81/'Action Plan'!$C$6 -> 0.0019230769 | I81: =SUMIF($J$5:$AN$5,TODAY(),J81:AN81) -> 0
C82: =Dashboard!K88 -> ZALO | D82: =Dashboard!M88 -> 0.05 | E82: =SUM(J82:AN82) -> 0 | F82: =E82-D82 -> -0.05 | G82: =_xludf.IFS(F82>0,0,F82<=0,E82/D82) -> #NAME? | H82: =D82/'Action Plan'!$C$6 -> 0.0019230769 | I82: =SUMIF($J$5:$AN$5,TODAY(),J82:AN82) -> 0

Sheet E-Com Operations
A1: KPIs TRACKING
A2: MONTH | B2: 4 | D2: 1. REPORT IN ORDER WITH LATEST DATE ON TOP. FILL IN BC IN ALL GREEN CELLS (AS ABOVE) 2. FINAL REPORT ON THE SAME DAY BEFORE 5:30 PM 3. ALL APPROVED EXPORT FILES MUST BE SAVED IN THE COMPANY ACCOUNT IN ACCORDANCE WITH THE FOLDER AND FILE NAMING INSTRUCTIONS AS FOLLOWS: HB MARKETING -> LOCATION + NAME -> BY DEPLOYMENT CONTENT -> FILE NAME: TITLE FILE
A3: YEAR | B3: 2025
A4: VND | B4: 1000000
J5: 45748 | K5: =J5+1 -> 45749 | L5: =K5+1 -> 45750 | M5: =L5+1 -> 45751 | N5: =M5+1 -> 45752 | O5: =N5+1 -> 45753 | P5: =O5+1 -> 45754 | Q5: =P5+1 -> 45755 | R5: =Q5+1 -> 45756 | ... AN5: =AM5+1 -> 45778
D6: ESTIMATED | E6: ACTUAL | F6: REMAINING | G6: RATIO | H6: KPIs | I6: TASKS COMPLETED | J6: =IF(WEEKDAY(J5)=1,"CN","T"&WEEKDAY(J5)) -> T3 | K6: =IF(WEEKDAY(K5)=1,"CN","T"&WEEKDAY(K5)) -> T4 | L6: =IF(WEEKDAY(L5)=1,"CN","T"&WEEKDAY(L5)) -> T5 | M6: =IF(WEEKDAY(M5)=1,"CN","T"&WEEKDAY(M5)) -> T6 | N6: =IF(WEEKDAY(N5)=1,"CN","T"&WEEKDAY(N5)) -> T7 | O6: =IF(WEEKDAY(O5)=1,"CN","T"&WEEKDAY(O5)) -> CN | P6: =IF(WEEKDAY(P5)=1,"CN","T"&WEEKDAY(P5)) -> T2 | Q6: =IF(WEEKDAY(Q5)=1,"CN","T"&WEEKDAY(Q5)) -> T3 | ... AN6: =IF(WEEKDAY(AN5)=1,"CN","T"&WEEKDAY(AN5)) -> T5
C7: BUDGET | D7: =Dashboard!E15 -> 170000000 | E7: =E8 -> 16800000 | F7: =D7-E7 -> 153200000 | G7: =_xlfn.IFS(F7>0,1,F7<=0,D7/E7) -> 1 | H7: =D7/'Action Plan'!$C$6 -> 6538461.5 | I7: =SUMIF($J$5:$AN$5,TODAY(),J7:AN7) -> 0 | J7: =J8 -> 550000 | K7: =K8 -> 550000 | L7: =L8 -> 550000 | M7: =M8 -> 550000 | N7: =N8 -> 550000 | O7: =O8 -> 550000 | P7: =P8 -> 550000 | Q7: =Q8 -> 550000 | ... AN7: =AN8 -> 300000
C8: BUDGET | D8: =D9+D15+D21+D24+D25+D27+D28+D26 -> 200000000 | E8: =E9+E15+E21+E24+E25+E26+E27+E28 -> 16800000 | F8: =F9+F15+F21+F24+F25+F26+F27+F28 -> 183200000 | G8: =_xlfn.IFS(F8>0,1,F8<=0,D8/E8) -> 1 | H8: =H9+H15+H21+H24+H25+H27+H28+H26 -> 7692307.7 | I8: =I9+I15+I21+I24+I25+I27+I28+I26 -> 0 | J8: =J9+J15+J21+J24+J25+J27+J28+J26 -> 550000 | K8: =K9+K15+K21+K24+K25+K27+K28+K26 -> 550000 | L8: =L9+L15+L21+L24+L25+L27+L28+L26 -> 550000 | M8: =M9+M15+M21+M24+M25+M27+M28+M26 -> 550000 | N8: =N9+N15+N21+N24+N25+N27+N28+N26 -> 550000 | O8: =O9+O15+O21+O24+O25+O27+O28+O26 -> 550000 | ... AN8: =AN9+AN15+AN21+AN24+AN25+AN27+AN28+AN26 -> 300000
C9: =Dashboard!B16 -> FACEBOOK | D9: =Dashboard!E16*Dashboard!$P$9 -> 10000000 | E9: =SUM(E10:E14) -> 0 | F9: =D9-E9 -> 10000000 | G9: =_xlfn.IFS(F9>0,1,F9<=0,D9/E9) -> 1 | H9: =D9/'Action Plan'!$C$6 -> 384615.38 | I9: =SUM(I10:I14) -> 0 | J9: =SUM(J10:J14) -> 0 | K9: =SUM(K10:K14) -> 0 | L9: =SUM(L10:L14) -> 0 | M9: =SUM(M10:M14) -> 0 | N9: =SUM(N10:N14) -> 0 | O9: =SUM(O10:O14) -> 0 | P9: =SUM(P10:P14) -> 0 | ... AN9: =SUM(AN10:AN14) -> 0
C10: VISION | D10: =$D$9/5 -> 2000000 | E10: =SUM(J10:AN10) -> 0 | F10: =D10-E10 -> 2000000 | I10: =SUMIF($J$5:$AN$5,TODAY(),J10:AN10) -> 0 | J10: 0 | K10: 0 | L10: 0 | M10: 0 | N10: 0 | O10: 0 | P10: 0 | Q10: 0 | R10: 0 | S10: 0 | T10: 0 | U10: 0 | V10: 0 | W10: 0 | X10: 0 | Y10: 0 | Z10: 0 | AA10: 0 | AB10: 0 | AC10: 0 | AD10: 0 | AE10: 0 | AF10: 0 | AG10: 0 | AH10: 0 | AI10: 0 | AJ10: 0 | AK10: 0 | AL10: 0 | AM10: 0 | AN10: 0
C11: BLACKHAIR | D11: =$D$9/5 -> 2000000 | E11: =SUM(J11:AN11) -> 0 | F11: =D11-E11 -> 2000000 | I11: =SUMIF($J$5:$AN$5,TODAY(),J11:AN11) -> 0 | J11: 0 | K11: 0 | L11: 0 | M11: 0 | N11: 0 | O11: 0 | P11: 0 | Q11: 0 | R11: 0 | S11: 0 | T11: 0 | U11: 0 | V11: 0 | W11: 0 | X11: 0 | Y11: 0 | Z11: 0 | AA11: 0 | AB11: 0 | AC11: 0 | AD11: 0 | AE11: 0 | AF11: 0 | AG11: 0 | AH11: 0 | AI11: 0 | AJ11: 0 | AK11: 0 | AL11: 0 | AM11: 0 | AN11: 0
C12: GLUTAWHITE | D12: =$D$9/5 -> 2000000 | E12: =SUM(J12:AN12) -> 0 | F12: =D12-E12 -> 2000000 | I12: =SUMIF($J$5:$AN$5,TODAY(),J12:AN12) -> 0 | J12: 0 | K12: 0 | L12: 0 | M12: 0 | N12: 0 | O12: 0 | P12: 0 | Q12: 0 | R12: 0 | S12: 0 | T12: 0 | U12: 0 | V12: 0 | W12: 0 | X12: 0 | Y12: 0 | Z12: 0 | AA12: 0 | AB12: 0 | AC12: 0 | AD12: 0 | AE12: 0 | AF12: 0 | AG12: 0 | AH12: 0 | AI12: 0 | AJ12: 0 | AK12: 0 | AL12: 0 | AM12: 0 | AN12: 0
C13: GLUTATHION | D13: =$D$9/5 -> 2000000 | E13: =SUM(J13:AN13) -> 0 | F13: =D13-E13 -> 2000000 | I13: =SUMIF($J$5:$AN$5,TODAY(),J13:AN13) -> 0 | J13: 0 | K13: 0 | L13: 0 | M13: 0 | N13: 0 | O13: 0 | P13: 0 | Q13: 0 | R13: 0 | S13: 0 | T13: 0 | U13: 0 | V13: 0 | W13: 0 | X13: 0 | Y13: 0 | Z13: 0 | AA13: 0 | AB13: 0 | AC13: 0 | AD13: 0 | AE13: 0 | AF13: 0 | AG13: 0 | AH13: 0 | AI13: 0 | AJ13: 0 | AK13: 0 | AL13: 0 | AM13: 0 | AN13: 0
C14: CORDY | D14: =$D$9/5 -> 2000000 | E14: =SUM(J14:AN14) -> 0 | F14: =D14-E14 -> 2000000 | I14: =SUMIF($J$5:$AN$5,TODAY(),J14:AN14) -> 0 | J14: 0 | K14: 0 | L14: 0 | M14: 0 | N14: 0 | O14: 0 | P14: 0 | Q14: 0 | R14: 0 | S14: 0 | T14: 0 | U14: 0 | V14: 0 | W14: 0 | X14: 0 | Y14: 0 | Z14: 0 | AA14: 0 | AB14: 0 | AC14: 0 | AD14: 0 | AE14: 0 | AF14: 0 | AG14: 0 | AH14: 0 | AI14: 0 | AJ14: 0 | AK14: 0 | AL14: 0 | AM14: 0 | AN14: 0
C15: =Dashboard!B17 -> LANDING PAGE | D15: =Dashboard!E17*Dashboard!$P$9 -> 60000000 | E15: =SUM(E16:E20) -> 0 | F15: =D15-E15 -> 60000000 | G15: =_xlfn.IFS(F15>0,1,F15<=0,D15/E15) -> 1 | H15: =D15/'Action Plan'!$C$6 -> 2307692.3 | I15: =SUM(I16:I20) -> 0 | J15: =SUM(J16:J20) -> 0 | K15: =SUM(K16:K20) -> 0 | L15: =SUM(L16:L20) -> 0 | M15: =SUM(M16:M20) -> 0 | N15: =SUM(N16:N20) -> 0 | O15: =SUM(O16:O20) -> 0 | P15: =SUM(P16:P20) -> 0 | ... AN15: =SUM(AN16:AN20) -> 0
C16: VISION | D16: =$D$15/8 -> 7500000 | E16: =SUM(J16:AN16) -> 0 | F16: =D16-E16 -> 7500000 | I16: =SUMIF($J$5:$AN$5,TODAY(),J16:AN16) -> 0 | J16: 0 | K16: 0 | L16: 0 | M16: 0 | N16: 0 | O16: 0 | P16: 0 | Q16: 0 | R16: 0 | S16: 0 | T16: 0 | U16: 0 | V16: 0 | W16: 0 | X16: 0 | Y16: 0 | Z16: 0 | AA16: 0 | AB16: 0 | AC16: 0 | AD16: 0 | AE16: 0 | AF16: 0 | AG16: 0 | AH16: 0 | AI16: 0 | AJ16: 0 | AK16: 0 | AL16: 0 | AM16: 0 | AN16: 0
C17: BLACKHAIR | D17: =$D$15/8 -> 7500000 | E17: =SUM(J17:AN17) -> 0 | F17: =D17-E17 -> 7500000 | I17: =SUMIF($J$5:$AN$5,TODAY(),J17:AN17) -> 0 | J17: 0 | K17: 0 | L17: 0 | M17: 0 | N17: 0 | O17: 0 | P17: 0 | Q17: 0 | R17: 0 | S17: 0 | T17: 0 | U17: 0 | V17: 0 | W17: 0 | X17: 0 | Y17: 0 | Z17: 0 | AA17: 0 | AB17: 0 | AC17: 0 | AD17: 0 | AE17: 0 | AF17: 0 | AG17: 0 | AH17: 0 | AI17: 0 | AJ17: 0 | AK17: 0 | AL17: 0 | AM17: 0 | AN17: 0
C18: GLUTAWHITE | D18: =$D$15/8 -> 7500000 | E18: =SUM(J18:AN18) -> 0 | F18: =D18-E18 -> 7500000 | I18: =SUMIF($J$5:$AN$5,TODAY(),J18:AN18) -> 0 | J18: 0 | K18: 0 | L18: 0 | M18: 0 | N18: 0 | O18: 0 | P18: 0 | Q18: 0 | R18: 0 | S18: 0 | T18: 0 | U18: 0 | V18: 0 | W18: 0 | X18: 0 | Y18: 0 | Z18: 0 | AA18: 0 | AB18: 0 | AC18: 0 | AD18: 0 | AE18: 0 | AF18: 0 | AG18: 0 | AH18: 0 | AI18: 0 | AJ18: 0 | AK18: 0 | AL18: 0 | AM18: 0 | AN18: 0
C19: GLUTATHION | D19: =$D$15/8 -> 7500000 | E19: =SUM(J19:AN19) -> 0 | F19: =D19-E19 -> 7500000 | I19: =SUMIF($J$5:$AN$5,TODAY(),J19:AN19) -> 0 | J19: 0 | K19: 0 | L19: 0 | M19: 0 | N19: 0 | O19: 0 | P19: 0 | Q19: 0 | R19: 0 | S19: 0 | T19: 0 | U19: 0 | V19: 0 | W19: 0 | X19: 0 | Y19: 0 | Z19: 0 | AA19: 0 | AB19: 0 | AC19: 0 | AD19: 0 | AE19: 0 | AF19: 0 | AG19: 0 | AH19: 0 | AI19: 0 | AJ19: 0 | AK19: 0 | AL19: 0 | AM19: 0 | AN19: 0
C20: CORDY | D20: =$D$15/8 -> 7500000 | E20: =SUM(J20:AN20) -> 0 | F20: =D20-E20 -> 7500000 | I20: =SUMIF($J$5:$AN$5,TODAY(),J20:AN20) -> 0 | J20: 0 | K20: 0 | L20: 0 | M20: 0 | N20: 0 | O20: 0 | P20: 0 | Q20: 0 | R20: 0 | S20: 0 | T20: 0 | U20: 0 | V20: 0 | W20: 0 | X20: 0 | Y20: 0 | Z20: 0 | AA20: 0 | AB20: 0 | AC20: 0 | AD20: 0 | AE20: 0 | AF20: 0 | AG20: 0 | AH20: 0 | AI20: 0 | AJ20: 0 | AK20: 0 | AL20: 0 | AM20: 0 | AN20: 0
C21: =Dashboard!B18 -> WEBSITE | D21: =Dashboard!E18*Dashboard!$P$9 -> 10000000 | E21: =SUM(E22:E23) -> 0 | F21: =D21-E21 -> 10000000 | G21: =_xlfn.IFS(F21>0,1,F21<=0,D21/E21) -> 1 | H21: =D21/'Action Plan'!$C$6 -> 384615.38 | I21: =SUM(I22:I23) -> 0 | J21: =SUM(J22:J23) -> 0 | K21: =SUM(K22:K23) -> 0 | L21: =SUM(L22:L23) -> 0 | M21: =SUM(M22:M23) -> 0 | N21: =SUM(N22:N23) -> 0 | O21: =SUM(O22:O23) -> 0 | P21: =SUM(P22:P23) -> 0 | ... AN21: =SUM(AN22:AN23) -> 0
C22: HBPHARMA | D22: =$D$21/6 -> 1666666.7 | E22: =SUM(J22:AN22) -> 0 | F22: =D22-E22 -> 1666666.7 | H22: =D22/'Action Plan'!$C$6 -> 64102.564 | I22: =SUMIF($J$5:$AN$5,TODAY(),J22:AN22) -> 0 | J22: 0 | K22: 0 | L22: 0 | M22: 0 | N22: 0 | O22: 0 | P22: 0 | Q22: 0 | R22: 0 | S22: 0 | T22: 0 | U22: 0 | V22: 0 | W22: 0 | X22: 0 | Y22: 0 | Z22: 0 | AA22: 0 | AB22: 0 | AC22: 0 | AD22: 0 | AE22: 0 | AF22: 0 | AG22: 0 | AH22: 0 | AI22: 0 | AJ22: 0 | AK22: 0 | AL22: 0 | AM22: 0 | AN22: 0
C23: HOTLINE | D23: =$D$21/6 -> 1666666.7 | E23: =SUM(J23:AN23) -> 0 | F23: =D23-E23 -> 1666666.7 | H23: =D23/'Action Plan'!$C$6 -> 64102.564 | I23: =SUMIF($J$5:$AN$5,TODAY(),J23:AN23) -> 0 | J23: 0 | K23: 0 | L23: 0 | M23: 0 | N23: 0 | O23: 0 | P23: 0 | Q23: 0 | R23: 0 | S23: 0 | T23: 0 | U23: 0 | V23: 0 | W23: 0 | X23: 0 | Y23: 0 | Z23: 0 | AA23: 0 | AB23: 0 | AC23: 0 | AD23: 0 | AE23: 0 | AF23: 0 | AG23: 0 | AH23: 0 | AI23: 0 | AJ23: 0 | AK23: 0 | AL23: 0 | AM23: 0 | AN23: 0
C24: =Dashboard!B19 -> TIKTOK SHOP | D24: =Dashboard!E19*Dashboard!$P$9 -> 20000000 | E24: =SUM(J24:AN24) -> 6100000 | F24: =D24-E24 -> 13900000 | G24: =_xlfn.IFS(F24>0,1,F24<=0,D24/E24) -> 1 | H24: =D24/'Action Plan'!$C$6 -> 769230.77 | I24: =SUMIF($J$5:$AN$5,TODAY(),J24:AN24) -> 0 | J24: 200000 | K24: 200000 | L24: 200000 | M24: 200000 | N24: 200000 | O24: 200000 | P24: 200000 | Q24: 200000 | R24: 200000 | S24: 200000 | T24: 200000 | U24: 200000 | V24: 200000 | W24: 200000 | X24: 200000 | Y24: 200000 | Z24: 200000 | AA24: 200000 | AB24: 200000 | AC24: 200000 | AD24: 200000 | AE24: 200000 | AF24: 200000 | AG24: 200000 | AH24: 200000 | AI24: 200000 | AJ24: 200000 | AK24: 200000 | AL24: 200000 | AM24: 200000 | AN24: 100000
C25: =Dashboard!B20 -> SHOPEE | D25: =Dashboard!E20*Dashboard!$P$8 -> 10000000 | E25: =SUM(J25:AN25) -> 6100000 | F25: =D25-E25 -> 3900000 | G25: =_xlfn.IFS(F25>0,1,F25<=0,D25/E25) -> 1 | H25: =D25/'Action Plan'!$C$6 -> 384615.38 | I25: =SUMIF($J$5:$AN$5,TODAY(),J25:AN25) -> 0 | J25: 200000 | K25: 200000 | L25: 200000 | M25: 200000 | N25: 200000 | O25: 200000 | P25: 200000 | Q25: 200000 | R25: 200000 | S25: 200000 | T25: 200000 | U25: 200000 | V25: 200000 | W25: 200000 | X25: 200000 | Y25: 200000 | Z25: 200000 | AA25: 200000 | AB25: 200000 | AC25: 200000 | AD25: 200000 | AE25: 200000 | AF25: 200000 | AG25: 200000 | AH25: 200000 | AI25: 200000 | AJ25: 200000 | AK25: 200000 | AL25: 200000 | AM25: 200000 | AN25: 100000
C26: =Dashboard!B21 -> ZALO | D26: =Dashboard!E21*Dashboard!$P$9 -> 40000000 | E26: =SUM(J26:AN26) -> 100000 | F26: =D26-E26 -> 39900000 | G26: =_xlfn.IFS(F26>0,1,F26<=0,D26/E26) -> 1 | H26: =D26/'Action Plan'!$C$6 -> 1538461.5 | I26: =SUMIF($J$5:$AN$5,TODAY(),J26:AN26) -> 0 | J26: 0 | K26: 0 | L26: 0 | M26: 0 | N26: 0 | O26: 0 | P26: 0 | Q26: 0 | R26: 0 | S26: 0 | T26: 0 | U26: 0 | V26: 0 | W26: 0 | X26: 0 | Y26: 0 | Z26: 0 | AA26: 0 | AB26: 0 | AC26: 0 | AD26: 0 | AE26: 0 | AF26: 0 | AG26: 0 | AH26: 0 | AI26: 0 | AJ26: 0 | AK26: 0 | AL26: 0 | AM26: 0 | AN26: 100000
C27: =Dashboard!B22 -> BOOKING | D27: =Dashboard!E21*Dashboard!$P$9 -> 40000000 | E27: =SUM(J27:AN27) -> 3000000 | F27: =D27-E27 -> 37000000 | G27: =_xlfn.IFS(F27>0,1,F27<=0,D27/E27) -> 1 | H27: =D27/'Action Plan'!$C$6 -> 1538461.5 | I27: =SUMIF($J$5:$AN$5,TODAY(),J27:AN27) -> 0 | J27: 100000 | K27: 100000 | L27: 100000 | M27: 100000 | N27: 100000 | O27: 100000 | P27: 100000 | Q27: 100000 | R27: 100000 | S27: 100000 | T27: 100000 | U27: 100000 | V27: 100000 | W27: 100000 | X27: 100000 | Y27: 100000 | Z27: 100000 | AA27: 100000 | AB27: 100000 | AC27: 100000 | AD27: 100000 | AE27: 100000 | AF27: 100000 | AG27: 100000 | AH27: 100000 | AI27: 100000 | AJ27: 100000 | AK27: 100000 | AL27: 100000 | AM27: 100000 | AN27: 0
C28: =Dashboard!B23 -> BRANDING | D28: =Dashboard!E22*Dashboard!$P$9 -> 10000000 | E28: =SUM(J28:AN28) -> 1500000 | F28: =D28-E28 -> 8500000 | G28: =_xlfn.IFS(F28>0,1,F28<=0,D28/E28) -> 1 | H28: =D28/'Action Plan'!$C$6 -> 384615.38 | I28: =SUMIF($J$5:$AN$5,TODAY(),J28:AN28) -> 0 | J28: 50000 | K28: 50000 | L28: 50000 | M28: 50000 | N28: 50000 | O28: 50000 | P28: 50000 | Q28: 50000 | R28: 50000 | S28: 50000 | T28: 50000 | U28: 50000 | V28: 50000 | W28: 50000 | X28: 50000 | Y28: 50000 | Z28: 50000 | AA28: 50000 | AB28: 50000 | AC28: 50000 | AD28: 50000 | AE28: 50000 | AF28: 50000 | AG28: 50000 | AH28: 50000 | AI28: 50000 | AJ28: 50000 | AK28: 50000 | AL28: 50000 | AM28: 50000 | AN28: 0
C29: =Dashboard!K52 -> P2
C30: DATA | D30: =Dashboard!E53 -> 1680 | E30: =Dashboard!F53 -> 1528 | F30: =E30-D30 -> -152 | G30: =_xlfn.IFS(F30>0,1,F30<0,E30/D30,F30=0,0) -> 0.90952381 | H30: =D30/'Action Plan'!$C$6 -> 64.615385 | I30: =SUMIF($J$5:$AN$5,TODAY(),J30:AN30) -> 0 | J30: =J31 -> 13 | K30: =K31 -> 13 | L30: =L31 -> 13 | M30: =M31 -> 13 | N30: =N31 -> 13 | O30: =O31 -> 13 | P30: =P31 -> 13 | Q30: =Q31 -> 13 | ... AN30: =AN31 -> 13
C31: =Dashboard!K53 -> DATA | D31: =Dashboard!U53 -> 572 | E31: =SUM(E32:E37) -> 403 | F31: =E31-D31 -> -169 | G31: =_xlfn.IFS(F31>0,1,F31<0,E31/D31,F31=0,0) -> 0.70454545 | H31: =D31/'Action Plan'!$C$6 -> 22 | I31: =SUM(I32:I37) -> 0 | J31: =SUM(J32:J37) -> 13 | K31: =SUM(K32:K37) -> 13 | L31: =SUM(L32:L37) -> 13 | M31: =SUM(M32:M37) -> 13 | N31: =SUM(N32:N37) -> 13 | O31: =SUM(O32:O37) -> 13 | P31: =SUM(P32:P37) -> 13 | ... AN31: =SUM(AN32:AN37) -> 13
C32: =Dashboard!K54 -> FACEBOOK | D32: =Dashboard!U54 -> -87 | E32: =SUM(J32:AN32) -> 62 | F32: =E32-D32 -> 149 | G32: =_xlfn.IFS(F32>0,1,F32<0,E32/D32,F32=0,0) -> 1 | H32: =D32/'Action Plan'!$C$6 -> -3.3461538 | I32: =SUMIF($J$5:$AN$5,TODAY(),J32:AN32) -> 0 | J32: 2 | K32: 2 | L32: 2 | M32: 2 | N32: 2 | O32: 2 | P32: 2 | Q32: 2 | R32: 2 | S32: 2 | T32: 2 | U32: 2 | V32: 2 | W32: 2 | X32: 2 | Y32: 2 | Z32: 2 | AA32: 2 | AB32: 2 | AC32: 2 | AD32: 2 | AE32: 2 | AF32: 2 | AG32: 2 | AH32: 2 | AI32: 2 | AJ32: 2 | AK32: 2 | AL32: 2 | AM32: 2 | AN32: 2
C33: =Dashboard!K55 -> LANDING PAGE | D33: =Dashboard!U55 -> 48 | E33: =SUM(J33:AN33) -> 31 | F33: =E33-D33 -> -17 | G33: =_xlfn.IFS(F33>0,1,F33<0,E33/D33,F33=0,0) -> 0.64583333 | H33: =D33/'Action Plan'!$C$6 -> 1.8461538 | I33: =SUMIF($J$5:$AN$5,TODAY(),J33:AN33) -> 0 | J33: 1 | K33: 1 | L33: 1 | M33: 1 | N33: 1 | O33: 1 | P33: 1 | Q33: 1 | R33: 1 | S33: 1 | T33: 1 | U33: 1 | V33: 1 | W33: 1 | X33: 1 | Y33: 1 | Z33: 1 | AA33: 1 | AB33: 1 | AC33: 1 | AD33: 1 | AE33: 1 | AF33: 1 | AG33: 1 | AH33: 1 | AI33: 1 | AJ33: 1 | AK33: 1 | AL33: 1 | AM33: 1 | AN33: 1
C34: =Dashboard!K56 -> WEBSITE | D34: =Dashboard!U56 -> 25 | E34: =SUM(J34:AN34) -> 31 | F34: =E34-D34 -> 6 | G34: =_xlfn.IFS(F34>0,1,F34<0,E34/D34,F34=0,0) -> 1 | H34: =D34/'Action Plan'!$C$6 -> 0.96153846 | I34: =SUMIF($J$5:$AN$5,TODAY(),J34:AN34) -> 0 | J34: 1 | K34: 1 | L34: 1 | M34: 1 | N34: 1 | O34: 1 | P34: 1 | Q34: 1 | R34: 1 | S34: 1 | T34: 1 | U34: 1 | V34: 1 | W34: 1 | X34: 1 | Y34: 1 | Z34: 1 | AA34: 1 | AB34: 1 | AC34: 1 | AD34: 1 | AE34: 1 | AF34: 1 | AG34: 1 | AH34: 1 | AI34: 1 | AJ34: 1 | AK34: 1 | AL34: 1 | AM34: 1 | AN34: 1
C35: =Dashboard!K57 -> TIKTOKSHOP | D35: =Dashboard!U57 -> 263 | E35: =SUM(J35:AN35) -> 0 | F35: =E35-D35 -> -263 | G35: =_xlfn.IFS(F35>0,1,F35<0,E35/D35,F35=0,0) -> 0 | H35: =D35/'Action Plan'!$C$6 -> 10.115385 | I35: =SUMIF($J$5:$AN$5,TODAY(),J35:AN35) -> 0 | J35: 0 | K35: 0 | L35: 0 | M35: 0 | N35: 0 | O35: 0 | P35: 0 | Q35: 0 | R35: 0 | S35: 0 | T35: 0 | U35: 0 | V35: 0 | W35: 0 | X35: 0 | Y35: 0 | Z35: 0 | AA35: 0 | AB35: 0 | AC35: 0 | AD35: 0 | AE35: 0 | AF35: 0 | AG35: 0 | AH35: 0 | AI35: 0 | AJ35: 0 | AK35: 0 | AL35: 0 | AM35: 0 | AN35: 0
C36: =Dashboard!K58 -> SHOPPEE | D36: =Dashboard!U58 -> 298 | E36: =SUM(J36:AN36) -> 124 | F36: =E36-D36 -> -174 | G36: =_xlfn.IFS(F36>0,1,F36<0,E36/D36,F36=0,0) -> 0.41610738 | H36: =D36/'Action Plan'!$C$6 -> 11.461538 | I36: =SUMIF($J$5:$AN$5,TODAY(),J36:AN36) -> 0 | J36: 4 | K36: 4 | L36: 4 | M36: 4 | N36: 4 | O36: 4 | P36: 4 | Q36: 4 | R36: 4 | S36: 4 | T36: 4 | U36: 4 | V36: 4 | W36: 4 | X36: 4 | Y36: 4 | Z36: 4 | AA36: 4 | AB36: 4 | AC36: 4 | AD36: 4 | AE36: 4 | AF36: 4 | AG36: 4 | AH36: 4 | AI36: 4 | AJ36: 4 | AK36: 4 | AL36: 4 | AM36: 4 | AN36: 4
C37: =Dashboard!K59 -> ZALO | D37: =Dashboard!U59 -> 25 | E37: =SUM(J37:AN37) -> 155 | F37: =E37-D37 -> 130 | G37: =_xlfn.IFS(F37>0,1,F37<0,E37/D37,F37=0,0) -> 1 | H37: =D37/'Action Plan'!$C$6 -> 0.96153846 | I37: =SUMIF($J$5:$AN$5,TODAY(),J37:AN37) -> 0 | J37: 5 | K37: 5 | L37: 5 | M37: 5 | N37: 5 | O37: 5 | P37: 5 | Q37: 5 | R37: 5 | S37: 5 | T37: 5 | U37: 5 | V37: 5 | W37: 5 | X37: 5 | Y37: 5 | Z37: 5 | AA37: 5 | AB37: 5 | AC37: 5 | AD37: 5 | AE37: 5 | AF37: 5 | AG37: 5 | AH37: 5 | AI37: 5 | AJ37: 5 | AK37: 5 | AL37: 5 | AM37: 5 | AN37: 5
C38: ADS | D38: =Dashboard!E60 -> 70 | E38: =Dashboard!F60 -> 188 | F38: =E38-D38 -> 118 | G38: =_xlfn.IFS(F38>0,1,F38<=0,E38/D38) -> 1 | H38: =D38/'Action Plan'!$C$6 -> 2.6923077 | I38: =SUMIF($J$5:$AN$5,TODAY(),J38:AN38) -> 0 | J38: =J39 -> 1 | K38: =K39 -> 1 | L38: =L39 -> 1 | M38: =M39 -> 1 | N38: =N39 -> 1 | O38: =O39 -> 1 | P38: =P39 -> 1 | Q38: =Q39 -> 1 | ... AN38: =AN39 -> 2
C39: =Dashboard!K60 -> ADS | D39: =Dashboard!U60 -> 40 | E39: =SUM(E40:E45) -> 32 | F39: =E39-D39 -> -8 | G39: =_xlfn.IFS(F39>0,1,F39<=0,E39/D39) -> 0.8 | H39: =D39/'Action Plan'!$C$6 -> 1.5384615 | I39: =SUM(I40:I45) -> 0 | J39: =SUM(J40:J45) -> 1 | K39: =SUM(K40:K45) -> 1 | L39: =SUM(L40:L45) -> 1 | M39: =SUM(M40:M45) -> 1 | N39: =SUM(N40:N45) -> 1 | O39: =SUM(O40:O45) -> 1 | P39: =SUM(P40:P45) -> 1 | ... AN39: =SUM(AN40:AN45) -> 2
C40: =Dashboard!K61 -> FACEBOOK | D40: =Dashboard!U61 -> 0 | E40: =SUM(J40:AN40) -> 0 | F40: =E40-D40 -> 0 | G40: =_xlfn.IFS(F40>0,1,F40<0,E40/D40,F40=0,0) -> 0 | H40: =D40/'Action Plan'!$C$6 -> 0 | I40: =SUMIF($J$5:$AN$5,TODAY(),J40:AN40) -> 0 | J40: 0 | K40: 0 | L40: 0 | M40: 0 | N40: 0 | O40: 0 | P40: 0 | Q40: 0 | R40: 0 | S40: 0 | T40: 0 | U40: 0 | V40: 0 | W40: 0 | X40: 0 | Y40: 0 | Z40: 0 | AA40: 0 | AB40: 0 | AC40: 0 | AD40: 0 | AE40: 0 | AF40: 0 | AG40: 0 | AH40: 0 | AI40: 0 | AJ40: 0 | AK40: 0 | AL40: 0 | AM40: 0 | AN40: 0
C41: =Dashboard!K62 -> LANDING PAGE | D41: =Dashboard!U62 -> 0 | E41: =SUM(J41:AN41) -> 0 | F41: =E41-D41 -> 0 | G41: =_xlfn.IFS(F41>0,1,F41<0,E41/D41,F41=0,0) -> 0 | H41: =D41/'Action Plan'!$C$6 -> 0 | I41: =SUMIF($J$5:$AN$5,TODAY(),J41:AN41) -> 0 | J41: 0 | K41: 0 | L41: 0 | M41: 0 | N41: 0 | O41: 0 | P41: 0 | Q41: 0 | R41: 0 | S41: 0 | T41: 0 | U41: 0 | V41: 0 | W41: 0 | X41: 0 | Y41: 0 | Z41: 0 | AA41: 0 | AB41: 0 | AC41: 0 | AD41: 0 | AE41: 0 | AF41: 0 | AG41: 0 | AH41: 0 | AI41: 0 | AJ41: 0 | AK41: 0 | AL41: 0 | AM41: 0 | AN41: 0
C42: =Dashboard!K63 -> WEBSITE | D42: =Dashboard!U63 -> 0 | E42: =SUM(J42:AN42) -> 0 | F42: =E42-D42 -> 0 | G42: =_xlfn.IFS(F42>0,1,F42<0,E42/D42,F42=0,0) -> 0 | H42: =D42/'Action Plan'!$C$6 -> 0 | I42: =SUMIF($J$5:$AN$5,TODAY(),J42:AN42) -> 0 | J42: 0 | K42: 0 | L42: 0 | M42: 0 | N42: 0 | O42: 0 | P42: 0 | Q42: 0 | R42: 0 | S42: 0 | T42: 0 | U42: 0 | V42: 0 | W42: 0 | X42: 0 | Y42: 0 | Z42: 0 | AA42: 0 | AB42: 0 | AC42: 0 | AD42: 0 | AE42: 0 | AF42: 0 | AG42: 0 | AH42: 0 | AI42: 0 | AJ42: 0 | AK42: 0 | AL42: 0 | AM42: 0 | AN42: 0
C43: =Dashboard!K64 -> TIKTOKSHOP | D43: =Dashboard!U64 -> 20 | E43: =SUM(J43:AN43) -> 1 | F43: =E43-D43 -> -19 | G43: =_xlfn.IFS(F43>0,1,F43<0,E43/D43,F43=0,0) -> 0.05 | H43: =D43/'Action Plan'!$C$6 -> 0.76923077 | I43: =SUMIF($J$5:$AN$5,TODAY(),J43:AN43) -> 0 | J43: 0 | K43: 0 | L43: 0 | M43: 0 | N43: 0 | O43: 0 | P43: 0 | Q43: 0 | R43: 0 | S43: 0 | T43: 0 | U43: 0 | V43: 0 | W43: 0 | X43: 0 | Y43: 0 | Z43: 0 | AA43: 0 | AB43: 0 | AC43: 0 | AD43: 0 | AE43: 0 | AF43: 0 | AG43: 0 | AH43: 0 | AI43: 0 | AJ43: 0 | AK43: 0 | AL43: 0 | AM43: 0 | AN43: 1
C44: =Dashboard!K65 -> SHOPPEE | D44: =Dashboard!U65 -> 20 | E44: =SUM(J44:AN44) -> 31 | F44: =E44-D44 -> 11 | G44: =_xlfn.IFS(F44>0,1,F44<0,E44/D44,F44=0,0) -> 1 | H44: =D44/'Action Plan'!$C$6 -> 0.76923077 | I44: =SUMIF($J$5:$AN$5,TODAY(),J44:AN44) -> 0 | J44: 1 | K44: 1 | L44: 1 | M44: 1 | N44: 1 | O44: 1 | P44: 1 | Q44: 1 | R44: 1 | S44: 1 | T44: 1 | U44: 1 | V44: 1 | W44: 1 | X44: 1 | Y44: 1 | Z44: 1 | AA44: 1 | AB44: 1 | AC44: 1 | AD44: 1 | AE44: 1 | AF44: 1 | AG44: 1 | AH44: 1 | AI44: 1 | AJ44: 1 | AK44: 1 | AL44: 1 | AM44: 1 | AN44: 1
C45: =Dashboard!K66 -> ZALO | D45: =Dashboard!U66 -> 0 | E45: =SUM(J45:AN45) -> 0 | F45: =E45-D45 -> 0 | G45: =_xlfn.IFS(F45>0,1,F45<0,E45/D45,F45=0,0) -> 0 | H45: =D45/'Action Plan'!$C$6 -> 0 | I45: =SUMIF($J$5:$AN$5,TODAY(),J45:AN45) -> 0 | J45: 0 | K45: 0 | L45: 0 | M45: 0 | N45: 0 | O45: 0 | P45: 0 | Q45: 0 | R45: 0 | S45: 0 | T45: 0 | U45: 0 | V45: 0 | W45: 0 | X45: 0 | Y45: 0 | Z45: 0 | AA45: 0 | AB45: 0 | AC45: 0 | AD45: 0 | AE45: 0 | AF45: 0 | AG45: 0 | AH45: 0 | AI45: 0 | AJ45: 0 | AK45: 0 | AL45: 0 | AM45: 0 | AN45: 0
C46: =Dashboard!K67 -> P3
C47: SALES | D47: =Dashboard!E68 -> 500000000 | E47: =Dashboard!F68 -> 373050000 | F47: =E47-D47 -> -126950000 | G47: =_xlfn.IFS(F47>0,1,F47<=0,E47/D47) -> 0.7461 | H47: =D47/'Action Plan'!$C$6 -> 19230769 | I47: =SUMIF($J$5:$AN$5,TODAY(),J47:AN47) -> 0 | J47: =J48 -> 24000000 | K47: =K48 -> 10000000 | L47: =L48 -> 10000000 | M47: =M48 -> 10000000 | N47: =N48 -> 10000000 | O47: =O48 -> 10000000 | P47: =P48 -> 10000000 | Q47: =Q48 -> 10000000 | ... AN47: =AN48 -> 6000000
C48: =Dashboard!K68 -> SALES REVENUE | D48: =Dashboard!U68 -> 250000000 | E48: =SUM(E49:E54) -> 320000000 | F48: =E48-D48 -> 70000000 | G48: =_xlfn.IFS(F48>0,1,F48<=0,E48/D48) -> 1 | H48: =D48/'Action Plan'!$C$6 -> 9615384.6 | I48: =SUM(I49:I54) -> 0 | J48: =SUM(J49:J54) -> 24000000 | K48: =SUM(K49:K54) -> 10000000 | L48: =SUM(L49:L54) -> 10000000 | M48: =SUM(M49:M54) -> 10000000 | N48: =SUM(N49:N54) -> 10000000 | O48: =SUM(O49:O54) -> 10000000 | P48: =SUM(P49:P54) -> 10000000 | ... AN48: =SUM(AN49:AN54) -> 6000000
C49: =Dashboard!K69 -> FACEBOOK | D49: =Dashboard!U69 -> 25000000 | E49: =SUM(J49:AN49) -> 36000000 | F49: =E49-D49 -> 11000000 | G49: =_xlfn.IFS(F49>0,1,F49<=0,E49/D49) -> 1 | H49: =D49/'Action Plan'!$C$6 -> 961538.46 | I49: =SUMIF($J$5:$AN$5,TODAY(),J49:AN49) -> 0 | J49: 6000000 | K49: 1000000 | L49: 1000000 | M49: 1000000 | N49: 1000000 | O49: 1000000 | P49: 1000000 | Q49: 1000000 | R49: 1000000 | S49: 1000000 | T49: 1000000 | U49: 1000000 | V49: 1000000 | W49: 1000000 | X49: 1000000 | Y49: 1000000 | Z49: 1000000 | AA49: 1000000 | AB49: 1000000 | AC49: 1000000 | AD49: 1000000 | AE49: 1000000 | AF49: 1000000 | AG49: 1000000 | AH49: 1000000 | AI49: 1000000 | AJ49: 1000000 | AK49: 1000000 | AL49: 1000000 | AM49: 1000000 | AN49: 1000000
C50: =Dashboard!K70 -> LANDING PAGE | D50: =Dashboard!U70 -> 125000000 | E50: =SUM(J50:AN50) -> 36000000 | F50: =E50-D50 -> -89000000 | G50: =_xlfn.IFS(F50>0,1,F50<=0,E50/D50) -> 0.288 | H50: =D50/'Action Plan'!$C$6 -> 4807692.3 | I50: =SUMIF($J$5:$AN$5,TODAY(),J50:AN50) -> 0 | J50: 6000000 | K50: 1000000 | L50: 1000000 | M50: 1000000 | N50: 1000000 | O50: 1000000 | P50: 1000000 | Q50: 1000000 | R50: 1000000 | S50: 1000000 | T50: 1000000 | U50: 1000000 | V50: 1000000 | W50: 1000000 | X50: 1000000 | Y50: 1000000 | Z50: 1000000 | AA50: 1000000 | AB50: 1000000 | AC50: 1000000 | AD50: 1000000 | AE50: 1000000 | AF50: 1000000 | AG50: 1000000 | AH50: 1000000 | AI50: 1000000 | AJ50: 1000000 | AK50: 1000000 | AL50: 1000000 | AM50: 1000000 | AN50: 1000000
C51: =Dashboard!K71 -> WEBSITE | D51: =Dashboard!U71 -> 25000000 | E51: =SUM(J51:AN51) -> 33000000 | F51: =E51-D51 -> 8000000 | G51: =_xlfn.IFS(F51>0,1,F51<=0,E51/D51) -> 1 | H51: =D51/'Action Plan'!$C$6 -> 961538.46 | I51: =SUMIF($J$5:$AN$5,TODAY(),J51:AN51) -> 0 | J51: 3000000 | K51: 1000000 | L51: 1000000 | M51: 1000000 | N51: 1000000 | O51: 1000000 | P51: 1000000 | Q51: 1000000 | R51: 1000000 | S51: 1000000 | T51: 1000000 | U51: 1000000 | V51: 1000000 | W51: 1000000 | X51: 1000000 | Y51: 1000000 | Z51: 1000000 | AA51: 1000000 | AB51: 1000000 | AC51: 1000000 | AD51: 1000000 | AE51: 1000000 | AF51: 1000000 | AG51: 1000000 | AH51: 1000000 | AI51: 1000000 | AJ51: 1000000 | AK51: 1000000 | AL51: 1000000 | AM51: 1000000 | AN51: 1000000
C52: =Dashboard!K72 -> TIKTOKSHOP | D52: =Dashboard!U72 -> 25000000 | E52: =SUM(J52:AN52) -> 91000000 | F52: =E52-D52 -> 66000000 | G52: =_xlfn.IFS(F52>0,1,F52<=0,E52/D52) -> 1 | H52: =D52/'Action Plan'!$C$6 -> 961538.46 | I52: =SUMIF($J$5:$AN$5,TODAY(),J52:AN52) -> 0 | J52: 3000000 | K52: 3000000 | L52: 3000000 | M52: 3000000 | N52: 3000000 | O52: 3000000 | P52: 3000000 | Q52: 3000000 | R52: 3000000 | S52: 3000000 | T52: 3000000 | U52: 3000000 | V52: 3000000 | W52: 3000000 | X52: 3000000 | Y52: 3000000 | Z52: 3000000 | AA52: 3000000 | AB52: 3000000 | AC52: 3000000 | AD52: 3000000 | AE52: 3000000 | AF52: 3000000 | AG52: 3000000 | AH52: 3000000 | AI52: 3000000 | AJ52: 3000000 | AK52: 3000000 | AL52: 3000000 | AM52: 3000000 | AN52: 1000000
C53: =Dashboard!K73 -> SHOPPEE | D53: =Dashboard!U73 -> 25000000 | E53: =SUM(J53:AN53) -> 91000000 | F53: =E53-D53 -> 66000000 | G53: =_xlfn.IFS(F53>0,1,F53<=0,E53/D53) -> 1 | H53: =D53/'Action Plan'!$C$6 -> 961538.46 | I53: =SUMIF($J$5:$AN$5,TODAY(),J53:AN53) -> 0 | J53: 3000000 | K53: 3000000 | L53: 3000000 | M53: 3000000 | N53: 3000000 | O53: 3000000 | P53: 3000000 | Q53: 3000000 | R53: 3000000 | S53: 3000000 | T53: 3000000 | U53: 3000000 | V53: 3000000 | W53: 3000000 | X53: 3000000 | Y53: 3000000 | Z53: 3000000 | AA53: 3000000 | AB53: 3000000 | AC53: 3000000 | AD53: 3000000 | AE53: 3000000 | AF53: 3000000 | AG53: 3000000 | AH53: 3000000 | AI53: 3000000 | AJ53: 3000000 | AK53: 3000000 | AL53: 3000000 | AM53: 3000000 | AN53: 1000000
C54: =Dashboard!K74 -> ZALO | D54: =Dashboard!U74 -> 25000000 | E54: =SUM(J54:AN54) -> 33000000 | F54: =E54-D54 -> 8000000 | G54: =_xlfn.IFS(F54>0,1,F54<=0,E54/D54) -> 1 | H54: =D54/'Action Plan'!$C$6 -> 961538.46 | I54: =SUMIF($J$5:$AN$5,TODAY(),J54:AN54) -> 0 | J54: 3000000 | K54: 1000000 | L54: 1000000 | M54: 1000000 | N54: 1000000 | O54: 1000000 | P54: 1000000 | Q54: 1000000 | R54: 1000000 | S54: 1000000 | T54: 1000000 | U54: 1000000 | V54: 1000000 | W54: 1000000 | X54: 1000000 | Y54: 1000000 | Z54: 1000000 | AA54: 1000000 | AB54: 1000000 | AC54: 1000000 | AD54: 1000000 | AE54: 1000000 | AF54: 1000000 | AG54: 1000000 | AH54: 1000000 | AI54: 1000000 | AJ54: 1000000 | AK54: 1000000 | AL54: 1000000 | AM54: 1000000 | AN54: 1000000
B55: HIGHER = BAD | C55: =Dashboard!K75 -> A/S RATIO | D55: =Dashboard!U75 -> 0.18666667 | E55: =AVERAGE(E56:E61) -> 0.71666667 | F55: =D55-E55 -> -0.53 | G55: =_xlfn.IFS(F55>0,1,F55<=0,D55/E55) -> 0.26046512 | H55: =D55/'Action Plan'!$C$6 -> 0.0071794872 | I55: =AVERAGE(I56:I61) -> 0 | J55: =SUM(J56:J61) -> 0.13333333 | K55: =SUM(K56:K61) -> 0.13333333 | L55: =SUM(L56:L61) -> 0.13333333 | M55: =SUM(M56:M61) -> 0.13333333 | N55: =SUM(N56:N61) -> 0.13333333 | O55: =SUM(O56:O61) -> 0.13333333 | P55: =SUM(P56:P61) -> 0.13333333 | Q55: =SUM(Q56:Q61) -> 0.13333333 | ... AN55: =SUM(AN56:AN61) -> 0.3
C56: =Dashboard!K76 -> FACEBOOK | D56: =Dashboard!U76 -> 0.1 | E56: =SUM(J56:AN56) -> 0 | F56: =D56-E56 -> 0.1 | G56: =_xlfn.IFS(F56>0,1,F56<=0,D56/E56) -> 1 | H56: =D56/'Action Plan'!$C$6 -> 0.0038461538 | I56: =SUMIF($J$5:$AN$5,TODAY(),J56:AN56) -> 0 | J56: =J9/J49 -> 0 | K56: =K9/K49 -> 0 | L56: =L9/L49 -> 0 | M56: =M9/M49 -> 0 | N56: =N9/N49 -> 0 | O56: =O9/O49 -> 0 | P56: =P9/P49 -> 0 | Q56: =Q9/Q49 -> 0 | ... AN56: =AN9/AN49 -> 0
C57: =Dashboard!K77 -> LANDING PAGE | D57: =Dashboard!U77 -> 0.12 | E57: =SUM(J57:AN57) -> 0 | F57: =D57-E57 -> 0.12 | G57: =_xlfn.IFS(F57>0,1,F57<=0,D57/E57) -> 1 | H57: =D57/'Action Plan'!$C$6 -> 0.0046153846 | I57: =SUMIF($J$5:$AN$5,TODAY(),J57:AN57) -> 0 | J57: =J15/J50 -> 0 | K57: =K15/K50 -> 0 | L57: =L15/L50 -> 0 | M57: =M15/M50 -> 0 | N57: =N15/N50 -> 0 | O57: =O15/O50 -> 0 | P57: =P15/P50 -> 0 | Q57: =Q15/Q50 -> 0 | ... AN57: =AN15/AN50 -> 0
C58: =Dashboard!K78 -> WEBSITE | D58: =Dashboard!U78 -> 0.1 | E58: =SUM(J58:AN58) -> 0 | F58: =D58-E58 -> 0.1 | G58: =_xlfn.IFS(F58>0,1,F58<=0,D58/E58) -> 1 | H58: =D58/'Action Plan'!$C$6 -> 0.0038461538 | I58: =SUMIF($J$5:$AN$5,TODAY(),J58:AN58) -> 0 | J58: =J21/J51 -> 0 | K58: =K21/K51 -> 0 | L58: =L21/L51 -> 0 | M58: =M21/M51 -> 0 | N58: =N21/N51 -> 0 | O58: =O21/O51 -> 0 | P58: =P21/P51 -> 0 | Q58: =Q21/Q51 -> 0 | ... AN58: =AN21/AN51 -> 0
C59: =Dashboard!K79 -> TIKTOKSHOP | D59: =Dashboard!U79 -> 0.3 | E59: =SUM(J59:AN59) -> 2.1 | F59: =D59-E59 -> -1.8 | G59: =_xlfn.IFS(F59>0,1,F59<=0,D59/E59) -> 0.14285714 | H59: =D59/'Action Plan'!$C$6 -> 0.011538462 | I59: =SUMIF($J$5:$AN$5,TODAY(),J59:AN59) -> 0 | J59: =J24/J52 -> 0.066666667 | K59: =K24/K52 -> 0.066666667 | L59: =L24/L52 -> 0.066666667 | M59: =M24/M52 -> 0.066666667 | N59: =N24/N52 -> 0.066666667 | O59: =O24/O52 -> 0.066666667 | P59: =P24/P52 -> 0.066666667 | Q59: =Q24/Q52 -> 0.066666667 | ... AN59: =AN24/AN52 -> 0.1
C60: =Dashboard!K80 -> SHOPPEE | D60: =Dashboard!U80 -> 0.1 | E60: =SUM(J60:AN60) -> 2.1 | F60: =D60-E60 -> -2 | G60: =_xlfn.IFS(F60>0,1,F60<=0,D60/E60) -> 0.047619048 | H60: =D60/'Action Plan'!$C$6 -> 0.0038461538 | I60: =SUMIF($J$5:$AN$5,TODAY(),J60:AN60) -> 0 | J60: =J25/J53 -> 0.066666667 | K60: =K25/K53 -> 0.066666667 | L60: =L25/L53 -> 0.066666667 | M60: =M25/M53 -> 0.066666667 | N60: =N25/N53 -> 0.066666667 | O60: =O25/O53 -> 0.066666667 | P60: =P25/P53 -> 0.066666667 | Q60: =Q25/Q53 -> 0.066666667 | ... AN60: =AN25/AN53 -> 0.1
C61: =Dashboard!K81 -> ZALO | D61: =Dashboard!U81 -> 0.4 | E61: =SUM(J61:AN61) -> 0.1 | F61: =D61-E61 -> 0.3 | G61: =_xlfn.IFS(F61>0,1,F61<=0,D61/E61) -> 1 | H61: =D61/'Action Plan'!$C$6 -> 0.015384615 | I61: =SUMIF($J$5:$AN$5,TODAY(),J61:AN61) -> 0 | J61: =J26/J54 -> 0 | K61: =K26/K54 -> 0 | L61: =L26/L54 -> 0 | M61: =M26/M54 -> 0 | N61: =N26/N54 -> 0 | O61: =O26/O54 -> 0 | P61: =P26/P54 -> 0 | Q61: =Q26/Q54 -> 0 | ... AN61: =AN26/AN54 -> 0.1
B62: HIGHER = GOOD | C62: =Dashboard!K82 -> CONVERSION RATE | D62: =Dashboard!U82 -> 0.2 | E62: =AVERAGE(E63:E68) -> 0.21833333 | F62: =E62-D62 -> 0.018333333 | G62: =_xlfn.IFS(F62>0,1,F62<=0,E62/D62) -> 1 | H62: =D62/'Action Plan'!$C$6 -> 0.0076923077 | I62: =AVERAGE(I63:I68) -> 0 | J62: =SUM(J63:J69) -> 0.04 | K62: =SUM(K63:K69) -> 0.04 | L62: =SUM(L63:L69) -> 0.04 | M62: =SUM(M63:M69) -> 0.04 | N62: =SUM(N63:N69) -> 0.04 | O62: =SUM(O63:O69) -> 0.04 | P62: =SUM(P63:P69) -> 0.04 | Q62: =SUM(Q63:Q69) -> 0.04 | ... AN62: =SUM(AN63:AN69) -> 0.11
C63: =Dashboard!K83 -> FACEBOOK | D63: =Dashboard!U83 -> 0.05 | E63: =SUM(J63:AN63) -> 0.03 | F63: =E63-D63 -> -0.02 | G63: =_xlfn.IFS(F63>0,1,F63<=0,E63/D63) -> 0.6 | H63: =D63/'Action Plan'!$C$6 -> 0.0019230769 | I63: =SUMIF($J$5:$AN$5,TODAY(),J63:AN63) -> 0 | J63: 0 | K63: 0 | L63: 0 | M63: 0 | N63: 0 | O63: 0 | P63: 0 | Q63: 0 | R63: 0 | S63: 0 | T63: 0 | U63: 0 | V63: 0 | W63: 0 | X63: 0 | Y63: 0 | Z63: 0 | AA63: 0 | AB63: 0 | AC63: 0 | AD63: 0 | AE63: 0 | AF63: 0 | AG63: 0 | AH63: 0 | AI63: 0 | AJ63: 0 | AK63: 0 | AL63: 0 | AM63: 0 | AN63: 0.03
C64: =Dashboard!K84 -> LANDING PAGE | D64: =Dashboard!U84 -> 0.1 | E64: =SUM(J64:AN64) -> 0.03 | F64: =E64-D64 -> -0.07 | G64: =_xlfn.IFS(F64>0,1,F64<=0,E64/D64) -> 0.3 | H64: =D64/'Action Plan'!$C$6 -> 0.0038461538 | I64: =SUMIF($J$5:$AN$5,TODAY(),J64:AN64) -> 0 | J64: 0 | K64: 0 | L64: 0 | M64: 0 | N64: 0 | O64: 0 | P64: 0 | Q64: 0 | R64: 0 | S64: 0 | T64: 0 | U64: 0 | V64: 0 | W64: 0 | X64: 0 | Y64: 0 | Z64: 0 | AA64: 0 | AB64: 0 | AC64: 0 | AD64: 0 | AE64: 0 | AF64: 0 | AG64: 0 | AH64: 0 | AI64: 0 | AJ64: 0 | AK64: 0 | AL64: 0 | AM64: 0 | AN64: 0.03
C65: =Dashboard!K85 -> WEBSITE | D65: =Dashboard!U85 -> 0.05 | E65: =SUM(J65:AN65) -> 0.02 | F65: =E65-D65 -> -0.03 | G65: =_xlfn.IFS(F65>0,1,F65<=0,E65/D65) -> 0.4 | H65: =D65/'Action Plan'!$C$6 -> 0.0019230769 | I65: =SUMIF($J$5:$AN$5,TODAY(),J65:AN65) -> 0 | J65: 0 | K65: 0 | L65: 0 | M65: 0 | N65: 0 | O65: 0 | P65: 0 | Q65: 0 | R65: 0 | S65: 0 | T65: 0 | U65: 0 | V65: 0 | W65: 0 | X65: 0 | Y65: 0 | Z65: 0 | AA65: 0 | AB65: 0 | AC65: 0 | AD65: 0 | AE65: 0 | AF65: 0 | AG65: 0 | AH65: 0 | AI65: 0 | AJ65: 0 | AK65: 0 | AL65: 0 | AM65: 0 | AN65: 0.02
C66: =Dashboard!K86 -> TIKTOKSHOP | D66: =Dashboard!U86 -> 0.65 | E66: =SUM(J66:AN66) -> 0.91 | F66: =E66-D66 -> 0.26 | G66: =_xlfn.IFS(F66>0,1,F66<=0,E66/D66) -> 1 | H66: =D66/'Action Plan'!$C$6 -> 0.025 | I66: =SUMIF($J$5:$AN$5,TODAY(),J66:AN66) -> 0 | J66: 0.03 | K66: 0.03 | L66: 0.03 | M66: 0.03 | N66: 0.03 | O66: 0.03 | P66: 0.03 | Q66: 0.03 | R66: 0.03 | S66: 0.03 | T66: 0.03 | U66: 0.03 | V66: 0.03 | W66: 0.03 | X66: 0.03 | Y66: 0.03 | Z66: 0.03 | AA66: 0.03 | AB66: 0.03 | AC66: 0.03 | AD66: 0.03 | AE66: 0.03 | AF66: 0.03 | AG66: 0.03 | AH66: 0.03 | AI66: 0.03 | AJ66: 0.03 | AK66: 0.03 | AL66: 0.03 | AM66: 0.03 | AN66: 0.01
C67: =Dashboard!K87 -> SHOPPEE | D67: =Dashboard!U87 -> 0.3 | E67: =SUM(J67:AN67) -> 0.31 | F67: =E67-D67 -> 0.01 | G67: =_xlfn.IFS(F67>0,1,F67<=0,E67/D67) -> 1 | H67: =D67/'Action Plan'!$C$6 -> 0.011538462 | I67: =SUMIF($J$5:$AN$5,TODAY(),J67:AN67) -> 0 | J67: 0.01 | K67: 0.01 | L67: 0.01 | M67: 0.01 | N67: 0.01 | O67: 0.01 | P67: 0.01 | Q67: 0.01 | R67: 0.01 | S67: 0.01 | T67: 0.01 | U67: 0.01 | V67: 0.01 | W67: 0.01 | X67: 0.01 | Y67: 0.01 | Z67: 0.01 | AA67: 0.01 | AB67: 0.01 | AC67: 0.01 | AD67: 0.01 | AE67: 0.01 | AF67: 0.01 | AG67: 0.01 | AH67: 0.01 | AI67: 0.01 | AJ67: 0.01 | AK67: 0.01 | AL67: 0.01 | AM67: 0.01 | AN67: 0.01
C68: =Dashboard!K88 -> ZALO | D68: =Dashboard!U88 -> 0.05 | E68: =SUM(J68:AN68) -> 0.01 | F68: =E68-D68 -> -0.04 | G68: =_xlfn.IFS(F68>0,1,F68<=0,E68/D68) -> 0.2 | H68: =D68/'Action Plan'!$C$6 -> 0.0019230769 | I68: =SUMIF($J$5:$AN$5,TODAY(),J68:AN68) -> 0 | J68: 0 | K68: 0 | L68: 0 | M68: 0 | N68: 0 | O68: 0 | P68: 0 | Q68: 0 | R68: 0 | S68: 0 | T68: 0 | U68: 0 | V68: 0 | W68: 0 | X68: 0 | Y68: 0 | Z68: 0 | AA68: 0 | AB68: 0 | AC68: 0 | AD68: 0 | AE68: 0 | AF68: 0 | AG68: 0 | AH68: 0 | AI68: 0 | AJ68: 0 | AK68: 0 | AL68: 0 | AM68: 0 | AN68: 0.01
C69: =Dashboard!K74 -> ZALO | D69: =Dashboard!M74 -> 25000000 | E69: =SUM(J69:AN69) -> 0 | F69: =E69-D69 -> -25000000 | G69: =_xludf.IFS(F69>0,1,F69<=0,E69/D69) -> #NAME? | H69: =D69/'Action Plan'!$C$6 -> 961538.46 | I69: =SUMIF($J$5:$AN$5,TODAY(),J69:AN69) -> 0
C70: TỔNG A/S | D70: =Dashboard!E75 -> 0.37333333 | E70: =Dashboard!F75 -> 19.066667 | F70: =E70-D70 -> 18.693333 | G70: =_xludf.IFS(F70>0,0,F70<=0,E70/D70) -> #NAME? | H70: =D70/'Action Plan'!$C$6 -> 0.014358974 | I70: =SUMIF($J$5:$AN$5,TODAY(),J70:AN70) -> 0 | J70: =(J71+#REF!)/2 -> #REF! | K70: =(K71+#REF!)/2 -> #REF! | L70: =(L71+#REF!)/2 -> #REF! | M70: =(M71+#REF!)/2 -> #REF! | N70: =(N71+#REF!)/2 -> #REF! | O70: =(O71+#REF!)/2 -> #REF! | P70: =(P71+#REF!)/2 -> #REF! | Q70: =(Q71+#REF!)/2 -> #REF! | ... AN70: =(AN71+#REF!)/2 -> #REF!
C71: =Dashboard!K75 -> A/S RATIO | D71: =Dashboard!M75 -> 0.18666667 | E71: =AVERAGE(E72:E77) -> 45000000 | F71: =AVERAGE(F72:F77) -> 45000000 | G71: =_xludf.IFS(F71>0,0,F71<=0,E71/D71) -> #NAME? | H71: =AVERAGE(H72:H77) -> 0.0071794872 | I71: =AVERAGE(I72:I77) -> 0 | J71: =AVERAGE(J72:J77) -> 1388888.9 | K71: =AVERAGE(K72:K77) -> 1388888.9 | L71: =AVERAGE(L72:L77) -> 1388888.9 | M71: =AVERAGE(M72:M77) -> 1388888.9 | N71: =AVERAGE(N72:N77) -> 1388888.9 | O71: =AVERAGE(O72:O77) -> 1388888.9 | ... AN71: =AVERAGE(AN72:AN77) -> 3333333.3
C72: =Dashboard!K76 -> FACEBOOK | D72: =Dashboard!M76 -> 0.1 | E72: =SUM(J72:AN72) -> 0 | F72: =E72-D72 -> -0.1 | G72: =_xludf.IFS(F72>0,0,F72<=0,E72/D72) -> #NAME? | H72: =D72/'Action Plan'!$C$6 -> 0.0038461538 | I72: =SUMIF($J$5:$AN$5,TODAY(),J72:AN72) -> 0 | J72: =IF(J63<>0,J$9/J63,0) -> 0 | K72: =IF(K63<>0,K$9/K63,0) -> 0 | L72: =IF(L63<>0,L$9/L63,0) -> 0 | M72: =IF(M63<>0,M$9/M63,0) -> 0 | N72: =IF(N63<>0,N$9/N63,0) -> 0 | O72: =IF(O63<>0,O$9/O63,0) -> 0 | P72: =IF(P63<>0,P$9/P63,0) -> 0 | Q72: =IF(Q63<>0,Q$9/Q63,0) -> 0 | ... AN72: =IF(AN63<>0,AN$9/AN63,0) -> 0
C73: =Dashboard!K77 -> LANDING PAGE | D73: =Dashboard!M77 -> 0.12 | E73: =SUM(J73:AN73) -> 0 | F73: =E73-D73 -> -0.12 | G73: =_xludf.IFS(F73>0,0,F73<=0,E73/D73) -> #NAME? | H73: =D73/'Action Plan'!$C$6 -> 0.0046153846 | I73: =SUMIF($J$5:$AN$5,TODAY(),J73:AN73) -> 0 | J73: =IF(J64<>0,J$15/J64,0) -> 0 | K73: =IF(K64<>0,K$15/K64,0) -> 0 | L73: =IF(L64<>0,L$15/L64,0) -> 0 | M73: =IF(M64<>0,M$15/M64,0) -> 0 | N73: =IF(N64<>0,N$15/N64,0) -> 0 | O73: =IF(O64<>0,O$15/O64,0) -> 0 | P73: =IF(P64<>0,P$15/P64,0) -> 0 | Q73: =IF(Q64<>0,Q$15/Q64,0) -> 0 | ... AN73: =IF(AN64<>0,AN$15/AN64,0) -> 0
C74: =Dashboard!K78 -> WEBSITE | D74: =Dashboard!M78 -> 0.1 | E74: =SUM(J74:AN74) -> 0 | F74: =E74-D74 -> -0.1 | G74: =_xludf.IFS(F74>0,0,F74<=0,E74/D74) -> #NAME? | H74: =D74/'Action Plan'!$C$6 -> 0.0038461538 | I74: =SUMIF($J$5:$AN$5,TODAY(),J74:AN74) -> 0 | J74: =IF(J65<>0,J$21/J65,0) -> 0 | K74: =IF(K65<>0,K$21/K65,0) -> 0 | L74: =IF(L65<>0,L$21/L65,0) -> 0 | M74: =IF(M65<>0,M$21/M65,0) -> 0 | N74: =IF(N65<>0,N$21/N65,0) -> 0 | O74: =IF(O65<>0,O$21/O65,0) -> 0 | P74: =IF(P65<>0,P$21/P65,0) -> 0 | Q74: =IF(Q65<>0,Q$21/Q65,0) -> 0 | ... AN74: =IF(AN65<>0,AN$21/AN65,0) -> 0
C75: =Dashboard!K79 -> TIKTOKSHOP | D75: =Dashboard!M79 -> 0.3 | E75: =SUM(J75:AN75) -> 2.6e+08 | F75: =E75-D75 -> 2.6e+08 | G75: =_xludf.IFS(F75>0,0,F75<=0,E75/D75) -> #NAME? | H75: =D75/'Action Plan'!$C$6 -> 0.011538462 | I75: =SUMIF($J$5:$AN$5,TODAY(),J75:AN75) -> 0 | J75: =IF(J66<>0,(J$24+J$28)/J66,0) -> 8333333.3 | K75: =IF(K66<>0,(K$24+K$28)/K66,0) -> 8333333.3 | L75: =IF(L66<>0,(L$24+L$28)/L66,0) -> 8333333.3 | M75: =IF(M66<>0,(M$24+M$28)/M66,0) -> 8333333.3 | N75: =IF(N66<>0,(N$24+N$28)/N66,0) -> 8333333.3 | O75: =IF(O66<>0,(O$24+O$28)/O66,0) -> 8333333.3 | P75: =IF(P66<>0,(P$24+P$28)/P66,0) -> 8333333.3 | Q75: =IF(Q66<>0,(Q$24+Q$28)/Q66,0) -> 8333333.3 | ... AN75: =IF(AN66<>0,(AN$24+AN$28)/AN66,0) -> 10000000
C76: =Dashboard!K80 -> SHOPPEE | D76: =Dashboard!M80 -> 0.1 | E76: =SUM(J76:AN76) -> 10000000 | F76: =E76-D76 -> 9999999.9 | G76: =_xludf.IFS(F76>0,0,F76<=0,E76/D76) -> #NAME? | H76: =D76/'Action Plan'!$C$6 -> 0.0038461538 | I76: =SUMIF($J$5:$AN$5,TODAY(),J76:AN76) -> 0 | J76: =IF(J68<>0,J$25/J68,0) -> 0 | K76: =IF(K68<>0,K$25/K68,0) -> 0 | L76: =IF(L68<>0,L$25/L68,0) -> 0 | M76: =IF(M68<>0,M$25/M68,0) -> 0 | N76: =IF(N68<>0,N$25/N68,0) -> 0 | O76: =IF(O68<>0,O$25/O68,0) -> 0 | P76: =IF(P68<>0,P$25/P68,0) -> 0 | Q76: =IF(Q68<>0,Q$25/Q68,0) -> 0 | ... AN76: =IF(AN68<>0,AN$25/AN68,0) -> 10000000
C77: =Dashboard!K81 -> ZALO | D77: =Dashboard!M81 -> 0.4 | E77: =SUM(J77:AN77) -> 0 | F77: =E77-D77 -> -0.4 | G77: =_xludf.IFS(F77>0,0,F77<=0,E77/D77) -> #NAME? | H77: =D77/'Action Plan'!$C$6 -> 0.015384615 | I77: =SUMIF($J$5:$AN$5,TODAY(),J77:AN77) -> 0 | J77: =IF(J69<>0,J$28/J69,0) -> 0 | K77: =IF(K69<>0,K$28/K69,0) -> 0 | L77: =IF(L69<>0,L$28/L69,0) -> 0 | M77: =IF(M69<>0,M$28/M69,0) -> 0 | N77: =IF(N69<>0,N$28/N69,0) -> 0 | O77: =IF(O69<>0,O$28/O69,0) -> 0 | P77: =IF(P69<>0,P$28/P69,0) -> 0 | Q77: =IF(Q69<>0,Q$28/Q69,0) -> 0 | ... AN77: =IF(AN69<>0,AN$28/AN69,0) -> 0
C78: TỔNG CVR | D78: =Dashboard!E82 -> 0.45833333 | E78: =Dashboard!F82 -> 0.45 | F78: =E78-D78 -> -0.0083333333 | G78: =_xludf.IFS(F78>0,0,F78<=0,E78/D78) -> #NAME? | H78: =D78/'Action Plan'!$C$6 -> 0.017628205 | I78: =SUMIF($J$5:$AN$5,TODAY(),J78:AN78) -> 0 | J78: =(J79+#REF!)/2 -> #DIV/0! | K78: =(K79+#REF!)/2 -> #DIV/0! | L78: =(L79+#REF!)/2 -> #DIV/0! | M78: =(M79+#REF!)/2 -> #DIV/0! | N78: =(N79+#REF!)/2 -> #DIV/0! | O78: =(O79+#REF!)/2 -> #DIV/0! | P78: =(P79+#REF!)/2 -> #DIV/0! | Q78: =(Q79+#REF!)/2 -> #DIV/0! | ... AN78: =(AN79+#REF!)/2 -> #DIV/0!
C79: =Dashboard!K82 -> CONVERSION RATE | D79: =Dashboard!M82 -> 0.25833333 | E79: =AVERAGE(E80:E82) -> 0 | F79: =AVERAGE(F80:F82) -> -0.05 | G79: =_xludf.IFS(F79>0,0,F79<=0,E79/D79) -> #NAME? | H79: =AVERAGE(H80:H82) -> 0.0019230769 | I79: =AVERAGE(I80:I82) -> 0 | J79: =AVERAGE(J80:J82) -> #DIV/0! | K79: =AVERAGE(K80:K82) -> #DIV/0! | L79: =AVERAGE(L80:L82) -> #DIV/0! | M79: =AVERAGE(M80:M82) -> #DIV/0! | N79: =AVERAGE(N80:N82) -> #DIV/0! | O79: =AVERAGE(O80:O82) -> #DIV/0! | ... AN79: =AVERAGE(AN80:AN82) -> #DIV/0!
C80: =Dashboard!K86 -> TIKTOKSHOP | D80: =Dashboard!M86 -> 0.05 | E80: =SUM(J80:AN80) -> 0 | F80: =E80-D80 -> -0.05 | G80: =_xludf.IFS(F80>0,0,F80<=0,E80/D80) -> #NAME? | H80: =D80/'Action Plan'!$C$6 -> 0.0019230769 | I80: =SUMIF($J$5:$AN$5,TODAY(),J80:AN80) -> 0
C81: =Dashboard!K87 -> SHOPPEE | D81: =Dashboard!M87 -> 0.05 | E81: =SUM(J81:AN81) -> 0 | F81: =E81-D81 -> -0.05 | G81: =_xludf.IFS(F81>0,0,F81<=0,E81/D81) -> #NAME? | H81: =D81/'Action Plan'!$C$6 -> 0.0019230769 | I81: =SUMIF($J$5:$AN$5,TODAY(),J81:AN81) -> 0
C82: =Dashboard!K88 -> ZALO | D82: =Dashboard!M88 -> 0.05 | E82: =SUM(J82:AN82) -> 0 | F82: =E82-D82 -> -0.05 | G82: =_xludf.IFS(F82>0,0,F82<=0,E82/D82) -> #NAME? | H82: =D82/'Action Plan'!$C$6 -> 0.0019230769 | I82: =SUMIF($J$5:$AN$5,TODAY(),J82:AN82) -> 0

Sheet Sale #1
A1: KPIs TRACKING | M1: =M8-($D$15+$D$16) -> -489.46337 | N1: =N8-(N2*$I$20+N3*$I$26+N4*$I$32+N5*I$35+N6*I$36+N7*I$39) -> 25.1875 | O1: =O8-$I$19 -> 0.46458333 | P1: =P8-$K$19 -> -3530769.2 | Q1: =Q8-($D$15+$D$16) -> -491.46337 | R1: =R8-(R2*$I$20+R3*$I$26+R4*$I$32+R5*M$35+R6*M$36+R7*M$39) -> 5.1875 | S1: =S8-$I$19 -> 0.6004529 | T1: =T8-$K$19 -> -3530769.2 | U1: =U8-($D$15+$D$16) -> -491.46337 | V1: =V8-(V2*$I$20+V3*$I$26+V4*$I$32+V5*Q$35+V6*Q$36+V7*Q$39) -> 9.1875 | W1: =W8-$I$19 -> 0.6004529 | X1: =X8-$K$19 -> -3530769.2 | Y1: =Y8-($D$15+$D$16) -> -491.46337 | Z1: =Z8-(Z2*$I$20+Z3*$I$26+Z4*$I$32+Z5*U$35+Z6*U$36+Z7*U$39) -> 9.1875 | AA1: =AA8-$I$19 -> 0.6004529 | AB1: =AB8-$K$19 -> -3530769.2 | AC1: =AC8-($D$15+$D$16) -> -491.46337 | AD1: =AD8-(AD2*$I$20+AD3*$I$26+AD4*$I$32+AD5*Y$35+AD6*Y$36+AD7*Y$39) -> 9.1875 | AE1: =AE8-$I$19 -> 0.6004529 | AF1: =AF8-$K$19 -> -3530769.2 | AG1: =AG8-($D$15+$D$16) -> -491.46337 | AH1: =AH8-(AH2*$I$20+AH3*$I$26+AH4*$I$32+AH5*AC$35+AH6*AC$36+AH7*AC$39) -> 9.1875 | AI1: =AI8-$I$19 -> 0.6004529 | AJ1: =AJ8-$K$19 -> -3530769.2 | AK1: =AK8-($D$15+$D$16) -> -491.46337 | AL1: =AL8-(AL2*$I$20+AL3*$I$26+AL4*$I$32+AL5*AG$35+AL6*AG$36+AL7*AG$39) -> 9.1875 | AM1: =AM8-$I$19 -> 0.6004529 | AN1: =AN8-$K$19 -> -3530769.2 | AO1: =AO8-($D$15+$D$16) -> -491.46337 | AP1: =AP8-(AP2*$I$20+AP3*$I$26+AP4*$I$32+AP5*AK$35+AP6*AK$36+AP7*AK$39) -> 9.1875 | AQ1: =AQ8-$I$19 -> 0.6004529 | AR1: =AR8-$K$19 -> -3530769.2 | AS1: =AS8-($D$15+$D$16) -> -491.46337 | AT1: =AT8-(AT2*$I$20+AT3*$I$26+AT4*$I$32+AT5*AO$35+AT6*AO$36+AT7*AO$39) -> 9.1875 | AU1: =AU8-$I$19 -> 0.6004529 | AV1: =AV8-$K$19 -> -3530769.2 | AW1: =AW8-($D$15+$D$16) -> -491.46337 | AX1: =AX8-(AX2*$I$20+AX3*$I$26+AX4*$I$32+AX5*AS$35+AX6*AS$36+AX7*AS$39) -> 9.1875 | AY1: =AY8-$I$19 -> 0.6004529 | AZ1: =AZ8-$K$19 -> -3530769.2 | BA1: =BA8-($D$15+$D$16) -> -491.46337 | BB1: =BB8-(BB2*$I$20+BB3*$I$26+BB4*$I$32+BB5*AW$35+BB6*AW$36+BB7*AW$39) -> 9.1875 | BC1: =BC8-$I$19 -> 0.6004529 | BD1: =BD8-$K$19 -> -3530769.2 | BE1: =BE8-($D$15+$D$16) -> -491.46337 | BF1: =BF8-(BF2*$I$20+BF3*$I$26+BF4*$I$32+BF5*BA$35+BF6*BA$36+BF7*BA$39) -> 9.1875 | BG1: =BG8-$I$19 -> 0.6004529 | BH1: =BH8-$K$19 -> -3530769.2 | BI1: =BI8-($D$15+$D$16) -> -491.46337 | BJ1: =BJ8-(BJ2*$I$20+BJ3*$I$26+BJ4*$I$32+BJ5*BE$35+BJ6*BE$36+BJ7*BE$39) -> 9.1875 | BK1: =BK8-$I$19 -> 0.6004529 | BL1: =BL8-$K$19 -> -3530769.2 | BM1: =BM8-($D$15+$D$16) -> -491.46337 | BN1: =BN8-(BN2*$I$20+BN3*$I$26+BN4*$I$32+BN5*BI$35+BN6*BI$36+BN7*BI$39) -> 9.1875 | BO1: =BO8-$I$19 -> 0.6004529 | BP1: =BP8-$K$19 -> -3530769.2 | BQ1: =BQ8-($D$15+$D$16) -> -491.46337 | BR1: =BR8-(BR2*$I$20+BR3*$I$26+BR4*$I$32+BR5*BM$35+BR6*BM$36+BR7*BM$39) -> 9.1875 | BS1: =BS8-$I$19 -> 0.6004529 | BT1: =BT8-$K$19 -> -3530769.2 | BU1: =BU8-($D$15+$D$16) -> -491.46337 | BV1: =BV8-(BV2*$I$20+BV3*$I$26+BV4*$I$32+BV5*BQ$35+BV6*BQ$36+BV7*BQ$39) -> 9.1875 | BW1: =BW8-$I$19 -> 0.6004529 | BX1: =BX8-$K$19 -> -3530769.2 | BY1: =BY8-($D$15+$D$16) -> -491.46337 | BZ1: =BZ8-(BZ2*$I$20+BZ3*$I$26+BZ4*$I$32+BZ5*BU$35+BZ6*BU$36+BZ7*BU$39) -> 9.1875 | CA1: =CA8-$I$19 -> 0.6004529 | CB1: =CB8-$K$19 -> -3530769.2 | CC1: =CC8-($D$15+$D$16) -> -491.46337 | CD1: =CD8-(CD2*$I$20+CD3*$I$26+CD4*$I$32+CD5*BY$35+CD6*BY$36+CD7*BY$39) -> 9.1875 | CE1: =CE8-$I$19 -> 0.6004529 | CF1: =CF8-$K$19 -> -3530769.2 | CG1: =CG8-($D$15+$D$16) -> -491.46337 | CH1: =CH8-(CH2*$I$20+CH3*$I$26+CH4*$I$32+CH5*CC$35+CH6*CC$36+CH7*CC$39) -> 9.1875 | CI1: =CI8-$I$19 -> 0.6004529 | CJ1: =CJ8-$K$19 -> -3530769.2 | CK1: =CK8-($D$15+$D$16) -> -491.46337 | CL1: =CL8-(CL2*$I$20+CL3*$I$26+CL4*$I$32+CL5*CG$35+CL6*CG$36+CL7*CG$39) -> 9.1875 | CM1: =CM8-$I$19 -> 0.6004529 | CN1: =CN8-$K$19 -> -3530769.2 | CO1: =CO8-($D$15+$D$16) -> -491.46337 | CP1: =CP8-(CP2*$I$20+CP3*$I$26+CP4*$I$32+CP5*CK$35+CP6*CK$36+CP7*CK$39) -> 9.1875 | CQ1: =CQ8-$I$19 -> 0.6004529 | CR1: =CR8-$K$19 -> -3530769.2 | CS1: =CS8-($D$15+$D$16) -> -491.46337 | CT1: =CT8-(CT2*$I$20+CT3*$I$26+CT4*$I$32+CT5*CO$35+CT6*CO$36+CT7*CO$39) -> 9.1875 | CU1: =CU8-$I$19 -> 0.6004529 | CV1: =CV8-$K$19 -> -3530769.2 | CW1: =CW8-($D$15+$D$16) -> -491.46337 | CX1: =CX8-(CX2*$I$20+CX3*$I$26+CX4*$I$32+CX5*CS$35+CX6*CS$36+CX7*CS$39) -> 9.1875 | CY1: =CY8-$I$19 -> 0.6004529 | CZ1: =CZ8-$K$19 -> -3530769.2 | DA1: =DA8-($D$15+$D$16) -> -491.46337 | DB1: =DB8-(DB2*$I$20+DB3*$I$26+DB4*$I$32+DB5*CW$35+DB6*CW$36+DB7*CW$39) -> 9.1875 | DC1: =DC8-$I$19 -> 0.6004529 | DD1: =DD8-$K$19 -> -3530769.2 | DE1: =DE8-($D$15+$D$16) -> -491.46337 | DF1: =DF8-(DF2*$I$20+DF3*$I$26+DF4*$I$32+DF5*DA$35+DF6*DA$36+DF7*DA$39) -> 9.1875 | DG1: =DG8-$I$19 -> 0.6004529 | DH1: =DH8-$K$19 -> -3530769.2 | DI1: =DI8-($D$15+$D$16) -> -491.46337 | DJ1: =DJ8-(DJ2*$I$20+DJ3*$I$26+DJ4*$I$32+DJ5*DE$35+DJ6*DE$36+DJ7*DE$39) -> 9.1875 | DK1: =DK8-$I$19 -> 0.6004529 | DL1: =DL8-$K$19 -> -3530769.2 | DM1: =DM8-($D$15+$D$16) -> -491.46337 | DN1: =DN8-(DN2*$I$20+DN3*$I$26+DN4*$I$32+DN5*DI$35+DN6*DI$36+DN7*DI$39) -> 9.1875 | DO1: =DO8-$I$19 -> 0.6004529 | DP1: =DP8-$K$19 -> -3530769.2 | DQ1: =DQ8-($D$15+$D$16) -> -491.46337 | DR1: =DR8-(DR2*$I$20+DR3*$I$26+DR4*$I$32+DR5*DM$35+DR6*DM$36+DR7*DM$39) -> 9.1875 | DS1: =DS8-$I$19 -> 0.6004529 | DT1: =DT8-$K$19 -> -3530769.2 | DU1: =DU8-($D$15+$D$16) -> -491.46337 | DV1: =DV8-(DV2*$I$20+DV3*$I$26+DV4*$I$32+DV5*DQ$35+DV6*DQ$36+DV7*DQ$39) -> 9.1875 | DW1: =DW8-$I$19 -> 0.6004529 | DX1: =DX8-$K$19 -> -3530769.2 | DY1: =DY8-($D$15+$D$16) -> -491.46337 | DZ1: =DZ8-(DZ2*$I$20+DZ3*$I$26+DZ4*$I$32+DZ5*DU$35+DZ6*DU$36+DZ7*DU$39) -> 9.1875 | EA1: =EA8-$I$19 -> 0.6004529 | EB1: =EB8-$K$19 -> -3530769.2 | EC1: =EC8-($D$15+$D$16) -> -491.46337 | ED1: =ED8-(ED2*$I$20+ED3*$I$26+ED4*$I$32+ED5*DY$35+ED6*DY$36+ED7*DY$39) -> 9.1875 | EE1: =EE8-$I$19 -> 0.6004529 | EF1: =EF8-$K$19 -> -3530769.2
A2: MONTH | B2: 2024 | C2: =E4 -> Person #1 | E2: ='Action Plan'!L2 -> Person in charge | I2: =$H$20 -> 0.9952957 | J2: =IF($E$19=0,0,K2/$E$19) -> 0.234375 | K2: =$E$20 -> 23250000 | L2: =C20 -> FACEBOOK | M2: =M$20 -> 14 | N2: =N$20 -> 11 | O2: =O$20 -> 0.85416667 | P2: =P$20 -> 750000 | Q2: =Q$20 -> 15 | R2: =R$20 -> 15 | S2: =S$20 -> 1 | T2: =T$20 -> 750000 | ... EF2: =EF$20 -> 750000
A3: YEAR | B3: 12 | C3: =E6 -> 0.35 | E3: TRUE | F3: TRUE | G3: TRUE | H3: TRUE | I3: =$H$26 -> 0.76344086 | J3: =IF($E$19=0,0,K3/$E$19) -> 0.15625 | K3: =$E$26 -> 15500000 | L3: =C26 -> LANDING PAGE | M3: =M$26 -> 14 | N3: =N$26 -> 9 | O3: =O$26 -> 0.66666667 | P3: =P$26 -> 500000 | Q3: =Q$26 -> 15 | R3: =R$26 -> 12 | S3: =S$26 -> 0.76666667 | T3: =T$26 -> 500000 | ... EF3: =EF$26 -> 500000
A4: VND | B4: 1000000 | C4: SATURDAY | E4: =Dashboard!P5 -> Person #1 | F4: =Dashboard!Q5 -> Person #2 | G4: =Dashboard!R5 -> Person #3 | H4: =Dashboard!S5 -> Person #4 | I4: =$H$32 -> 0.41666667 | J4: =IF($E$19=0,0,K4/$E$19) -> 0.171875 | K4: =$E$32 -> 17050000 | L4: =C32 -> WEBSITE | M4: =M$32 -> 7 | N4: =N$32 -> 3 | O4: =O$32 -> 0.41666667 | P4: =P$32 -> 550000 | Q4: =Q$32 -> 7 | R4: =R$32 -> 3 | S4: =S$32 -> 0.41666667 | T4: =T$32 -> 550000 | ... EF4: =EF$32 -> 550000
I5: =$H$35 -> 0.50322581 | J5: =IF($E$19=0,0,K5/$E$19) -> 0.15625 | K5: =$E$35 -> 15500000 | L5: =C35 -> TIKTOKSHOP | M5: =M$35 -> 5 | N5: =N$35 -> 3 | O5: =O$35 -> 0.6 | P5: =P$35 -> 500000 | Q5: =Q$35 -> 2 | R5: =R$35 -> 1 | S5: =S$35 -> 0.5 | T5: =T$35 -> 500000 | ... EF5: =EF$35 -> 500000
E6: =Dashboard!P13 -> 0.35 | F6: =Dashboard!Q13 -> 0.3 | G6: =Dashboard!R13 -> 0.25 | H6: =Dashboard!S13 -> 0.2 | I6: =$H$36 -> 0.5 | J6: =IF($E$19=0,0,K6/$E$19) -> 0.1875 | K6: =$E$36 -> 18600000 | L6: =C36 -> SHOPPEE | M6: =M$36 -> 6 | N6: =N$36 -> 3 | O6: =O$36 -> 0.5 | P6: =P$36 -> 600000 | Q6: =Q$36 -> 6 | R6: =R$36 -> 3 | S6: =S$36 -> 0.5 | T6: =T$36 -> 600000 | ... EF6: =EF$36 -> 600000
A7: HALF-DAY | B7: 1 | C7: =COUNTIF(M12:EF12,"T7") -> 4 | I7: =IF(ISNUMBER($H$39), $H$39, 0) -> 0.98387097 | J7: =IF($E$19=0,0,K7/$E$19) -> 0.09375 | K7: =$E$39 -> 9300000 | L7: =C39 -> ZALO | M7: =M$39 -> 2 | N7: =N$39 -> 1 | O7: =O$39 -> 0.5 | P7: =P$39 -> 300000 | Q7: =Q$39 -> 1 | R7: =R$39 -> 1 | S7: =S$39 -> 1 | T7: =T$39 -> 300000 | ... EF7: =EF$39 -> 300000
A8: FULL DAY | B8: =COUNTIF($L$9:$EE$9,"TRUE") -> 31 | I8: MONTHLY CVR OF PERSON BY PLATFORM | J8: MONTHLY REVENUE RATIO OF PERSON BY PLATFORM | K8: SALES REVENUE | L8: WORKDAYS | M8: =SUM(M2:M7) -> 48 | N8: =SUM(N2:N7) -> 30 | O8: =_xlfn.IFS(M8=0,0,N8<=M8,N8/M8,N8>M8,1) -> 0.625 | P8: =SUM(P2:P7) -> 3200000 | Q8: =SUM(Q2:Q7) -> 46 | R8: =SUM(R2:R7) -> 35 | S8: =_xlfn.IFS(Q8=0,0,R8<=Q8,R8/Q8,R8>Q8,1) -> 0.76086957 | T8: =SUM(T2:T7) -> 3200000 | U8: =SUM(U2:U7) -> 46 | V8: =SUM(V2:V7) -> 35 | W8: =_xlfn.IFS(U8=0,0,V8<=U8,V8/U8,V8>U8,1) -> 0.76086957 | X8: =SUM(X2:X7) -> 3200000 | Y8: =SUM(Y2:Y7) -> 46 | Z8: =SUM(Z2:Z7) -> 35 | AA8: =_xlfn.IFS(Y8=0,0,Z8<=Y8,Z8/Y8,Z8>Y8,1) -> 0.76086957 | AB8: =SUM(AB2:AB7) -> 3200000 | AC8: =SUM(AC2:AC7) -> 46 | AD8: =SUM(AD2:AD7) -> 35 | AE8: =_xlfn.IFS(AC8=0,0,AD8<=AC8,AD8/AC8,AD8>AC8,1) -> 0.76086957 | AF8: =SUM(AF2:AF7) -> 3200000 | AG8: =SUM(AG2:AG7) -> 46 | AH8: =SUM(AH2:AH7) -> 35 | AI8: =_xlfn.IFS(AG8=0,0,AH8<=AG8,AH8/AG8,AH8>AG8,1) -> 0.76086957 | AJ8: =SUM(AJ2:AJ7) -> 3200000 | AK8: =SUM(AK2:AK7) -> 46 | AL8: =SUM(AL2:AL7) -> 35 | AM8: =_xlfn.IFS(AK8=0,0,AL8<=AK8,AL8/AK8,AL8>AK8,1) -> 0.76086957 | AN8: =SUM(AN2:AN7) -> 3200000 | AO8: =SUM(AO2:AO7) -> 46 | AP8: =SUM(AP2:AP7) -> 35 | AQ8: =_xlfn.IFS(AO8=0,0,AP8<=AO8,AP8/AO8,AP8>AO8,1) -> 0.76086957 | AR8: =SUM(AR2:AR7) -> 3200000 | AS8: =SUM(AS2:AS7) -> 46 | AT8: =SUM(AT2:AT7) -> 35 | AU8: =_xlfn.IFS(AS8=0,0,AT8<=AS8,AT8/AS8,AT8>AS8,1) -> 0.76086957 | AV8: =SUM(AV2:AV7) -> 3200000 | AW8: =SUM(AW2:AW7) -> 46 | AX8: =SUM(AX2:AX7) -> 35 | AY8: =_xlfn.IFS(AW8=0,0,AX8<=AW8,AX8/AW8,AX8>AW8,1) -> 0.76086957 | AZ8: =SUM(AZ2:AZ7) -> 3200000 | BA8: =SUM(BA2:BA7) -> 46 | BB8: =SUM(BB2:BB7) -> 35 | BC8: =_xlfn.IFS(BA8=0,0,BB8<=BA8,BB8/BA8,BB8>BA8,1) -> 0.76086957 | BD8: =SUM(BD2:BD7) -> 3200000 | BE8: =SUM(BE2:BE7) -> 46 | BF8: =SUM(BF2:BF7) -> 35 | BG8: =_xlfn.IFS(BE8=0,0,BF8<=BE8,BF8/BE8,BF8>BE8,1) -> 0.76086957 | BH8: =SUM(BH2:BH7) -> 3200000 | BI8: =SUM(BI2:BI7) -> 46 | BJ8: =SUM(BJ2:BJ7) -> 35 | BK8: =_xlfn.IFS(BI8=0,0,BJ8<=BI8,BJ8/BI8,BJ8>BI8,1) -> 0.76086957 | BL8: =SUM(BL2:BL7) -> 3200000 | BM8: =SUM(BM2:BM7) -> 46 | BN8: =SUM(BN2:BN7) -> 35 | BO8: =_xlfn.IFS(BM8=0,0,BN8<=BM8,BN8/BM8,BN8>BM8,1) -> 0.76086957 | BP8: =SUM(BP2:BP7) -> 3200000 | BQ8: =SUM(BQ2:BQ7) -> 46 | BR8: =SUM(BR2:BR7) -> 35 | BS8: =_xlfn.IFS(BQ8=0,0,BR8<=BQ8,BR8/BQ8,BR8>BQ8,1) -> 0.76086957 | BT8: =SUM(BT2:BT7) -> 3200000 | BU8: =SUM(BU2:BU7) -> 46 | BV8: =SUM(BV2:BV7) -> 35 | BW8: =_xlfn.IFS(BU8=0,0,BV8<=BU8,BV8/BU8,BV8>BU8,1) -> 0.76086957 | BX8: =SUM(BX2:BX7) -> 3200000 | BY8: =SUM(BY2:BY7) -> 46 | BZ8: =SUM(BZ2:BZ7) -> 35 | CA8: =_xlfn.IFS(BY8=0,0,BZ8<=BY8,BZ8/BY8,BZ8>BY8,1) -> 0.76086957 | CB8: =SUM(CB2:CB7) -> 3200000 | CC8: =SUM(CC2:CC7) -> 46 | CD8: =SUM(CD2:CD7) -> 35 | CE8: =_xlfn.IFS(CC8=0,0,CD8<=CC8,CD8/CC8,CD8>CC8,1) -> 0.76086957 | CF8: =SUM(CF2:CF7) -> 3200000 | CG8: =SUM(CG2:CG7) -> 46 | CH8: =SUM(CH2:CH7) -> 35 | CI8: =_xlfn.IFS(CG8=0,0,CH8<=CG8,CH8/CG8,CH8>CG8,1) -> 0.76086957 | CJ8: =SUM(CJ2:CJ7) -> 3200000 | CK8: =SUM(CK2:CK7) -> 46 | CL8: =SUM(CL2:CL7) -> 35 | CM8: =_xlfn.IFS(CK8=0,0,CL8<=CK8,CL8/CK8,CL8>CK8,1) -> 0.76086957 | CN8: =SUM(CN2:CN7) -> 3200000 | CO8: =SUM(CO2:CO7) -> 46 | CP8: =SUM(CP2:CP7) -> 35 | CQ8: =_xlfn.IFS(CO8=0,0,CP8<=CO8,CP8/CO8,CP8>CO8,1) -> 0.76086957 | CR8: =SUM(CR2:CR7) -> 3200000 | CS8: =SUM(CS2:CS7) -> 46 | CT8: =SUM(CT2:CT7) -> 35 | CU8: =_xlfn.IFS(CS8=0,0,CT8<=CS8,CT8/CS8,CT8>CS8,1) -> 0.76086957 | CV8: =SUM(CV2:CV7) -> 3200000 | CW8: =SUM(CW2:CW7) -> 46 | CX8: =SUM(CX2:CX7) -> 35 | CY8: =_xlfn.IFS(CW8=0,0,CX8<=CW8,CX8/CW8,CX8>CW8,1) -> 0.76086957 | CZ8: =SUM(CZ2:CZ7) -> 3200000 | DA8: =SUM(DA2:DA7) -> 46 | DB8: =SUM(DB2:DB7) -> 35 | DC8: =_xlfn.IFS(DA8=0,0,DB8<=DA8,DB8/DA8,DB8>DA8,1) -> 0.76086957 | DD8: =SUM(DD2:DD7) -> 3200000 | DE8: =SUM(DE2:DE7) -> 46 | DF8: =SUM(DF2:DF7) -> 35 | DG8: =_xlfn.IFS(DE8=0,0,DF8<=DE8,DF8/DE8,DF8>DE8,1) -> 0.76086957 | DH8: =SUM(DH2:DH7) -> 3200000 | DI8: =SUM(DI2:DI7) -> 46 | DJ8: =SUM(DJ2:DJ7) -> 35 | DK8: =_xlfn.IFS(DI8=0,0,DJ8<=DI8,DJ8/DI8,DJ8>DI8,1) -> 0.76086957 | DL8: =SUM(DL2:DL7) -> 3200000 | DM8: =SUM(DM2:DM7) -> 46 | DN8: =SUM(DN2:DN7) -> 35 | DO8: =_xlfn.IFS(DM8=0,0,DN8<=DM8,DN8/DM8,DN8>DM8,1) -> 0.76086957 | DP8: =SUM(DP2:DP7) -> 3200000 | DQ8: =SUM(DQ2:DQ7) -> 46 | DR8: =SUM(DR2:DR7) -> 35 | DS8: =_xlfn.IFS(DQ8=0,0,DR8<=DQ8,DR8/DQ8,DR8>DQ8,1) -> 0.76086957 | DT8: =SUM(DT2:DT7) -> 3200000 | DU8: =SUM(DU2:DU7) -> 46 | DV8: =SUM(DV2:DV7) -> 35 | DW8: =_xlfn.IFS(DU8=0,0,DV8<=DU8,DV8/DU8,DV8>DU8,1) -> 0.76086957 | DX8: =SUM(DX2:DX7) -> 3200000 | DY8: =SUM(DY2:DY7) -> 46 | DZ8: =SUM(DZ2:DZ7) -> 35 | EA8: =_xlfn.IFS(DY8=0,0,DZ8<=DY8,DZ8/DY8,DZ8>DY8,1) -> 0.76086957 | EB8: =SUM(EB2:EB7) -> 3200000 | EC8: =SUM(EC2:EC7) -> 46 | ED8: =SUM(ED2:ED7) -> 35 | EE8: =_xlfn.IFS(EC8=0,0,ED8<=EC8,ED8/EC8,ED8>EC8,1) -> 0.76086957 | EF8: =SUM(EF2:EF7) -> 3200000
A9: TOTAL WORKDAY | B9: =B8-B7/2-C7/2 -> 28.5 | L9: TOTAL WORKDAYS | M9: TRUE | Q9: TRUE | U9: TRUE | Y9: TRUE | AC9: TRUE | AG9: TRUE | AK9: TRUE | AO9: TRUE | AS9: TRUE | AW9: TRUE | BA9: TRUE | BE9: TRUE | BI9: TRUE | BM9: TRUE | BQ9: TRUE | BU9: TRUE | BY9: TRUE | CC9: TRUE | CG9: TRUE | CK9: TRUE | CO9: TRUE | CS9: TRUE | CW9: TRUE | DA9: TRUE | DE9: TRUE | DI9: TRUE | DM9: TRUE | DQ9: TRUE | DU9: TRUE | DY9: TRUE | EC9: TRUE
A10: *FILL IN BOX B5 THE NUMBER OF HALF-DAY OFF DAYS IN THE MONTH (EXCEPT SATURDAY) | M10: 45748 | Q10: =M10+1 -> 45749 | U10: =Q10+1 -> 45750 | Y10: =U10+1 -> 45751 | AC10: =Y10+1 -> 45752 | AG10: =AC10+1 -> 45753 | AK10: =AG10+1 -> 45754 | AO10: =AK10+1 -> 45755 | AS10: =AO10+1 -> 45756 | AW10: =AS10+1 -> 45757 | BA10: =AW10+1 -> 45758 | BE10: =BA10+1 -> 45759 | BI10: =BE10+1 -> 45760 | BM10: =BI10+1 -> 45761 | BQ10: =BM10+1 -> 45762 | BU10: =BQ10+1 -> 45763 | BY10: =BU10+1 -> 45764 | CC10: =BY10+1 -> 45765 | CG10: =CC10+1 -> 45766 | CK10: =CG10+1 -> 45767 | CO10: =CK10+1 -> 45768 | CS10: =CO10+1 -> 45769 | CW10: =CS10+1 -> 45770 | DA10: =CW10+1 -> 45771 | DE10: =DA10+1 -> 45772 | DI10: =DE10+1 -> 45773 | DM10: =DI10+1 -> 45774 | DQ10: =DM10+1 -> 45775 | DU10: =DQ10+1 -> 45776 | DY10: =DU10+1 -> 45777 | EC10: =DY10+1 -> 45778
A11: *UNTICK SUNDAY AND FULL HOLIDAY | M11: =$M$10 -> 45748 | N11: =$M$10 -> 45748 | O11: =$M$10 -> 45748 | P11: =$M$10 -> 45748 | Q11: =Q$10 -> 45749 | R11: =Q$10 -> 45749 | S11: =Q$10 -> 45749 | T11: =Q$10 -> 45749 | U11: =U$10 -> 45750 | V11: =U$10 -> 45750 | W11: =U$10 -> 45750 | X11: =U$10 -> 45750 | Y11: =Y$10 -> 45751 | Z11: =Y$10 -> 45751 | AA11: =Y$10 -> 45751 | AB11: =Y$10 -> 45751 | AC11: =AC$10 -> 45752 | AD11: =AC$10 -> 45752 | AE11: =AC$10 -> 45752 | AF11: =AC$10 -> 45752 | AG11: =AG$10 -> 45753 | AH11: =AG$10 -> 45753 | AI11: =AG$10 -> 45753 | AJ11: =AG$10 -> 45753 | AK11: =AK$10 -> 45754 | AL11: =AK$10 -> 45754 | AM11: =AK$10 -> 45754 | AN11: =AK$10 -> 45754 | AO11: =AO$10 -> 45755 | AP11: =AO$10 -> 45755 | AQ11: =AO$10 -> 45755 | AR11: =AO$10 -> 45755 | AS11: =AS$10 -> 45756 | AT11: =AS$10 -> 45756 | AU11: =AS$10 -> 45756 | AV11: =AS$10 -> 45756 | AW11: =AW$10 -> 45757 | AX11: =AW$10 -> 45757 | AY11: =AW$10 -> 45757 | AZ11: =AW$10 -> 45757 | BA11: =BA$10 -> 45758 | BB11: =BA$10 -> 45758 | BC11: =BA$10 -> 45758 | BD11: =BA$10 -> 45758 | BE11: =BE$10 -> 45759 | BF11: =BE$10 -> 45759 | BG11: =BE$10 -> 45759 | BH11: =BE$10 -> 45759 | BI11: =BI$10 -> 45760 | BJ11: =BI$10 -> 45760 | BK11: =BI$10 -> 45760 | BL11: =BI$10 -> 45760 | BM11: =BM$10 -> 45761 | BN11: =BM$10 -> 45761 | BO11: =BM$10 -> 45761 | BP11: =BM$10 -> 45761 | BQ11: =BQ$10 -> 45762 | BR11: =BQ$10 -> 45762 | BS11: =BQ$10 -> 45762 | BT11: =BQ$10 -> 45762 | BU11: =BU$10 -> 45763 | BV11: =BU$10 -> 45763 | BW11: =BU$10 -> 45763 | BX11: =BU$10 -> 45763 | BY11: =BY$10 -> 45764 | BZ11: =BY$10 -> 45764 | CA11: =BY$10 -> 45764 | CB11: =BY$10 -> 45764 | CC11: =CC$10 -> 45765 | CD11: =CC$10 -> 45765 | CE11: =CC$10 -> 45765 | CF11: =CC$10 -> 45765 | CG11: =CG$10 -> 45766 | CH11: =CG$10 -> 45766 | CI11: =CG$10 -> 45766 | CJ11: =CG$10 -> 45766 | CK11: =CK$10 -> 45767 | CL11: =CK$10 -> 45767 | CM11: =CK$10 -> 45767 | CN11: =CK$10 -> 45767 | CO11: =CO$10 -> 45768 | CP11: =CO$10 -> 45768 | CQ11: =CO$10 -> 45768 | CR11: =CO$10 -> 45768 | CS11: =CS$10 -> 45769 | CT11: =CS$10 -> 45769 | CU11: =CS$10 -> 45769 | CV11: =CS$10 -> 45769 | CW11: =CW$10 -> 45770 | CX11: =CW$10 -> 45770 | CY11: =CW$10 -> 45770 | CZ11: =CW$10 -> 45770 | DA11: =DA$10 -> 45771 | DB11: =DA$10 -> 45771 | DC11: =DA$10 -> 45771 | DD11: =DA$10 -> 45771 | DE11: =DE$10 -> 45772 | DF11: =DE$10 -> 45772 | DG11: =DE$10 -> 45772 | DH11: =DE$10 -> 45772 | DI11: =DI$10 -> 45773 | DJ11: =DI$10 -> 45773 | DK11: =DI$10 -> 45773 | DL11: =DI$10 -> 45773 | DM11: =DM$10 -> 45774 | DN11: =DM$10 -> 45774 | DO11: =DM$10 -> 45774 | DP11: =DM$10 -> 45774 | DQ11: =DQ$10 -> 45775 | DR11: =DQ$10 -> 45775 | DS11: =DQ$10 -> 45775 | DT11: =DQ$10 -> 45775 | DU11: =DU$10 -> 45776 | DV11: =DU$10 -> 45776 | DW11: =DU$10 -> 45776 | DX11: =DU$10 -> 45776 | DY11: =DY$10 -> 45777 | DZ11: =DY$10 -> 45777 | EA11: =DY$10 -> 45777 | EB11: =DY$10 -> 45777 | EC11: =EC$10 -> 45778 | ED11: =EC$10 -> 45778 | EE11: =EC$10 -> 45778 | EF11: =EC$10 -> 45778
D12: MONTH | I12: AVERAGE CVR | J12: DAY T-1 | M12: =IF(WEEKDAY(M11)=1,"CN","T"&WEEKDAY(M11)) -> T3 | Q12: =IF(WEEKDAY(Q11)=1,"CN","T"&WEEKDAY(Q11)) -> T4 | U12: =IF(WEEKDAY(U11)=1,"CN","T"&WEEKDAY(U11)) -> T5 | Y12: =IF(WEEKDAY(Y11)=1,"CN","T"&WEEKDAY(Y11)) -> T6 | AC12: =IF(WEEKDAY(AC11)=1,"CN","T"&WEEKDAY(AC11)) -> T7 | AG12: =IF(WEEKDAY(AG11)=1,"CN","T"&WEEKDAY(AG11)) -> CN | AK12: =IF(WEEKDAY(AK11)=1,"CN","T"&WEEKDAY(AK11)) -> T2 | AO12: =IF(WEEKDAY(AO11)=1,"CN","T"&WEEKDAY(AO11)) -> T3 | AS12: =IF(WEEKDAY(AS11)=1,"CN","T"&WEEKDAY(AS11)) -> T4 | AW12: =IF(WEEKDAY(AW11)=1,"CN","T"&WEEKDAY(AW11)) -> T5 | BA12: =IF(WEEKDAY(BA11)=1,"CN","T"&WEEKDAY(BA11)) -> T6 | BE12: =IF(WEEKDAY(BE11)=1,"CN","T"&WEEKDAY(BE11)) -> T7 | BI12: =IF(WEEKDAY(BI11)=1,"CN","T"&WEEKDAY(BI11)) -> CN | BM12: =IF(WEEKDAY(BM11)=1,"CN","T"&WEEKDAY(BM11)) -> T2 | BQ12: =IF(WEEKDAY(BQ11)=1,"CN","T"&WEEKDAY(BQ11)) -> T3 | BU12: =IF(WEEKDAY(BU11)=1,"CN","T"&WEEKDAY(BU11)) -> T4 | BY12: =IF(WEEKDAY(BY11)=1,"CN","T"&WEEKDAY(BY11)) -> T5 | CC12: =IF(WEEKDAY(CC11)=1,"CN","T"&WEEKDAY(CC11)) -> T6 | CG12: =IF(WEEKDAY(CG11)=1,"CN","T"&WEEKDAY(CG11)) -> T7 | CK12: =IF(WEEKDAY(CK11)=1,"CN","T"&WEEKDAY(CK11)) -> CN | CO12: =IF(WEEKDAY(CO11)=1,"CN","T"&WEEKDAY(CO11)) -> T2 | CS12: =IF(WEEKDAY(CS11)=1,"CN","T"&WEEKDAY(CS11)) -> T3 | CW12: =IF(WEEKDAY(CW11)=1,"CN","T"&WEEKDAY(CW11)) -> T4 | DA12: =IF(WEEKDAY(DA11)=1,"CN","T"&WEEKDAY(DA11)) -> T5 | DE12: =IF(WEEKDAY(DE11)=1,"CN","T"&WEEKDAY(DE11)) -> T6 | DI12: =IF(WEEKDAY(DI11)=1,"CN","T"&WEEKDAY(DI11)) -> T7 | DM12: =IF(WEEKDAY(DM11)=1,"CN","T"&WEEKDAY(DM11)) -> CN | DQ12: =IF(WEEKDAY(DQ11)=1,"CN","T"&WEEKDAY(DQ11)) -> T2 | DU12: =IF(WEEKDAY(DU11)=1,"CN","T"&WEEKDAY(DU11)) -> T3 | DY12: =IF(WEEKDAY(DY11)=1,"CN","T"&WEEKDAY(DY11)) -> T4 | EC12: =IF(WEEKDAY(EC11)=1,"CN","T"&WEEKDAY(EC11)) -> T5
A13: 1. FILL IN BC IN ALL GREEN CELLS (AS ABOVE) 2. CLOSE BC ON DAY T BEFORE 12AM ON DAY T+1 3. FILL IN Q&A AT LINK 4. O40:O42 IS THE NUMBER OF COMPLETED ORDERS IN THE DAY ON THE PLATFORMS 5. DO NOT FILL IN THE CELLS THAT ALREADY HAVE THE FORMULA | D13: ESTIMATED | E13: ACTUAL | F13: REMAINING | G13: RATIO | H13: MONTHLY CVR | I13: KPIs | J13: DAILY CVR | K13: KPIs | L13: TASKS COMPLETED | M13: NEW ORDER | N13: DONE | O13: CVR | P13: SALES | Q13: NEW ORDER | R13: DONE | S13: CVR | T13: SALES | U13: NEW ORDER | V13: DONE | W13: CVR | X13: SALES | Y13: NEW ORDER | Z13: DONE | AA13: CVR | AB13: SALES | AC13: NEW ORDER | AD13: DONE | AE13: CVR | AF13: SALES | AG13: NEW ORDER | AH13: DONE | AI13: CVR | AJ13: SALES | AK13: NEW ORDER | AL13: DONE | AM13: CVR | AN13: SALES | AO13: NEW ORDER | AP13: DONE | AQ13: CVR | AR13: SALES | AS13: NEW ORDER | AT13: DONE | AU13: CVR | AV13: SALES | AW13: NEW ORDER | AX13: DONE | AY13: CVR | AZ13: SALES | BA13: NEW ORDER | BB13: DONE | BC13: CVR | BD13: SALES | BE13: NEW ORDER | BF13: DONE | BG13: CVR | BH13: SALES | BI13: NEW ORDER | BJ13: DONE | BK13: CVR | BL13: SALES | BM13: NEW ORDER | BN13: DONE | BO13: CVR | BP13: SALES | BQ13: NEW ORDER | BR13: DONE | BS13: CVR | BT13: SALES | BU13: NEW ORDER | BV13: DONE | BW13: CVR | BX13: SALES | BY13: NEW ORDER | BZ13: DONE | CA13: CVR | CB13: SALES | CC13: NEW ORDER | CD13: DONE | CE13: CVR | CF13: SALES | CG13: NEW ORDER | CH13: DONE | CI13: CVR | CJ13: SALES | CK13: NEW ORDER | CL13: DONE | CM13: CVR | CN13: SALES | CO13: NEW ORDER | CP13: DONE | CQ13: CVR | CR13: SALES | CS13: NEW ORDER | CT13: DONE | CU13: CVR | CV13: SALES | CW13: NEW ORDER | CX13: DONE | CY13: CVR | CZ13: SALES | DA13: NEW ORDER | DB13: DONE | DC13: CVR | DD13: SALES | DE13: NEW ORDER | DF13: DONE | DG13: CVR | DH13: SALES | DI13: NEW ORDER | DJ13: DONE | DK13: CVR | DL13: SALES | DM13: NEW ORDER | DN13: DONE | DO13: CVR | DP13: SALES | DQ13: NEW ORDER | DR13: DONE | DS13: CVR | DT13: SALES | DU13: NEW ORDER | DV13: DONE | DW13: CVR | DX13: SALES | DY13: NEW ORDER | DZ13: DONE | EA13: CVR | EB13: SALES | EC13: NEW ORDER | ED13: DONE | EE13: CVR | EF13: SALES
C14: =Dashboard!K90 -> P2 | D14: =Dashboard!M90 -> 0.35
A15: =_xlfn.IFS(B15=0,0,E15>B15,1,E15<=B15,E15/B15) -> 0 | C15: =Dashboard!K91 -> CALL | D15: =Dashboard!M91 -> 427.91337 | E15: =SUMIF($M$13:$EF$13,$M$13,$M15:$EF15) -> 681 | F15: =E15-D15 -> 253.08663 | G15: =_xlfn.IFS(F15>0,1,F15<=0,E15/D15) -> 1 | K15: =D15/$B$9 -> 15.014504 | L15: =SUMIFS($M15:$EF15,$M$11:$EF$11,TODAY()-1,$M$13:$EF$13,$M$13) -> 0 | M15: =M26+M32 -> 21 | N15: =N26+N32 -> 12 | O15: =_xlfn.IFS(M15=0,0,N15<=M15,N15/M15,N15>M15,1) -> 0.57142857 | P15: =P26+P32 -> 1050000 | Q15: =Q26+Q32 -> 22 | R15: =R26+R32 -> 15 | S15: =_xlfn.IFS(Q15=0,0,R15<=Q15,R15/Q15,R15>Q15,1) -> 0.68181818 | T15: =T26+T32 -> 1050000 | U15: =U26+U32 -> 22 | V15: =V26+V32 -> 15 | W15: =_xlfn.IFS(U15=0,0,V15<=U15,V15/U15,V15>U15,1) -> 0.68181818 | X15: =X26+X32 -> 1050000 | Y15: =Y26+Y32 -> 22 | Z15: =Z26+Z32 -> 15 | AA15: =_xlfn.IFS(Y15=0,0,Z15<=Y15,Z15/Y15,Z15>Y15,1) -> 0.68181818 | AB15: =AB26+AB32 -> 1050000 | AC15: =AC26+AC32 -> 22 | AD15: =AD26+AD32 -> 15 | AE15: =_xlfn.IFS(AC15=0,0,AD15<=AC15,AD15/AC15,AD15>AC15,1) -> 0.68181818 | AF15: =AF26+AF32 -> 1050000 | AG15: =AG26+AG32 -> 22 | AH15: =AH26+AH32 -> 15 | AI15: =_xlfn.IFS(AG15=0,0,AH15<=AG15,AH15/AG15,AH15>AG15,1) -> 0.68181818 | AJ15: =AJ26+AJ32 -> 1050000 | AK15: =AK26+AK32 -> 22 | AL15: =AL26+AL32 -> 15 | AM15: =_xlfn.IFS(AK15=0,0,AL15<=AK15,AL15/AK15,AL15>AK15,1) -> 0.68181818 | AN15: =AN26+AN32 -> 1050000 | AO15: =AO26+AO32 -> 22 | AP15: =AP26+AP32 -> 15 | AQ15: =_xlfn.IFS(AO15=0,0,AP15<=AO15,AP15/AO15,AP15>AO15,1) -> 0.68181818 | AR15: =AR26+AR32 -> 1050000 | AS15: =AS26+AS32 -> 22 | AT15: =AT26+AT32 -> 15 | AU15: =_xlfn.IFS(AS15=0,0,AT15<=AS15,AT15/AS15,AT15>AS15,1) -> 0.68181818 | AV15: =AV26+AV32 -> 1050000 | AW15: =AW26+AW32 -> 22 | AX15: =AX26+AX32 -> 15 | AY15: =_xlfn.IFS(AW15=0,0,AX15<=AW15,AX15/AW15,AX15>AW15,1) -> 0.68181818 | AZ15: =AZ26+AZ32 -> 1050000 | BA15: =BA26+BA32 -> 22 | BB15: =BB26+BB32 -> 15 | BC15: =_xlfn.IFS(BA15=0,0,BB15<=BA15,BB15/BA15,BB15>BA15,1) -> 0.68181818 | BD15: =BD26+BD32 -> 1050000 | BE15: =BE26+BE32 -> 22 | BF15: =BF26+BF32 -> 15 | BG15: =_xlfn.IFS(BE15=0,0,BF15<=BE15,BF15/BE15,BF15>BE15,1) -> 0.68181818 | BH15: =BH26+BH32 -> 1050000 | BI15: =BI26+BI32 -> 22 | BJ15: =BJ26+BJ32 -> 15 | BK15: =_xlfn.IFS(BI15=0,0,BJ15<=BI15,BJ15/BI15,BJ15>BI15,1) -> 0.68181818 | BL15: =BL26+BL32 -> 1050000 | BM15: =BM26+BM32 -> 22 | BN15: =BN26+BN32 -> 15 | BO15: =_xlfn.IFS(BM15=0,0,BN15<=BM15,BN15/BM15,BN15>BM15,1) -> 0.68181818 | BP15: =BP26+BP32 -> 1050000 | BQ15: =BQ26+BQ32 -> 22 | BR15: =BR26+BR32 -> 15 | BS15: =_xlfn.IFS(BQ15=0,0,BR15<=BQ15,BR15/BQ15,BR15>BQ15,1) -> 0.68181818 | BT15: =BT26+BT32 -> 1050000 | BU15: =BU26+BU32 -> 22 | BV15: =BV26+BV32 -> 15 | BW15: =_xlfn.IFS(BU15=0,0,BV15<=BU15,BV15/BU15,BV15>BU15,1) -> 0.68181818 | BX15: =BX26+BX32 -> 1050000 | BY15: =BY26+BY32 -> 22 | BZ15: =BZ26+BZ32 -> 15 | CA15: =_xlfn.IFS(BY15=0,0,BZ15<=BY15,BZ15/BY15,BZ15>BY15,1) -> 0.68181818 | CB15: =CB26+CB32 -> 1050000 | CC15: =CC26+CC32 -> 22 | CD15: =CD26+CD32 -> 15 | CE15: =_xlfn.IFS(CC15=0,0,CD15<=CC15,CD15/CC15,CD15>CC15,1) -> 0.68181818 | CF15: =CF26+CF32 -> 1050000 | CG15: =CG26+CG32 -> 22 | CH15: =CH26+CH32 -> 15 | CI15: =_xlfn.IFS(CG15=0,0,CH15<=CG15,CH15/CG15,CH15>CG15,1) -> 0.68181818 | CJ15: =CJ26+CJ32 -> 1050000 | CK15: =CK26+CK32 -> 22 | CL15: =CL26+CL32 -> 15 | CM15: =_xlfn.IFS(CK15=0,0,CL15<=CK15,CL15/CK15,CL15>CK15,1) -> 0.68181818 | CN15: =CN26+CN32 -> 1050000 | CO15: =CO26+CO32 -> 22 | CP15: =CP26+CP32 -> 15 | CQ15: =_xlfn.IFS(CO15=0,0,CP15<=CO15,CP15/CO15,CP15>CO15,1) -> 0.68181818 | CR15: =CR26+CR32 -> 1050000 | CS15: =CS26+CS32 -> 22 | CT15: =CT26+CT32 -> 15 | CU15: =_xlfn.IFS(CS15=0,0,CT15<=CS15,CT15/CS15,CT15>CS15,1) -> 0.68181818 | CV15: =CV26+CV32 -> 1050000 | CW15: =CW26+CW32 -> 22 | CX15: =CX26+CX32 -> 15 | CY15: =_xlfn.IFS(CW15=0,0,CX15<=CW15,CX15/CW15,CX15>CW15,1) -> 0.68181818 | CZ15: =CZ26+CZ32 -> 1050000 | DA15: =DA26+DA32 -> 22 | DB15: =DB26+DB32 -> 15 | DC15: =_xlfn.IFS(DA15=0,0,DB15<=DA15,DB15/DA15,DB15>DA15,1) -> 0.68181818 | DD15: =DD26+DD32 -> 1050000 | DE15: =DE26+DE32 -> 22 | DF15: =DF26+DF32 -> 15 | DG15: =_xlfn.IFS(DE15=0,0,DF15<=DE15,DF15/DE15,DF15>DE15,1) -> 0.68181818 | DH15: =DH26+DH32 -> 1050000 | DI15: =DI26+DI32 -> 22 | DJ15: =DJ26+DJ32 -> 15 | DK15: =_xlfn.IFS(DI15=0,0,DJ15<=DI15,DJ15/DI15,DJ15>DI15,1) -> 0.68181818 | DL15: =DL26+DL32 -> 1050000 | DM15: =DM26+DM32 -> 22 | DN15: =DN26+DN32 -> 15 | DO15: =_xlfn.IFS(DM15=0,0,DN15<=DM15,DN15/DM15,DN15>DM15,1) -> 0.68181818 | DP15: =DP26+DP32 -> 1050000 | DQ15: =DQ26+DQ32 -> 22 | DR15: =DR26+DR32 -> 15 | DS15: =_xlfn.IFS(DQ15=0,0,DR15<=DQ15,DR15/DQ15,DR15>DQ15,1) -> 0.68181818 | DT15: =DT26+DT32 -> 1050000 | DU15: =DU26+DU32 -> 22 | DV15: =DV26+DV32 -> 15 | DW15: =_xlfn.IFS(DU15=0,0,DV15<=DU15,DV15/DU15,DV15>DU15,1) -> 0.68181818 | DX15: =DX26+DX32 -> 1050000 | DY15: =DY26+DY32 -> 22 | DZ15: =DZ26+DZ32 -> 15 | EA15: =_xlfn.IFS(DY15=0,0,DZ15<=DY15,DZ15/DY15,DZ15>DY15,1) -> 0.68181818 | EB15: =EB26+EB32 -> 1050000 | EC15: =EC26+EC32 -> 22 | ED15: =ED26+ED32 -> 15 | EE15: =_xlfn.IFS(EC15=0,0,ED15<=EC15,ED15/EC15,ED15>EC15,1) -> 0.68181818 | EF15: =EF26+EF32 -> 1050000
